Workbook

Sheet REV
A1: OFERTAS VÁLIDAS APENAS PARA PLANOS CONSUMER
B4: Inclusão de Preços
B5: Alteração de Preços
A7: Preços Elegíveis a Price Back
A8: Preços Elegíveis a Price Oferta
A9: CANAL: | B9: REVENDAS
C11: DATA INÍCIO: | D11: 46092 | J11: COM FIDELIZAÇÃO - GROSS / MIGRAÇÃO / UPGRADE / PORTABILIDADE / BASE SEM MOVIMENTAÇÃO | AB11: TIM FIBRA | AM11: TIM FIXO | AP11: TIM CASA
A12: Regra Reembolso Pós Fidelizado | B12: CATEGORIA MKT | C12: CÓDIGO | D12: DESCRIÇÃO COMERCIAL | E12: DESCRIÇÃO SAP | F12: PRÉ | G12: PREÇO BASE FATURAMENTO RETAIL | H12: CONTROLE NÃO FIDELIZADO - TODOS (Fatura / Express) | I12: PÓS PAGO NÃO FIDELIZADO - VIDE ABA DE REGRAS | J12: TIM CONTROLE | K12: TIM CONTROLE PLUS | L12: TIM CONTROLE PREMIUM | M12: TIM CONTROLE SMART | N12: TIM CONTROLE REDES SOCIAIS | O12: TIM BLACK | P12: TIM BLACK PLUS | Q12: TIM BLACK PREMIUM | R12: TIM BLACK A (15GB) | S12: TIM BLACK B (20GB) | T12: TIM BLACK C (25GB) | U12: TIM BLACK C ULTRA | V12: TIM BLACK FAMÍLIA | W12: TIM BLACK FAMÍLIA A ONE | X12: TIM BLACK FAMÍLIA PLUS | Y12: TIM BLACK FAMÍLIA PREMIUM | Z12: TIM BLACK FAMÍLIA C ONE | AA12: TIM BLACK FAMÍLIA VIP | AB12: TIM Fibra 300M 24 | AC12: TIM Fibra 400M 24 | AD12: TIM Fibra 500M 24 - 2 | AE12: TIM Fibra 600M 24 - 2 | AF12: TIM Fibra 600M P 24 - 2 | AG12: TIM Fibra 600M M 24 - 2 | AH12: TIM Fibra 600M GP 25 | AI12: TIM Fibra 1GB 24 | AJ12: TIM Fibra 1GB P 24 | AK12: TIM Fibra 1GB M 24 | AL12: TIM Fibra 2GB 24 | AM12: TIM FIXO LOCAL TOTAL PLUS (Plano Fidelizado) | AN12: TIM FIXO BRASIL TOTAL PLUS (Plano Fidelizado) | AO12: TIM FIXO TOTAL LDI PLUS (Plano Fidelizado) | AP12: TIM LIVE INTERNET 30GB (sem fidelização) | AQ12: TIM LIVE INTERNET 50GB (sem fidelização) | AR12: TIM LIVE INTERNET 80GB (sem fidelização) | AS12: TIM LIVE INTERNET 30GB PLUS | AT12: TIM LIVE INTERNET 50GB PLUS | AU12: TIM LIVE INTERNET 80GB PLUS | AW12: DATA FIM DA OFERTA | AX12: TECNOLOGIA
A13: ADM | B13: 21X | C13: 4010990 | D13: Alcatel Pixi 4.5 4G | E13: Alcatel Pixi 4.5 4G-Preto | F13: 479 | G13: 479 | H13: 479 | I13: 479 | J13: =M13 -> 479 | K13: =M13 -> 479 | L13: =N13 -> 479 | M13: 479 | N13: 479 | AW13: 31.03.2026 | AX13: 4G
A14: ADM | B14: 21X | C14: 4010991 | D14: Alcatel Pixi 4.5 4G | E14: Alcatel Pixi 4.5 4G-Branco | F14: 479 | G14: 479 | H14: 479 | I14: 479 | J14: =M14 -> 479 | K14: =M14 -> 479 | L14: =N14 -> 479 | M14: 479 | N14: 479 | AW14: 31.03.2026 | AX14: 4G
A15: ADM | B15: 21X | C15: 4011353 | D15: Alcatel Pixi 4.5 4G | E15: Alcatel Pixi 4.5 4G-Preto AM | F15: 479 | G15: 479 | H15: 479 | I15: 479 | J15: =M15 -> 479 | K15: =M15 -> 479 | L15: =N15 -> 479 | M15: 479 | N15: 479 | AW15: 31.03.2026 | AX15: 4G
A16: ADM | B16: 21X | C16: 4011354 | D16: Alcatel Pixi 4.5 4G | E16: Alcatel Pixi 4.5 4G-Branco AM | F16: 479 | G16: 479 | H16: 479 | I16: 479 | J16: =M16 -> 479 | K16: =M16 -> 479 | L16: =N16 -> 479 | M16: 479 | N16: 479 | AW16: 31.03.2026 | AX16: 4G
A17: Price Oferta | B17: 21X | C17: 4013660 | D17: APPLE IPHONE SE 64GB 2GER | E17: APPLE IPHONE SE 64GB 2GER-PRETO | F17: 999 | G17: 549 | H17: 999 | I17: 999 | J17: 799 | K17: 699 | L17: 699 | M17: 799 | N17: 799 | O17: 599 | P17: 599 | Q17: =T17 -> 599 | R17: 599 | S17: 599 | T17: 599 | U17: 599 | V17: 599 | W17: 599 | X17: 549 | Y17: 549 | Z17: 549 | AA17: 549 | AW17: 31.03.2026 | AX17: 4G
A18: Price Oferta | B18: 21X | C18: 4013661 | D18: APPLE IPHONE SE 64GB 2GER | E18: Apple iPhone SE 64GB 2Ger-Branco | F18: 999 | G18: 549 | H18: 999 | I18: 999 | J18: 799 | K18: 699 | L18: 699 | M18: 799 | N18: 799 | O18: 599 | P18: 599 | Q18: =T18 -> 599 | R18: 599 | S18: 599 | T18: 599 | U18: 599 | V18: 599 | W18: 599 | X18: 549 | Y18: 549 | Z18: 549 | AA18: 549 | AW18: 31.03.2026 | AX18: 4G
A19: Price Oferta | B19: 21X | C19: 4013662 | D19: APPLE IPHONE SE 64GB 2GER | E19: Apple iPhone SE 64GB 2Ger-Vermelho | F19: 999 | G19: 549 | H19: 999 | I19: 999 | J19: 799 | K19: 699 | L19: 699 | M19: 799 | N19: 799 | O19: 599 | P19: 599 | Q19: =T19 -> 599 | R19: 599 | S19: 599 | T19: 599 | U19: 599 | V19: 599 | W19: 599 | X19: 549 | Y19: 549 | Z19: 549 | AA19: 549 | AW19: 31.03.2026 | AX19: 4G
A20: Price Oferta | B20: 21X | C20: 4013981 | D20: APPLE IPHONE SE 64GB 2GER | E20: APPLE IPHONE SE 64GB 2GE-PRETO NAC | F20: 999 | G20: 549 | H20: 999 | I20: 999 | J20: 799 | K20: 699 | L20: 699 | M20: 799 | N20: 799 | O20: 599 | P20: 599 | Q20: =T20 -> 599 | R20: 599 | S20: 599 | T20: 599 | U20: 599 | V20: 599 | W20: 599 | X20: 549 | Y20: 549 | Z20: 549 | AA20: 549 | AW20: 31.03.2026 | AX20: 4G
A21: Price Oferta | B21: 21X | C21: 4013984 | D21: APPLE IPHONE SE 64GB 2GER | E21: APPLE IPHONE SE 64GB 2GE-BRANCO NAC | F21: 999 | G21: 549 | H21: 999 | I21: 999 | J21: 799 | K21: 699 | L21: 699 | M21: 799 | N21: 799 | O21: 599 | P21: 599 | Q21: =T21 -> 599 | R21: 599 | S21: 599 | T21: 599 | U21: 599 | V21: 599 | W21: 599 | X21: 549 | Y21: 549 | Z21: 549 | AA21: 549 | AW21: 31.03.2026 | AX21: 4G
A22: Price Oferta | B22: 21X | C22: 4013986 | D22: APPLE IPHONE SE 64GB 2GER | E22: APPLE IPHONE SE 64GB 2GE-VERMELHO NAC | F22: 999 | G22: 549 | H22: 999 | I22: 999 | J22: 799 | K22: 699 | L22: 699 | M22: 799 | N22: 799 | O22: 599 | P22: 599 | Q22: =T22 -> 599 | R22: 599 | S22: 599 | T22: 599 | U22: 599 | V22: 599 | W22: 599 | X22: 549 | Y22: 549 | Z22: 549 | AA22: 549 | AW22: 31.03.2026 | AX22: 4G
A23: Price Oferta | B23: 21X | C23: 4013852 | D23: APPLE IPHONE SE 64GB 2GER | E23: APPLE IPHONE SE 64GB 2GE-PRETO NAC S.KIT | F23: 999 | G23: 549 | H23: 999 | I23: 999 | J23: 799 | K23: 699 | L23: 699 | M23: 799 | N23: 799 | O23: 599 | P23: 599 | Q23: =T23 -> 599 | R23: 599 | S23: 599 | T23: 599 | U23: 599 | V23: 599 | W23: 599 | X23: 549 | Y23: 549 | Z23: 549 | AA23: 549 | AW23: 31.03.2026 | AX23: 4G
A24: Price Oferta | B24: 21X | C24: 4014002 | D24: APPLE IPHONE SE 64GB 2GER | E24: APPLE IPHONE SE 64GB 2GE-BRANC NAC S.KIT | F24: 999 | G24: 549 | H24: 999 | I24: 999 | J24: 799 | K24: 699 | L24: 699 | M24: 799 | N24: 799 | O24: 599 | P24: 599 | Q24: =T24 -> 599 | R24: 599 | S24: 599 | T24: 599 | U24: 599 | V24: 599 | W24: 599 | X24: 549 | Y24: 549 | Z24: 549 | AA24: 549 | AW24: 31.03.2026 | AX24: 4G
A25: Price Oferta | B25: 21X | C25: 4013875 | D25: APPLE IPHONE 12 64GB | E25: APPLE IPHONE 12 64GB-VERDE | F25: 6499 | G25: 2599 | H25: 999 | I25: 999 | J25: 999 | K25: 999 | L25: 999 | M25: 999 | N25: 999 | O25: 999 | P25: 999 | Q25: 999 | R25: 999 | S25: 999 | T25: 999 | U25: 999 | V25: 999 | W25: 999 | X25: 999 | Y25: 999 | Z25: 999 | AA25: 999 | AW25: 31.03.2026 | AX25: 5G
A26: Price Oferta | B26: 21X | C26: 4013877 | D26: APPLE IPHONE 12 64GB | E26: APPLE IPHONE 12 64GB-VERMELHO | F26: 6499 | G26: 2599 | H26: 999 | I26: 999 | J26: 999 | K26: 999 | L26: 999 | M26: 999 | N26: 999 | O26: 999 | P26: 999 | Q26: 999 | R26: 999 | S26: 999 | T26: 999 | U26: 999 | V26: 999 | W26: 999 | X26: 999 | Y26: 999 | Z26: 999 | AA26: 999 | AW26: 31.03.2026 | AX26: 5G
A27: Price Oferta | B27: 21X | C27: 4013878 | D27: APPLE IPHONE 12 64GB | E27: APPLE IPHONE 12 64GB-BRANCO | F27: 6499 | G27: 2599 | H27: 999 | I27: 999 | J27: 999 | K27: 999 | L27: 999 | M27: 999 | N27: 999 | O27: 999 | P27: 999 | Q27: 999 | R27: 999 | S27: 999 | T27: 999 | U27: 999 | V27: 999 | W27: 999 | X27: 999 | Y27: 999 | Z27: 999 | AA27: 999 | AW27: 31.03.2026 | AX27: 5G
A28: Price Oferta | B28: 21X | C28: 4013879 | D28: APPLE IPHONE 12 64GB | E28: APPLE IPHONE 12 64GB-PRETO | F28: 6499 | G28: 2599 | H28: 999 | I28: 999 | J28: 999 | K28: 999 | L28: 999 | M28: 999 | N28: 999 | O28: 999 | P28: 999 | Q28: 999 | R28: 999 | S28: 999 | T28: 999 | U28: 999 | V28: 999 | W28: 999 | X28: 999 | Y28: 999 | Z28: 999 | AA28: 999 | AW28: 31.03.2026 | AX28: 5G
A29: Price Oferta | B29: 21X | C29: 4013880 | D29: APPLE IPHONE 12 64GB | E29: APPLE IPHONE 12 64GB-AZUL | F29: 6499 | G29: 2599 | H29: 999 | I29: 999 | J29: 999 | K29: 999 | L29: 999 | M29: 999 | N29: 999 | O29: 999 | P29: 999 | Q29: 999 | R29: 999 | S29: 999 | T29: 999 | U29: 999 | V29: 999 | W29: 999 | X29: 999 | Y29: 999 | Z29: 999 | AA29: 999 | AW29: 31.03.2026 | AX29: 5G
A30: Price Oferta | B30: 21X | C30: 4014295 | D30: APPLE IPHONE 12 64GB | E30: APPLE IPHONE 12 64GB-ROXO | F30: 6499 | G30: 2599 | H30: 999 | I30: 999 | J30: 999 | K30: 999 | L30: 999 | M30: 999 | N30: 999 | O30: 999 | P30: 999 | Q30: 999 | R30: 999 | S30: 999 | T30: 999 | U30: 999 | V30: 999 | W30: 999 | X30: 999 | Y30: 999 | Z30: 999 | AA30: 999 | AW30: 31.03.2026 | AX30: 5G
A31: Price Oferta | B31: 21X | C31: 4014386 | D31: APPLE IPHONE 12 64GB | E31: APPLE IPHONE 12 64GB-AZUL NAC | F31: 6499 | G31: 2599 | H31: 999 | I31: 999 | J31: 999 | K31: 999 | L31: 999 | M31: 999 | N31: 999 | O31: 999 | P31: 999 | Q31: 999 | R31: 999 | S31: 999 | T31: 999 | U31: 999 | V31: 999 | W31: 999 | X31: 999 | Y31: 999 | Z31: 999 | AA31: 999 | AW31: 31.03.2026 | AX31: 5G
A32: Price Oferta | B32: 21X | C32: 4014380 | D32: APPLE IPHONE 12 64GB | E32: APPLE IPHONE 12 64GB-PRETO NAC | F32: 6499 | G32: 2599 | H32: 999 | I32: 999 | J32: 999 | K32: 999 | L32: 999 | M32: 999 | N32: 999 | O32: 999 | P32: 999 | Q32: 999 | R32: 999 | S32: 999 | T32: 999 | U32: 999 | V32: 999 | W32: 999 | X32: 999 | Y32: 999 | Z32: 999 | AA32: 999 | AW32: 31.03.2026 | AX32: 5G
A33: Price Oferta | B33: 21X | C33: 4014382 | D33: APPLE IPHONE 12 64GB | E33: APPLE IPHONE 12 64GB-BRANCO NAC | F33: 6499 | G33: 2599 | H33: 999 | I33: 999 | J33: 999 | K33: 999 | L33: 999 | M33: 999 | N33: 999 | O33: 999 | P33: 999 | Q33: 999 | R33: 999 | S33: 999 | T33: 999 | U33: 999 | V33: 999 | W33: 999 | X33: 999 | Y33: 999 | Z33: 999 | AA33: 999 | AW33: 31.03.2026 | AX33: 5G
A34: Price Oferta | B34: 21X | C34: 4013881 | D34: APPLE IPHONE 12 128GB | E34: APPLE IPHONE 12 128GB-VERDE | F34: 4499 | G34: 2299 | H34: 999 | I34: 999 | J34: 999 | K34: 999 | L34: 999 | M34: 999 | N34: 999 | O34: 999 | P34: 999 | Q34: 999 | R34: 999 | S34: 999 | T34: 999 | U34: 999 | V34: 999 | W34: 999 | X34: 999 | Y34: 999 | Z34: 999 | AA34: 999 | AW34: 31.03.2026 | AX34: 5G
A35: Price Oferta | B35: 21X | C35: 4013882 | D35: APPLE IPHONE 12 128GB | E35: APPLE IPHONE 12 128GB-VERMELHO | F35: 4499 | G35: 2299 | H35: 999 | I35: 999 | J35: 999 | K35: 999 | L35: 999 | M35: 999 | N35: 999 | O35: 999 | P35: 999 | Q35: 999 | R35: 999 | S35: 999 | T35: 999 | U35: 999 | V35: 999 | W35: 999 | X35: 999 | Y35: 999 | Z35: 999 | AA35: 999 | AW35: 31.03.2026 | AX35: 5G
A36: Price Oferta | B36: 21X | C36: 4013883 | D36: APPLE IPHONE 12 128GB | E36: APPLE IPHONE 12 128GB-BRANCO | F36: 4499 | G36: 2299 | H36: 999 | I36: 999 | J36: 999 | K36: 999 | L36: 999 | M36: 999 | N36: 999 | O36: 999 | P36: 999 | Q36: 999 | R36: 999 | S36: 999 | T36: 999 | U36: 999 | V36: 999 | W36: 999 | X36: 999 | Y36: 999 | Z36: 999 | AA36: 999 | AW36: 31.03.2026 | AX36: 5G
... A69: Price Oferta | B69: 21X | C69: 4014884 | D69: APPLE IPHONE 13 PRO 256GB | E69: APPLE IPHONE 13 PRO 256GB-VERDE ALPINO | F69: 10499 | G69: 5199 | H69: 3999 | I69: 3999 | J69: 3999 | K69: 3999 | L69: 3999 | M69: 3999 | N69: 3999 | O69: 3999 | P69: 3999 | Q69: 3999 | R69: 3999 | S69: 3999 | T69: 3999 | U69: 3999 | V69: 3999 | W69: 3999 | X69: 3999 | Y69: 3999 | Z69: 3999 | AA69: 3999 | AW69: 31.03.2026 | AX69: 5G
A70: Price Oferta | B70: 21X | C70: 4014593 | D70: APPLE IPHONE 13 PRO MAX 256GB | E70: APPLE IPHONE 13 PRO MAX 256GB-GRAFITE | F70: 11499 | G70: 6199 | H70: 6999 | I70: 6999 | J70: =M70 -> 6799 | K70: 6699 | L70: 6699 | M70: 6799 | N70: 6799 | O70: =R70 -> 6499 | P70: =S70 -> 6299 | Q70: 5999 | R70: 6499 | S70: 6299 | T70: 5999 | U70: 5899 | V70: 5899 | W70: 5799 | X70: 5699 | Y70: 5499 | Z70: 5399 | AA70: 5399 | AW70: 31.03.2026 | AX70: 5G
A71: Price Oferta | B71: 21X | C71: 4014599 | D71: APPLE IPHONE 13 PRO MAX 256GB | E71: APPLE IPHONE 13 PRO MAX 256GB-PRATEADO | F71: 11499 | G71: 6199 | H71: 6999 | I71: 6999 | J71: =M71 -> 6799 | K71: 6699 | L71: 6699 | M71: 6799 | N71: 6799 | O71: =R71 -> 6499 | P71: =S71 -> 6299 | Q71: 5999 | R71: 6499 | S71: 6299 | T71: 5999 | U71: 5899 | V71: 5899 | W71: 5799 | X71: 5699 | Y71: 5499 | Z71: 5399 | AA71: 5399 | AW71: 31.03.2026 | AX71: 5G
A72: Price Oferta | B72: 21X | C72: 4014605 | D72: APPLE IPHONE 13 PRO MAX 256GB | E72: APPLE IPHONE 13 PRO MAX 256GB-DOURADO | F72: 11499 | G72: 6199 | H72: 6999 | I72: 6999 | J72: =M72 -> 6799 | K72: 6699 | L72: 6699 | M72: 6799 | N72: 6799 | O72: =R72 -> 6499 | P72: =S72 -> 6299 | Q72: 5999 | R72: 6499 | S72: 6299 | T72: 5999 | U72: 5899 | V72: 5899 | W72: 5799 | X72: 5699 | Y72: 5499 | Z72: 5399 | AA72: 5399 | AW72: 31.03.2026 | AX72: 5G
A73: Price Oferta | B73: 21X | C73: 4014612 | D73: APPLE IPHONE 13 PRO MAX 256GB | E73: APPLE IPHONE 13 PRO MAX 256GB-AZUL SIERR | F73: 11499 | G73: 6199 | H73: 6999 | I73: 6999 | J73: =M73 -> 6799 | K73: 6699 | L73: 6699 | M73: 6799 | N73: 6799 | O73: =R73 -> 6499 | P73: =S73 -> 6299 | Q73: 5999 | R73: 6499 | S73: 6299 | T73: 5999 | U73: 5899 | V73: 5899 | W73: 5799 | X73: 5699 | Y73: 5499 | Z73: 5399 | AA73: 5399 | AW73: 31.03.2026 | AX73: 5G
A74: Price Oferta | B74: 21X | C74: 4014868 | D74: APPLE IPHONE 13 PRO MAX 256GB | E74: APPLE IPHONE 13 PRO MAX 256GB-VERDE ALP | F74: 11499 | G74: 6199 | H74: 6999 | I74: 6999 | J74: =M74 -> 6799 | K74: 6699 | L74: 6699 | M74: 6799 | N74: 6799 | O74: =R74 -> 6499 | P74: =S74 -> 6299 | Q74: 5999 | R74: 6499 | S74: 6299 | T74: 5999 | U74: 5899 | V74: 5899 | W74: 5799 | X74: 5699 | Y74: 5499 | Z74: 5399 | AA74: 5399 | AW74: 31.03.2026 | AX74: 5G
A75: Price Oferta | B75: 21X | C75: 4015019 | D75: APPLE IPHONE 14 128GB | E75: APPLE IPHONE 14 128GB-AZUL | F75: 7299 | G75: 3899 | H75: 5299 | I75: 5299 | J75: 4199 | K75: 4199 | L75: 4199 | M75: 4199 | N75: 4199 | O75: 3899 | P75: 3799 | Q75: 3099 | R75: 3899 | S75: 3799 | T75: 3099 | U75: 3099 | V75: 3099 | W75: 3099 | X75: 2999 | Y75: 2499 | Z75: 2499 | AA75: 2499 | AW75: 31.03.2026 | AX75: 5G
A76: Price Oferta | B76: 21X | C76: 4015165 | D76: APPLE IPHONE 14 128GB | E76: APPLE IPHONE 14 128GB-ROXO | F76: 7299 | G76: 3899 | H76: 5299 | I76: 5299 | J76: 4199 | K76: 4199 | L76: 4199 | M76: 4199 | N76: 4199 | O76: 3899 | P76: 3799 | Q76: 3099 | R76: 3899 | S76: 3799 | T76: 3099 | U76: 3099 | V76: 3099 | W76: 3099 | X76: 2999 | Y76: 2499 | Z76: 2499 | AA76: 2499 | AW76: 31.03.2026 | AX76: 5G
A77: Price Oferta | B77: 21X | C77: 4015178 | D77: APPLE IPHONE 14 128GB | E77: APPLE IPHONE 14 128GB-BRANCO | F77: 7299 | G77: 3899 | H77: 5299 | I77: 5299 | J77: 4199 | K77: 4199 | L77: 4199 | M77: 4199 | N77: 4199 | O77: 3899 | P77: 3799 | Q77: 3099 | R77: 3899 | S77: 3799 | T77: 3099 | U77: 3099 | V77: 3099 | W77: 3099 | X77: 2999 | Y77: 2499 | Z77: 2499 | AA77: 2499 | AW77: 31.03.2026 | AX77: 5G
A78: Price Oferta | B78: 21X | C78: 4015185 | D78: APPLE IPHONE 14 128GB | E78: APPLE IPHONE 14 128GB-PRETO | F78: 7299 | G78: 3899 | H78: 5299 | I78: 5299 | J78: 4199 | K78: 4199 | L78: 4199 | M78: 4199 | N78: 4199 | O78: 3899 | P78: 3799 | Q78: 3099 | R78: 3899 | S78: 3799 | T78: 3099 | U78: 3099 | V78: 3099 | W78: 3099 | X78: 2999 | Y78: 2499 | Z78: 2499 | AA78: 2499 | AW78: 31.03.2026 | AX78: 5G
A79: Price Oferta | B79: 21X | C79: 4015171 | D79: APPLE IPHONE 14 128GB | E79: APPLE IPHONE 14 128GB-VERMELHO | F79: 7299 | G79: 3899 | H79: 5299 | I79: 5299 | J79: 4199 | K79: 4199 | L79: 4199 | M79: 4199 | N79: 4199 | O79: 3899 | P79: 3799 | Q79: 3099 | R79: 3899 | S79: 3799 | T79: 3099 | U79: 3099 | V79: 3099 | W79: 3099 | X79: 2999 | Y79: 2499 | Z79: 2499 | AA79: 2499 | AW79: 31.03.2026 | AX79: 5G
A80: Price Oferta | B80: 21X | C80: 4015262 | D80: APPLE IPHONE 14 128GB | E80: APPLE IPHONE 14 128GB-PRETO NAC | F80: 7299 | G80: 3899 | H80: 5299 | I80: 5299 | J80: 4199 | K80: 4199 | L80: 4199 | M80: 4199 | N80: 4199 | O80: 3899 | P80: 3799 | Q80: 3099 | R80: 3899 | S80: 3799 | T80: 3099 | U80: 3099 | V80: 3099 | W80: 3099 | X80: 2999 | Y80: 2499 | Z80: 2499 | AA80: 2499 | AW80: 31.03.2026 | AX80: 5G
A81: Price Oferta | B81: 21X | C81: 4015263 | D81: APPLE IPHONE 14 128GB | E81: APPLE IPHONE 14 128GB-BRANCO NAC | F81: 7299 | G81: 3899 | H81: 5299 | I81: 5299 | J81: 4199 | K81: 4199 | L81: 4199 | M81: 4199 | N81: 4199 | O81: 3899 | P81: 3799 | Q81: 3099 | R81: 3899 | S81: 3799 | T81: 3099 | U81: 3099 | V81: 3099 | W81: 3099 | X81: 2999 | Y81: 2499 | Z81: 2499 | AA81: 2499 | AW81: 31.03.2026 | AX81: 5G
A82: Price Oferta | B82: 21X | C82: 4015264 | D82: APPLE IPHONE 14 128GB | E82: APPLE IPHONE 14 128GB-ROXO NAC | F82: 7299 | G82: 3899 | H82: 5299 | I82: 5299 | J82: 4199 | K82: 4199 | L82: 4199 | M82: 4199 | N82: 4199 | O82: 3899 | P82: 3799 | Q82: 3099 | R82: 3899 | S82: 3799 | T82: 3099 | U82: 3099 | V82: 3099 | W82: 3099 | X82: 2999 | Y82: 2499 | Z82: 2499 | AA82: 2499 | AW82: 31.03.2026 | AX82: 5G
A83: Price Oferta | B83: 21X | C83: 4015266 | D83: APPLE IPHONE 14 128GB | E83: APPLE IPHONE 14 128GB-AZUL NAC | F83: 7299 | G83: 3899 | H83: 5299 | I83: 5299 | J83: 4199 | K83: 4199 | L83: 4199 | M83: 4199 | N83: 4199 | O83: 3899 | P83: 3799 | Q83: 3099 | R83: 3899 | S83: 3799 | T83: 3099 | U83: 3099 | V83: 3099 | W83: 3099 | X83: 2999 | Y83: 2499 | Z83: 2499 | AA83: 2499 | AW83: 31.03.2026 | AX83: 5G
A84: Price Oferta | B84: 21X | C84: 4015265 | D84: APPLE IPHONE 14 128GB | E84: APPLE IPHONE 14 128GB-VERMELHO NAC | F84: 7299 | G84: 3899 | H84: 5299 | I84: 5299 | J84: 4199 | K84: 4199 | L84: 4199 | M84: 4199 | N84: 4199 | O84: 3899 | P84: 3799 | Q84: 3099 | R84: 3899 | S84: 3799 | T84: 3099 | U84: 3099 | V84: 3099 | W84: 3099 | X84: 2999 | Y84: 2499 | Z84: 2499 | AA84: 2499 | AW84: 31.03.2026 | AX84: 5G
A85: Price Oferta | B85: 21X | C85: 4015017 | D85: APPLE IPHONE 14 256GB | E85: APPLE IPHONE 14 256GB-AZUL | F85: 7799 | G85: 2899 | H85: 4399 | I85: 4399 | J85: 4399 | K85: 4399 | L85: 4399 | M85: 4399 | N85: 4399 | O85: 4299 | P85: 4199 | Q85: 3499 | R85: 4299 | S85: 4199 | T85: 3499 | U85: 3499 | V85: 3499 | W85: 3499 | X85: 3399 | Y85: 2499 | Z85: 2499 | AA85: 2499 | AW85: 31.03.2026 | AX85: 5G
A86: Price Oferta | B86: 21X | C86: 4015163 | D86: APPLE IPHONE 14 256GB | E86: APPLE IPHONE 14 256GB-ROXO | F86: 7799 | G86: 2899 | H86: 4399 | I86: 4399 | J86: 4399 | K86: 4399 | L86: 4399 | M86: 4399 | N86: 4399 | O86: 4299 | P86: 4199 | Q86: 3499 | R86: 4299 | S86: 4199 | T86: 3499 | U86: 3499 | V86: 3499 | W86: 3499 | X86: 3399 | Y86: 2499 | Z86: 2499 | AA86: 2499 | AW86: 31.03.2026 | AX86: 5G
... A106: Price Oferta | B106: 21X | C106: 4015183 | D106: APPLE IPHONE 14 PRO MAX 256GB | E106: APPLE IPHONE 14 PRO MAX 256GB-ROXO | F106: 11499 | G106: 6899 | H106: 7999 | I106: 7999 | J106: 6399 | K106: 6399 | L106: 6399 | M106: 6399 | N106: 6399 | O106: 6299 | P106: 6199 | Q106: 5999 | R106: 6299 | S106: 6199 | T106: 5999 | U106: 5999 | V106: 5999 | W106: 5999 | X106: 5899 | Y106: 5499 | Z106: 5499 | AA106: 5499 | AW106: 31.03.2026 | AX106: 5G
A107: Price Oferta | B107: 21X | C107: 4015160 | D107: APPLE IPHONE 14 PRO 128GB | E107: APPLE IPHONE 14 PRO 128GB-GRAFITE | F107: 9499 | G107: 5199 | H107: 5999 | I107: 5999 | J107: =M107 -> 5999 | K107: 5899 | L107: 5899 | M107: 5999 | N107: 5999 | O107: 5799 | P107: 5699 | Q107: 4999 | R107: 5799 | S107: 5699 | T107: 4999 | U107: 4899 | V107: 4899 | W107: 4799 | X107: 4699 | Y107: 4499 | Z107: 4399 | AA107: 4399 | AW107: 31.03.2026 | AX107: 5G
A108: Price Oferta | B108: 21X | C108: 4015174 | D108: APPLE IPHONE 14 PRO 128GB | E108: APPLE IPHONE 14 PRO 128GB-DOURADO | F108: 9499 | G108: 5199 | H108: 5999 | I108: 5999 | J108: =M108 -> 5999 | K108: 5899 | L108: 5899 | M108: 5999 | N108: 5999 | O108: 5799 | P108: 5699 | Q108: 4999 | R108: 5799 | S108: 5699 | T108: 4999 | U108: 4899 | V108: 4899 | W108: 4799 | X108: 4699 | Y108: 4499 | Z108: 4399 | AA108: 4399 | AW108: 31.03.2026 | AX108: 5G
A109: Price Oferta | B109: 21X | C109: 4015181 | D109: APPLE IPHONE 14 PRO 128GB | E109: APPLE IPHONE 14 PRO 128GB-ROXO | F109: 9499 | G109: 5199 | H109: 5999 | I109: 5999 | J109: =M109 -> 5999 | K109: 5899 | L109: 5899 | M109: 5999 | N109: 5999 | O109: 5799 | P109: 5699 | Q109: 4999 | R109: 5799 | S109: 5699 | T109: 4999 | U109: 4899 | V109: 4899 | W109: 4799 | X109: 4699 | Y109: 4499 | Z109: 4399 | AA109: 4399 | AW109: 31.03.2026 | AX109: 5G
A110: Price Oferta | B110: 21X | C110: 4015112 | D110: APPLE IPHONE 14 PRO 256GB | E110: APPLE IPHONE 14 PRO 256GB-GRAFITE | F110: 10499 | G110: 5899 | H110: 6999 | I110: 6999 | J110: 5899 | K110: 5899 | L110: 5899 | M110: 5899 | N110: 5899 | O110: 5799 | P110: 5699 | Q110: 5499 | R110: 5799 | S110: 5699 | T110: 5499 | U110: 5499 | V110: 5499 | W110: 5499 | X110: 5399 | Y110: 4999 | Z110: 4999 | AA110: 4999 | AW110: 31.03.2026 | AX110: 5G
A111: Price Oferta | B111: 21X | C111: 4015116 | D111: APPLE IPHONE 14 PRO 256GB | E111: APPLE IPHONE 14 PRO 256GB-DOURADO | F111: 10499 | G111: 5899 | H111: 6999 | I111: 6999 | J111: 5899 | K111: 5899 | L111: 5899 | M111: 5899 | N111: 5899 | O111: 5799 | P111: 5699 | Q111: 5499 | R111: 5799 | S111: 5699 | T111: 5499 | U111: 5499 | V111: 5499 | W111: 5499 | X111: 5399 | Y111: 4999 | Z111: 4999 | AA111: 4999 | AW111: 31.03.2026 | AX111: 5G
A112: Price Oferta | B112: 21X | C112: 4015118 | D112: APPLE IPHONE 14 PRO 256GB | E112: APPLE IPHONE 14 PRO 256GB-ROXO | F112: 10499 | G112: 5899 | H112: 6999 | I112: 6999 | J112: 5899 | K112: 5899 | L112: 5899 | M112: 5899 | N112: 5899 | O112: 5799 | P112: 5699 | Q112: 5499 | R112: 5799 | S112: 5699 | T112: 5499 | U112: 5499 | V112: 5499 | W112: 5499 | X112: 5399 | Y112: 4999 | Z112: 4999 | AA112: 4999 | AW112: 31.03.2026 | AX112: 5G
A113: Price Oferta | B113: 21X | C113: 4015742 | D113: APPLE IPHONE 15 128GB | E113: APPLE IPHONE 15 128GB-PRETO | F113: 7299 | G113: 5399 | H113: 5699 | I113: 5699 | J113: 4999 | K113: 4899 | L113: 4899 | M113: 4999 | N113: 4899 | O113: 4799 | P113: 4699 | Q113: 4499 | R113: 4799 | S113: 4699 | T113: 4499 | U113: 4399 | V113: 4399 | W113: 4299 | X113: 4199 | Y113: 3499 | Z113: 3499 | AA113: 3499 | AW113: 31.03.2026 | AX113: 5G
A114: Price Oferta | B114: 21X | C114: 4015724 | D114: APPLE IPHONE 15 128GB | E114: APPLE IPHONE 15 128GB-AZUL | F114: 7299 | G114: 5399 | H114: 5699 | I114: 5699 | J114: 4999 | K114: 4899 | L114: 4899 | M114: 4999 | N114: 4899 | O114: 4799 | P114: 4699 | Q114: 4499 | R114: 4799 | S114: 4699 | T114: 4499 | U114: 4399 | V114: 4399 | W114: 4299 | X114: 4199 | Y114: 3499 | Z114: 3499 | AA114: 3499 | AW114: 31.03.2026 | AX114: 5G
A115: Price Oferta | B115: 21X | C115: 4015725 | D115: APPLE IPHONE 15 128GB | E115: APPLE IPHONE 15 128GB-ROSA | F115: 7299 | G115: 5399 | H115: 5699 | I115: 5699 | J115: 4999 | K115: 4899 | L115: 4899 | M115: 4999 | N115: 4899 | O115: 4799 | P115: 4699 | Q115: 4499 | R115: 4799 | S115: 4699 | T115: 4499 | U115: 4399 | V115: 4399 | W115: 4299 | X115: 4199 | Y115: 3499 | Z115: 3499 | AA115: 3499 | AW115: 31.03.2026 | AX115: 5G
A116: Price Oferta | B116: 21X | C116: 4015794 | D116: APPLE IPHONE 15 128GB | E116: APPLE IPHONE 15 128GB-VERDE | F116: 7299 | G116: 5399 | H116: 5699 | I116: 5699 | J116: 4999 | K116: 4899 | L116: 4899 | M116: 4999 | N116: 4899 | O116: 4799 | P116: 4699 | Q116: 4499 | R116: 4799 | S116: 4699 | T116: 4499 | U116: 4399 | V116: 4399 | W116: 4299 | X116: 4199 | Y116: 3499 | Z116: 3499 | AA116: 3499 | AW116: 31.03.2026 | AX116: 5G
A117: Price Oferta | B117: 21X | C117: 4015808 | D117: APPLE IPHONE 15 128GB | E117: APPLE IPHONE 15 128GB-AMARELO | F117: 7299 | G117: 5399 | H117: 5699 | I117: 5699 | J117: 4999 | K117: 4899 | L117: 4899 | M117: 4999 | N117: 4899 | O117: 4799 | P117: 4699 | Q117: 4499 | R117: 4799 | S117: 4699 | T117: 4499 | U117: 4399 | V117: 4399 | W117: 4299 | X117: 4199 | Y117: 3499 | Z117: 3499 | AA117: 3499 | AW117: 31.03.2026 | AX117: 5G
A118: Price Oferta | B118: 21X | C118: 4015743 | D118: APPLE IPHONE 15 256GB | E118: APPLE IPHONE 15 256GB-PRETO | F118: 8099 | G118: 3899 | H118: 5299 | I118: 5299 | J118: 5199 | K118: 5199 | L118: 5199 | M118: 5199 | N118: 5199 | O118: 4999 | P118: 4899 | Q118: 3999 | R118: 4999 | S118: 4899 | T118: 3999 | U118: 3999 | V118: 3999 | W118: 3999 | X118: 3899 | Y118: 3799 | Z118: 3799 | AA118: 3799 | AW118: 31.03.2026 | AX118: 5G
A119: Price Oferta | B119: 21X | C119: 4015770 | D119: APPLE IPHONE 15 256GB | E119: APPLE IPHONE 15 256GB-AZUL | F119: 8099 | G119: 3899 | H119: 5299 | I119: 5299 | J119: 5199 | K119: 5199 | L119: 5199 | M119: 5199 | N119: 5199 | O119: 4999 | P119: 4899 | Q119: 3999 | R119: 4999 | S119: 4899 | T119: 3999 | U119: 3999 | V119: 3999 | W119: 3999 | X119: 3899 | Y119: 3799 | Z119: 3799 | AA119: 3799 | AW119: 31.03.2026 | AX119: 5G
A120: Price Oferta | B120: 21X | C120: 4015783 | D120: APPLE IPHONE 15 256GB | E120: APPLE IPHONE 15 256GB-ROSA | F120: 8099 | G120: 3899 | H120: 5299 | I120: 5299 | J120: 5199 | K120: 5199 | L120: 5199 | M120: 5199 | N120: 5199 | O120: 4999 | P120: 4899 | Q120: 3999 | R120: 4999 | S120: 4899 | T120: 3999 | U120: 3999 | V120: 3999 | W120: 3999 | X120: 3899 | Y120: 3799 | Z120: 3799 | AA120: 3799 | AW120: 31.03.2026 | AX120: 5G
A121: Price Oferta | B121: 21X | C121: 4015800 | D121: APPLE IPHONE 15 256GB | E121: APPLE IPHONE 15 256GB-VERDE | F121: 8099 | G121: 3899 | H121: 5299 | I121: 5299 | J121: 5199 | K121: 5199 | L121: 5199 | M121: 5199 | N121: 5199 | O121: 4999 | P121: 4899 | Q121: 3999 | R121: 4999 | S121: 4899 | T121: 3999 | U121: 3999 | V121: 3999 | W121: 3999 | X121: 3899 | Y121: 3799 | Z121: 3799 | AA121: 3799 | AW121: 31.03.2026 | AX121: 5G
... A184: Price Oferta | B184: 21X | C184: 4016609 | D184: APPLE IPHONE 16 PRO MAX 512GB | E184: APPLE IPHONE 16 PRO MAX 512GB-TITANIO | F184: 13999 | G184: 10799 | H184: 12099 | I184: 12099 | J184: 11999 | K184: 11999 | L184: 11999 | M184: 11999 | N184: 11999 | O184: 11699 | P184: 11599 | Q184: 10999 | R184: 11699 | S184: 11599 | T184: 10999 | U184: 10999 | V184: 10999 | W184: 10999 | X184: 10799 | Y184: 10299 | Z184: 10299 | AA184: 10299 | AW184: 31.03.2026 | AX184: 5G
A185: Price Oferta | B185: 21X | C185: 4016916 | D185: APPLE IPHONE 16E 256GB | E185: APPLE IPHONE 16E 256GB-PRETO NAC | F185: 6599 | G185: 3499 | H185: 4799 | I185: 4799 | J185: 4799 | K185: 4799 | L185: 4799 | M185: 4799 | N185: 4799 | O185: 4699 | P185: 4599 | Q185: 3599 | R185: 4699 | S185: 4599 | T185: 3599 | U185: 3599 | V185: 3599 | W185: 3599 | X185: 3499 | Y185: 3299 | Z185: 3299 | AA185: 3299 | AB185: 4799 | AC185: 4799 | AD185: 4799 | AE185: 4799 | AF185: 4699 | AG185: 4599 | AH185: 3599 | AI185: 3599 | AJ185: 3599 | AK185: 3599 | AL185: 3299 | AW185: 31.03.2026 | AX185: 5G
A186: Price Oferta | B186: 21X | C186: 4016917 | D186: APPLE IPHONE 16E 256GB | E186: APPLE IPHONE 16E 256GB-BRANCO NAC | F186: 6599 | G186: 3499 | H186: 4799 | I186: 4799 | J186: 4799 | K186: 4799 | L186: 4799 | M186: 4799 | N186: 4799 | O186: 4699 | P186: 4599 | Q186: 3599 | R186: 4699 | S186: 4599 | T186: 3599 | U186: 3599 | V186: 3599 | W186: 3599 | X186: 3499 | Y186: 3299 | Z186: 3299 | AA186: 3299 | AB186: 4799 | AC186: 4799 | AD186: 4799 | AE186: 4799 | AF186: 4699 | AG186: 4599 | AH186: 3599 | AI186: 3599 | AJ186: 3599 | AK186: 3599 | AL186: 3299 | AW186: 31.03.2026 | AX186: 5G
A187: Price Oferta | B187: 21X | C187: 4017449 | D187: APPLE IPHONE 17 256GB | E187: APPLE IPHONE 17 256GB-LAVANDA | F187: 7999 | G187: 5799 | H187: 7499 | I187: 7499 | J187: 7499 | K187: 7499 | L187: 7499 | M187: 7499 | N187: 7499 | O187: 7399 | P187: 7299 | Q187: 6499 | R187: 7399 | S187: 7299 | T187: 6499 | U187: 6499 | V187: 6499 | W187: 6399 | X187: 6399 | Y187: 5799 | Z187: 5799 | AA187: 5799 | AB187: 7499 | AC187: 7499 | AD187: 7499 | AE187: 7499 | AF187: 7399 | AG187: 7299 | AH187: 6499 | AI187: 6499 | AJ187: 6499 | AK187: 6499 | AL187: 5799 | AW187: 31.03.2026 | AX187: 5G
A188: Price Oferta | B188: 21X | C188: 4017480 | D188: APPLE IPHONE 17 256GB | E188: APPLE IPHONE 17 256GB-AZUL NEVOA | F188: 7999 | G188: 5799 | H188: 7499 | I188: 7499 | J188: 7499 | K188: 7499 | L188: 7499 | M188: 7499 | N188: 7499 | O188: 7399 | P188: 7299 | Q188: 6499 | R188: 7399 | S188: 7299 | T188: 6499 | U188: 6499 | V188: 6499 | W188: 6399 | X188: 6399 | Y188: 5799 | Z188: 5799 | AA188: 5799 | AB188: 7499 | AC188: 7499 | AD188: 7499 | AE188: 7499 | AF188: 7399 | AG188: 7299 | AH188: 6499 | AI188: 6499 | AJ188: 6499 | AK188: 6499 | AL188: 5799 | AW188: 31.03.2026 | AX188: 5G
A189: Price Oferta | B189: 21X | C189: 4017485 | D189: APPLE IPHONE 17 256GB | E189: APPLE IPHONE 17 256GB-PRETO | F189: 7999 | G189: 5799 | H189: 7499 | I189: 7499 | J189: 7499 | K189: 7499 | L189: 7499 | M189: 7499 | N189: 7499 | O189: 7399 | P189: 7299 | Q189: 6499 | R189: 7399 | S189: 7299 | T189: 6499 | U189: 6499 | V189: 6499 | W189: 6399 | X189: 6399 | Y189: 5799 | Z189: 5799 | AA189: 5799 | AB189: 7499 | AC189: 7499 | AD189: 7499 | AE189: 7499 | AF189: 7399 | AG189: 7299 | AH189: 6499 | AI189: 6499 | AJ189: 6499 | AK189: 6499 | AL189: 5799 | AW189: 31.03.2026 | AX189: 5G
A190: Price Oferta | B190: 21X | C190: 4017486 | D190: APPLE IPHONE 17 256GB | E190: APPLE IPHONE 17 256GB-BRANCO | F190: 7999 | G190: 5799 | H190: 7499 | I190: 7499 | J190: 7499 | K190: 7499 | L190: 7499 | M190: 7499 | N190: 7499 | O190: 7399 | P190: 7299 | Q190: 6499 | R190: 7399 | S190: 7299 | T190: 6499 | U190: 6499 | V190: 6499 | W190: 6399 | X190: 6399 | Y190: 5799 | Z190: 5799 | AA190: 5799 | AB190: 7499 | AC190: 7499 | AD190: 7499 | AE190: 7499 | AF190: 7399 | AG190: 7299 | AH190: 6499 | AI190: 6499 | AJ190: 6499 | AK190: 6499 | AL190: 5799 | AW190: 31.03.2026 | AX190: 5G
A191: Price Oferta | B191: 21X | C191: 4017483 | D191: APPLE IPHONE 17 256GB | E191: APPLE IPHONE 17 256GB-SALVIA | F191: 7999 | G191: 5799 | H191: 7499 | I191: 7499 | J191: 7499 | K191: 7499 | L191: 7499 | M191: 7499 | N191: 7499 | O191: 7399 | P191: 7299 | Q191: 6499 | R191: 7399 | S191: 7299 | T191: 6499 | U191: 6499 | V191: 6499 | W191: 6399 | X191: 6399 | Y191: 5799 | Z191: 5799 | AA191: 5799 | AB191: 7499 | AC191: 7499 | AD191: 7499 | AE191: 7499 | AF191: 7399 | AG191: 7299 | AH191: 6499 | AI191: 6499 | AJ191: 6499 | AK191: 6499 | AL191: 5799 | AW191: 31.03.2026 | AX191: 5G
A192: Price Oferta | B192: 21X | C192: 4017484 | D192: APPLE IPHONE 17 512GB | E192: APPLE IPHONE 17 512GB-BRANCO | F192: 9499 | G192: 7699 | H192: 8199 | I192: 8199 | J192: 8099 | K192: 8099 | L192: 8099 | M192: 8099 | N192: 8099 | O192: 7999 | P192: 7899 | Q192: 7799 | R192: 7999 | S192: 7899 | T192: 7799 | U192: 7799 | V192: 7799 | W192: 7799 | X192: 7699 | Y192: 7499 | Z192: 7499 | AA192: 7499 | AW192: 31.03.2026 | AX192: 5G
A193: Price Oferta | B193: 21X | C193: 4017506 | D193: APPLE IPHONE 17 512GB | E193: APPLE IPHONE 17 512GB-PRETO | F193: 9499 | G193: 7699 | H193: 8199 | I193: 8199 | J193: 8099 | K193: 8099 | L193: 8099 | M193: 8099 | N193: 8099 | O193: 7999 | P193: 7899 | Q193: 7799 | R193: 7999 | S193: 7899 | T193: 7799 | U193: 7799 | V193: 7799 | W193: 7799 | X193: 7699 | Y193: 7499 | Z193: 7499 | AA193: 7499 | AW193: 31.03.2026 | AX193: 5G
A194: Price Oferta | B194: 21X | C194: 4017497 | D194: APPLE IPHONE 17 AIR 256GB | E194: APPLE IPHONE 17 AIR 256GB-PRETO | F194: 10499 | G194: 7299 | H194: 7799 | I194: 7799 | J194: 7699 | K194: 7699 | L194: 7699 | M194: 7699 | N194: 7699 | O194: 7599 | P194: 7499 | Q194: 7399 | R194: 7599 | S194: 7499 | T194: 7399 | U194: 7399 | V194: 7399 | W194: 7399 | X194: 7299 | Y194: 5999 | Z194: 5999 | AA194: 5999 | AW194: 31.03.2026 | AX194: 5G
A195: Price Oferta | B195: 21X | C195: 4017498 | D195: APPLE IPHONE 17 AIR 256GB | E195: APPLE IPHONE 17 AIR 256GB-BRANCO | F195: 10499 | G195: 7299 | H195: 7799 | I195: 7799 | J195: 7699 | K195: 7699 | L195: 7699 | M195: 7699 | N195: 7699 | O195: 7599 | P195: 7499 | Q195: 7399 | R195: 7599 | S195: 7499 | T195: 7399 | U195: 7399 | V195: 7399 | W195: 7399 | X195: 7299 | Y195: 5999 | Z195: 5999 | AA195: 5999 | AW195: 31.03.2026 | AX195: 5G
A196: Price Oferta | B196: 21X | C196: 4017499 | D196: APPLE IPHONE 17 AIR 256GB | E196: APPLE IPHONE 17 AIR 256GB-AZUL CEU | F196: 10499 | G196: 7299 | H196: 7799 | I196: 7799 | J196: 7699 | K196: 7699 | L196: 7699 | M196: 7699 | N196: 7699 | O196: 7599 | P196: 7499 | Q196: 7399 | R196: 7599 | S196: 7499 | T196: 7399 | U196: 7399 | V196: 7399 | W196: 7399 | X196: 7299 | Y196: 5999 | Z196: 5999 | AA196: 5999 | AW196: 31.03.2026 | AX196: 5G
A197: Price Oferta | B197: 21X | C197: 4017521 | D197: APPLE IPHONE 17 AIR 256GB | E197: APPLE IPHONE 17 AIR 256GB-DOURADO | F197: 10499 | G197: 7299 | H197: 7799 | I197: 7799 | J197: 7699 | K197: 7699 | L197: 7699 | M197: 7699 | N197: 7699 | O197: 7599 | P197: 7499 | Q197: 7399 | R197: 7599 | S197: 7499 | T197: 7399 | U197: 7399 | V197: 7399 | W197: 7399 | X197: 7299 | Y197: 5999 | Z197: 5999 | AA197: 5999 | AW197: 31.03.2026 | AX197: 5G
A198: Price Oferta | B198: 21X | C198: 4017496 | D198: APPLE IPHONE 17 AIR 512GB | E198: APPLE IPHONE 17 AIR 512GB-BRANCO | F198: 11999 | G198: 8399 | H198: 9099 | I198: 9099 | J198: 8999 | K198: 8999 | L198: 8999 | M198: 8999 | N198: 8999 | O198: 8899 | P198: 8799 | Q198: 8499 | R198: 8899 | S198: 8799 | T198: 8499 | U198: 8499 | V198: 8499 | W198: 8499 | X198: 8399 | Y198: 7799 | Z198: 7799 | AA198: 7799 | AW198: 31.03.2026 | AX198: 5G
A199: Price Oferta | B199: 21X | C199: 4017519 | D199: APPLE IPHONE 17 AIR 512GB | E199: APPLE IPHONE 17 AIR 512GB-DOURADO | F199: 11999 | G199: 8399 | H199: 9099 | I199: 9099 | J199: 8999 | K199: 8999 | L199: 8999 | M199: 8999 | N199: 8999 | O199: 8899 | P199: 8799 | Q199: 8499 | R199: 8899 | S199: 8799 | T199: 8499 | U199: 8499 | V199: 8499 | W199: 8499 | X199: 8399 | Y199: 7799 | Z199: 7799 | AA199: 7799 | AW199: 31.03.2026 | AX199: 5G
A200: Price Oferta | B200: 21X | C200: 4017525 | D200: APPLE IPHONE 17 AIR 512GB | E200: APPLE IPHONE 17 AIR 512GB-PRETO | F200: 11999 | G200: 8399 | H200: 9099 | I200: 9099 | J200: 8999 | K200: 8999 | L200: 8999 | M200: 8999 | N200: 8999 | O200: 8899 | P200: 8799 | Q200: 8499 | R200: 8899 | S200: 8799 | T200: 8499 | U200: 8499 | V200: 8499 | W200: 8499 | X200: 8399 | Y200: 7799 | Z200: 7799 | AA200: 7799 | AW200: 31.03.2026 | AX200: 5G
A201: Price Oferta | B201: 21X | C201: 4017518 | D201: APPLE IPHONE 17 AIR 512GB | E201: APPLE IPHONE 17 AIR 512GB-AZUL CEU | F201: 11999 | G201: 8399 | H201: 9099 | I201: 9099 | J201: 8999 | K201: 8999 | L201: 8999 | M201: 8999 | N201: 8999 | O201: 8899 | P201: 8799 | Q201: 8499 | R201: 8899 | S201: 8799 | T201: 8499 | U201: 8499 | V201: 8499 | W201: 8499 | X201: 8399 | Y201: 7799 | Z201: 7799 | AA201: 7799 | AW201: 31.03.2026 | AX201: 5G
A202: Price Oferta | B202: 21X | C202: 4017487 | D202: APPLE IPHONE 17 PRO 256GB | E202: APPLE IPHONE 17 PRO 256GB-AZUL INTENSO | F202: 11499 | G202: 8799 | H202: 10799 | I202: 10799 | J202: 10799 | K202: 10799 | L202: 10799 | M202: 10799 | N202: 10799 | O202: 10699 | P202: 10599 | Q202: 9799 | R202: 10699 | S202: 10599 | T202: 9799 | U202: 9799 | V202: 9799 | W202: 9699 | X202: 9699 | Y202: 8799 | Z202: 8799 | AA202: 8799 | AB202: 10799 | AC202: 10799 | AD202: 10799 | AE202: 10799 | AF202: 10699 | AG202: 10599 | AH202: 9799 | AI202: 9799 | AJ202: 9799 | AK202: 9799 | AL202: 8799 | AW202: 31.03.2026 | AX202: 5G
A203: Price Oferta | B203: 21X | C203: 4017510 | D203: APPLE IPHONE 17 PRO 256GB | E203: APPLE IPHONE 17 PRO 256GB-LARANJA COSMIC | F203: 11499 | G203: 8799 | H203: 10799 | I203: 10799 | J203: 10799 | K203: 10799 | L203: 10799 | M203: 10799 | N203: 10799 | O203: 10699 | P203: 10599 | Q203: 9799 | R203: 10699 | S203: 10599 | T203: 9799 | U203: 9799 | V203: 9799 | W203: 9699 | X203: 9699 | Y203: 8799 | Z203: 8799 | AA203: 8799 | AB203: 10799 | AC203: 10799 | AD203: 10799 | AE203: 10799 | AF203: 10699 | AG203: 10599 | AH203: 9799 | AI203: 9799 | AJ203: 9799 | AK203: 9799 | AL203: 8799 | AW203: 31.03.2026 | AX203: 5G
A204: Price Oferta | B204: 21X | C204: 4017513 | D204: APPLE IPHONE 17 PRO 256GB | E204: APPLE IPHONE 17 PRO 256GB-PRATEADO | F204: 11499 | G204: 8799 | H204: 10799 | I204: 10799 | J204: 10799 | K204: 10799 | L204: 10799 | M204: 10799 | N204: 10799 | O204: 10699 | P204: 10599 | Q204: 9799 | R204: 10699 | S204: 10599 | T204: 9799 | U204: 9799 | V204: 9799 | W204: 9699 | X204: 9699 | Y204: 8799 | Z204: 8799 | AA204: 8799 | AB204: 10799 | AC204: 10799 | AD204: 10799 | AE204: 10799 | AF204: 10699 | AG204: 10599 | AH204: 9799 | AI204: 9799 | AJ204: 9799 | AK204: 9799 | AL204: 8799 | AW204: 31.03.2026 | AX204: 5G
A205: Price Oferta | B205: 21X | C205: 4017488 | D205: APPLE IPHONE 17 PRO 512GB | E205: APPLE IPHONE 17 PRO 512GB-AZUL INTENSO | F205: 12999 | G205: 9999 | H205: 12199 | I205: 12199 | J205: 12199 | K205: 12199 | L205: 12199 | M205: 12199 | N205: 12199 | O205: 12099 | P205: 11999 | Q205: 11199 | R205: 12099 | S205: 11999 | T205: 11199 | U205: 11199 | V205: 11199 | W205: 11099 | X205: 11099 | Y205: 9999 | Z205: 9999 | AA205: 9899 | AW205: 31.03.2026 | AX205: 5G
A206: Price Oferta | B206: 21X | C206: 4017508 | D206: APPLE IPHONE 17 PRO 512GB | E206: APPLE IPHONE 17 PRO 512GB-LARANJA COSMIC | F206: 12999 | G206: 9999 | H206: 12199 | I206: 12199 | J206: 12199 | K206: 12199 | L206: 12199 | M206: 12199 | N206: 12199 | O206: 12099 | P206: 11999 | Q206: 11199 | R206: 12099 | S206: 11999 | T206: 11199 | U206: 11199 | V206: 11199 | W206: 11099 | X206: 11099 | Y206: 9999 | Z206: 9999 | AA206: 9899 | AW206: 31.03.2026 | AX206: 5G
A207: Price Oferta | B207: 21X | C207: 4017489 | D207: APPLE IPHONE 17 PRO 512GB | E207: APPLE IPHONE 17 PRO 512GB-PRATEADO | F207: 12999 | G207: 9999 | H207: 12199 | I207: 12199 | J207: 12199 | K207: 12199 | L207: 12199 | M207: 12199 | N207: 12199 | O207: 12099 | P207: 11999 | Q207: 11199 | R207: 12099 | S207: 11999 | T207: 11199 | U207: 11199 | V207: 11199 | W207: 11099 | X207: 11099 | Y207: 9999 | Z207: 9999 | AA207: 9899 | AW207: 31.03.2026 | AX207: 5G
A208: Price Oferta | B208: 21X | C208: 4017493 | D208: APPLE IPHONE 17 PRO MAX 256GB | E208: APPLE IPHONE 17 PRO MAX 256GB- AZUL INTE | F208: 12499 | G208: 9799 | H208: 11699 | I208: 11699 | J208: 11699 | K208: 11699 | L208: 11699 | M208: 11699 | N208: 11699 | O208: 11599 | P208: 11499 | Q208: 10699 | R208: 11599 | S208: 11499 | T208: 10699 | U208: 10699 | V208: 10699 | W208: 10599 | X208: 10599 | Y208: 9799 | Z208: 9799 | AA208: 9799 | AB208: 11699 | AC208: 11699 | AD208: 11699 | AE208: 11699 | AF208: 11599 | AG208: 11499 | AH208: 10699 | AI208: 10699 | AJ208: 10699 | AK208: 10699 | AL208: 9799 | AW208: 31.03.2026 | AX208: 5G
A209: Price Oferta | B209: 21X | C209: 4017494 | D209: APPLE IPHONE 17 PRO MAX 256GB | E209: APPLE IPHONE 17 PRO MAX 256GB-PRATEADO | F209: 12499 | G209: 9799 | H209: 11699 | I209: 11699 | J209: 11699 | K209: 11699 | L209: 11699 | M209: 11699 | N209: 11699 | O209: 11599 | P209: 11499 | Q209: 10699 | R209: 11599 | S209: 11499 | T209: 10699 | U209: 10699 | V209: 10699 | W209: 10599 | X209: 10599 | Y209: 9799 | Z209: 9799 | AA209: 9799 | AB209: 11699 | AC209: 11699 | AD209: 11699 | AE209: 11699 | AF209: 11599 | AG209: 11499 | AH209: 10699 | AI209: 10699 | AJ209: 10699 | AK209: 10699 | AL209: 9799 | AW209: 31.03.2026 | AX209: 5G
A210: Price Oferta | B210: 21X | C210: 4017514 | D210: APPLE IPHONE 17 PRO MAX 256GB | E210: APPLE IPHONE 17 PRO MAX 256GB-LARANJA CO | F210: 12499 | G210: 9799 | H210: 11699 | I210: 11699 | J210: 11699 | K210: 11699 | L210: 11699 | M210: 11699 | N210: 11699 | O210: 11599 | P210: 11499 | Q210: 10699 | R210: 11599 | S210: 11499 | T210: 10699 | U210: 10699 | V210: 10699 | W210: 10599 | X210: 10599 | Y210: 9799 | Z210: 9799 | AA210: 9799 | AB210: 11699 | AC210: 11699 | AD210: 11699 | AE210: 11699 | AF210: 11599 | AG210: 11499 | AH210: 10699 | AI210: 10699 | AJ210: 10699 | AK210: 10699 | AL210: 9799 | AW210: 31.03.2026 | AX210: 5G
A211: Price Oferta | B211: 21X | C211: 4017503 | D211: APPLE IPHONE 17 PRO MAX 512GB | E211: APPLE IPHONE 17 PRO MAX 512GB-LARANJA CO | F211: 13999 | G211: 10999 | H211: 13099 | I211: 13099 | J211: 13099 | K211: 13099 | L211: 13099 | M211: 13099 | N211: 13099 | O211: 12999 | P211: 12899 | Q211: 12099 | R211: 12999 | S211: 12899 | T211: 12099 | U211: 12099 | V211: 12099 | W211: 11999 | X211: 11999 | Y211: 10999 | Z211: 10999 | AA211: 10899 | AW211: 31.03.2026 | AX211: 5G
A212: Price Oferta | B212: 21X | C212: 4017520 | D212: APPLE IPHONE 17 PRO MAX 512GB | E212: APPLE IPHONE 17 PRO MAX 512GB-AZUL INTEN | F212: 13999 | G212: 10999 | H212: 13099 | I212: 13099 | J212: 13099 | K212: 13099 | L212: 13099 | M212: 13099 | N212: 13099 | O212: 12999 | P212: 12899 | Q212: 12099 | R212: 12999 | S212: 12899 | T212: 12099 | U212: 12099 | V212: 12099 | W212: 11999 | X212: 11999 | Y212: 10999 | Z212: 10999 | AA212: 10899 | AW212: 31.03.2026 | AX212: 5G
A213: Price Oferta | B213: 21X | C213: 4017522 | D213: APPLE IPHONE 17 PRO MAX 512GB | E213: APPLE IPHONE 17 PRO MAX 512GB-PRATEADO | F213: 13999 | G213: 10999 | H213: 13099 | I213: 13099 | J213: 13099 | K213: 13099 | L213: 13099 | M213: 13099 | N213: 13099 | O213: 12999 | P213: 12899 | Q213: 12099 | R213: 12999 | S213: 12899 | T213: 12099 | U213: 12099 | V213: 12099 | W213: 11999 | X213: 11999 | Y213: 10999 | Z213: 10999 | AA213: 10899 | AW213: 31.03.2026 | AX213: 5G
A214: Price Oferta | B214: 21X | C214: 4017020 | D214: JOVI V50 512GB | E214: JOVI V50 512GB-VERMELHO | F214: 4999 | G214: 2399 | H214: 3399 | I214: 3399 | J214: 3299 | K214: 3299 | L214: 3299 | M214: 3299 | N214: 3299 | O214: 3249 | P214: 3199 | Q214: 2499 | R214: 3249 | S214: 3199 | T214: 2499 | U214: 2499 | V214: 2499 | W214: 2499 | X214: 2399 | Y214: 1799 | Z214: 1799 | AA214: 1799 | AW214: 31.03.2026 | AX214: 5G
A215: Price Oferta | B215: 21X | C215: 4017022 | D215: JOVI V50 512GB | E215: JOVI V50 512GB-PRETO | F215: 4999 | G215: 2399 | H215: 3399 | I215: 3399 | J215: 3299 | K215: 3299 | L215: 3299 | M215: 3299 | N215: 3299 | O215: 3249 | P215: 3199 | Q215: 2499 | R215: 3249 | S215: 3199 | T215: 2499 | U215: 2499 | V215: 2499 | W215: 2499 | X215: 2399 | Y215: 1799 | Z215: 1799 | AA215: 1799 | AW215: 31.03.2026 | AX215: 5G
A216: Price Oferta | B216: 21X | C216: 4017045 | D216: JOVI V50 LITE 256GB | E216: JOVI V50 LITE 256GB-OURO | F216: 3199 | G216: 999 | H216: 1919 | I216: 1919 | J216: 1799 | K216: 1799 | L216: 1799 | M216: 1799 | N216: 1799 | O216: 1699 | P216: 1599 | Q216: 999 | R216: 1699 | S216: 1599 | T216: 999 | U216: 999 | V216: 999 | W216: 999 | X216: 999 | Y216: 799 | Z216: 799 | AA216: 799 | AW216: 31.03.2026 | AX216: 5G
A217: Price Oferta | B217: 21X | C217: 4017047 | D217: JOVI V50 LITE 256GB | E217: JOVI V50 LITE 256GB-PRETO | F217: 3199 | G217: 999 | H217: 1919 | I217: 1919 | J217: 1799 | K217: 1799 | L217: 1799 | M217: 1799 | N217: 1799 | O217: 1699 | P217: 1599 | Q217: 999 | R217: 1699 | S217: 1599 | T217: 999 | U217: 999 | V217: 999 | W217: 999 | X217: 999 | Y217: 799 | Z217: 799 | AA217: 799 | AW217: 31.03.2026 | AX217: 5G
...

Sheet ACESSÓRIOS REV
B1: TABELA DE PREÇOS - ACESSÓRIOS
B3: CANAL: | C3: REVENDAS
B4: Inclusão de Preço
B5: Alteração de Preço
C6: DATA INÍCIO: | D6: =REV!D11 -> 46092 | AB6: TIM FIBRA
B7: CATEGORIA MKT | C7: CÓDIGO | D7: DESCRIÇÃO COMERCIAL | E7: DESCRIÇÃO SAP | F7: PRÉ | G7: PREÇO BASE FATURAMENTO RETAIL | H7: CONTROLE NÃO FIDELIZADO - TODOS (Fatura / Express) | I7: PÓS PAGO NÃO FIDELIZADO - VIDE ABA DE REGRAS | J7: TIM CONTROLE | K7: TIM CONTROLE PLUS | L7: TIM CONTROLE PREMIUM | M7: TIM CONTROLE SMART | N7: TIM CONTROLE REDES SOCIAIS | O7: TIM BLACK | P7: TIM BLACK PLUS | Q7: TIM BLACK PREMIUM | R7: TIM BLACK A (15GB) | S7: TIM BLACK B (20GB) | T7: TIM BLACK C (25GB) | U7: TIM BLACK C ULTRA | V7: TIM BLACK FAMÍLIA | W7: TIM BLACK FAMÍLIA A ONE | X7: TIM BLACK FAMÍLIA PLUS | Y7: TIM BLACK FAMÍLIA PREMIUM | Z7: TIM BLACK FAMÍLIA C ONE | AA7: TIM BLACK FAMÍLIA VIP | AB7: TIM Fibra 300M 24 | AC7: TIM Fibra 400M 24 | AD7: TIM Fibra 500M 24 - 2 | AE7: TIM Fibra 600M 24 - 2 | AF7: TIM Fibra 600M P 24 - 2 | AG7: TIM Fibra 600M M 24 - 2 | AH7: TIM Fibra 600M GP 25 | AI7: TIM Fibra 1GB 24 | AJ7: TIM Fibra 1GB P 24 | AK7: TIM Fibra 1GB M 24 | AL7: TIM Fibra 2GB 24 | AM7: DATA FIM DA OFERTA
B8: SMARTHOME | C8: 4014927 | D8: BALANCA INTELIGENTE GEONAV | E8: BALANCA INTELIGENTE GEONAV-BRANCO | F8: 199 | G8: 199 | AB8: 169 | AC8: 169 | AD8: 169 | AE8: 169 | AF8: 169 | AG8: 169 | AH8: 169 | AI8: 169 | AJ8: 169 | AK8: 169 | AL8: 169 | AM8: 31.12.9999
B9: GAMER | C9: 4016500 | D9: BASE DE CARREGAMENTO SONY DUALSENSE | E9: BASE DE CARREGAMENTO SONY DUALSENSE-BRAN | F9: 199 | G9: 199 | AM9: 31.12.9999
B10: MUSICA | C10: 4014444 | D10: CAIXA DE SOM BT JBL CHARGE 5 | E10: CAIXA DE SOM BT JBL CHARGE 5-PRETO | F10: 799 | G10: 799 | H10: 799 | I10: 799 | J10: 749 | K10: 749 | L10: 749 | M10: 749 | N10: 749 | O10: 699 | P10: 599 | Q10: 449 | R10: 699 | S10: 599 | T10: 449 | U10: 449 | V10: 449 | W10: 449 | X10: 449 | Y10: 449 | Z10: 449 | AA10: 449 | AM10: 31.12.9999
B11: MUSICA | C11: 4017142 | D11: CAIXA DE SOM BT JBL CHARGE 6 | E11: CAIXA DE SOM BT JBL CHARGE 6-AZUL | F11: 999 | G11: 999 | H11: 999 | I11: 999 | J11: 949 | K11: 949 | L11: 949 | M11: 949 | N11: 949 | O11: 899 | P11: 799 | Q11: 599 | R11: 899 | S11: 799 | T11: 599 | U11: 599 | V11: 599 | W11: 599 | X11: 549 | Y11: 549 | Z11: 549 | AA11: 549 | AM11: 31.12.9999
B12: MUSICA | C12: 4014958 | D12: CAIXA DE SOM BT JBL FLIP 6 | E12: CAIXA DE SOM BT JBL FLIP 6-PRETO | F12: 399 | G12: 399 | H12: 399 | I12: 399 | J12: 349 | K12: 349 | L12: 349 | M12: 349 | N12: 349 | O12: 299 | P12: 299 | Q12: 249 | R12: 299 | S12: 249 | T12: 249 | U12: 249 | V12: 249 | W12: 249 | X12: 249 | Y12: 249 | Z12: 249 | AA12: 249 | AM12: 31.12.9999
B13: MÚSICA | C13: 4017062 | D13: CAIXA DE SOM BT JBL FLIP 7 | E13: CAIXA DE SOM BT JBL FLIP 7-PRETO | F13: 899 | G13: 899 | H13: 899 | I13: 899 | J13: 849 | K13: 849 | L13: 849 | M13: 849 | N13: 849 | O13: 799 | P13: 799 | Q13: 699 | R13: 799 | S13: 699 | T13: 499 | U13: 499 | V13: 499 | W13: 499 | X13: 499 | Y13: 499 | Z13: 499 | AA13: 499 | AM13: 31.12.9999
B14: MUSICA | C14: 4016330 | D14: CAIXA DE SOM BT JBL GO4 | E14: CAIXA DE SOM BT JBL GO4-PRETO | F14: 299 | G14: 199 | H14: 299 | I14: 299 | J14: 249 | K14: 249 | L14: 249 | M14: 249 | N14: 249 | O14: 199 | P14: 199 | Q14: 199 | R14: 199 | S14: 199 | T14: 199 | U14: 199 | V14: 199 | W14: 199 | X14: 199 | Y14: 199 | Z14: 199 | AA14: 199 | AB14: 249 | AC14: 249 | AD14: 249 | AE14: 249 | AF14: 249 | AG14: 249 | AH14: 249 | AI14: 249 | AJ14: 249 | AK14: 249 | AL14: 249 | AM14: 31.12.9999
B15: MUSICA | C15: 4015270 | D15: CAIXA DE SOM JBL BOOMBOX 3 | E15: CAIXA DE SOM JBL BOOMBOX 3-PRETO | F15: 2499 | G15: 999 | H15: 2499 | I15: 2499 | J15: 2449 | K15: 2449 | L15: 2449 | M15: 2449 | N15: 2449 | O15: 2399 | P15: 2299 | Q15: 1299 | R15: 2399 | S15: 2299 | T15: 1299 | U15: 1299 | V15: 1299 | W15: 1299 | X15: 1299 | Y15: 999 | Z15: 999 | AA15: 949 | AB15: 2449 | AC15: 2449 | AD15: 2449 | AE15: 2449 | AF15: 2399 | AG15: 2399 | AH15: 1299 | AI15: 1299 | AJ15: 1299 | AK15: 1299 | AL15: 999 | AM15: 31.12.9999
B16: MUSICA | C16: 4015688 | D16: CAIXA DE SOM JBL BOOMBOX 3 | E16: CAIXA DE SOM JBL BOOMBOX 3-PRETO AM | F16: 2499 | G16: 999 | H16: 2499 | I16: 2499 | J16: 2449 | K16: 2449 | L16: 2449 | M16: 2449 | N16: 2449 | O16: 2399 | P16: 2299 | Q16: 1299 | R16: 2399 | S16: 2299 | T16: 1299 | U16: 1299 | V16: 1299 | W16: 1299 | X16: 1299 | Y16: 999 | Z16: 999 | AA16: 949 | AB16: 2449 | AC16: 2449 | AD16: 2449 | AE16: 2449 | AF16: 2399 | AG16: 2399 | AH16: 1299 | AI16: 1299 | AJ16: 1299 | AK16: 1299 | AL16: 999 | AM16: 31.12.9999
B17: MUSICA | C17: 4016341 | D17: CAIXA DE SOM JBL ENCORE ESSENTIAL | E17: CAIXA DE SOM JBL ENCORE ESSENTIAL-PRE AM | F17: 1199 | G17: 1199 | H17: 1199 | I17: 1199 | J17: 1149 | K17: 1149 | L17: 1149 | M17: 1149 | N17: 1149 | O17: 1099 | P17: 1099 | Q17: 999 | R17: 1099 | S17: 999 | T17: 799 | U17: 799 | V17: 799 | W17: 799 | X17: 699 | Y17: 649 | Z17: 649 | AA17: 649 | AM17: 31.12.9999
B18: MUSICA | C18: 4015273 | D18: CAIXA DE SOM JBL ENCORE ESSENTIAL | E18: CAIXA DE SOM JBL ENCORE ESSENTIAL-PRETO | F18: 1199 | G18: 1199 | H18: 1199 | I18: 1199 | J18: 1149 | K18: 1149 | L18: 1149 | M18: 1149 | N18: 1149 | O18: 1099 | P18: 1099 | Q18: 999 | R18: 1099 | S18: 999 | T18: 799 | U18: 799 | V18: 799 | W18: 799 | X18: 699 | Y18: 649 | Z18: 649 | AA18: 649 | AM18: 31.12.9999
B19: MUSICA | C19: 4017250 | D19: CAIXA DE SOM JBL ENCORE ESSENTIAL 2 | E19: CAIXA DE SOM JBL ENCORE ESSENTIAL 2-PRET | F19: 1699 | G19: 999 | H19: 1699 | I19: 1699 | J19: 1649 | K19: 1649 | L19: 1649 | M19: 1649 | N19: 1649 | O19: 1599 | P19: 1499 | Q19: 999 | R19: 1599 | S19: 1499 | T19: 999 | U19: 999 | V19: 999 | W19: 999 | X19: 999 | Y19: 899 | Z19: 899 | AA19: 899 | AB19: 1649 | AC19: 1649 | AD19: 1649 | AE19: 1649 | AF19: 1599 | AG19: 1599 | AH19: 1599 | AI19: 999 | AJ19: 999 | AK19: 999 | AL19: 899 | AM19: 31.12.9999
B20: CAIXA DE SOM | C20: 4017581 | D20: CAIXA DE SOM JBL GO ESSENTIAL 2 | E20: CAIXA DE SOM JBL GO ESSENTIAL 2-PRETO | F20: 219 | G20: 219 | H20: 219 | I20: 219 | J20: 149 | K20: 149 | L20: 149 | M20: 149 | N20: 149 | O20: 99 | P20: 99 | Q20: 99 | R20: 99 | S20: 99 | T20: 99 | U20: 99 | V20: 99 | W20: 99 | X20: 99 | Y20: 99 | Z20: 99 | AA20: 99 | AM20: 31.12.9999
B21: MUSICA | C21: 4016351 | D21: CAIXA DE SOM JBL XTREME 4 | E21: CAIXA DE SOM JBL XTREME 4 | F21: 999 | G21: 999 | H21: 999 | I21: 999 | J21: 949 | K21: 949 | L21: 949 | M21: 949 | N21: 949 | O21: 899 | P21: 899 | Q21: 799 | R21: 899 | S21: 799 | T21: 599 | U21: 599 | V21: 599 | W21: 599 | X21: 549 | Y21: 549 | Z21: 549 | AA21: 549 | AM21: 31.12.9999
B22: BASICO | C22: 4016004 | D22: CAPA CLEAR GALAXY S24 | E22: CAPA CLEAR GALAXY S24-TRANSPARENTE | F22: 129 | G22: 129 | AM22: 31.12.9999
B23: BASICO | C23: 4016005 | D23: CAPA CLEAR GALAXY S24 PLUS | E23: CAPA CLEAR GALAXY S24 PLUS-TRANSPARENTE | F23: 129 | G23: 129 | AM23: 31.12.9999
B24: BASICO | C24: 4016006 | D24: CAPA CLEAR GALAXY S24 ULTRA | E24: CAPA CLEAR GALAXY S24 ULTRA-TRANSPARENTE | F24: 129 | G24: 129 | AM24: 31.12.9999
B25: BASICO | C25: 4015729 | D25: CAPA PROTECTIC COVER GALAXY S23 FE | E25: CAPA PROTECTIC COVER GALAXY S23 FE-TRANS | F25: 10 | G25: 10 | AM25: 31.12.9999
B26: BASICO | C26: 4013975 | D26: CARREGADOR APPLE USB-C 20W | E26: CARREGADOR APPLE USB-C 20W-BRANCO | F26: 219 | G26: 219 | AM26: 31.12.9999
B27: CARREGADOR | C27: 4016254 | D27: CARREGADOR APPLE USB-C 20W 2024 | E27: CARREGADOR APPLE USB-C 20W 2024-BRANCO | F27: 219 | G27: 219 | AM27: 31.12.9999
B28: GAMER | C28: 4016340 | D28: CONTROLE SEM FIO PS5 DUALSENSE | E28: CONTROLE SEM FIO PS5 DUALSENSE-BRANCO | F28: 499 | G28: 399 | H28: 499 | I28: 499 | J28: 449 | K28: 449 | L28: 449 | M28: 449 | N28: 449 | O28: 399 | P28: 299 | Q28: 299 | R28: 399 | S28: 299 | T28: 299 | U28: 299 | V28: 299 | W28: 299 | X28: 299 | Y28: 299 | Z28: 299 | AA28: 299 | AB28: 449 | AC28: 449 | AD28: 449 | AE28: 449 | AF28: 399 | AG28: 399 | AH28: 299 | AI28: 299 | AJ28: 299 | AK28: 299 | AL28: 299 | AM28: 31.12.9999
B29: GAMER | C29: 4016494 | D29: CONTROLE SEM FIO PS5 DUALSENSE | E29: CONTROLE SEM FIO PS5 DUALSENSE-PRETO | F29: 499 | G29: 399 | H29: 499 | I29: 499 | J29: 449 | K29: 449 | L29: 449 | M29: 449 | N29: 449 | O29: 399 | P29: 299 | Q29: 299 | R29: 399 | S29: 299 | T29: 299 | U29: 299 | V29: 299 | W29: 299 | X29: 299 | Y29: 299 | Z29: 299 | AA29: 299 | AB29: 449 | AC29: 449 | AD29: 449 | AE29: 449 | AF29: 399 | AG29: 399 | AH29: 299 | AI29: 299 | AJ29: 299 | AK29: 299 | AL29: 299 | AM29: 31.12.9999
B30: GAMER | C30: 4017140 | D30: CONTROLE SEM FIO PS5 DUALSENSE | E30: CONTROLE SEM FIO PS5 DUALSENSE-CAMUFLADO | F30: 499 | G30: 399 | H30: 499 | I30: 499 | J30: 449 | K30: 449 | L30: 449 | M30: 449 | N30: 449 | O30: 399 | P30: 299 | Q30: 299 | R30: 399 | S30: 299 | T30: 299 | U30: 299 | V30: 299 | W30: 299 | X30: 299 | Y30: 299 | Z30: 299 | AA30: 299 | AB30: 449 | AC30: 449 | AD30: 449 | AE30: 449 | AF30: 399 | AG30: 399 | AH30: 299 | AI30: 299 | AJ30: 299 | AK30: 299 | AL30: 299 | AM30: 31.12.9999
B31: GAMER | C31: 4015506 | D31: CONTROLE SEM FIO XBOX SERIES | E31: CONTROLE SEM FIO XBOX SERIES-BRANCO | F31: 299 | G31: 299 | H31: 299 | I31: 299 | J31: 249 | K31: 249 | L31: 249 | M31: 249 | N31: 249 | O31: 199 | P31: 199 | Q31: 199 | R31: 199 | S31: 199 | T31: 199 | U31: 199 | V31: 199 | W31: 199 | X31: 199 | Y31: 199 | Z31: 199 | AA31: 199 | AM31: 31.12.9999
B32: GADGETS | C32: 4015637 | D32: ESTABILIZADOR DJI OSMO MOBILE SE | E32: ESTABILIZADOR DJI OSMO MOBILE SE-CINZA | F32: 999 | G32: 999 | H32: 999 | I32: 999 | J32: 949 | K32: 949 | L32: 949 | M32: 949 | N32: 949 | O32: 899 | P32: 799 | Q32: 599 | R32: 899 | S32: 799 | T32: 599 | U32: 599 | V32: 599 | W32: 599 | X32: 549 | Y32: 549 | Z32: 549 | AA32: 549 | AM32: 31.12.9999
B33: GADGETS | C33: 4015591 | D33: FILME INSTAX MINI 10 FOTOS | E33: FILME INSTAX MINI 10 FOTOS-BRANCO | F33: 49 | G33: 49 | AM33: 31.12.9999
B34: GADGETS | C34: 4015592 | D34: FILME INSTAX MINI 20 FOTOS | E34: FILME INSTAX MINI 20 FOTOS-BRANCO | F34: 89 | G34: 89 | AM34: 31.12.9999
B35: MUSICA | C35: 4013141 | D35: FONE APPLE EARPODS | E35: FONE APPLE EARPODS-BRANCO | F35: 199 | G35: 199 | AM35: 31.12.9999
B36: MUSICA | C36: 4015880 | D36: FONE APPLE EARPODS USBC | E36: FONE APPLE EARPODS USBC-BRANCO | F36: 199 | G36: 199 | AM36: 31.12.9999
B37: MUSICA | C37: 4016971 | D37: FONE APPLE EARPODS USBC 2024 | E37: FONE APPLE EARPODS USBC 2024-BRANCO | F37: 199 | G37: 199 | AM37: 31.12.9999
B38: MUSICA | C38: 4013617 | D38: FONE JBL TUNE 110 | E38: FONE JBL TUNE 110-PRETO | F38: 99 | G38: 99 | AM38: 31.12.9999
B39: MUSICA | C39: 4014261 | D39: FONE JBL TUNE 125BT | E39: FONE JBL TUNE 125BT-PRETO | F39: 149 | G39: 149 | AM39: 31.12.9999
B40: MUSICA | C40: 4015696 | D40: FONE SAMSUNG GALAXY BUDS FE | E40: FONE SAMSUNG GALAXY BUDS FE-GRAFITE | F40: 449 | G40: 449 | H40: 449 | I40: 449 | J40: 399 | K40: 399 | L40: 399 | M40: 399 | N40: 399 | O40: 349 | P40: 249 | Q40: 249 | R40: 349 | S40: 249 | T40: 249 | U40: 249 | V40: 249 | W40: 249 | X40: 249 | Y40: 249 | Z40: 249 | AA40: 249 | AB40: =$H40-70 -> 379 | AC40: =$H40-70 -> 379 | AD40: =$H40-70 -> 379 | AE40: =$H40-100 -> 349 | AF40: =$H40-100 -> 349 | AG40: =$H40-100 -> 349 | AH40: 249 | AI40: =$H40-200 -> 249 | AJ40: =$H40-200 -> 249 | AK40: =$H40-200 -> 249 | AL40: =$H40-200 -> 249 | AM40: 31.12.9999
B41: FONE DE OUVIDO | C41: 4016533 | D41: FONE TWS GALAXY BUDS 3 2024 | E41: FONE TWS GALAXY BUDS 3 2024-BRANCO | F41: 799 | G41: 799 | H41: 799 | I41: 799 | J41: 749 | K41: 749 | L41: 749 | M41: 749 | N41: 749 | O41: 699 | P41: 599 | Q41: 399 | R41: 699 | S41: 599 | T41: 399 | U41: 399 | V41: 399 | W41: 399 | X41: 399 | Y41: 399 | Z41: 399 | AA41: 399 | AM41: 31.12.9999
B42: FONE DE OUVIDO | C42: 4016531 | D42: FONE TWS GALAXY BUDS 3 2024 | E42: FONE TWS GALAXY BUDS 3 2024-CINZA | F42: 799 | G42: 799 | H42: 799 | I42: 799 | J42: 749 | K42: 749 | L42: 749 | M42: 749 | N42: 749 | O42: 699 | P42: 599 | Q42: 399 | R42: 699 | S42: 599 | T42: 399 | U42: 399 | V42: 399 | W42: 399 | X42: 399 | Y42: 399 | Z42: 399 | AA42: 399 | AM42: 31.12.9999
B43: FONE DE OUVIDO | C43: 4017339 | D43: FONE TWS GALAXY BUDS 3 CORE | E43: FONE TWS GALAXY BUDS 3 CORE-PRETO | F43: 299 | G43: 299 | H43: 299 | I43: 299 | J43: 249 | K43: 249 | L43: 249 | M43: 249 | N43: 249 | O43: 199 | P43: 199 | Q43: 199 | R43: 199 | S43: 199 | T43: 199 | U43: 199 | V43: 199 | W43: 199 | X43: 199 | Y43: 199 | Z43: 199 | AA43: 199 | AM43: 31.12.9999
B44: FONE DE OUVIDO | C44: 4017404 | D44: FONE TWS GALAXY BUDS 3 FE | E44: FONE TWS GALAXY BUDS 3 FE-PRETO | F44: 1099 | G44: 1099 | H44: 1099 | I44: 1099 | J44: 1049 | K44: 1049 | L44: 1049 | M44: 1049 | N44: 1049 | O44: 999 | P44: 899 | Q44: 699 | R44: 999 | S44: 899 | T44: 699 | U44: 699 | V44: 699 | W44: 699 | X44: 599 | Y44: 599 | Z44: 599 | AA44: 599 | AM44: 31.12.9999
B45: FONE DE OUVIDO | C45: 4016537 | D45: FONE TWS GALAXY BUDS 3 PRO 2024 | E45: FONE TWS GALAXY BUDS 3 PRO 2024-CINZA | F45: 1199 | G45: 1199 | H45: 1199 | I45: 1199 | J45: 1149 | K45: 1149 | L45: 1149 | M45: 1149 | N45: 1149 | O45: 1099 | P45: 999 | Q45: 799 | R45: 1099 | S45: 999 | T45: 799 | U45: 799 | V45: 799 | W45: 799 | X45: 799 | Y45: 799 | Z45: 799 | AA45: 799 | AM45: 31.12.9999
B46: MUSICA | C46: 4016523 | D46: FONE TWS GALAXY BUDS FE 2024 | E46: FONE TWS GALAXY BUDS FE 2024-GRAFITE | F46: 449 | G46: 449 | H46: 449 | I46: 449 | J46: 399 | K46: 399 | L46: 399 | M46: 399 | N46: 399 | O46: 349 | P46: 249 | Q46: 249 | R46: 349 | S46: 249 | T46: 249 | U46: 249 | V46: 249 | W46: 249 | X46: 249 | Y46: 249 | Z46: 249 | AA46: 249 | AB46: =$H46-70 -> 379 | AC46: =$H46-70 -> 379 | AD46: =$H46-70 -> 379 | AE46: =$H46-100 -> 349 | AF46: =$H46-100 -> 349 | AG46: =$H46-100 -> 349 | AH46: 249 | AI46: =$H46-200 -> 249 | AJ46: =$H46-200 -> 249 | AK46: =$H46-200 -> 249 | AL46: =$H46-200 -> 249 | AM46: 31.12.9999
B47: FONE DE OUVIDO | C47: 4016310 | D47: FONE TWS MOTO BUDS | E47: FONE TWS MOTO BUDS-AZUL ESCURO | F47: 399 | G47: 399 | H47: 399 | I47: 399 | J47: 349 | K47: 349 | L47: 349 | M47: 349 | N47: 349 | O47: 299 | P47: 299 | Q47: 249 | R47: 299 | S47: 249 | T47: 249 | U47: 249 | V47: 249 | W47: 249 | X47: 249 | Y47: 249 | Z47: 249 | AA47: 249 | AM47: 31.12.9999
B48: FONE DE OUVIDO | C48: 4016311 | D48: FONE TWS MOTO BUDS | E48: FONE TWS MOTO BUDS-AZUL CLARO | F48: 399 | G48: 399 | H48: 399 | I48: 399 | J48: 349 | K48: 349 | L48: 349 | M48: 349 | N48: 349 | O48: 299 | P48: 299 | Q48: 249 | R48: 299 | S48: 249 | T48: 249 | U48: 249 | V48: 249 | W48: 249 | X48: 249 | Y48: 249 | Z48: 249 | AA48: 249 | AM48: 31.12.9999
B49: MUSICA | C49: 4016544 | D49: FONE TWS MOTO BUDS 65 2024 | E49: FONE TWS MOTO BUDS 65 2024-PRETO | F49: 199 | G49: 199 | H49: 199 | I49: 199 | J49: 149 | K49: 149 | L49: 149 | M49: 149 | N49: 149 | O49: 99 | P49: 99 | Q49: 99 | R49: 99 | S49: 99 | T49: 99 | U49: 99 | V49: 99 | W49: 99 | X49: 99 | Y49: 99 | Z49: 99 | AA49: 99 | AM49: 31.12.9999
B50: GADGETS | C50: 4016406 | D50: FONE TWS SAMSUNG GALAXY BUDS 3 | E50: FONE TWS SAMSUNG GALAXY BUDS 3-BRANCO | F50: 799 | G50: 799 | H50: 799 | I50: 799 | J50: 749 | K50: 749 | L50: 749 | M50: 749 | N50: 749 | O50: 699 | P50: 599 | Q50: 399 | R50: 699 | S50: 599 | T50: 399 | U50: 399 | V50: 399 | W50: 399 | X50: 399 | Y50: 399 | Z50: 399 | AA50: 399 | AM50: 31.12.9999
B51: GADGETS | C51: 4016403 | D51: FONE TWS SAMSUNG GALAXY BUDS 3 | E51: FONE TWS SAMSUNG GALAXY BUDS 3-CINZA | F51: 799 | G51: 799 | H51: 799 | I51: 799 | J51: 749 | K51: 749 | L51: 749 | M51: 749 | N51: 749 | O51: 699 | P51: 599 | Q51: 399 | R51: 699 | S51: 599 | T51: 399 | U51: 399 | V51: 399 | W51: 399 | X51: 399 | Y51: 399 | Z51: 399 | AA51: 399 | AM51: 31.12.9999
B52: FONE DE OUVIDO | C52: 4016367 | D52: FONE USB-C JBL 310C | E52: FONE USB-C JBL 310C-PRETO | F52: 129 | G52: 129 | AM52: 31.12.9999
B53: INFOTECH | C53: 4016407 | D53: GALAXY BOOK4 I3 256GB SSD 4GB | E53: GALAXY BOOK4 I5 8GB 256GB-GRAFITE | F53: 3499 | G53: 2699 | H53: 3499 | I53: 3499 | J53: 3449 | K53: 3449 | L53: 3449 | M53: 3449 | N53: 3449 | O53: 3399 | P53: 3299 | Q53: 3099 | R53: 3399 | S53: 3299 | T53: 3099 | U53: 3099 | V53: 3099 | W53: 3099 | X53: 2999 | Y53: 2699 | Z53: 2699 | AA53: 2649 | AM53: 31.12.9999
B54: INFOTECH | C54: 4016404 | D54: GALAXY BOOK4 I5 512GB SSD 8GB | E54: GALAXY BOOK4 I5 8GB 512GB-GRAFITE | F54: 3799 | G54: 2999 | H54: 3799 | I54: 3799 | J54: 3749 | K54: 3749 | L54: 3749 | M54: 3749 | N54: 3749 | O54: 3699 | P54: 3599 | Q54: 3399 | R54: 3699 | S54: 3599 | T54: 3399 | U54: 3399 | V54: 3399 | W54: 3399 | X54: 3299 | Y54: 2999 | Z54: 2999 | AA54: 2949 | AM54: 31.12.9999
B55: INFOTECH | C55: 4016410 | D55: GALAXY BOOK4 I3 8GB 256GB | E55: GALAXY BOOK4 I3 8GB 256GB-GRAFITE | F55: 2999 | G55: 2199 | H55: 2999 | I55: 2999 | J55: 2949 | K55: 2949 | L55: 2949 | M55: 2949 | N55: 2949 | O55: 2899 | P55: 2799 | Q55: 2599 | R55: 2899 | S55: 2799 | T55: 2599 | U55: 2599 | V55: 2599 | W55: 2599 | X55: 2499 | Y55: 2199 | Z55: 2199 | AA55: 2149 | AM55: 31.12.9999
B56: MUSICA | C56: 4015498 | D56: HEADPHONE BT JBL TUNE 520 | E56: HEADPHONE BT JBL TUNE 520-PRETO | F56: 199 | G56: 199 | H56: 0 | I56: 0 | J56: 0 | K56: 0 | L56: 0 | M56: 0 | N56: 0 | O56: 0 | P56: 0 | Q56: 0 | R56: 0 | S56: 0 | T56: 0 | U56: 0 | V56: 0 | W56: 0 | X56: 0 | Y56: 0 | Z56: 0 | AA56: 0 | AM56: 31.12.9999
B57: MUSICA | C57: 4016014 | D57: HEADPHONE BT JBL TUNE 720 | E57: HEADPHONE BT JBL TUNE 720-PRETO | F57: 399 | G57: 399 | H57: 399 | I57: 399 | J57: 349 | K57: 349 | L57: 349 | M57: 349 | N57: 349 | O57: 299 | P57: 299 | Q57: 249 | R57: 299 | S57: 249 | T57: 249 | U57: 249 | V57: 249 | W57: 249 | X57: 249 | Y57: 249 | Z57: 249 | AA57: 249 | AM57: 31.12.9999
B58: GAMER | C58: 4016400 | D58: HEADSET RAZER BLACKSHARK V2 | E58: HEADSET RAZER BLACKSHARK V2-PRETO | F58: 299 | G58: 299 | H58: 299 | I58: 299 | J58: 249 | K58: 249 | L58: 249 | M58: 249 | N58: 249 | O58: 199 | P58: 199 | Q58: 199 | R58: 199 | S58: 199 | T58: 199 | U58: 199 | V58: 199 | W58: 199 | X58: 199 | Y58: 199 | Z58: 199 | AA58: 199 | AM58: 31.12.9999
B59: GAMER | C59: 4016502 | D59: HEADSET SEM FIO SONY PULSE 3D | E59: HEADSET SEM FIO SONY PULSE 3D-BRANCO | F59: 599 | G59: 599 | H59: 599 | I59: 599 | J59: 549 | K59: 549 | L59: 549 | M59: 549 | N59: 549 | O59: 499 | P59: 399 | Q59: 349 | R59: 499 | S59: 399 | T59: 349 | U59: 349 | V59: 349 | W59: 349 | X59: 349 | Y59: 349 | Z59: 349 | AA59: 349 | AM59: 31.12.9999
B60: FOTOGRAFIA | C60: 4015538 | D60: IMPRESSORA INSTAX MINI LINK 2 | E60: IMPRESSORA INSTAX MINI LINK 2-BRANCO | F60: 699 | G60: 699 | H60: 699 | I60: 699 | J60: 649 | K60: 649 | L60: 649 | M60: 649 | N60: 649 | O60: 599 | P60: 599 | Q60: 499 | R60: 599 | S60: 499 | T60: 399 | U60: 399 | V60: 399 | W60: 399 | X60: 399 | Y60: 399 | Z60: 399 | AA60: 399 | AM60: 31.12.9999
B61: FOTOGRAFIA | C61: 4016434 | D61: IMPRESSORA INSTAX MINI LINK 2 2024 | E61: IMPRESSORA INSTAX MINI LINK 2 2024-BRANC | F61: 699 | G61: 699 | H61: 699 | I61: 699 | J61: 649 | K61: 649 | L61: 649 | M61: 649 | N61: 649 | O61: 599 | P61: 599 | Q61: 499 | R61: 599 | S61: 499 | T61: 399 | U61: 399 | V61: 399 | W61: 399 | X61: 399 | Y61: 399 | Z61: 399 | AA61: 399 | AM61: 31.12.9999
B62: SMARTHOME | C62: 4014960 | D62: LUMINARIA INTELIGENTE GEONAV | E62: LUMINARIA INTELIGENTE GEONAV-BRANCO | F62: 299 | G62: 299 | AB62: 289 | AC62: 289 | AD62: 289 | AE62: 289 | AF62: 289 | AG62: 289 | AH62: 289 | AI62: 289 | AJ62: 289 | AK62: 289 | AL62: 289 | AM62: 31.12.9999
B63: GAMER | C63: 4015580 | D63: MICROSOFT XBOX SERIES S 512GB | E63: MICROSOFT XBOX SERIES S 512GB-BRANCO | F63: 2499 | G63: 2499 | H63: 2499 | I63: 2499 | J63: 2449 | K63: 2449 | L63: 2449 | M63: 2449 | N63: 2449 | O63: 2399 | P63: 2399 | Q63: 2299 | R63: 2399 | S63: 2299 | T63: 2099 | U63: 2099 | V63: 2099 | W63: 2099 | X63: 1999 | Y63: 1699 | Z63: 1699 | AA63: 1649 | AM63: 31.12.9999
B64: GADGETS | C64: 4016307 | D64: OCULOS BT JBL SOUNDGEAR | E64: OCULOS BT JBL SOUNDGEAR-PEROLA | F64: 699 | G64: 699 | H64: 699 | I64: 699 | J64: 649 | K64: 649 | L64: 649 | M64: 649 | N64: 649 | O64: 599 | P64: 599 | Q64: 499 | R64: 599 | S64: 499 | T64: 399 | U64: 399 | V64: 399 | W64: 399 | X64: 399 | Y64: 399 | Z64: 399 | AA64: 399 | AM64: 31.12.9999
B65: GADGETS | C65: 4016308 | D65: OCULOS BT JBL SOUNDGEAR | E65: OCULOS BT JBL SOUNDGEAR-ONIX | F65: 699 | G65: 699 | H65: 699 | I65: 699 | J65: 649 | K65: 649 | L65: 649 | M65: 649 | N65: 649 | O65: 599 | P65: 599 | Q65: 499 | R65: 599 | S65: 499 | T65: 399 | U65: 399 | V65: 399 | W65: 399 | X65: 399 | Y65: 399 | Z65: 399 | AA65: 399 | AM65: 31.12.9999
B66: INFOTECH | C66: 4016180 | D66: POSITIVO VISION C15 4GB 128GB | E66: POSITIVO VISION C15 4GB 128GB-CINZA | F66: 1699 | G66: 1699 | H66: 1699 | I66: 1699 | J66: 1649 | K66: 1649 | L66: 1649 | M66: 1649 | N66: 1649 | O66: 1599 | P66: 1599 | Q66: 1499 | R66: 1599 | S66: 1499 | T66: 1299 | U66: 1299 | V66: 1299 | W66: 1299 | X66: 1199 | Y66: 899 | Z66: 899 | AA66: 899 | AM66: 31.12.9999
B67: GAMES | C67: 4017353 | D67: PS5 SLIM DIGI ASTRO BOT E GT7 2025 | E67: PS5 SLIM DIGI ASTRO BOT E GT7 2025-BRANC | F67: 3999 | G67: 2999 | H67: 3999 | I67: 3999 | J67: 3949 | K67: 3949 | L67: 3949 | M67: 3949 | N67: 3949 | O67: 3899 | P67: 3799 | Q67: 3599 | R67: 3899 | S67: 3799 | T67: 3599 | U67: 3599 | V67: 3599 | W67: 3599 | X67: 3499 | Y67: 2999 | Z67: 2999 | AA67: 2949 | AB67: 3949 | AC67: 3949 | AD67: 3949 | AE67: 3949 | AF67: 3899 | AG67: 3899 | AH67: 3599 | AI67: 3599 | AJ67: 3599 | AK67: 3599 | AL67: 2999 | AM67: 31.12.9999
B68: GAMER | C68: 4016511 | D68: PS5 SLIM DIGITAL 1TB 2 JOGOS | E68: PS5 SLIM DIGITAL 1TB 2 JOGOS-BRANCO | F68: 3999 | G68: 2999 | H68: 3999 | I68: 3999 | J68: 3949 | K68: 3949 | L68: 3949 | M68: 3949 | N68: 3949 | O68: 3899 | P68: 3799 | Q68: 3599 | R68: 3899 | S68: 3799 | T68: 3599 | U68: 3599 | V68: 3599 | W68: 3599 | X68: 3499 | Y68: 2999 | Z68: 2999 | AA68: 2949 | AB68: 3949 | AC68: 3949 | AD68: 3949 | AE68: 3949 | AF68: 3899 | AG68: 3899 | AH68: 3599 | AI68: 3599 | AJ68: 3599 | AK68: 3599 | AL68: 2999 | AM68: 31.12.9999
B69: GAMER | C69: 4016960 | D69: PS5 SLIM DIGITAL 1TB 2 JOGOS 2025 | E69: PS5 SLIM DIGITAL 1TB 2 JOGOS 2025-BRANCO | F69: 3999 | G69: 2999 | H69: 3999 | I69: 3999 | J69: 3949 | K69: 3949 | L69: 3949 | M69: 3949 | N69: 3949 | O69: 3899 | P69: 3799 | Q69: 3599 | R69: 3899 | S69: 3799 | T69: 3599 | U69: 3599 | V69: 3599 | W69: 3599 | X69: 3499 | Y69: 2999 | Z69: 2999 | AA69: 2949 | AB69: 3949 | AC69: 3949 | AD69: 3949 | AE69: 3949 | AF69: 3899 | AG69: 3899 | AH69: 3599 | AI69: 3599 | AJ69: 3599 | AK69: 3599 | AL69: 2999 | AM69: 31.12.9999
B70: GAMER | C70: 4017129 | D70: PS5 SLIM DIGITAL ASTRO BOT E GT7 | E70: PS5 SLIM DIGITAL ASTRO BOT E GT7-BRANCO | F70: 3999 | G70: 2999 | H70: 3999 | I70: 3999 | J70: 3949 | K70: 3949 | L70: 3949 | M70: 3949 | N70: 3949 | O70: 3899 | P70: 3799 | Q70: 3599 | R70: 3899 | S70: 3799 | T70: 3599 | U70: 3599 | V70: 3599 | W70: 3599 | X70: 3499 | Y70: 2999 | Z70: 2999 | AA70: 2949 | AB70: 3949 | AC70: 3949 | AD70: 3949 | AE70: 3949 | AF70: 3899 | AG70: 3899 | AH70: 3599 | AI70: 3599 | AJ70: 3599 | AK70: 3599 | AL70: 2999 | AM70: 31.12.9999
B71: GAMER | C71: 4016309 | D71: PS5 SLIM DISK 1TB 2 JOGOS | E71: PS5 SLIM DISK 1TB 2 JOGOS-BRANCO | F71: 4499 | G71: 3499 | H71: 4499 | I71: 4499 | J71: 4449 | K71: 4449 | L71: 4449 | M71: 4449 | N71: 4449 | O71: 4399 | P71: 4399 | Q71: 4299 | R71: 4399 | S71: 4299 | T71: 4099 | U71: 4099 | V71: 4099 | W71: 4099 | X71: 3999 | Y71: 3499 | Z71: 3499 | AA71: 3349 | AB71: 4449 | AC71: 4449 | AD71: 4449 | AE71: 4449 | AF71: 4399 | AG71: 4399 | AH71: 4099 | AI71: 4099 | AJ71: 4099 | AK71: 4099 | AL71: 3499 | AM71: 31.12.9999
B72: GAMES | C72: 4016958 | D72: PS5 SLIM DISK 1TB 2 JOGOS 2025 | E72: PS5 SLIM DISK 1TB 2 JOGOS 2025-BRANCO | F72: 4499 | G72: 3499 | H72: 4499 | I72: 4499 | J72: 4449 | K72: 4449 | L72: 4449 | M72: 4449 | N72: 4449 | O72: 4399 | P72: 4399 | Q72: 4299 | R72: 4399 | S72: 4299 | T72: 4099 | U72: 4099 | V72: 4099 | W72: 4099 | X72: 3999 | Y72: 3499 | Z72: 3499 | AA72: 3349 | AB72: 4449 | AC72: 4449 | AD72: 4449 | AE72: 4449 | AF72: 4399 | AG72: 4399 | AH72: 4099 | AI72: 4099 | AJ72: 4099 | AK72: 4099 | AL72: 3499 | AM72: 31.12.9999
B73: GAMER | C73: 4017128 | D73: PS5 SLIM DISK ASTRO BOT E GT7 | E73: PS5 SLIM DISK ASTRO BOT E GT7-BRANCO | F73: 4499 | G73: 3499 | H73: 4499 | I73: 4499 | J73: 4449 | K73: 4449 | L73: 4449 | M73: 4449 | N73: 4449 | O73: 4399 | P73: 4399 | Q73: 4299 | R73: 4399 | S73: 4299 | T73: 4099 | U73: 4099 | V73: 4099 | W73: 4099 | X73: 3999 | Y73: 3499 | Z73: 3499 | AA73: 3349 | AB73: 4449 | AC73: 4449 | AD73: 4449 | AE73: 4449 | AF73: 4399 | AG73: 4399 | AH73: 4099 | AI73: 4099 | AJ73: 4099 | AK73: 4099 | AL73: 3499 | AM73: 31.12.9999
B74: GAMES | C74: 4017326 | D74: PS5 SLIM DISK ASTRO BOT E GT7 2025 | E74: PS5 SLIM DISK ASTRO BOT E GT7 2025-BRANC | F74: 4499 | G74: 3499 | H74: 4499 | I74: 4499 | J74: 4449 | K74: 4449 | L74: 4449 | M74: 4449 | N74: 4449 | O74: 4399 | P74: 4399 | Q74: 4299 | R74: 4399 | S74: 4299 | T74: 4099 | U74: 4099 | V74: 4099 | W74: 4099 | X74: 3999 | Y74: 3499 | Z74: 3499 | AA74: 3349 | AB74: 4449 | AC74: 4449 | AD74: 4449 | AE74: 4449 | AF74: 4399 | AG74: 4399 | AH74: 4099 | AI74: 4099 | AJ74: 4099 | AK74: 4099 | AL74: 3499 | AM74: 31.12.9999
B75: SMARTHOME | C75: 4016298 | D75: ROBÔ ASPIRADOR POSITIVO WI-FI | E75: ROBÔ ASPIRADOR POSITIVO WI-FI | F75: 649 | G75: 649 | H75: 649 | I75: 649 | J75: 599 | K75: 599 | L75: 599 | M75: 599 | N75: 599 | O75: 549 | P75: 449 | Q75: 349 | R75: 549 | S75: 449 | T75: 349 | U75: 349 | V75: 349 | W75: 349 | X75: 349 | Y75: 349 | Z75: 349 | AA75: 349 | AM75: 31.12.9999
B76: GADGETS | C76: 4015924 | D76: SAMSUNG GALAXY FIT3 | E76: SAMSUNG GALAXY FIT3-ROSE | F76: 399 | G76: 399 | H76: 399 | I76: 399 | J76: 349 | K76: 349 | L76: 349 | M76: 349 | N76: 349 | O76: 299 | P76: 249 | Q76: 249 | R76: 299 | S76: 249 | T76: 249 | U76: 249 | V76: 249 | W76: 249 | X76: 249 | Y76: 249 | Z76: 249 | AA76: 249 | AB76: 379 | AC76: 379 | AD76: 379 | AE76: 299 | AF76: 249 | AG76: 249 | AH76: 199 | AI76: 199 | AJ76: 199 | AK76: 199 | AL76: 199 | AM76: 31.12.9999
B77: GADGETS | C77: 4015922 | D77: SAMSUNG GALAXY FIT3 | E77: SAMSUNG GALAXY FIT3-GRAFITE | F77: 399 | G77: 399 | H77: 399 | I77: 399 | J77: 349 | K77: 349 | L77: 349 | M77: 349 | N77: 349 | O77: 299 | P77: 249 | Q77: 249 | R77: 299 | S77: 249 | T77: 249 | U77: 249 | V77: 249 | W77: 249 | X77: 249 | Y77: 249 | Z77: 249 | AA77: 249 | AB77: 379 | AC77: 379 | AD77: 379 | AE77: 299 | AF77: 249 | AG77: 249 | AH77: 199 | AI77: 199 | AJ77: 199 | AK77: 199 | AL77: 199 | AM77: 31.12.9999
B78: GADGETS | C78: 4017424 | D78: SAMSUNG GALAXY FIT3 2025 | E78: SAMSUNG GALAXY FIT3 2025-PRATA | F78: 399 | G78: 399 | H78: 399 | I78: 399 | J78: 349 | K78: 349 | L78: 349 | M78: 349 | N78: 349 | O78: 299 | P78: 249 | Q78: 249 | R78: 299 | S78: 249 | T78: 249 | U78: 249 | V78: 249 | W78: 249 | X78: 249 | Y78: 249 | Z78: 249 | AA78: 249 | AB78: 379 | AC78: 379 | AD78: 379 | AE78: 299 | AF78: 249 | AG78: 249 | AH78: 199 | AI78: 199 | AJ78: 199 | AK78: 199 | AL78: 199 | AM78: 31.12.9999
B79: GADGETS | C79: 4017419 | D79: SAMSUNG GALAXY FIT3 2025 | E79: SAMSUNG GALAXY FIT3 2025-GRAFITE | F79: 399 | G79: 399 | H79: 399 | I79: 399 | J79: 349 | K79: 349 | L79: 349 | M79: 349 | N79: 349 | O79: 299 | P79: 249 | Q79: 249 | R79: 299 | S79: 249 | T79: 249 | U79: 249 | V79: 249 | W79: 249 | X79: 249 | Y79: 249 | Z79: 249 | AA79: 249 | AB79: 379 | AC79: 379 | AD79: 379 | AE79: 299 | AF79: 249 | AG79: 249 | AH79: 199 | AI79: 199 | AJ79: 199 | AK79: 199 | AL79: 199 | AM79: 31.12.9999
B80: GADGETS | C80: 4017414 | D80: SAMSUNG GALAXY FIT3 2025 | E80: SAMSUNG GALAXY FIT3 2025-ROSE | F80: 399 | G80: 399 | H80: 399 | I80: 399 | J80: 349 | K80: 349 | L80: 349 | M80: 349 | N80: 349 | O80: 299 | P80: 249 | Q80: 249 | R80: 299 | S80: 249 | T80: 249 | U80: 249 | V80: 249 | W80: 249 | X80: 249 | Y80: 249 | Z80: 249 | AA80: 249 | AB80: 379 | AC80: 379 | AD80: 379 | AE80: 299 | AF80: 249 | AG80: 249 | AH80: 199 | AI80: 199 | AJ80: 199 | AK80: 199 | AL80: 199 | AM80: 31.12.9999
B81: GADGETS | C81: 4015728 | D81: SAMSUNG GALAXY SMARTTAG 2 | E81: TRACKER SAMSUNG GALAXY SMARTTAG 2-PRETO | F81: 199 | G81: 199 | AM81: 31.12.9999
B82: GADGETS | C82: 4015883 | D82: SAMSUNG GALAXY SMARTTAG 2 | E82: SAMSUNG GALAXY SMARTTAG 2-BRANCO | F82: 199 | G82: 199 | AM82: 31.12.9999
B83: GADGETS | C83: 4015882 | D83: SAMSUNG GALAXY SMARTTAG 2 | E83: SAMSUNG GALAXY SMARTTAG 2-PRETO | F83: 199 | G83: 199 | AM83: 31.12.9999
B84: GADGETS | C84: 4016401 | D84: SAMSUNG WATCH 7 BT 40MM | E84: SAMSUNG WATCH 7 BT 40MM-CREME | F84: 1299 | G84: 899 | H84: 1299 | I84: 1299 | J84: 1249 | K84: 1249 | L84: 1249 | M84: 1249 | N84: 1249 | O84: 1199 | P84: 1199 | Q84: 899 | R84: 1199 | S84: 1099 | T84: 899 | U84: 899 | V84: 899 | W84: 899 | X84: 799 | Y84: 699 | Z84: 699 | AA84: 699 | AM84: 31.12.9999
B85: GADGETS | C85: 4016405 | D85: SAMSUNG WATCH 7 BT 40MM | E85: SAMSUNG WATCH 7 BT 40MM-VERDE | F85: 1299 | G85: 899 | H85: 1299 | I85: 1299 | J85: 1249 | K85: 1249 | L85: 1249 | M85: 1249 | N85: 1249 | O85: 1199 | P85: 1199 | Q85: 899 | R85: 1199 | S85: 1099 | T85: 899 | U85: 899 | V85: 899 | W85: 899 | X85: 799 | Y85: 699 | Z85: 699 | AA85: 699 | AM85: 31.12.9999
B86: GADGETS | C86: 4016413 | D86: SAMSUNG WATCH 7 BT 44MM | E86: SAMSUNG WATCH 7 BT 44MM-VERDE | F86: 1499 | G86: 999 | H86: 1499 | I86: 1499 | J86: 1449 | K86: 1449 | L86: 1449 | M86: 1449 | N86: 1449 | O86: 1399 | P86: 1399 | Q86: 999 | R86: 1399 | S86: 1299 | T86: 999 | U86: 999 | V86: 1099 | W86: 1099 | X86: 999 | Y86: 799 | Z86: 799 | AA86: 799 | AM86: 31.12.9999
B87: GADGETS | C87: 4016414 | D87: SAMSUNG WATCH 7 BT 44MM | E87: SAMSUNG WATCH 7 BT 44MM-PRATA | F87: 1499 | G87: 999 | H87: 1499 | I87: 1499 | J87: 1449 | K87: 1449 | L87: 1449 | M87: 1449 | N87: 1449 | O87: 1399 | P87: 1399 | Q87: 999 | R87: 1399 | S87: 1299 | T87: 999 | U87: 999 | V87: 1099 | W87: 1099 | X87: 999 | Y87: 799 | Z87: 799 | AA87: 799 | AM87: 31.12.9999
B88: GADGETS | C88: 4017227 | D88: SAMSUNG WATCH 8 BT 40MM | E88: SAMSUNG WATCH 8 BT 40MM-GRAFITE | F88: 1899 | G88: 1899 | H88: 1899 | I88: 1899 | J88: 1849 | K88: 1849 | L88: 1849 | M88: 1849 | N88: 1849 | O88: 1799 | P88: 1699 | Q88: 1499 | R88: 1799 | S88: 1699 | T88: 1499 | U88: 1499 | V88: 1499 | W88: 1499 | X88: 1399 | Y88: 1099 | Z88: 1099 | AA88: 1049 | AM88: 31.12.9999
B89: GADGETS | C89: 4017223 | D89: SAMSUNG WATCH 8 BT 44MM | E89: SAMSUNG WATCH 8 BT 44MM-GRAFITE | F89: 2099 | G89: 2099 | H89: 2099 | I89: 2099 | J89: 2049 | K89: 2049 | L89: 2049 | M89: 2049 | N89: 2049 | O89: 1999 | P89: 1899 | Q89: 1699 | R89: 1999 | S89: 1899 | T89: 1699 | U89: 1699 | V89: 1699 | W89: 1699 | X89: 1599 | Y89: 1299 | Z89: 1299 | AA89: 1249 | AM89: 31.12.9999
B90: SMARTHOME | C90: 4014008 | D90: SENSOR DE MOVIMENTO GEONAV | E90: SENSOR DE MOVIMENTO GEONAV-BRANCO | F90: 49 | G90: 49 | AB90: 39 | AC90: 39 | AD90: 39 | AE90: 39 | AF90: 39 | AG90: 39 | AH90: 39 | AI90: 39 | AJ90: 39 | AK90: 39 | AL90: 39 | AM90: 31.12.9999
B91: SMARTHOME | C91: 4013980 | D91: SMART CAMERA FULL HD GEONAV | E91: SMART CAMERA FULL HD GEONAV-BRANCO | F91: 299 | G91: 299 | AB91: 289 | AC91: 289 | AD91: 289 | AE91: 289 | AF91: 289 | AG91: 289 | AH91: 289 | AI91: 289 | AJ91: 289 | AK91: 289 | AL91: 289 | AM91: 31.12.9999
B92: GAMER | C92: 4016356 | D92: TECLADO RAZER CYNOSA LITE | E92: TECLADO RAZER CYNOSA LITE-PRETO | F92: 149 | G92: 149 | AM92: 31.12.9999
B93: GADGETS | C93: 4017692 | D93: TV SAMSUNG 50 CRYSTAL UHD U8600F | E93: TV SAMSUNG 50 CRYSTAL UHD U8600F-PRETA | F93: 2499 | G93: 1999 | H93: 2499 | I93: 2499 | J93: 2449 | K93: 2449 | L93: 2449 | M93: 2449 | N93: 2449 | O93: 2399 | P93: 2299 | Q93: 2099 | R93: 2399 | S93: 2299 | T93: 2099 | U93: 2099 | V93: 2099 | W93: 2099 | X93: 1999 | Y93: 1399 | Z93: 1399 | AA93: 1349 | AB93: 2449 | AC93: 2449 | AD93: 2449 | AE93: 2449 | AF93: 2449 | AG93: 2449 | AH93: 2449 | AI93: 2099 | AJ93: 2099 | AK93: 2099 | AL93: 1399 | AM93: 31.12.9999
M500: 1249 | N500: 1049 | R500: 949 | S500: 849 | T500: 749 | U500: 749 | V500: 699 | W500: 649 | X500: 599
M501: 1249 | N501: 1049 | R501: 949 | S501: 849 | T501: 749 | U501: 749 | V501: 699 | W501: 649 | X501: 599
M502: 1249 | N502: 1049 | R502: 949 | S502: 849 | T502: 749 | U502: 749 | V502: 699 | W502: 649 | X502: 599
M503: 1249 | N503: 1049 | R503: 949 | S503: 849 | T503: 749 | U503: 749 | V503: 699 | W503: 649 | X503: 599
M504: 1249 | N504: 1049 | R504: 949 | S504: 849 | T504: 749 | U504: 749 | V504: 699 | W504: 649 | X504: 599
M505: 1249 | N505: 1049 | R505: 949 | S505: 849 | T505: 749 | U505: 749 | V505: 699 | W505: 649 | X505: 599
M506: 1249 | N506: 1049 | R506: 949 | S506: 849 | T506: 749 | U506: 749 | V506: 699 | W506: 649 | X506: 599
M507: 1249 | N507: 1049 | R507: 949 | S507: 849 | T507: 749 | U507: 749 | V507: 699 | W507: 649 | X507: 599
...

Sheet TRADE IN
A1: OFERTAS VÁLIDAS APENAS PARA PLANOS CONSUMER
B4: Inclusão de Preços
B5: Alteração de Preços
A7: Preços Elegíveis a Price Back
A8: Preços Elegíveis a Price Oferta
A9: CANAL: | B9: REVENDAS
C11: DATA INÍCIO: | D11: =REV!D11 -> 46092 | J11: COM FIDELIZAÇÃO - GROSS / MIGRAÇÃO / UPGRADE / PORTABILIDADE / BASE SEM MOVIMENTAÇÃO | AB11: TIM FIBRA | AM11: TIM FIXO | AP11: TIM CASA
A12: Regra Reembolso Pós Fidelizado | B12: CATEGORIA MKT | C12: CÓDIGO | D12: DESCRIÇÃO COMERCIAL | E12: DESCRIÇÃO SAP | F12: BOOST TRADE IN | G12: PREÇO BASE FATURAMENTO RETAIL | H12: CONTROLE NÃO FIDELIZADO - TODOS (Fatura / Express) | I12: PÓS PAGO NÃO FIDELIZADO - VIDE ABA DE REGRAS | J12: TIM CONTROLE | K12: TIM CONTROLE PLUS | L12: TIM CONTROLE PREMIUM | M12: TIM CONTROLE SMART | N12: TIM CONTROLE REDES SOCIAIS | O12: TIM BLACK | P12: TIM BLACK PLUS | Q12: TIM BLACK PREMIUM | R12: TIM BLACK A (15GB) | S12: TIM BLACK B (20GB) | T12: TIM BLACK C (25GB) | U12: TIM BLACK C ULTRA | V12: TIM BLACK FAMÍLIA | W12: TIM BLACK FAMÍLIA A ONE | X12: TIM BLACK FAMÍLIA PLUS | Y12: TIM BLACK FAMÍLIA PREMIUM | Z12: TIM BLACK FAMÍLIA C ONE | AA12: TIM BLACK FAMÍLIA VIP | AB12: TIM Fibra 300M 24 | AC12: TIM Fibra 400M 24 | AD12: TIM Fibra 500M 24 - 2 | AE12: TIM Fibra 600M 24 - 2 | AF12: TIM Fibra 600M P 24 - 2 | AG12: TIM Fibra 600M M 24 - 2 | AH12: TIM Fibra 600M GP 25 | AI12: TIM Fibra 1GB 24 | AJ12: TIM Fibra 1GB P 24 | AK12: TIM Fibra 1GB M 24 | AL12: TIM Fibra 2GB 24 | AM12: TIM FIXO LOCAL TOTAL PLUS (Plano Fidelizado) | AN12: TIM FIXO BRASIL TOTAL PLUS (Plano Fidelizado) | AO12: TIM FIXO TOTAL LDI PLUS (Plano Fidelizado) | AP12: TIM LIVE INTERNET 30GB (sem fidelização) | AQ12: TIM LIVE INTERNET 50GB (sem fidelização) | AR12: TIM LIVE INTERNET 80GB (sem fidelização) | AS12: TIM LIVE INTERNET 30GB PLUS | AT12: TIM LIVE INTERNET 50GB PLUS | AU12: TIM LIVE INTERNET 80GB PLUS | AW12: DATA FIM DA OFERTA | AX12: TECNOLOGIA
A13: ADM | B13: 21X | C13: 4010990 | D13: Alcatel Pixi 4.5 4G | E13: Alcatel Pixi 4.5 4G-Preto | J13: =IF(VLOOKUP($C13,REV!$C:$AA,8,0)-'TRADE IN'!$F13=0,"",(VLOOKUP($C13,REV!$C:$AA,8,0)-'TRADE IN'!$F13)) -> 479 | K13: =IF(VLOOKUP($C13,REV!$C:$AA,9,0)-'TRADE IN'!$F13=0,"",(VLOOKUP($C13,REV!$C:$AA,9,0)-'TRADE IN'!$F13)) -> 479 | L13: =IF(VLOOKUP($C13,REV!$C:$AA,10,0)-'TRADE IN'!$F22=0,"",(VLOOKUP($C13,REV!$C:$AA,10,0)-'TRADE IN'!$F13)) -> 479 | M13: =IF(VLOOKUP($C13,REV!$C:$AA,11,0)-'TRADE IN'!$F22=0,"",(VLOOKUP($C13,REV!$C:$AA,11,0)-'TRADE IN'!$F13)) -> 479 | N13: =IF(VLOOKUP($C13,REV!$C:$AA,12,0)-'TRADE IN'!$F22=0,"",(VLOOKUP($C13,REV!$C:$AA,12,0)-'TRADE IN'!$F13)) -> 479 | O13: =IF(VLOOKUP($C13,REV!$C:$AA,13,0)-'TRADE IN'!$F22=0,"",(VLOOKUP($C13,REV!$C:$AA,13,0)-'TRADE IN'!$F13)) | P13: =IF(VLOOKUP($C13,REV!$C:$AA,14,0)-'TRADE IN'!$F22=0,"",(VLOOKUP($C13,REV!$C:$AA,14,0)-'TRADE IN'!$F13)) | Q13: =IF(VLOOKUP($C13,REV!$C:$AA,15,0)-'TRADE IN'!$F22=0,"",(VLOOKUP($C13,REV!$C:$AA,15,0)-'TRADE IN'!$F13)) | R13: =IF(VLOOKUP($C13,REV!$C:$AA,16,0)-'TRADE IN'!$F22=0,"",(VLOOKUP($C13,REV!$C:$AA,16,0)-'TRADE IN'!$F13)) | S13: =IF(VLOOKUP($C13,REV!$C:$AA,17,0)-'TRADE IN'!$F22=0,"",(VLOOKUP($C13,REV!$C:$AA,17,0)-'TRADE IN'!$F13)) | T13: =IF(VLOOKUP($C13,REV!$C:$AA,18,0)-'TRADE IN'!$F22=0,"",(VLOOKUP($C13,REV!$C:$AA,18,0)-'TRADE IN'!$F13)) | U13: =IF(VLOOKUP($C13,REV!$C:$AA,19,0)-'TRADE IN'!$F22=0,"",(VLOOKUP($C13,REV!$C:$AA,19,0)-'TRADE IN'!$F13)) | V13: =IF(VLOOKUP($C13,REV!$C:$AA,20,0)-'TRADE IN'!$F22=0,"",(VLOOKUP($C13,REV!$C:$AA,20,0)-'TRADE IN'!$F13)) | W13: =IF(VLOOKUP($C13,REV!$C:$AA,21,0)-'TRADE IN'!$F22=0,"",(VLOOKUP($C13,REV!$C:$AA,21,0)-'TRADE IN'!$F13)) | X13: =IF(VLOOKUP($C13,REV!$C:$AA,22,0)-'TRADE IN'!$F22=0,"",(VLOOKUP($C13,REV!$C:$AA,22,0)-'TRADE IN'!$F13)) | Y13: =IF(VLOOKUP($C13,REV!$C:$AA,23,0)-'TRADE IN'!$F22=0,"",(VLOOKUP($C13,REV!$C:$AA,23,0)-'TRADE IN'!$F13)) | Z13: =IF(VLOOKUP($C13,REV!$C:$AA,24,0)-'TRADE IN'!$F22=0,"",(VLOOKUP($C13,REV!$C:$AA,24,0)-'TRADE IN'!$F13)) | AA13: =IF(VLOOKUP($C13,REV!$C:$AA,25,0)-'TRADE IN'!$F22=0,"",(VLOOKUP($C13,REV!$C:$AA,25,0)-'TRADE IN'!$F13)) | AW13: =IF(REV!AW13=0,"",REV!AW13) -> 31.03.2026 | AX13: 4G
A14: ADM | B14: 21X | C14: 4010991 | D14: Alcatel Pixi 4.5 4G | E14: Alcatel Pixi 4.5 4G-Branco | J14: =IF(VLOOKUP($C14,REV!$C:$AA,8,0)-'TRADE IN'!$F14=0,"",(VLOOKUP($C14,REV!$C:$AA,8,0)-'TRADE IN'!$F14)) -> 479 | K14: =IF(VLOOKUP($C14,REV!$C:$AA,9,0)-'TRADE IN'!$F14=0,"",(VLOOKUP($C14,REV!$C:$AA,9,0)-'TRADE IN'!$F14)) -> 479 | L14: =IF(VLOOKUP($C14,REV!$C:$AA,10,0)-'TRADE IN'!$F23=0,"",(VLOOKUP($C14,REV!$C:$AA,10,0)-'TRADE IN'!$F14)) -> 479 | M14: =IF(VLOOKUP($C14,REV!$C:$AA,11,0)-'TRADE IN'!$F23=0,"",(VLOOKUP($C14,REV!$C:$AA,11,0)-'TRADE IN'!$F14)) -> 479 | N14: =IF(VLOOKUP($C14,REV!$C:$AA,12,0)-'TRADE IN'!$F23=0,"",(VLOOKUP($C14,REV!$C:$AA,12,0)-'TRADE IN'!$F14)) -> 479 | O14: =IF(VLOOKUP($C14,REV!$C:$AA,13,0)-'TRADE IN'!$F23=0,"",(VLOOKUP($C14,REV!$C:$AA,13,0)-'TRADE IN'!$F14)) | P14: =IF(VLOOKUP($C14,REV!$C:$AA,14,0)-'TRADE IN'!$F23=0,"",(VLOOKUP($C14,REV!$C:$AA,14,0)-'TRADE IN'!$F14)) | Q14: =IF(VLOOKUP($C14,REV!$C:$AA,15,0)-'TRADE IN'!$F23=0,"",(VLOOKUP($C14,REV!$C:$AA,15,0)-'TRADE IN'!$F14)) | R14: =IF(VLOOKUP($C14,REV!$C:$AA,16,0)-'TRADE IN'!$F23=0,"",(VLOOKUP($C14,REV!$C:$AA,16,0)-'TRADE IN'!$F14)) | S14: =IF(VLOOKUP($C14,REV!$C:$AA,17,0)-'TRADE IN'!$F23=0,"",(VLOOKUP($C14,REV!$C:$AA,17,0)-'TRADE IN'!$F14)) | T14: =IF(VLOOKUP($C14,REV!$C:$AA,18,0)-'TRADE IN'!$F23=0,"",(VLOOKUP($C14,REV!$C:$AA,18,0)-'TRADE IN'!$F14)) | U14: =IF(VLOOKUP($C14,REV!$C:$AA,19,0)-'TRADE IN'!$F23=0,"",(VLOOKUP($C14,REV!$C:$AA,19,0)-'TRADE IN'!$F14)) | V14: =IF(VLOOKUP($C14,REV!$C:$AA,20,0)-'TRADE IN'!$F23=0,"",(VLOOKUP($C14,REV!$C:$AA,20,0)-'TRADE IN'!$F14)) | W14: =IF(VLOOKUP($C14,REV!$C:$AA,21,0)-'TRADE IN'!$F23=0,"",(VLOOKUP($C14,REV!$C:$AA,21,0)-'TRADE IN'!$F14)) | X14: =IF(VLOOKUP($C14,REV!$C:$AA,22,0)-'TRADE IN'!$F23=0,"",(VLOOKUP($C14,REV!$C:$AA,22,0)-'TRADE IN'!$F14)) | Y14: =IF(VLOOKUP($C14,REV!$C:$AA,23,0)-'TRADE IN'!$F23=0,"",(VLOOKUP($C14,REV!$C:$AA,23,0)-'TRADE IN'!$F14)) | Z14: =IF(VLOOKUP($C14,REV!$C:$AA,24,0)-'TRADE IN'!$F23=0,"",(VLOOKUP($C14,REV!$C:$AA,24,0)-'TRADE IN'!$F14)) | AA14: =IF(VLOOKUP($C14,REV!$C:$AA,25,0)-'TRADE IN'!$F23=0,"",(VLOOKUP($C14,REV!$C:$AA,25,0)-'TRADE IN'!$F14)) | AW14: =IF(REV!AW14=0,"",REV!AW14) -> 31.03.2026 | AX14: 4G
A15: ADM | B15: 21X | C15: 4011353 | D15: Alcatel Pixi 4.5 4G | E15: Alcatel Pixi 4.5 4G-Preto AM | J15: =IF(VLOOKUP($C15,REV!$C:$AA,8,0)-'TRADE IN'!$F15=0,"",(VLOOKUP($C15,REV!$C:$AA,8,0)-'TRADE IN'!$F15)) -> 479 | K15: =IF(VLOOKUP($C15,REV!$C:$AA,9,0)-'TRADE IN'!$F15=0,"",(VLOOKUP($C15,REV!$C:$AA,9,0)-'TRADE IN'!$F15)) -> 479 | L15: =IF(VLOOKUP($C15,REV!$C:$AA,10,0)-'TRADE IN'!$F24=0,"",(VLOOKUP($C15,REV!$C:$AA,10,0)-'TRADE IN'!$F15)) -> 479 | M15: =IF(VLOOKUP($C15,REV!$C:$AA,11,0)-'TRADE IN'!$F24=0,"",(VLOOKUP($C15,REV!$C:$AA,11,0)-'TRADE IN'!$F15)) -> 479 | N15: =IF(VLOOKUP($C15,REV!$C:$AA,12,0)-'TRADE IN'!$F24=0,"",(VLOOKUP($C15,REV!$C:$AA,12,0)-'TRADE IN'!$F15)) -> 479 | O15: =IF(VLOOKUP($C15,REV!$C:$AA,13,0)-'TRADE IN'!$F24=0,"",(VLOOKUP($C15,REV!$C:$AA,13,0)-'TRADE IN'!$F15)) | P15: =IF(VLOOKUP($C15,REV!$C:$AA,14,0)-'TRADE IN'!$F24=0,"",(VLOOKUP($C15,REV!$C:$AA,14,0)-'TRADE IN'!$F15)) | Q15: =IF(VLOOKUP($C15,REV!$C:$AA,15,0)-'TRADE IN'!$F24=0,"",(VLOOKUP($C15,REV!$C:$AA,15,0)-'TRADE IN'!$F15)) | R15: =IF(VLOOKUP($C15,REV!$C:$AA,16,0)-'TRADE IN'!$F24=0,"",(VLOOKUP($C15,REV!$C:$AA,16,0)-'TRADE IN'!$F15)) | S15: =IF(VLOOKUP($C15,REV!$C:$AA,17,0)-'TRADE IN'!$F24=0,"",(VLOOKUP($C15,REV!$C:$AA,17,0)-'TRADE IN'!$F15)) | T15: =IF(VLOOKUP($C15,REV!$C:$AA,18,0)-'TRADE IN'!$F24=0,"",(VLOOKUP($C15,REV!$C:$AA,18,0)-'TRADE IN'!$F15)) | U15: =IF(VLOOKUP($C15,REV!$C:$AA,19,0)-'TRADE IN'!$F24=0,"",(VLOOKUP($C15,REV!$C:$AA,19,0)-'TRADE IN'!$F15)) | V15: =IF(VLOOKUP($C15,REV!$C:$AA,20,0)-'TRADE IN'!$F24=0,"",(VLOOKUP($C15,REV!$C:$AA,20,0)-'TRADE IN'!$F15)) | W15: =IF(VLOOKUP($C15,REV!$C:$AA,21,0)-'TRADE IN'!$F24=0,"",(VLOOKUP($C15,REV!$C:$AA,21,0)-'TRADE IN'!$F15)) | X15: =IF(VLOOKUP($C15,REV!$C:$AA,22,0)-'TRADE IN'!$F24=0,"",(VLOOKUP($C15,REV!$C:$AA,22,0)-'TRADE IN'!$F15)) | Y15: =IF(VLOOKUP($C15,REV!$C:$AA,23,0)-'TRADE IN'!$F24=0,"",(VLOOKUP($C15,REV!$C:$AA,23,0)-'TRADE IN'!$F15)) | Z15: =IF(VLOOKUP($C15,REV!$C:$AA,24,0)-'TRADE IN'!$F24=0,"",(VLOOKUP($C15,REV!$C:$AA,24,0)-'TRADE IN'!$F15)) | AA15: =IF(VLOOKUP($C15,REV!$C:$AA,25,0)-'TRADE IN'!$F24=0,"",(VLOOKUP($C15,REV!$C:$AA,25,0)-'TRADE IN'!$F15)) | AW15: =IF(REV!AW15=0,"",REV!AW15) -> 31.03.2026 | AX15: 4G
A16: ADM | B16: 21X | C16: 4011354 | D16: Alcatel Pixi 4.5 4G | E16: Alcatel Pixi 4.5 4G-Branco AM | J16: =IF(VLOOKUP($C16,REV!$C:$AA,8,0)-'TRADE IN'!$F16=0,"",(VLOOKUP($C16,REV!$C:$AA,8,0)-'TRADE IN'!$F16)) -> 479 | K16: =IF(VLOOKUP($C16,REV!$C:$AA,9,0)-'TRADE IN'!$F16=0,"",(VLOOKUP($C16,REV!$C:$AA,9,0)-'TRADE IN'!$F16)) -> 479 | L16: =IF(VLOOKUP($C16,REV!$C:$AA,10,0)-'TRADE IN'!$F25=0,"",(VLOOKUP($C16,REV!$C:$AA,10,0)-'TRADE IN'!$F16)) -> 479 | M16: =IF(VLOOKUP($C16,REV!$C:$AA,11,0)-'TRADE IN'!$F25=0,"",(VLOOKUP($C16,REV!$C:$AA,11,0)-'TRADE IN'!$F16)) -> 479 | N16: =IF(VLOOKUP($C16,REV!$C:$AA,12,0)-'TRADE IN'!$F25=0,"",(VLOOKUP($C16,REV!$C:$AA,12,0)-'TRADE IN'!$F16)) -> 479 | O16: =IF(VLOOKUP($C16,REV!$C:$AA,13,0)-'TRADE IN'!$F25=0,"",(VLOOKUP($C16,REV!$C:$AA,13,0)-'TRADE IN'!$F16)) | P16: =IF(VLOOKUP($C16,REV!$C:$AA,14,0)-'TRADE IN'!$F25=0,"",(VLOOKUP($C16,REV!$C:$AA,14,0)-'TRADE IN'!$F16)) | Q16: =IF(VLOOKUP($C16,REV!$C:$AA,15,0)-'TRADE IN'!$F25=0,"",(VLOOKUP($C16,REV!$C:$AA,15,0)-'TRADE IN'!$F16)) | R16: =IF(VLOOKUP($C16,REV!$C:$AA,16,0)-'TRADE IN'!$F25=0,"",(VLOOKUP($C16,REV!$C:$AA,16,0)-'TRADE IN'!$F16)) | S16: =IF(VLOOKUP($C16,REV!$C:$AA,17,0)-'TRADE IN'!$F25=0,"",(VLOOKUP($C16,REV!$C:$AA,17,0)-'TRADE IN'!$F16)) | T16: =IF(VLOOKUP($C16,REV!$C:$AA,18,0)-'TRADE IN'!$F25=0,"",(VLOOKUP($C16,REV!$C:$AA,18,0)-'TRADE IN'!$F16)) | U16: =IF(VLOOKUP($C16,REV!$C:$AA,19,0)-'TRADE IN'!$F25=0,"",(VLOOKUP($C16,REV!$C:$AA,19,0)-'TRADE IN'!$F16)) | V16: =IF(VLOOKUP($C16,REV!$C:$AA,20,0)-'TRADE IN'!$F25=0,"",(VLOOKUP($C16,REV!$C:$AA,20,0)-'TRADE IN'!$F16)) | W16: =IF(VLOOKUP($C16,REV!$C:$AA,21,0)-'TRADE IN'!$F25=0,"",(VLOOKUP($C16,REV!$C:$AA,21,0)-'TRADE IN'!$F16)) | X16: =IF(VLOOKUP($C16,REV!$C:$AA,22,0)-'TRADE IN'!$F25=0,"",(VLOOKUP($C16,REV!$C:$AA,22,0)-'TRADE IN'!$F16)) | Y16: =IF(VLOOKUP($C16,REV!$C:$AA,23,0)-'TRADE IN'!$F25=0,"",(VLOOKUP($C16,REV!$C:$AA,23,0)-'TRADE IN'!$F16)) | Z16: =IF(VLOOKUP($C16,REV!$C:$AA,24,0)-'TRADE IN'!$F25=0,"",(VLOOKUP($C16,REV!$C:$AA,24,0)-'TRADE IN'!$F16)) | AA16: =IF(VLOOKUP($C16,REV!$C:$AA,25,0)-'TRADE IN'!$F25=0,"",(VLOOKUP($C16,REV!$C:$AA,25,0)-'TRADE IN'!$F16)) | AW16: =IF(REV!AW16=0,"",REV!AW16) -> 31.03.2026 | AX16: 4G
A17: Price Oferta | B17: 21X | C17: 4013660 | D17: APPLE IPHONE SE 64GB 2GER | E17: APPLE IPHONE SE 64GB 2GER-PRETO | J17: =IF(VLOOKUP($C17,REV!$C:$AA,8,0)-'TRADE IN'!$F17=0,"",(VLOOKUP($C17,REV!$C:$AA,8,0)-'TRADE IN'!$F17)) -> 799 | K17: =IF(VLOOKUP($C17,REV!$C:$AA,9,0)-'TRADE IN'!$F17=0,"",(VLOOKUP($C17,REV!$C:$AA,9,0)-'TRADE IN'!$F17)) -> 699 | L17: =IF(VLOOKUP($C17,REV!$C:$AA,10,0)-'TRADE IN'!$F26=0,"",(VLOOKUP($C17,REV!$C:$AA,10,0)-'TRADE IN'!$F17)) -> 699 | M17: =IF(VLOOKUP($C17,REV!$C:$AA,11,0)-'TRADE IN'!$F26=0,"",(VLOOKUP($C17,REV!$C:$AA,11,0)-'TRADE IN'!$F17)) -> 799 | N17: =IF(VLOOKUP($C17,REV!$C:$AA,12,0)-'TRADE IN'!$F26=0,"",(VLOOKUP($C17,REV!$C:$AA,12,0)-'TRADE IN'!$F17)) -> 799 | O17: =IF(VLOOKUP($C17,REV!$C:$AA,13,0)-'TRADE IN'!$F26=0,"",(VLOOKUP($C17,REV!$C:$AA,13,0)-'TRADE IN'!$F17)) -> 599 | P17: =IF(VLOOKUP($C17,REV!$C:$AA,14,0)-'TRADE IN'!$F26=0,"",(VLOOKUP($C17,REV!$C:$AA,14,0)-'TRADE IN'!$F17)) -> 599 | Q17: =IF(VLOOKUP($C17,REV!$C:$AA,15,0)-'TRADE IN'!$F26=0,"",(VLOOKUP($C17,REV!$C:$AA,15,0)-'TRADE IN'!$F17)) -> 599 | R17: =IF(VLOOKUP($C17,REV!$C:$AA,16,0)-'TRADE IN'!$F26=0,"",(VLOOKUP($C17,REV!$C:$AA,16,0)-'TRADE IN'!$F17)) -> 599 | S17: =IF(VLOOKUP($C17,REV!$C:$AA,17,0)-'TRADE IN'!$F26=0,"",(VLOOKUP($C17,REV!$C:$AA,17,0)-'TRADE IN'!$F17)) -> 599 | T17: =IF(VLOOKUP($C17,REV!$C:$AA,18,0)-'TRADE IN'!$F26=0,"",(VLOOKUP($C17,REV!$C:$AA,18,0)-'TRADE IN'!$F17)) -> 599 | U17: =IF(VLOOKUP($C17,REV!$C:$AA,19,0)-'TRADE IN'!$F26=0,"",(VLOOKUP($C17,REV!$C:$AA,19,0)-'TRADE IN'!$F17)) -> 599 | V17: =IF(VLOOKUP($C17,REV!$C:$AA,20,0)-'TRADE IN'!$F26=0,"",(VLOOKUP($C17,REV!$C:$AA,20,0)-'TRADE IN'!$F17)) -> 599 | W17: =IF(VLOOKUP($C17,REV!$C:$AA,21,0)-'TRADE IN'!$F26=0,"",(VLOOKUP($C17,REV!$C:$AA,21,0)-'TRADE IN'!$F17)) -> 599 | X17: =IF(VLOOKUP($C17,REV!$C:$AA,22,0)-'TRADE IN'!$F26=0,"",(VLOOKUP($C17,REV!$C:$AA,22,0)-'TRADE IN'!$F17)) -> 549 | Y17: =IF(VLOOKUP($C17,REV!$C:$AA,23,0)-'TRADE IN'!$F26=0,"",(VLOOKUP($C17,REV!$C:$AA,23,0)-'TRADE IN'!$F17)) -> 549 | Z17: =IF(VLOOKUP($C17,REV!$C:$AA,24,0)-'TRADE IN'!$F26=0,"",(VLOOKUP($C17,REV!$C:$AA,24,0)-'TRADE IN'!$F17)) -> 549 | AA17: =IF(VLOOKUP($C17,REV!$C:$AA,25,0)-'TRADE IN'!$F26=0,"",(VLOOKUP($C17,REV!$C:$AA,25,0)-'TRADE IN'!$F17)) -> 549 | AW17: =IF(REV!AW17=0,"",REV!AW17) -> 31.03.2026 | AX17: 4G
A18: Price Oferta | B18: 21X | C18: 4013661 | D18: APPLE IPHONE SE 64GB 2GER | E18: Apple iPhone SE 64GB 2Ger-Branco | J18: =IF(VLOOKUP($C18,REV!$C:$AA,8,0)-'TRADE IN'!$F18=0,"",(VLOOKUP($C18,REV!$C:$AA,8,0)-'TRADE IN'!$F18)) -> 799 | K18: =IF(VLOOKUP($C18,REV!$C:$AA,9,0)-'TRADE IN'!$F18=0,"",(VLOOKUP($C18,REV!$C:$AA,9,0)-'TRADE IN'!$F18)) -> 699 | L18: =IF(VLOOKUP($C18,REV!$C:$AA,10,0)-'TRADE IN'!$F27=0,"",(VLOOKUP($C18,REV!$C:$AA,10,0)-'TRADE IN'!$F18)) -> 699 | M18: =IF(VLOOKUP($C18,REV!$C:$AA,11,0)-'TRADE IN'!$F27=0,"",(VLOOKUP($C18,REV!$C:$AA,11,0)-'TRADE IN'!$F18)) -> 799 | N18: =IF(VLOOKUP($C18,REV!$C:$AA,12,0)-'TRADE IN'!$F27=0,"",(VLOOKUP($C18,REV!$C:$AA,12,0)-'TRADE IN'!$F18)) -> 799 | O18: =IF(VLOOKUP($C18,REV!$C:$AA,13,0)-'TRADE IN'!$F27=0,"",(VLOOKUP($C18,REV!$C:$AA,13,0)-'TRADE IN'!$F18)) -> 599 | P18: =IF(VLOOKUP($C18,REV!$C:$AA,14,0)-'TRADE IN'!$F27=0,"",(VLOOKUP($C18,REV!$C:$AA,14,0)-'TRADE IN'!$F18)) -> 599 | Q18: =IF(VLOOKUP($C18,REV!$C:$AA,15,0)-'TRADE IN'!$F27=0,"",(VLOOKUP($C18,REV!$C:$AA,15,0)-'TRADE IN'!$F18)) -> 599 | R18: =IF(VLOOKUP($C18,REV!$C:$AA,16,0)-'TRADE IN'!$F27=0,"",(VLOOKUP($C18,REV!$C:$AA,16,0)-'TRADE IN'!$F18)) -> 599 | S18: =IF(VLOOKUP($C18,REV!$C:$AA,17,0)-'TRADE IN'!$F27=0,"",(VLOOKUP($C18,REV!$C:$AA,17,0)-'TRADE IN'!$F18)) -> 599 | T18: =IF(VLOOKUP($C18,REV!$C:$AA,18,0)-'TRADE IN'!$F27=0,"",(VLOOKUP($C18,REV!$C:$AA,18,0)-'TRADE IN'!$F18)) -> 599 | U18: =IF(VLOOKUP($C18,REV!$C:$AA,19,0)-'TRADE IN'!$F27=0,"",(VLOOKUP($C18,REV!$C:$AA,19,0)-'TRADE IN'!$F18)) -> 599 | V18: =IF(VLOOKUP($C18,REV!$C:$AA,20,0)-'TRADE IN'!$F27=0,"",(VLOOKUP($C18,REV!$C:$AA,20,0)-'TRADE IN'!$F18)) -> 599 | W18: =IF(VLOOKUP($C18,REV!$C:$AA,21,0)-'TRADE IN'!$F27=0,"",(VLOOKUP($C18,REV!$C:$AA,21,0)-'TRADE IN'!$F18)) -> 599 | X18: =IF(VLOOKUP($C18,REV!$C:$AA,22,0)-'TRADE IN'!$F27=0,"",(VLOOKUP($C18,REV!$C:$AA,22,0)-'TRADE IN'!$F18)) -> 549 | Y18: =IF(VLOOKUP($C18,REV!$C:$AA,23,0)-'TRADE IN'!$F27=0,"",(VLOOKUP($C18,REV!$C:$AA,23,0)-'TRADE IN'!$F18)) -> 549 | Z18: =IF(VLOOKUP($C18,REV!$C:$AA,24,0)-'TRADE IN'!$F27=0,"",(VLOOKUP($C18,REV!$C:$AA,24,0)-'TRADE IN'!$F18)) -> 549 | AA18: =IF(VLOOKUP($C18,REV!$C:$AA,25,0)-'TRADE IN'!$F27=0,"",(VLOOKUP($C18,REV!$C:$AA,25,0)-'TRADE IN'!$F18)) -> 549 | AW18: =IF(REV!AW18=0,"",REV!AW18) -> 31.03.2026 | AX18: 4G
A19: Price Oferta | B19: 21X | C19: 4013662 | D19: APPLE IPHONE SE 64GB 2GER | E19: Apple iPhone SE 64GB 2Ger-Vermelho | J19: =IF(VLOOKUP($C19,REV!$C:$AA,8,0)-'TRADE IN'!$F19=0,"",(VLOOKUP($C19,REV!$C:$AA,8,0)-'TRADE IN'!$F19)) -> 799 | K19: =IF(VLOOKUP($C19,REV!$C:$AA,9,0)-'TRADE IN'!$F19=0,"",(VLOOKUP($C19,REV!$C:$AA,9,0)-'TRADE IN'!$F19)) -> 699 | L19: =IF(VLOOKUP($C19,REV!$C:$AA,10,0)-'TRADE IN'!$F28=0,"",(VLOOKUP($C19,REV!$C:$AA,10,0)-'TRADE IN'!$F19)) -> 699 | M19: =IF(VLOOKUP($C19,REV!$C:$AA,11,0)-'TRADE IN'!$F28=0,"",(VLOOKUP($C19,REV!$C:$AA,11,0)-'TRADE IN'!$F19)) -> 799 | N19: =IF(VLOOKUP($C19,REV!$C:$AA,12,0)-'TRADE IN'!$F28=0,"",(VLOOKUP($C19,REV!$C:$AA,12,0)-'TRADE IN'!$F19)) -> 799 | O19: =IF(VLOOKUP($C19,REV!$C:$AA,13,0)-'TRADE IN'!$F28=0,"",(VLOOKUP($C19,REV!$C:$AA,13,0)-'TRADE IN'!$F19)) -> 599 | P19: =IF(VLOOKUP($C19,REV!$C:$AA,14,0)-'TRADE IN'!$F28=0,"",(VLOOKUP($C19,REV!$C:$AA,14,0)-'TRADE IN'!$F19)) -> 599 | Q19: =IF(VLOOKUP($C19,REV!$C:$AA,15,0)-'TRADE IN'!$F28=0,"",(VLOOKUP($C19,REV!$C:$AA,15,0)-'TRADE IN'!$F19)) -> 599 | R19: =IF(VLOOKUP($C19,REV!$C:$AA,16,0)-'TRADE IN'!$F28=0,"",(VLOOKUP($C19,REV!$C:$AA,16,0)-'TRADE IN'!$F19)) -> 599 | S19: =IF(VLOOKUP($C19,REV!$C:$AA,17,0)-'TRADE IN'!$F28=0,"",(VLOOKUP($C19,REV!$C:$AA,17,0)-'TRADE IN'!$F19)) -> 599 | T19: =IF(VLOOKUP($C19,REV!$C:$AA,18,0)-'TRADE IN'!$F28=0,"",(VLOOKUP($C19,REV!$C:$AA,18,0)-'TRADE IN'!$F19)) -> 599 | U19: =IF(VLOOKUP($C19,REV!$C:$AA,19,0)-'TRADE IN'!$F28=0,"",(VLOOKUP($C19,REV!$C:$AA,19,0)-'TRADE IN'!$F19)) -> 599 | V19: =IF(VLOOKUP($C19,REV!$C:$AA,20,0)-'TRADE IN'!$F28=0,"",(VLOOKUP($C19,REV!$C:$AA,20,0)-'TRADE IN'!$F19)) -> 599 | W19: =IF(VLOOKUP($C19,REV!$C:$AA,21,0)-'TRADE IN'!$F28=0,"",(VLOOKUP($C19,REV!$C:$AA,21,0)-'TRADE IN'!$F19)) -> 599 | X19: =IF(VLOOKUP($C19,REV!$C:$AA,22,0)-'TRADE IN'!$F28=0,"",(VLOOKUP($C19,REV!$C:$AA,22,0)-'TRADE IN'!$F19)) -> 549 | Y19: =IF(VLOOKUP($C19,REV!$C:$AA,23,0)-'TRADE IN'!$F28=0,"",(VLOOKUP($C19,REV!$C:$AA,23,0)-'TRADE IN'!$F19)) -> 549 | Z19: =IF(VLOOKUP($C19,REV!$C:$AA,24,0)-'TRADE IN'!$F28=0,"",(VLOOKUP($C19,REV!$C:$AA,24,0)-'TRADE IN'!$F19)) -> 549 | AA19: =IF(VLOOKUP($C19,REV!$C:$AA,25,0)-'TRADE IN'!$F28=0,"",(VLOOKUP($C19,REV!$C:$AA,25,0)-'TRADE IN'!$F19)) -> 549 | AW19: =IF(REV!AW19=0,"",REV!AW19) -> 31.03.2026 | AX19: 4G
A20: Price Oferta | B20: 21X | C20: 4013981 | D20: APPLE IPHONE SE 64GB 2GER | E20: APPLE IPHONE SE 64GB 2GE-PRETO NAC | J20: =IF(VLOOKUP($C20,REV!$C:$AA,8,0)-'TRADE IN'!$F20=0,"",(VLOOKUP($C20,REV!$C:$AA,8,0)-'TRADE IN'!$F20)) -> 799 | K20: =IF(VLOOKUP($C20,REV!$C:$AA,9,0)-'TRADE IN'!$F20=0,"",(VLOOKUP($C20,REV!$C:$AA,9,0)-'TRADE IN'!$F20)) -> 699 | L20: =IF(VLOOKUP($C20,REV!$C:$AA,10,0)-'TRADE IN'!$F29=0,"",(VLOOKUP($C20,REV!$C:$AA,10,0)-'TRADE IN'!$F20)) -> 699 | M20: =IF(VLOOKUP($C20,REV!$C:$AA,11,0)-'TRADE IN'!$F29=0,"",(VLOOKUP($C20,REV!$C:$AA,11,0)-'TRADE IN'!$F20)) -> 799 | N20: =IF(VLOOKUP($C20,REV!$C:$AA,12,0)-'TRADE IN'!$F29=0,"",(VLOOKUP($C20,REV!$C:$AA,12,0)-'TRADE IN'!$F20)) -> 799 | O20: =IF(VLOOKUP($C20,REV!$C:$AA,13,0)-'TRADE IN'!$F29=0,"",(VLOOKUP($C20,REV!$C:$AA,13,0)-'TRADE IN'!$F20)) -> 599 | P20: =IF(VLOOKUP($C20,REV!$C:$AA,14,0)-'TRADE IN'!$F29=0,"",(VLOOKUP($C20,REV!$C:$AA,14,0)-'TRADE IN'!$F20)) -> 599 | Q20: =IF(VLOOKUP($C20,REV!$C:$AA,15,0)-'TRADE IN'!$F29=0,"",(VLOOKUP($C20,REV!$C:$AA,15,0)-'TRADE IN'!$F20)) -> 599 | R20: =IF(VLOOKUP($C20,REV!$C:$AA,16,0)-'TRADE IN'!$F29=0,"",(VLOOKUP($C20,REV!$C:$AA,16,0)-'TRADE IN'!$F20)) -> 599 | S20: =IF(VLOOKUP($C20,REV!$C:$AA,17,0)-'TRADE IN'!$F29=0,"",(VLOOKUP($C20,REV!$C:$AA,17,0)-'TRADE IN'!$F20)) -> 599 | T20: =IF(VLOOKUP($C20,REV!$C:$AA,18,0)-'TRADE IN'!$F29=0,"",(VLOOKUP($C20,REV!$C:$AA,18,0)-'TRADE IN'!$F20)) -> 599 | U20: =IF(VLOOKUP($C20,REV!$C:$AA,19,0)-'TRADE IN'!$F29=0,"",(VLOOKUP($C20,REV!$C:$AA,19,0)-'TRADE IN'!$F20)) -> 599 | V20: =IF(VLOOKUP($C20,REV!$C:$AA,20,0)-'TRADE IN'!$F29=0,"",(VLOOKUP($C20,REV!$C:$AA,20,0)-'TRADE IN'!$F20)) -> 599 | W20: =IF(VLOOKUP($C20,REV!$C:$AA,21,0)-'TRADE IN'!$F29=0,"",(VLOOKUP($C20,REV!$C:$AA,21,0)-'TRADE IN'!$F20)) -> 599 | X20: =IF(VLOOKUP($C20,REV!$C:$AA,22,0)-'TRADE IN'!$F29=0,"",(VLOOKUP($C20,REV!$C:$AA,22,0)-'TRADE IN'!$F20)) -> 549 | Y20: =IF(VLOOKUP($C20,REV!$C:$AA,23,0)-'TRADE IN'!$F29=0,"",(VLOOKUP($C20,REV!$C:$AA,23,0)-'TRADE IN'!$F20)) -> 549 | Z20: =IF(VLOOKUP($C20,REV!$C:$AA,24,0)-'TRADE IN'!$F29=0,"",(VLOOKUP($C20,REV!$C:$AA,24,0)-'TRADE IN'!$F20)) -> 549 | AA20: =IF(VLOOKUP($C20,REV!$C:$AA,25,0)-'TRADE IN'!$F29=0,"",(VLOOKUP($C20,REV!$C:$AA,25,0)-'TRADE IN'!$F20)) -> 549 | AW20: =IF(REV!AW20=0,"",REV!AW20) -> 31.03.2026 | AX20: 4G
A21: Price Oferta | B21: 21X | C21: 4013984 | D21: APPLE IPHONE SE 64GB 2GER | E21: APPLE IPHONE SE 64GB 2GE-BRANCO NAC | J21: =IF(VLOOKUP($C21,REV!$C:$AA,8,0)-'TRADE IN'!$F21=0,"",(VLOOKUP($C21,REV!$C:$AA,8,0)-'TRADE IN'!$F21)) -> 799 | K21: =IF(VLOOKUP($C21,REV!$C:$AA,9,0)-'TRADE IN'!$F21=0,"",(VLOOKUP($C21,REV!$C:$AA,9,0)-'TRADE IN'!$F21)) -> 699 | L21: =IF(VLOOKUP($C21,REV!$C:$AA,10,0)-'TRADE IN'!$F30=0,"",(VLOOKUP($C21,REV!$C:$AA,10,0)-'TRADE IN'!$F21)) -> 699 | M21: =IF(VLOOKUP($C21,REV!$C:$AA,11,0)-'TRADE IN'!$F30=0,"",(VLOOKUP($C21,REV!$C:$AA,11,0)-'TRADE IN'!$F21)) -> 799 | N21: =IF(VLOOKUP($C21,REV!$C:$AA,12,0)-'TRADE IN'!$F30=0,"",(VLOOKUP($C21,REV!$C:$AA,12,0)-'TRADE IN'!$F21)) -> 799 | O21: =IF(VLOOKUP($C21,REV!$C:$AA,13,0)-'TRADE IN'!$F30=0,"",(VLOOKUP($C21,REV!$C:$AA,13,0)-'TRADE IN'!$F21)) -> 599 | P21: =IF(VLOOKUP($C21,REV!$C:$AA,14,0)-'TRADE IN'!$F30=0,"",(VLOOKUP($C21,REV!$C:$AA,14,0)-'TRADE IN'!$F21)) -> 599 | Q21: =IF(VLOOKUP($C21,REV!$C:$AA,15,0)-'TRADE IN'!$F30=0,"",(VLOOKUP($C21,REV!$C:$AA,15,0)-'TRADE IN'!$F21)) -> 599 | R21: =IF(VLOOKUP($C21,REV!$C:$AA,16,0)-'TRADE IN'!$F30=0,"",(VLOOKUP($C21,REV!$C:$AA,16,0)-'TRADE IN'!$F21)) -> 599 | S21: =IF(VLOOKUP($C21,REV!$C:$AA,17,0)-'TRADE IN'!$F30=0,"",(VLOOKUP($C21,REV!$C:$AA,17,0)-'TRADE IN'!$F21)) -> 599 | T21: =IF(VLOOKUP($C21,REV!$C:$AA,18,0)-'TRADE IN'!$F30=0,"",(VLOOKUP($C21,REV!$C:$AA,18,0)-'TRADE IN'!$F21)) -> 599 | U21: =IF(VLOOKUP($C21,REV!$C:$AA,19,0)-'TRADE IN'!$F30=0,"",(VLOOKUP($C21,REV!$C:$AA,19,0)-'TRADE IN'!$F21)) -> 599 | V21: =IF(VLOOKUP($C21,REV!$C:$AA,20,0)-'TRADE IN'!$F30=0,"",(VLOOKUP($C21,REV!$C:$AA,20,0)-'TRADE IN'!$F21)) -> 599 | W21: =IF(VLOOKUP($C21,REV!$C:$AA,21,0)-'TRADE IN'!$F30=0,"",(VLOOKUP($C21,REV!$C:$AA,21,0)-'TRADE IN'!$F21)) -> 599 | X21: =IF(VLOOKUP($C21,REV!$C:$AA,22,0)-'TRADE IN'!$F30=0,"",(VLOOKUP($C21,REV!$C:$AA,22,0)-'TRADE IN'!$F21)) -> 549 | Y21: =IF(VLOOKUP($C21,REV!$C:$AA,23,0)-'TRADE IN'!$F30=0,"",(VLOOKUP($C21,REV!$C:$AA,23,0)-'TRADE IN'!$F21)) -> 549 | Z21: =IF(VLOOKUP($C21,REV!$C:$AA,24,0)-'TRADE IN'!$F30=0,"",(VLOOKUP($C21,REV!$C:$AA,24,0)-'TRADE IN'!$F21)) -> 549 | AA21: =IF(VLOOKUP($C21,REV!$C:$AA,25,0)-'TRADE IN'!$F30=0,"",(VLOOKUP($C21,REV!$C:$AA,25,0)-'TRADE IN'!$F21)) -> 549 | AW21: =IF(REV!AW21=0,"",REV!AW21) -> 31.03.2026 | AX21: 4G
A22: Price Oferta | B22: 21X | C22: 4013986 | D22: APPLE IPHONE SE 64GB 2GER | E22: APPLE IPHONE SE 64GB 2GE-VERMELHO NAC | J22: =IF(VLOOKUP($C22,REV!$C:$AA,8,0)-'TRADE IN'!$F22=0,"",(VLOOKUP($C22,REV!$C:$AA,8,0)-'TRADE IN'!$F22)) -> 799 | K22: =IF(VLOOKUP($C22,REV!$C:$AA,9,0)-'TRADE IN'!$F22=0,"",(VLOOKUP($C22,REV!$C:$AA,9,0)-'TRADE IN'!$F22)) -> 699 | L22: =IF(VLOOKUP($C22,REV!$C:$AA,10,0)-'TRADE IN'!$F31=0,"",(VLOOKUP($C22,REV!$C:$AA,10,0)-'TRADE IN'!$F22)) -> 699 | M22: =IF(VLOOKUP($C22,REV!$C:$AA,11,0)-'TRADE IN'!$F31=0,"",(VLOOKUP($C22,REV!$C:$AA,11,0)-'TRADE IN'!$F22)) -> 799 | N22: =IF(VLOOKUP($C22,REV!$C:$AA,12,0)-'TRADE IN'!$F31=0,"",(VLOOKUP($C22,REV!$C:$AA,12,0)-'TRADE IN'!$F22)) -> 799 | O22: =IF(VLOOKUP($C22,REV!$C:$AA,13,0)-'TRADE IN'!$F31=0,"",(VLOOKUP($C22,REV!$C:$AA,13,0)-'TRADE IN'!$F22)) -> 599 | P22: =IF(VLOOKUP($C22,REV!$C:$AA,14,0)-'TRADE IN'!$F31=0,"",(VLOOKUP($C22,REV!$C:$AA,14,0)-'TRADE IN'!$F22)) -> 599 | Q22: =IF(VLOOKUP($C22,REV!$C:$AA,15,0)-'TRADE IN'!$F31=0,"",(VLOOKUP($C22,REV!$C:$AA,15,0)-'TRADE IN'!$F22)) -> 599 | R22: =IF(VLOOKUP($C22,REV!$C:$AA,16,0)-'TRADE IN'!$F31=0,"",(VLOOKUP($C22,REV!$C:$AA,16,0)-'TRADE IN'!$F22)) -> 599 | S22: =IF(VLOOKUP($C22,REV!$C:$AA,17,0)-'TRADE IN'!$F31=0,"",(VLOOKUP($C22,REV!$C:$AA,17,0)-'TRADE IN'!$F22)) -> 599 | T22: =IF(VLOOKUP($C22,REV!$C:$AA,18,0)-'TRADE IN'!$F31=0,"",(VLOOKUP($C22,REV!$C:$AA,18,0)-'TRADE IN'!$F22)) -> 599 | U22: =IF(VLOOKUP($C22,REV!$C:$AA,19,0)-'TRADE IN'!$F31=0,"",(VLOOKUP($C22,REV!$C:$AA,19,0)-'TRADE IN'!$F22)) -> 599 | V22: =IF(VLOOKUP($C22,REV!$C:$AA,20,0)-'TRADE IN'!$F31=0,"",(VLOOKUP($C22,REV!$C:$AA,20,0)-'TRADE IN'!$F22)) -> 599 | W22: =IF(VLOOKUP($C22,REV!$C:$AA,21,0)-'TRADE IN'!$F31=0,"",(VLOOKUP($C22,REV!$C:$AA,21,0)-'TRADE IN'!$F22)) -> 599 | X22: =IF(VLOOKUP($C22,REV!$C:$AA,22,0)-'TRADE IN'!$F31=0,"",(VLOOKUP($C22,REV!$C:$AA,22,0)-'TRADE IN'!$F22)) -> 549 | Y22: =IF(VLOOKUP($C22,REV!$C:$AA,23,0)-'TRADE IN'!$F31=0,"",(VLOOKUP($C22,REV!$C:$AA,23,0)-'TRADE IN'!$F22)) -> 549 | Z22: =IF(VLOOKUP($C22,REV!$C:$AA,24,0)-'TRADE IN'!$F31=0,"",(VLOOKUP($C22,REV!$C:$AA,24,0)-'TRADE IN'!$F22)) -> 549 | AA22: =IF(VLOOKUP($C22,REV!$C:$AA,25,0)-'TRADE IN'!$F31=0,"",(VLOOKUP($C22,REV!$C:$AA,25,0)-'TRADE IN'!$F22)) -> 549 | AW22: =IF(REV!AW22=0,"",REV!AW22) -> 31.03.2026 | AX22: 4G
A23: Price Oferta | B23: 21X | C23: 4013852 | D23: APPLE IPHONE SE 64GB 2GER | E23: APPLE IPHONE SE 64GB 2GE-PRETO NAC S.KIT | J23: =IF(VLOOKUP($C23,REV!$C:$AA,8,0)-'TRADE IN'!$F23=0,"",(VLOOKUP($C23,REV!$C:$AA,8,0)-'TRADE IN'!$F23)) -> 799 | K23: =IF(VLOOKUP($C23,REV!$C:$AA,9,0)-'TRADE IN'!$F23=0,"",(VLOOKUP($C23,REV!$C:$AA,9,0)-'TRADE IN'!$F23)) -> 699 | L23: =IF(VLOOKUP($C23,REV!$C:$AA,10,0)-'TRADE IN'!$F32=0,"",(VLOOKUP($C23,REV!$C:$AA,10,0)-'TRADE IN'!$F23)) -> 699 | M23: =IF(VLOOKUP($C23,REV!$C:$AA,11,0)-'TRADE IN'!$F32=0,"",(VLOOKUP($C23,REV!$C:$AA,11,0)-'TRADE IN'!$F23)) -> 799 | N23: =IF(VLOOKUP($C23,REV!$C:$AA,12,0)-'TRADE IN'!$F32=0,"",(VLOOKUP($C23,REV!$C:$AA,12,0)-'TRADE IN'!$F23)) -> 799 | O23: =IF(VLOOKUP($C23,REV!$C:$AA,13,0)-'TRADE IN'!$F32=0,"",(VLOOKUP($C23,REV!$C:$AA,13,0)-'TRADE IN'!$F23)) -> 599 | P23: =IF(VLOOKUP($C23,REV!$C:$AA,14,0)-'TRADE IN'!$F32=0,"",(VLOOKUP($C23,REV!$C:$AA,14,0)-'TRADE IN'!$F23)) -> 599 | Q23: =IF(VLOOKUP($C23,REV!$C:$AA,15,0)-'TRADE IN'!$F32=0,"",(VLOOKUP($C23,REV!$C:$AA,15,0)-'TRADE IN'!$F23)) -> 599 | R23: =IF(VLOOKUP($C23,REV!$C:$AA,16,0)-'TRADE IN'!$F32=0,"",(VLOOKUP($C23,REV!$C:$AA,16,0)-'TRADE IN'!$F23)) -> 599 | S23: =IF(VLOOKUP($C23,REV!$C:$AA,17,0)-'TRADE IN'!$F32=0,"",(VLOOKUP($C23,REV!$C:$AA,17,0)-'TRADE IN'!$F23)) -> 599 | T23: =IF(VLOOKUP($C23,REV!$C:$AA,18,0)-'TRADE IN'!$F32=0,"",(VLOOKUP($C23,REV!$C:$AA,18,0)-'TRADE IN'!$F23)) -> 599 | U23: =IF(VLOOKUP($C23,REV!$C:$AA,19,0)-'TRADE IN'!$F32=0,"",(VLOOKUP($C23,REV!$C:$AA,19,0)-'TRADE IN'!$F23)) -> 599 | V23: =IF(VLOOKUP($C23,REV!$C:$AA,20,0)-'TRADE IN'!$F32=0,"",(VLOOKUP($C23,REV!$C:$AA,20,0)-'TRADE IN'!$F23)) -> 599 | W23: =IF(VLOOKUP($C23,REV!$C:$AA,21,0)-'TRADE IN'!$F32=0,"",(VLOOKUP($C23,REV!$C:$AA,21,0)-'TRADE IN'!$F23)) -> 599 | X23: =IF(VLOOKUP($C23,REV!$C:$AA,22,0)-'TRADE IN'!$F32=0,"",(VLOOKUP($C23,REV!$C:$AA,22,0)-'TRADE IN'!$F23)) -> 549 | Y23: =IF(VLOOKUP($C23,REV!$C:$AA,23,0)-'TRADE IN'!$F32=0,"",(VLOOKUP($C23,REV!$C:$AA,23,0)-'TRADE IN'!$F23)) -> 549 | Z23: =IF(VLOOKUP($C23,REV!$C:$AA,24,0)-'TRADE IN'!$F32=0,"",(VLOOKUP($C23,REV!$C:$AA,24,0)-'TRADE IN'!$F23)) -> 549 | AA23: =IF(VLOOKUP($C23,REV!$C:$AA,25,0)-'TRADE IN'!$F32=0,"",(VLOOKUP($C23,REV!$C:$AA,25,0)-'TRADE IN'!$F23)) -> 549 | AW23: =IF(REV!AW23=0,"",REV!AW23) -> 31.03.2026 | AX23: 4G
A24: Price Oferta | B24: 21X | C24: 4014002 | D24: APPLE IPHONE SE 64GB 2GER | E24: APPLE IPHONE SE 64GB 2GE-BRANC NAC S.KIT | J24: =IF(VLOOKUP($C24,REV!$C:$AA,8,0)-'TRADE IN'!$F24=0,"",(VLOOKUP($C24,REV!$C:$AA,8,0)-'TRADE IN'!$F24)) -> 799 | K24: =IF(VLOOKUP($C24,REV!$C:$AA,9,0)-'TRADE IN'!$F24=0,"",(VLOOKUP($C24,REV!$C:$AA,9,0)-'TRADE IN'!$F24)) -> 699 | L24: =IF(VLOOKUP($C24,REV!$C:$AA,10,0)-'TRADE IN'!$F33=0,"",(VLOOKUP($C24,REV!$C:$AA,10,0)-'TRADE IN'!$F24)) -> 699 | M24: =IF(VLOOKUP($C24,REV!$C:$AA,11,0)-'TRADE IN'!$F33=0,"",(VLOOKUP($C24,REV!$C:$AA,11,0)-'TRADE IN'!$F24)) -> 799 | N24: =IF(VLOOKUP($C24,REV!$C:$AA,12,0)-'TRADE IN'!$F33=0,"",(VLOOKUP($C24,REV!$C:$AA,12,0)-'TRADE IN'!$F24)) -> 799 | O24: =IF(VLOOKUP($C24,REV!$C:$AA,13,0)-'TRADE IN'!$F33=0,"",(VLOOKUP($C24,REV!$C:$AA,13,0)-'TRADE IN'!$F24)) -> 599 | P24: =IF(VLOOKUP($C24,REV!$C:$AA,14,0)-'TRADE IN'!$F33=0,"",(VLOOKUP($C24,REV!$C:$AA,14,0)-'TRADE IN'!$F24)) -> 599 | Q24: =IF(VLOOKUP($C24,REV!$C:$AA,15,0)-'TRADE IN'!$F33=0,"",(VLOOKUP($C24,REV!$C:$AA,15,0)-'TRADE IN'!$F24)) -> 599 | R24: =IF(VLOOKUP($C24,REV!$C:$AA,16,0)-'TRADE IN'!$F33=0,"",(VLOOKUP($C24,REV!$C:$AA,16,0)-'TRADE IN'!$F24)) -> 599 | S24: =IF(VLOOKUP($C24,REV!$C:$AA,17,0)-'TRADE IN'!$F33=0,"",(VLOOKUP($C24,REV!$C:$AA,17,0)-'TRADE IN'!$F24)) -> 599 | T24: =IF(VLOOKUP($C24,REV!$C:$AA,18,0)-'TRADE IN'!$F33=0,"",(VLOOKUP($C24,REV!$C:$AA,18,0)-'TRADE IN'!$F24)) -> 599 | U24: =IF(VLOOKUP($C24,REV!$C:$AA,19,0)-'TRADE IN'!$F33=0,"",(VLOOKUP($C24,REV!$C:$AA,19,0)-'TRADE IN'!$F24)) -> 599 | V24: =IF(VLOOKUP($C24,REV!$C:$AA,20,0)-'TRADE IN'!$F33=0,"",(VLOOKUP($C24,REV!$C:$AA,20,0)-'TRADE IN'!$F24)) -> 599 | W24: =IF(VLOOKUP($C24,REV!$C:$AA,21,0)-'TRADE IN'!$F33=0,"",(VLOOKUP($C24,REV!$C:$AA,21,0)-'TRADE IN'!$F24)) -> 599 | X24: =IF(VLOOKUP($C24,REV!$C:$AA,22,0)-'TRADE IN'!$F33=0,"",(VLOOKUP($C24,REV!$C:$AA,22,0)-'TRADE IN'!$F24)) -> 549 | Y24: =IF(VLOOKUP($C24,REV!$C:$AA,23,0)-'TRADE IN'!$F33=0,"",(VLOOKUP($C24,REV!$C:$AA,23,0)-'TRADE IN'!$F24)) -> 549 | Z24: =IF(VLOOKUP($C24,REV!$C:$AA,24,0)-'TRADE IN'!$F33=0,"",(VLOOKUP($C24,REV!$C:$AA,24,0)-'TRADE IN'!$F24)) -> 549 | AA24: =IF(VLOOKUP($C24,REV!$C:$AA,25,0)-'TRADE IN'!$F33=0,"",(VLOOKUP($C24,REV!$C:$AA,25,0)-'TRADE IN'!$F24)) -> 549 | AW24: =IF(REV!AW24=0,"",REV!AW24) -> 31.03.2026 | AX24: 4G
... A182: Price Oferta | B182: 21X | C182: 4016613 | D182: APPLE IPHONE 16 PRO MAX 512GB | E182: APPLE IPHONE 16 PRO MAX 512GB-DESERTO | J182: =IF(VLOOKUP($C182,REV!$C:$AA,8,0)-'TRADE IN'!$F182=0,"",(VLOOKUP($C182,REV!$C:$AA,8,0)-'TRADE IN'!$F182)) -> 11999 | K182: =IF(VLOOKUP($C182,REV!$C:$AA,9,0)-'TRADE IN'!$F182=0,"",(VLOOKUP($C182,REV!$C:$AA,9,0)-'TRADE IN'!$F182)) -> 11999 | L182: =IF(VLOOKUP($C182,REV!$C:$AA,10,0)-'TRADE IN'!$F191=0,"",(VLOOKUP($C182,REV!$C:$AA,10,0)-'TRADE IN'!$F182)) -> 11999 | M182: =IF(VLOOKUP($C182,REV!$C:$AA,11,0)-'TRADE IN'!$F191=0,"",(VLOOKUP($C182,REV!$C:$AA,11,0)-'TRADE IN'!$F182)) -> 11999 | N182: =IF(VLOOKUP($C182,REV!$C:$AA,12,0)-'TRADE IN'!$F191=0,"",(VLOOKUP($C182,REV!$C:$AA,12,0)-'TRADE IN'!$F182)) -> 11999 | O182: =IF(VLOOKUP($C182,REV!$C:$AA,13,0)-'TRADE IN'!$F191=0,"",(VLOOKUP($C182,REV!$C:$AA,13,0)-'TRADE IN'!$F182)) -> 11699 | P182: =IF(VLOOKUP($C182,REV!$C:$AA,14,0)-'TRADE IN'!$F191=0,"",(VLOOKUP($C182,REV!$C:$AA,14,0)-'TRADE IN'!$F182)) -> 11599 | Q182: =IF(VLOOKUP($C182,REV!$C:$AA,15,0)-'TRADE IN'!$F191=0,"",(VLOOKUP($C182,REV!$C:$AA,15,0)-'TRADE IN'!$F182)) -> 10999 | R182: =IF(VLOOKUP($C182,REV!$C:$AA,16,0)-'TRADE IN'!$F191=0,"",(VLOOKUP($C182,REV!$C:$AA,16,0)-'TRADE IN'!$F182)) -> 11699 | S182: =IF(VLOOKUP($C182,REV!$C:$AA,17,0)-'TRADE IN'!$F191=0,"",(VLOOKUP($C182,REV!$C:$AA,17,0)-'TRADE IN'!$F182)) -> 11599 | T182: =IF(VLOOKUP($C182,REV!$C:$AA,18,0)-'TRADE IN'!$F191=0,"",(VLOOKUP($C182,REV!$C:$AA,18,0)-'TRADE IN'!$F182)) -> 10999 | U182: =IF(VLOOKUP($C182,REV!$C:$AA,19,0)-'TRADE IN'!$F191=0,"",(VLOOKUP($C182,REV!$C:$AA,19,0)-'TRADE IN'!$F182)) -> 10999 | V182: =IF(VLOOKUP($C182,REV!$C:$AA,20,0)-'TRADE IN'!$F191=0,"",(VLOOKUP($C182,REV!$C:$AA,20,0)-'TRADE IN'!$F182)) -> 10999 | W182: =IF(VLOOKUP($C182,REV!$C:$AA,21,0)-'TRADE IN'!$F191=0,"",(VLOOKUP($C182,REV!$C:$AA,21,0)-'TRADE IN'!$F182)) -> 10999 | X182: =IF(VLOOKUP($C182,REV!$C:$AA,22,0)-'TRADE IN'!$F191=0,"",(VLOOKUP($C182,REV!$C:$AA,22,0)-'TRADE IN'!$F182)) -> 10799 | Y182: =IF(VLOOKUP($C182,REV!$C:$AA,23,0)-'TRADE IN'!$F191=0,"",(VLOOKUP($C182,REV!$C:$AA,23,0)-'TRADE IN'!$F182)) -> 10299 | Z182: =IF(VLOOKUP($C182,REV!$C:$AA,24,0)-'TRADE IN'!$F191=0,"",(VLOOKUP($C182,REV!$C:$AA,24,0)-'TRADE IN'!$F182)) -> 10299 | AA182: =IF(VLOOKUP($C182,REV!$C:$AA,25,0)-'TRADE IN'!$F191=0,"",(VLOOKUP($C182,REV!$C:$AA,25,0)-'TRADE IN'!$F182)) -> 10299 | AW182: =IF(REV!AW182=0,"",REV!AW182) -> 31.03.2026 | AX182: 5G
A183: Price Oferta | B183: 21X | C183: 4016619 | D183: APPLE IPHONE 16 PRO MAX 512GB | E183: APPLE IPHONE 16 PRO MAX 512GB-PRETO | J183: =IF(VLOOKUP($C183,REV!$C:$AA,8,0)-'TRADE IN'!$F183=0,"",(VLOOKUP($C183,REV!$C:$AA,8,0)-'TRADE IN'!$F183)) -> 11999 | K183: =IF(VLOOKUP($C183,REV!$C:$AA,9,0)-'TRADE IN'!$F183=0,"",(VLOOKUP($C183,REV!$C:$AA,9,0)-'TRADE IN'!$F183)) -> 11999 | L183: =IF(VLOOKUP($C183,REV!$C:$AA,10,0)-'TRADE IN'!$F194=0,"",(VLOOKUP($C183,REV!$C:$AA,10,0)-'TRADE IN'!$F183)) -> 11999 | M183: =IF(VLOOKUP($C183,REV!$C:$AA,11,0)-'TRADE IN'!$F194=0,"",(VLOOKUP($C183,REV!$C:$AA,11,0)-'TRADE IN'!$F183)) -> 11999 | N183: =IF(VLOOKUP($C183,REV!$C:$AA,12,0)-'TRADE IN'!$F194=0,"",(VLOOKUP($C183,REV!$C:$AA,12,0)-'TRADE IN'!$F183)) -> 11999 | O183: =IF(VLOOKUP($C183,REV!$C:$AA,13,0)-'TRADE IN'!$F194=0,"",(VLOOKUP($C183,REV!$C:$AA,13,0)-'TRADE IN'!$F183)) -> 11699 | P183: =IF(VLOOKUP($C183,REV!$C:$AA,14,0)-'TRADE IN'!$F194=0,"",(VLOOKUP($C183,REV!$C:$AA,14,0)-'TRADE IN'!$F183)) -> 11599 | Q183: =IF(VLOOKUP($C183,REV!$C:$AA,15,0)-'TRADE IN'!$F194=0,"",(VLOOKUP($C183,REV!$C:$AA,15,0)-'TRADE IN'!$F183)) -> 10999 | R183: =IF(VLOOKUP($C183,REV!$C:$AA,16,0)-'TRADE IN'!$F194=0,"",(VLOOKUP($C183,REV!$C:$AA,16,0)-'TRADE IN'!$F183)) -> 11699 | S183: =IF(VLOOKUP($C183,REV!$C:$AA,17,0)-'TRADE IN'!$F194=0,"",(VLOOKUP($C183,REV!$C:$AA,17,0)-'TRADE IN'!$F183)) -> 11599 | T183: =IF(VLOOKUP($C183,REV!$C:$AA,18,0)-'TRADE IN'!$F194=0,"",(VLOOKUP($C183,REV!$C:$AA,18,0)-'TRADE IN'!$F183)) -> 10999 | U183: =IF(VLOOKUP($C183,REV!$C:$AA,19,0)-'TRADE IN'!$F194=0,"",(VLOOKUP($C183,REV!$C:$AA,19,0)-'TRADE IN'!$F183)) -> 10999 | V183: =IF(VLOOKUP($C183,REV!$C:$AA,20,0)-'TRADE IN'!$F194=0,"",(VLOOKUP($C183,REV!$C:$AA,20,0)-'TRADE IN'!$F183)) -> 10999 | W183: =IF(VLOOKUP($C183,REV!$C:$AA,21,0)-'TRADE IN'!$F194=0,"",(VLOOKUP($C183,REV!$C:$AA,21,0)-'TRADE IN'!$F183)) -> 10999 | X183: =IF(VLOOKUP($C183,REV!$C:$AA,22,0)-'TRADE IN'!$F194=0,"",(VLOOKUP($C183,REV!$C:$AA,22,0)-'TRADE IN'!$F183)) -> 10799 | Y183: =IF(VLOOKUP($C183,REV!$C:$AA,23,0)-'TRADE IN'!$F194=0,"",(VLOOKUP($C183,REV!$C:$AA,23,0)-'TRADE IN'!$F183)) -> 10299 | Z183: =IF(VLOOKUP($C183,REV!$C:$AA,24,0)-'TRADE IN'!$F194=0,"",(VLOOKUP($C183,REV!$C:$AA,24,0)-'TRADE IN'!$F183)) -> 10299 | AA183: =IF(VLOOKUP($C183,REV!$C:$AA,25,0)-'TRADE IN'!$F194=0,"",(VLOOKUP($C183,REV!$C:$AA,25,0)-'TRADE IN'!$F183)) -> 10299 | AW183: =IF(REV!AW183=0,"",REV!AW183) -> 31.03.2026 | AX183: 5G
A184: Price Oferta | B184: 21X | C184: 4016609 | D184: APPLE IPHONE 16 PRO MAX 512GB | E184: APPLE IPHONE 16 PRO MAX 512GB-TITANIO | J184: =IF(VLOOKUP($C184,REV!$C:$AA,8,0)-'TRADE IN'!$F184=0,"",(VLOOKUP($C184,REV!$C:$AA,8,0)-'TRADE IN'!$F184)) -> 11999 | K184: =IF(VLOOKUP($C184,REV!$C:$AA,9,0)-'TRADE IN'!$F184=0,"",(VLOOKUP($C184,REV!$C:$AA,9,0)-'TRADE IN'!$F184)) -> 11999 | L184: =IF(VLOOKUP($C184,REV!$C:$AA,10,0)-'TRADE IN'!$F195=0,"",(VLOOKUP($C184,REV!$C:$AA,10,0)-'TRADE IN'!$F184)) -> 11999 | M184: =IF(VLOOKUP($C184,REV!$C:$AA,11,0)-'TRADE IN'!$F195=0,"",(VLOOKUP($C184,REV!$C:$AA,11,0)-'TRADE IN'!$F184)) -> 11999 | N184: =IF(VLOOKUP($C184,REV!$C:$AA,12,0)-'TRADE IN'!$F195=0,"",(VLOOKUP($C184,REV!$C:$AA,12,0)-'TRADE IN'!$F184)) -> 11999 | O184: =IF(VLOOKUP($C184,REV!$C:$AA,13,0)-'TRADE IN'!$F195=0,"",(VLOOKUP($C184,REV!$C:$AA,13,0)-'TRADE IN'!$F184)) -> 11699 | P184: =IF(VLOOKUP($C184,REV!$C:$AA,14,0)-'TRADE IN'!$F195=0,"",(VLOOKUP($C184,REV!$C:$AA,14,0)-'TRADE IN'!$F184)) -> 11599 | Q184: =IF(VLOOKUP($C184,REV!$C:$AA,15,0)-'TRADE IN'!$F195=0,"",(VLOOKUP($C184,REV!$C:$AA,15,0)-'TRADE IN'!$F184)) -> 10999 | R184: =IF(VLOOKUP($C184,REV!$C:$AA,16,0)-'TRADE IN'!$F195=0,"",(VLOOKUP($C184,REV!$C:$AA,16,0)-'TRADE IN'!$F184)) -> 11699 | S184: =IF(VLOOKUP($C184,REV!$C:$AA,17,0)-'TRADE IN'!$F195=0,"",(VLOOKUP($C184,REV!$C:$AA,17,0)-'TRADE IN'!$F184)) -> 11599 | T184: =IF(VLOOKUP($C184,REV!$C:$AA,18,0)-'TRADE IN'!$F195=0,"",(VLOOKUP($C184,REV!$C:$AA,18,0)-'TRADE IN'!$F184)) -> 10999 | U184: =IF(VLOOKUP($C184,REV!$C:$AA,19,0)-'TRADE IN'!$F195=0,"",(VLOOKUP($C184,REV!$C:$AA,19,0)-'TRADE IN'!$F184)) -> 10999 | V184: =IF(VLOOKUP($C184,REV!$C:$AA,20,0)-'TRADE IN'!$F195=0,"",(VLOOKUP($C184,REV!$C:$AA,20,0)-'TRADE IN'!$F184)) -> 10999 | W184: =IF(VLOOKUP($C184,REV!$C:$AA,21,0)-'TRADE IN'!$F195=0,"",(VLOOKUP($C184,REV!$C:$AA,21,0)-'TRADE IN'!$F184)) -> 10999 | X184: =IF(VLOOKUP($C184,REV!$C:$AA,22,0)-'TRADE IN'!$F195=0,"",(VLOOKUP($C184,REV!$C:$AA,22,0)-'TRADE IN'!$F184)) -> 10799 | Y184: =IF(VLOOKUP($C184,REV!$C:$AA,23,0)-'TRADE IN'!$F195=0,"",(VLOOKUP($C184,REV!$C:$AA,23,0)-'TRADE IN'!$F184)) -> 10299 | Z184: =IF(VLOOKUP($C184,REV!$C:$AA,24,0)-'TRADE IN'!$F195=0,"",(VLOOKUP($C184,REV!$C:$AA,24,0)-'TRADE IN'!$F184)) -> 10299 | AA184: =IF(VLOOKUP($C184,REV!$C:$AA,25,0)-'TRADE IN'!$F195=0,"",(VLOOKUP($C184,REV!$C:$AA,25,0)-'TRADE IN'!$F184)) -> 10299 | AW184: =IF(REV!AW184=0,"",REV!AW184) -> 31.03.2026 | AX184: 5G
A185: Price Oferta | B185: 21X | C185: 4016916 | D185: APPLE IPHONE 16E 256GB | E185: APPLE IPHONE 16E 256GB-PRETO NAC | J185: =IF(VLOOKUP($C185,REV!$C:$AA,8,0)-'TRADE IN'!$F185=0,"",(VLOOKUP($C185,REV!$C:$AA,8,0)-'TRADE IN'!$F185)) -> 4799 | K185: =IF(VLOOKUP($C185,REV!$C:$AA,9,0)-'TRADE IN'!$F185=0,"",(VLOOKUP($C185,REV!$C:$AA,9,0)-'TRADE IN'!$F185)) -> 4799 | L185: =IF(VLOOKUP($C185,REV!$C:$AA,10,0)-'TRADE IN'!$F196=0,"",(VLOOKUP($C185,REV!$C:$AA,10,0)-'TRADE IN'!$F185)) -> 4799 | M185: =IF(VLOOKUP($C185,REV!$C:$AA,11,0)-'TRADE IN'!$F196=0,"",(VLOOKUP($C185,REV!$C:$AA,11,0)-'TRADE IN'!$F185)) -> 4799 | N185: =IF(VLOOKUP($C185,REV!$C:$AA,12,0)-'TRADE IN'!$F196=0,"",(VLOOKUP($C185,REV!$C:$AA,12,0)-'TRADE IN'!$F185)) -> 4799 | O185: =IF(VLOOKUP($C185,REV!$C:$AA,13,0)-'TRADE IN'!$F196=0,"",(VLOOKUP($C185,REV!$C:$AA,13,0)-'TRADE IN'!$F185)) -> 4699 | P185: =IF(VLOOKUP($C185,REV!$C:$AA,14,0)-'TRADE IN'!$F196=0,"",(VLOOKUP($C185,REV!$C:$AA,14,0)-'TRADE IN'!$F185)) -> 4599 | Q185: =IF(VLOOKUP($C185,REV!$C:$AA,15,0)-'TRADE IN'!$F196=0,"",(VLOOKUP($C185,REV!$C:$AA,15,0)-'TRADE IN'!$F185)) -> 3599 | R185: =IF(VLOOKUP($C185,REV!$C:$AA,16,0)-'TRADE IN'!$F196=0,"",(VLOOKUP($C185,REV!$C:$AA,16,0)-'TRADE IN'!$F185)) -> 4699 | S185: =IF(VLOOKUP($C185,REV!$C:$AA,17,0)-'TRADE IN'!$F196=0,"",(VLOOKUP($C185,REV!$C:$AA,17,0)-'TRADE IN'!$F185)) -> 4599 | T185: =IF(VLOOKUP($C185,REV!$C:$AA,18,0)-'TRADE IN'!$F196=0,"",(VLOOKUP($C185,REV!$C:$AA,18,0)-'TRADE IN'!$F185)) -> 3599 | U185: =IF(VLOOKUP($C185,REV!$C:$AA,19,0)-'TRADE IN'!$F196=0,"",(VLOOKUP($C185,REV!$C:$AA,19,0)-'TRADE IN'!$F185)) -> 3599 | V185: =IF(VLOOKUP($C185,REV!$C:$AA,20,0)-'TRADE IN'!$F196=0,"",(VLOOKUP($C185,REV!$C:$AA,20,0)-'TRADE IN'!$F185)) -> 3599 | W185: =IF(VLOOKUP($C185,REV!$C:$AA,21,0)-'TRADE IN'!$F196=0,"",(VLOOKUP($C185,REV!$C:$AA,21,0)-'TRADE IN'!$F185)) -> 3599 | X185: =IF(VLOOKUP($C185,REV!$C:$AA,22,0)-'TRADE IN'!$F196=0,"",(VLOOKUP($C185,REV!$C:$AA,22,0)-'TRADE IN'!$F185)) -> 3499 | Y185: =IF(VLOOKUP($C185,REV!$C:$AA,23,0)-'TRADE IN'!$F196=0,"",(VLOOKUP($C185,REV!$C:$AA,23,0)-'TRADE IN'!$F185)) -> 3299 | Z185: =IF(VLOOKUP($C185,REV!$C:$AA,24,0)-'TRADE IN'!$F196=0,"",(VLOOKUP($C185,REV!$C:$AA,24,0)-'TRADE IN'!$F185)) -> 3299 | AA185: =IF(VLOOKUP($C185,REV!$C:$AA,25,0)-'TRADE IN'!$F196=0,"",(VLOOKUP($C185,REV!$C:$AA,25,0)-'TRADE IN'!$F185)) -> 3299 | AW185: =IF(REV!AW185=0,"",REV!AW185) -> 31.03.2026 | AX185: 5G
A186: Price Oferta | B186: 21X | C186: 4016917 | D186: APPLE IPHONE 16E 256GB | E186: APPLE IPHONE 16E 256GB-BRANCO NAC | J186: =IF(VLOOKUP($C186,REV!$C:$AA,8,0)-'TRADE IN'!$F186=0,"",(VLOOKUP($C186,REV!$C:$AA,8,0)-'TRADE IN'!$F186)) -> 4799 | K186: =IF(VLOOKUP($C186,REV!$C:$AA,9,0)-'TRADE IN'!$F186=0,"",(VLOOKUP($C186,REV!$C:$AA,9,0)-'TRADE IN'!$F186)) -> 4799 | L186: =IF(VLOOKUP($C186,REV!$C:$AA,10,0)-'TRADE IN'!$F197=0,"",(VLOOKUP($C186,REV!$C:$AA,10,0)-'TRADE IN'!$F186)) -> 4799 | M186: =IF(VLOOKUP($C186,REV!$C:$AA,11,0)-'TRADE IN'!$F197=0,"",(VLOOKUP($C186,REV!$C:$AA,11,0)-'TRADE IN'!$F186)) -> 4799 | N186: =IF(VLOOKUP($C186,REV!$C:$AA,12,0)-'TRADE IN'!$F197=0,"",(VLOOKUP($C186,REV!$C:$AA,12,0)-'TRADE IN'!$F186)) -> 4799 | O186: =IF(VLOOKUP($C186,REV!$C:$AA,13,0)-'TRADE IN'!$F197=0,"",(VLOOKUP($C186,REV!$C:$AA,13,0)-'TRADE IN'!$F186)) -> 4699 | P186: =IF(VLOOKUP($C186,REV!$C:$AA,14,0)-'TRADE IN'!$F197=0,"",(VLOOKUP($C186,REV!$C:$AA,14,0)-'TRADE IN'!$F186)) -> 4599 | Q186: =IF(VLOOKUP($C186,REV!$C:$AA,15,0)-'TRADE IN'!$F197=0,"",(VLOOKUP($C186,REV!$C:$AA,15,0)-'TRADE IN'!$F186)) -> 3599 | R186: =IF(VLOOKUP($C186,REV!$C:$AA,16,0)-'TRADE IN'!$F197=0,"",(VLOOKUP($C186,REV!$C:$AA,16,0)-'TRADE IN'!$F186)) -> 4699 | S186: =IF(VLOOKUP($C186,REV!$C:$AA,17,0)-'TRADE IN'!$F197=0,"",(VLOOKUP($C186,REV!$C:$AA,17,0)-'TRADE IN'!$F186)) -> 4599 | T186: =IF(VLOOKUP($C186,REV!$C:$AA,18,0)-'TRADE IN'!$F197=0,"",(VLOOKUP($C186,REV!$C:$AA,18,0)-'TRADE IN'!$F186)) -> 3599 | U186: =IF(VLOOKUP($C186,REV!$C:$AA,19,0)-'TRADE IN'!$F197=0,"",(VLOOKUP($C186,REV!$C:$AA,19,0)-'TRADE IN'!$F186)) -> 3599 | V186: =IF(VLOOKUP($C186,REV!$C:$AA,20,0)-'TRADE IN'!$F197=0,"",(VLOOKUP($C186,REV!$C:$AA,20,0)-'TRADE IN'!$F186)) -> 3599 | W186: =IF(VLOOKUP($C186,REV!$C:$AA,21,0)-'TRADE IN'!$F197=0,"",(VLOOKUP($C186,REV!$C:$AA,21,0)-'TRADE IN'!$F186)) -> 3599 | X186: =IF(VLOOKUP($C186,REV!$C:$AA,22,0)-'TRADE IN'!$F197=0,"",(VLOOKUP($C186,REV!$C:$AA,22,0)-'TRADE IN'!$F186)) -> 3499 | Y186: =IF(VLOOKUP($C186,REV!$C:$AA,23,0)-'TRADE IN'!$F197=0,"",(VLOOKUP($C186,REV!$C:$AA,23,0)-'TRADE IN'!$F186)) -> 3299 | Z186: =IF(VLOOKUP($C186,REV!$C:$AA,24,0)-'TRADE IN'!$F197=0,"",(VLOOKUP($C186,REV!$C:$AA,24,0)-'TRADE IN'!$F186)) -> 3299 | AA186: =IF(VLOOKUP($C186,REV!$C:$AA,25,0)-'TRADE IN'!$F197=0,"",(VLOOKUP($C186,REV!$C:$AA,25,0)-'TRADE IN'!$F186)) -> 3299 | AW186: =IF(REV!AW186=0,"",REV!AW186) -> 31.03.2026 | AX186: 5G
A187: Price Oferta | B187: 21X | C187: 4017449 | D187: APPLE IPHONE 17 256GB | E187: APPLE IPHONE 17 256GB-LAVANDA | J187: =IF(VLOOKUP($C187,REV!$C:$AA,8,0)-'TRADE IN'!$F187=0,"",(VLOOKUP($C187,REV!$C:$AA,8,0)-'TRADE IN'!$F187)) -> 7499 | K187: =IF(VLOOKUP($C187,REV!$C:$AA,9,0)-'TRADE IN'!$F187=0,"",(VLOOKUP($C187,REV!$C:$AA,9,0)-'TRADE IN'!$F187)) -> 7499 | L187: =IF(VLOOKUP($C187,REV!$C:$AA,10,0)-'TRADE IN'!$F198=0,"",(VLOOKUP($C187,REV!$C:$AA,10,0)-'TRADE IN'!$F187)) -> 7499 | M187: =IF(VLOOKUP($C187,REV!$C:$AA,11,0)-'TRADE IN'!$F198=0,"",(VLOOKUP($C187,REV!$C:$AA,11,0)-'TRADE IN'!$F187)) -> 7499 | N187: =IF(VLOOKUP($C187,REV!$C:$AA,12,0)-'TRADE IN'!$F198=0,"",(VLOOKUP($C187,REV!$C:$AA,12,0)-'TRADE IN'!$F187)) -> 7499 | O187: =IF(VLOOKUP($C187,REV!$C:$AA,13,0)-'TRADE IN'!$F198=0,"",(VLOOKUP($C187,REV!$C:$AA,13,0)-'TRADE IN'!$F187)) -> 7399 | P187: =IF(VLOOKUP($C187,REV!$C:$AA,14,0)-'TRADE IN'!$F198=0,"",(VLOOKUP($C187,REV!$C:$AA,14,0)-'TRADE IN'!$F187)) -> 7299 | Q187: =IF(VLOOKUP($C187,REV!$C:$AA,15,0)-'TRADE IN'!$F198=0,"",(VLOOKUP($C187,REV!$C:$AA,15,0)-'TRADE IN'!$F187)) -> 6499 | R187: =IF(VLOOKUP($C187,REV!$C:$AA,16,0)-'TRADE IN'!$F198=0,"",(VLOOKUP($C187,REV!$C:$AA,16,0)-'TRADE IN'!$F187)) -> 7399 | S187: =IF(VLOOKUP($C187,REV!$C:$AA,17,0)-'TRADE IN'!$F198=0,"",(VLOOKUP($C187,REV!$C:$AA,17,0)-'TRADE IN'!$F187)) -> 7299 | T187: =IF(VLOOKUP($C187,REV!$C:$AA,18,0)-'TRADE IN'!$F198=0,"",(VLOOKUP($C187,REV!$C:$AA,18,0)-'TRADE IN'!$F187)) -> 6499 | U187: =IF(VLOOKUP($C187,REV!$C:$AA,19,0)-'TRADE IN'!$F198=0,"",(VLOOKUP($C187,REV!$C:$AA,19,0)-'TRADE IN'!$F187)) -> 6499 | V187: =IF(VLOOKUP($C187,REV!$C:$AA,20,0)-'TRADE IN'!$F198=0,"",(VLOOKUP($C187,REV!$C:$AA,20,0)-'TRADE IN'!$F187)) -> 6499 | W187: =IF(VLOOKUP($C187,REV!$C:$AA,21,0)-'TRADE IN'!$F198=0,"",(VLOOKUP($C187,REV!$C:$AA,21,0)-'TRADE IN'!$F187)) -> 6399 | X187: =IF(VLOOKUP($C187,REV!$C:$AA,22,0)-'TRADE IN'!$F198=0,"",(VLOOKUP($C187,REV!$C:$AA,22,0)-'TRADE IN'!$F187)) -> 6399 | Y187: =IF(VLOOKUP($C187,REV!$C:$AA,23,0)-'TRADE IN'!$F198=0,"",(VLOOKUP($C187,REV!$C:$AA,23,0)-'TRADE IN'!$F187)) -> 5799 | Z187: =IF(VLOOKUP($C187,REV!$C:$AA,24,0)-'TRADE IN'!$F198=0,"",(VLOOKUP($C187,REV!$C:$AA,24,0)-'TRADE IN'!$F187)) -> 5799 | AA187: =IF(VLOOKUP($C187,REV!$C:$AA,25,0)-'TRADE IN'!$F198=0,"",(VLOOKUP($C187,REV!$C:$AA,25,0)-'TRADE IN'!$F187)) -> 5799 | AW187: =IF(REV!AW187=0,"",REV!AW187) -> 31.03.2026 | AX187: 5G
A188: Price Oferta | B188: 21X | C188: 4017480 | D188: APPLE IPHONE 17 256GB | E188: APPLE IPHONE 17 256GB-AZUL NEVOA | J188: =IF(VLOOKUP($C188,REV!$C:$AA,8,0)-'TRADE IN'!$F188=0,"",(VLOOKUP($C188,REV!$C:$AA,8,0)-'TRADE IN'!$F188)) -> 7499 | K188: =IF(VLOOKUP($C188,REV!$C:$AA,9,0)-'TRADE IN'!$F188=0,"",(VLOOKUP($C188,REV!$C:$AA,9,0)-'TRADE IN'!$F188)) -> 7499 | L188: =IF(VLOOKUP($C188,REV!$C:$AA,10,0)-'TRADE IN'!$F199=0,"",(VLOOKUP($C188,REV!$C:$AA,10,0)-'TRADE IN'!$F188)) -> 7499 | M188: =IF(VLOOKUP($C188,REV!$C:$AA,11,0)-'TRADE IN'!$F199=0,"",(VLOOKUP($C188,REV!$C:$AA,11,0)-'TRADE IN'!$F188)) -> 7499 | N188: =IF(VLOOKUP($C188,REV!$C:$AA,12,0)-'TRADE IN'!$F199=0,"",(VLOOKUP($C188,REV!$C:$AA,12,0)-'TRADE IN'!$F188)) -> 7499 | O188: =IF(VLOOKUP($C188,REV!$C:$AA,13,0)-'TRADE IN'!$F199=0,"",(VLOOKUP($C188,REV!$C:$AA,13,0)-'TRADE IN'!$F188)) -> 7399 | P188: =IF(VLOOKUP($C188,REV!$C:$AA,14,0)-'TRADE IN'!$F199=0,"",(VLOOKUP($C188,REV!$C:$AA,14,0)-'TRADE IN'!$F188)) -> 7299 | Q188: =IF(VLOOKUP($C188,REV!$C:$AA,15,0)-'TRADE IN'!$F199=0,"",(VLOOKUP($C188,REV!$C:$AA,15,0)-'TRADE IN'!$F188)) -> 6499 | R188: =IF(VLOOKUP($C188,REV!$C:$AA,16,0)-'TRADE IN'!$F199=0,"",(VLOOKUP($C188,REV!$C:$AA,16,0)-'TRADE IN'!$F188)) -> 7399 | S188: =IF(VLOOKUP($C188,REV!$C:$AA,17,0)-'TRADE IN'!$F199=0,"",(VLOOKUP($C188,REV!$C:$AA,17,0)-'TRADE IN'!$F188)) -> 7299 | T188: =IF(VLOOKUP($C188,REV!$C:$AA,18,0)-'TRADE IN'!$F199=0,"",(VLOOKUP($C188,REV!$C:$AA,18,0)-'TRADE IN'!$F188)) -> 6499 | U188: =IF(VLOOKUP($C188,REV!$C:$AA,19,0)-'TRADE IN'!$F199=0,"",(VLOOKUP($C188,REV!$C:$AA,19,0)-'TRADE IN'!$F188)) -> 6499 | V188: =IF(VLOOKUP($C188,REV!$C:$AA,20,0)-'TRADE IN'!$F199=0,"",(VLOOKUP($C188,REV!$C:$AA,20,0)-'TRADE IN'!$F188)) -> 6499 | W188: =IF(VLOOKUP($C188,REV!$C:$AA,21,0)-'TRADE IN'!$F199=0,"",(VLOOKUP($C188,REV!$C:$AA,21,0)-'TRADE IN'!$F188)) -> 6399 | X188: =IF(VLOOKUP($C188,REV!$C:$AA,22,0)-'TRADE IN'!$F199=0,"",(VLOOKUP($C188,REV!$C:$AA,22,0)-'TRADE IN'!$F188)) -> 6399 | Y188: =IF(VLOOKUP($C188,REV!$C:$AA,23,0)-'TRADE IN'!$F199=0,"",(VLOOKUP($C188,REV!$C:$AA,23,0)-'TRADE IN'!$F188)) -> 5799 | Z188: =IF(VLOOKUP($C188,REV!$C:$AA,24,0)-'TRADE IN'!$F199=0,"",(VLOOKUP($C188,REV!$C:$AA,24,0)-'TRADE IN'!$F188)) -> 5799 | AA188: =IF(VLOOKUP($C188,REV!$C:$AA,25,0)-'TRADE IN'!$F199=0,"",(VLOOKUP($C188,REV!$C:$AA,25,0)-'TRADE IN'!$F188)) -> 5799 | AW188: =IF(REV!AW188=0,"",REV!AW188) -> 31.03.2026 | AX188: 5G
A189: Price Oferta | B189: 21X | C189: 4017485 | D189: APPLE IPHONE 17 256GB | E189: APPLE IPHONE 17 256GB-PRETO | J189: =IF(VLOOKUP($C189,REV!$C:$AA,8,0)-'TRADE IN'!$F189=0,"",(VLOOKUP($C189,REV!$C:$AA,8,0)-'TRADE IN'!$F189)) -> 7499 | K189: =IF(VLOOKUP($C189,REV!$C:$AA,9,0)-'TRADE IN'!$F189=0,"",(VLOOKUP($C189,REV!$C:$AA,9,0)-'TRADE IN'!$F189)) -> 7499 | L189: =IF(VLOOKUP($C189,REV!$C:$AA,10,0)-'TRADE IN'!$F200=0,"",(VLOOKUP($C189,REV!$C:$AA,10,0)-'TRADE IN'!$F189)) -> 7499 | M189: =IF(VLOOKUP($C189,REV!$C:$AA,11,0)-'TRADE IN'!$F200=0,"",(VLOOKUP($C189,REV!$C:$AA,11,0)-'TRADE IN'!$F189)) -> 7499 | N189: =IF(VLOOKUP($C189,REV!$C:$AA,12,0)-'TRADE IN'!$F200=0,"",(VLOOKUP($C189,REV!$C:$AA,12,0)-'TRADE IN'!$F189)) -> 7499 | O189: =IF(VLOOKUP($C189,REV!$C:$AA,13,0)-'TRADE IN'!$F200=0,"",(VLOOKUP($C189,REV!$C:$AA,13,0)-'TRADE IN'!$F189)) -> 7399 | P189: =IF(VLOOKUP($C189,REV!$C:$AA,14,0)-'TRADE IN'!$F200=0,"",(VLOOKUP($C189,REV!$C:$AA,14,0)-'TRADE IN'!$F189)) -> 7299 | Q189: =IF(VLOOKUP($C189,REV!$C:$AA,15,0)-'TRADE IN'!$F200=0,"",(VLOOKUP($C189,REV!$C:$AA,15,0)-'TRADE IN'!$F189)) -> 6499 | R189: =IF(VLOOKUP($C189,REV!$C:$AA,16,0)-'TRADE IN'!$F200=0,"",(VLOOKUP($C189,REV!$C:$AA,16,0)-'TRADE IN'!$F189)) -> 7399 | S189: =IF(VLOOKUP($C189,REV!$C:$AA,17,0)-'TRADE IN'!$F200=0,"",(VLOOKUP($C189,REV!$C:$AA,17,0)-'TRADE IN'!$F189)) -> 7299 | T189: =IF(VLOOKUP($C189,REV!$C:$AA,18,0)-'TRADE IN'!$F200=0,"",(VLOOKUP($C189,REV!$C:$AA,18,0)-'TRADE IN'!$F189)) -> 6499 | U189: =IF(VLOOKUP($C189,REV!$C:$AA,19,0)-'TRADE IN'!$F200=0,"",(VLOOKUP($C189,REV!$C:$AA,19,0)-'TRADE IN'!$F189)) -> 6499 | V189: =IF(VLOOKUP($C189,REV!$C:$AA,20,0)-'TRADE IN'!$F200=0,"",(VLOOKUP($C189,REV!$C:$AA,20,0)-'TRADE IN'!$F189)) -> 6499 | W189: =IF(VLOOKUP($C189,REV!$C:$AA,21,0)-'TRADE IN'!$F200=0,"",(VLOOKUP($C189,REV!$C:$AA,21,0)-'TRADE IN'!$F189)) -> 6399 | X189: =IF(VLOOKUP($C189,REV!$C:$AA,22,0)-'TRADE IN'!$F200=0,"",(VLOOKUP($C189,REV!$C:$AA,22,0)-'TRADE IN'!$F189)) -> 6399 | Y189: =IF(VLOOKUP($C189,REV!$C:$AA,23,0)-'TRADE IN'!$F200=0,"",(VLOOKUP($C189,REV!$C:$AA,23,0)-'TRADE IN'!$F189)) -> 5799 | Z189: =IF(VLOOKUP($C189,REV!$C:$AA,24,0)-'TRADE IN'!$F200=0,"",(VLOOKUP($C189,REV!$C:$AA,24,0)-'TRADE IN'!$F189)) -> 5799 | AA189: =IF(VLOOKUP($C189,REV!$C:$AA,25,0)-'TRADE IN'!$F200=0,"",(VLOOKUP($C189,REV!$C:$AA,25,0)-'TRADE IN'!$F189)) -> 5799 | AW189: =IF(REV!AW189=0,"",REV!AW189) -> 31.03.2026 | AX189: 5G
A190: Price Oferta | B190: 21X | C190: 4017486 | D190: APPLE IPHONE 17 256GB | E190: APPLE IPHONE 17 256GB-BRANCO | J190: =IF(VLOOKUP($C190,REV!$C:$AA,8,0)-'TRADE IN'!$F190=0,"",(VLOOKUP($C190,REV!$C:$AA,8,0)-'TRADE IN'!$F190)) -> 7499 | K190: =IF(VLOOKUP($C190,REV!$C:$AA,9,0)-'TRADE IN'!$F190=0,"",(VLOOKUP($C190,REV!$C:$AA,9,0)-'TRADE IN'!$F190)) -> 7499 | L190: =IF(VLOOKUP($C190,REV!$C:$AA,10,0)-'TRADE IN'!$F202=0,"",(VLOOKUP($C190,REV!$C:$AA,10,0)-'TRADE IN'!$F190)) -> 7499 | M190: =IF(VLOOKUP($C190,REV!$C:$AA,11,0)-'TRADE IN'!$F202=0,"",(VLOOKUP($C190,REV!$C:$AA,11,0)-'TRADE IN'!$F190)) -> 7499 | N190: =IF(VLOOKUP($C190,REV!$C:$AA,12,0)-'TRADE IN'!$F202=0,"",(VLOOKUP($C190,REV!$C:$AA,12,0)-'TRADE IN'!$F190)) -> 7499 | O190: =IF(VLOOKUP($C190,REV!$C:$AA,13,0)-'TRADE IN'!$F202=0,"",(VLOOKUP($C190,REV!$C:$AA,13,0)-'TRADE IN'!$F190)) -> 7399 | P190: =IF(VLOOKUP($C190,REV!$C:$AA,14,0)-'TRADE IN'!$F202=0,"",(VLOOKUP($C190,REV!$C:$AA,14,0)-'TRADE IN'!$F190)) -> 7299 | Q190: =IF(VLOOKUP($C190,REV!$C:$AA,15,0)-'TRADE IN'!$F202=0,"",(VLOOKUP($C190,REV!$C:$AA,15,0)-'TRADE IN'!$F190)) -> 6499 | R190: =IF(VLOOKUP($C190,REV!$C:$AA,16,0)-'TRADE IN'!$F202=0,"",(VLOOKUP($C190,REV!$C:$AA,16,0)-'TRADE IN'!$F190)) -> 7399 | S190: =IF(VLOOKUP($C190,REV!$C:$AA,17,0)-'TRADE IN'!$F202=0,"",(VLOOKUP($C190,REV!$C:$AA,17,0)-'TRADE IN'!$F190)) -> 7299 | T190: =IF(VLOOKUP($C190,REV!$C:$AA,18,0)-'TRADE IN'!$F202=0,"",(VLOOKUP($C190,REV!$C:$AA,18,0)-'TRADE IN'!$F190)) -> 6499 | U190: =IF(VLOOKUP($C190,REV!$C:$AA,19,0)-'TRADE IN'!$F202=0,"",(VLOOKUP($C190,REV!$C:$AA,19,0)-'TRADE IN'!$F190)) -> 6499 | V190: =IF(VLOOKUP($C190,REV!$C:$AA,20,0)-'TRADE IN'!$F202=0,"",(VLOOKUP($C190,REV!$C:$AA,20,0)-'TRADE IN'!$F190)) -> 6499 | W190: =IF(VLOOKUP($C190,REV!$C:$AA,21,0)-'TRADE IN'!$F202=0,"",(VLOOKUP($C190,REV!$C:$AA,21,0)-'TRADE IN'!$F190)) -> 6399 | X190: =IF(VLOOKUP($C190,REV!$C:$AA,22,0)-'TRADE IN'!$F202=0,"",(VLOOKUP($C190,REV!$C:$AA,22,0)-'TRADE IN'!$F190)) -> 6399 | Y190: =IF(VLOOKUP($C190,REV!$C:$AA,23,0)-'TRADE IN'!$F202=0,"",(VLOOKUP($C190,REV!$C:$AA,23,0)-'TRADE IN'!$F190)) -> 5799 | Z190: =IF(VLOOKUP($C190,REV!$C:$AA,24,0)-'TRADE IN'!$F202=0,"",(VLOOKUP($C190,REV!$C:$AA,24,0)-'TRADE IN'!$F190)) -> 5799 | AA190: =IF(VLOOKUP($C190,REV!$C:$AA,25,0)-'TRADE IN'!$F202=0,"",(VLOOKUP($C190,REV!$C:$AA,25,0)-'TRADE IN'!$F190)) -> 5799 | AW190: =IF(REV!AW190=0,"",REV!AW190) -> 31.03.2026 | AX190: 5G
A191: Price Oferta | B191: 21X | C191: 4017483 | D191: APPLE IPHONE 17 256GB | E191: APPLE IPHONE 17 256GB-SALVIA | J191: =IF(VLOOKUP($C191,REV!$C:$AA,8,0)-'TRADE IN'!$F191=0,"",(VLOOKUP($C191,REV!$C:$AA,8,0)-'TRADE IN'!$F191)) -> 7499 | K191: =IF(VLOOKUP($C191,REV!$C:$AA,9,0)-'TRADE IN'!$F191=0,"",(VLOOKUP($C191,REV!$C:$AA,9,0)-'TRADE IN'!$F191)) -> 7499 | L191: =IF(VLOOKUP($C191,REV!$C:$AA,10,0)-'TRADE IN'!$F203=0,"",(VLOOKUP($C191,REV!$C:$AA,10,0)-'TRADE IN'!$F191)) -> 7499 | M191: =IF(VLOOKUP($C191,REV!$C:$AA,11,0)-'TRADE IN'!$F203=0,"",(VLOOKUP($C191,REV!$C:$AA,11,0)-'TRADE IN'!$F191)) -> 7499 | N191: =IF(VLOOKUP($C191,REV!$C:$AA,12,0)-'TRADE IN'!$F203=0,"",(VLOOKUP($C191,REV!$C:$AA,12,0)-'TRADE IN'!$F191)) -> 7499 | O191: =IF(VLOOKUP($C191,REV!$C:$AA,13,0)-'TRADE IN'!$F203=0,"",(VLOOKUP($C191,REV!$C:$AA,13,0)-'TRADE IN'!$F191)) -> 7399 | P191: =IF(VLOOKUP($C191,REV!$C:$AA,14,0)-'TRADE IN'!$F203=0,"",(VLOOKUP($C191,REV!$C:$AA,14,0)-'TRADE IN'!$F191)) -> 7299 | Q191: =IF(VLOOKUP($C191,REV!$C:$AA,15,0)-'TRADE IN'!$F203=0,"",(VLOOKUP($C191,REV!$C:$AA,15,0)-'TRADE IN'!$F191)) -> 6499 | R191: =IF(VLOOKUP($C191,REV!$C:$AA,16,0)-'TRADE IN'!$F203=0,"",(VLOOKUP($C191,REV!$C:$AA,16,0)-'TRADE IN'!$F191)) -> 7399 | S191: =IF(VLOOKUP($C191,REV!$C:$AA,17,0)-'TRADE IN'!$F203=0,"",(VLOOKUP($C191,REV!$C:$AA,17,0)-'TRADE IN'!$F191)) -> 7299 | T191: =IF(VLOOKUP($C191,REV!$C:$AA,18,0)-'TRADE IN'!$F203=0,"",(VLOOKUP($C191,REV!$C:$AA,18,0)-'TRADE IN'!$F191)) -> 6499 | U191: =IF(VLOOKUP($C191,REV!$C:$AA,19,0)-'TRADE IN'!$F203=0,"",(VLOOKUP($C191,REV!$C:$AA,19,0)-'TRADE IN'!$F191)) -> 6499 | V191: =IF(VLOOKUP($C191,REV!$C:$AA,20,0)-'TRADE IN'!$F203=0,"",(VLOOKUP($C191,REV!$C:$AA,20,0)-'TRADE IN'!$F191)) -> 6499 | W191: =IF(VLOOKUP($C191,REV!$C:$AA,21,0)-'TRADE IN'!$F203=0,"",(VLOOKUP($C191,REV!$C:$AA,21,0)-'TRADE IN'!$F191)) -> 6399 | X191: =IF(VLOOKUP($C191,REV!$C:$AA,22,0)-'TRADE IN'!$F203=0,"",(VLOOKUP($C191,REV!$C:$AA,22,0)-'TRADE IN'!$F191)) -> 6399 | Y191: =IF(VLOOKUP($C191,REV!$C:$AA,23,0)-'TRADE IN'!$F203=0,"",(VLOOKUP($C191,REV!$C:$AA,23,0)-'TRADE IN'!$F191)) -> 5799 | Z191: =IF(VLOOKUP($C191,REV!$C:$AA,24,0)-'TRADE IN'!$F203=0,"",(VLOOKUP($C191,REV!$C:$AA,24,0)-'TRADE IN'!$F191)) -> 5799 | AA191: =IF(VLOOKUP($C191,REV!$C:$AA,25,0)-'TRADE IN'!$F203=0,"",(VLOOKUP($C191,REV!$C:$AA,25,0)-'TRADE IN'!$F191)) -> 5799 | AW191: =IF(REV!AW191=0,"",REV!AW191) -> 31.03.2026 | AX191: 5G
A192: Price Oferta | B192: 21X | C192: 4017484 | D192: APPLE IPHONE 17 512GB | E192: APPLE IPHONE 17 512GB-BRANCO | J192: =IF(VLOOKUP($C192,REV!$C:$AA,8,0)-'TRADE IN'!$F192=0,"",(VLOOKUP($C192,REV!$C:$AA,8,0)-'TRADE IN'!$F192)) -> 8099 | K192: =IF(VLOOKUP($C192,REV!$C:$AA,9,0)-'TRADE IN'!$F192=0,"",(VLOOKUP($C192,REV!$C:$AA,9,0)-'TRADE IN'!$F192)) -> 8099 | L192: =IF(VLOOKUP($C192,REV!$C:$AA,10,0)-'TRADE IN'!$F204=0,"",(VLOOKUP($C192,REV!$C:$AA,10,0)-'TRADE IN'!$F192)) -> 8099 | M192: =IF(VLOOKUP($C192,REV!$C:$AA,11,0)-'TRADE IN'!$F204=0,"",(VLOOKUP($C192,REV!$C:$AA,11,0)-'TRADE IN'!$F192)) -> 8099 | N192: =IF(VLOOKUP($C192,REV!$C:$AA,12,0)-'TRADE IN'!$F204=0,"",(VLOOKUP($C192,REV!$C:$AA,12,0)-'TRADE IN'!$F192)) -> 8099 | O192: =IF(VLOOKUP($C192,REV!$C:$AA,13,0)-'TRADE IN'!$F204=0,"",(VLOOKUP($C192,REV!$C:$AA,13,0)-'TRADE IN'!$F192)) -> 7999 | P192: =IF(VLOOKUP($C192,REV!$C:$AA,14,0)-'TRADE IN'!$F204=0,"",(VLOOKUP($C192,REV!$C:$AA,14,0)-'TRADE IN'!$F192)) -> 7899 | Q192: =IF(VLOOKUP($C192,REV!$C:$AA,15,0)-'TRADE IN'!$F204=0,"",(VLOOKUP($C192,REV!$C:$AA,15,0)-'TRADE IN'!$F192)) -> 7799 | R192: =IF(VLOOKUP($C192,REV!$C:$AA,16,0)-'TRADE IN'!$F204=0,"",(VLOOKUP($C192,REV!$C:$AA,16,0)-'TRADE IN'!$F192)) -> 7999 | S192: =IF(VLOOKUP($C192,REV!$C:$AA,17,0)-'TRADE IN'!$F204=0,"",(VLOOKUP($C192,REV!$C:$AA,17,0)-'TRADE IN'!$F192)) -> 7899 | T192: =IF(VLOOKUP($C192,REV!$C:$AA,18,0)-'TRADE IN'!$F204=0,"",(VLOOKUP($C192,REV!$C:$AA,18,0)-'TRADE IN'!$F192)) -> 7799 | U192: =IF(VLOOKUP($C192,REV!$C:$AA,19,0)-'TRADE IN'!$F204=0,"",(VLOOKUP($C192,REV!$C:$AA,19,0)-'TRADE IN'!$F192)) -> 7799 | V192: =IF(VLOOKUP($C192,REV!$C:$AA,20,0)-'TRADE IN'!$F204=0,"",(VLOOKUP($C192,REV!$C:$AA,20,0)-'TRADE IN'!$F192)) -> 7799 | W192: =IF(VLOOKUP($C192,REV!$C:$AA,21,0)-'TRADE IN'!$F204=0,"",(VLOOKUP($C192,REV!$C:$AA,21,0)-'TRADE IN'!$F192)) -> 7799 | X192: =IF(VLOOKUP($C192,REV!$C:$AA,22,0)-'TRADE IN'!$F204=0,"",(VLOOKUP($C192,REV!$C:$AA,22,0)-'TRADE IN'!$F192)) -> 7699 | Y192: =IF(VLOOKUP($C192,REV!$C:$AA,23,0)-'TRADE IN'!$F204=0,"",(VLOOKUP($C192,REV!$C:$AA,23,0)-'TRADE IN'!$F192)) -> 7499 | Z192: =IF(VLOOKUP($C192,REV!$C:$AA,24,0)-'TRADE IN'!$F204=0,"",(VLOOKUP($C192,REV!$C:$AA,24,0)-'TRADE IN'!$F192)) -> 7499 | AA192: =IF(VLOOKUP($C192,REV!$C:$AA,25,0)-'TRADE IN'!$F204=0,"",(VLOOKUP($C192,REV!$C:$AA,25,0)-'TRADE IN'!$F192)) -> 7499 | AW192: =IF(REV!AW192=0,"",REV!AW192) -> 31.03.2026 | AX192: 5G
A193: Price Oferta | B193: 21X | C193: 4017506 | D193: APPLE IPHONE 17 512GB | E193: APPLE IPHONE 17 512GB-PRETO | J193: =IF(VLOOKUP($C193,REV!$C:$AA,8,0)-'TRADE IN'!$F193=0,"",(VLOOKUP($C193,REV!$C:$AA,8,0)-'TRADE IN'!$F193)) -> 8099 | K193: =IF(VLOOKUP($C193,REV!$C:$AA,9,0)-'TRADE IN'!$F193=0,"",(VLOOKUP($C193,REV!$C:$AA,9,0)-'TRADE IN'!$F193)) -> 8099 | L193: =IF(VLOOKUP($C193,REV!$C:$AA,10,0)-'TRADE IN'!$F205=0,"",(VLOOKUP($C193,REV!$C:$AA,10,0)-'TRADE IN'!$F193)) -> 8099 | M193: =IF(VLOOKUP($C193,REV!$C:$AA,11,0)-'TRADE IN'!$F205=0,"",(VLOOKUP($C193,REV!$C:$AA,11,0)-'TRADE IN'!$F193)) -> 8099 | N193: =IF(VLOOKUP($C193,REV!$C:$AA,12,0)-'TRADE IN'!$F205=0,"",(VLOOKUP($C193,REV!$C:$AA,12,0)-'TRADE IN'!$F193)) -> 8099 | O193: =IF(VLOOKUP($C193,REV!$C:$AA,13,0)-'TRADE IN'!$F205=0,"",(VLOOKUP($C193,REV!$C:$AA,13,0)-'TRADE IN'!$F193)) -> 7999 | P193: =IF(VLOOKUP($C193,REV!$C:$AA,14,0)-'TRADE IN'!$F205=0,"",(VLOOKUP($C193,REV!$C:$AA,14,0)-'TRADE IN'!$F193)) -> 7899 | Q193: =IF(VLOOKUP($C193,REV!$C:$AA,15,0)-'TRADE IN'!$F205=0,"",(VLOOKUP($C193,REV!$C:$AA,15,0)-'TRADE IN'!$F193)) -> 7799 | R193: =IF(VLOOKUP($C193,REV!$C:$AA,16,0)-'TRADE IN'!$F205=0,"",(VLOOKUP($C193,REV!$C:$AA,16,0)-'TRADE IN'!$F193)) -> 7999 | S193: =IF(VLOOKUP($C193,REV!$C:$AA,17,0)-'TRADE IN'!$F205=0,"",(VLOOKUP($C193,REV!$C:$AA,17,0)-'TRADE IN'!$F193)) -> 7899 | T193: =IF(VLOOKUP($C193,REV!$C:$AA,18,0)-'TRADE IN'!$F205=0,"",(VLOOKUP($C193,REV!$C:$AA,18,0)-'TRADE IN'!$F193)) -> 7799 | U193: =IF(VLOOKUP($C193,REV!$C:$AA,19,0)-'TRADE IN'!$F205=0,"",(VLOOKUP($C193,REV!$C:$AA,19,0)-'TRADE IN'!$F193)) -> 7799 | V193: =IF(VLOOKUP($C193,REV!$C:$AA,20,0)-'TRADE IN'!$F205=0,"",(VLOOKUP($C193,REV!$C:$AA,20,0)-'TRADE IN'!$F193)) -> 7799 | W193: =IF(VLOOKUP($C193,REV!$C:$AA,21,0)-'TRADE IN'!$F205=0,"",(VLOOKUP($C193,REV!$C:$AA,21,0)-'TRADE IN'!$F193)) -> 7799 | X193: =IF(VLOOKUP($C193,REV!$C:$AA,22,0)-'TRADE IN'!$F205=0,"",(VLOOKUP($C193,REV!$C:$AA,22,0)-'TRADE IN'!$F193)) -> 7699 | Y193: =IF(VLOOKUP($C193,REV!$C:$AA,23,0)-'TRADE IN'!$F205=0,"",(VLOOKUP($C193,REV!$C:$AA,23,0)-'TRADE IN'!$F193)) -> 7499 | Z193: =IF(VLOOKUP($C193,REV!$C:$AA,24,0)-'TRADE IN'!$F205=0,"",(VLOOKUP($C193,REV!$C:$AA,24,0)-'TRADE IN'!$F193)) -> 7499 | AA193: =IF(VLOOKUP($C193,REV!$C:$AA,25,0)-'TRADE IN'!$F205=0,"",(VLOOKUP($C193,REV!$C:$AA,25,0)-'TRADE IN'!$F193)) -> 7499 | AW193: =IF(REV!AW193=0,"",REV!AW193) -> 31.03.2026 | AX193: 5G
A194: Price Oferta | B194: 21X | C194: 4017497 | D194: APPLE IPHONE 17 AIR 256GB | E194: APPLE IPHONE 17 AIR 256GB-PRETO | F194: 1000 | J194: =IF(VLOOKUP($C194,REV!$C:$AA,8,0)-'TRADE IN'!$F194=0,"",(VLOOKUP($C194,REV!$C:$AA,8,0)-'TRADE IN'!$F194)) -> 6699 | K194: =IF(VLOOKUP($C194,REV!$C:$AA,9,0)-'TRADE IN'!$F194=0,"",(VLOOKUP($C194,REV!$C:$AA,9,0)-'TRADE IN'!$F194)) -> 6699 | L194: =IF(VLOOKUP($C194,REV!$C:$AA,10,0)-'TRADE IN'!$F205=0,"",(VLOOKUP($C194,REV!$C:$AA,10,0)-'TRADE IN'!$F194)) -> 6699 | M194: =IF(VLOOKUP($C194,REV!$C:$AA,11,0)-'TRADE IN'!$F205=0,"",(VLOOKUP($C194,REV!$C:$AA,11,0)-'TRADE IN'!$F194)) -> 6699 | N194: =IF(VLOOKUP($C194,REV!$C:$AA,12,0)-'TRADE IN'!$F205=0,"",(VLOOKUP($C194,REV!$C:$AA,12,0)-'TRADE IN'!$F194)) -> 6699 | O194: =IF(VLOOKUP($C194,REV!$C:$AA,13,0)-'TRADE IN'!$F205=0,"",(VLOOKUP($C194,REV!$C:$AA,13,0)-'TRADE IN'!$F194)) -> 6599 | P194: =IF(VLOOKUP($C194,REV!$C:$AA,14,0)-'TRADE IN'!$F205=0,"",(VLOOKUP($C194,REV!$C:$AA,14,0)-'TRADE IN'!$F194)) -> 6499 | Q194: =IF(VLOOKUP($C194,REV!$C:$AA,15,0)-'TRADE IN'!$F205=0,"",(VLOOKUP($C194,REV!$C:$AA,15,0)-'TRADE IN'!$F194)) -> 6399 | R194: =IF(VLOOKUP($C194,REV!$C:$AA,16,0)-'TRADE IN'!$F205=0,"",(VLOOKUP($C194,REV!$C:$AA,16,0)-'TRADE IN'!$F194)) -> 6599 | S194: =IF(VLOOKUP($C194,REV!$C:$AA,17,0)-'TRADE IN'!$F205=0,"",(VLOOKUP($C194,REV!$C:$AA,17,0)-'TRADE IN'!$F194)) -> 6499 | T194: =IF(VLOOKUP($C194,REV!$C:$AA,18,0)-'TRADE IN'!$F205=0,"",(VLOOKUP($C194,REV!$C:$AA,18,0)-'TRADE IN'!$F194)) -> 6399 | U194: =IF(VLOOKUP($C194,REV!$C:$AA,19,0)-'TRADE IN'!$F205=0,"",(VLOOKUP($C194,REV!$C:$AA,19,0)-'TRADE IN'!$F194)) -> 6399 | V194: =IF(VLOOKUP($C194,REV!$C:$AA,20,0)-'TRADE IN'!$F205=0,"",(VLOOKUP($C194,REV!$C:$AA,20,0)-'TRADE IN'!$F194)) -> 6399 | W194: =IF(VLOOKUP($C194,REV!$C:$AA,21,0)-'TRADE IN'!$F205=0,"",(VLOOKUP($C194,REV!$C:$AA,21,0)-'TRADE IN'!$F194)) -> 6399 | X194: =IF(VLOOKUP($C194,REV!$C:$AA,22,0)-'TRADE IN'!$F205=0,"",(VLOOKUP($C194,REV!$C:$AA,22,0)-'TRADE IN'!$F194)) -> 6299 | Y194: =IF(VLOOKUP($C194,REV!$C:$AA,23,0)-'TRADE IN'!$F205=0,"",(VLOOKUP($C194,REV!$C:$AA,23,0)-'TRADE IN'!$F194)) -> 4999 | Z194: =IF(VLOOKUP($C194,REV!$C:$AA,24,0)-'TRADE IN'!$F205=0,"",(VLOOKUP($C194,REV!$C:$AA,24,0)-'TRADE IN'!$F194)) -> 4999 | AA194: =IF(VLOOKUP($C194,REV!$C:$AA,25,0)-'TRADE IN'!$F205=0,"",(VLOOKUP($C194,REV!$C:$AA,25,0)-'TRADE IN'!$F194)) -> 4999 | AW194: =IF(REV!AW194=0,"",REV!AW194) -> 31.03.2026 | AX194: 5G
A195: Price Oferta | B195: 21X | C195: 4017498 | D195: APPLE IPHONE 17 AIR 256GB | E195: APPLE IPHONE 17 AIR 256GB-BRANCO | F195: 1000 | J195: =IF(VLOOKUP($C195,REV!$C:$AA,8,0)-'TRADE IN'!$F195=0,"",(VLOOKUP($C195,REV!$C:$AA,8,0)-'TRADE IN'!$F195)) -> 6699 | K195: =IF(VLOOKUP($C195,REV!$C:$AA,9,0)-'TRADE IN'!$F195=0,"",(VLOOKUP($C195,REV!$C:$AA,9,0)-'TRADE IN'!$F195)) -> 6699 | L195: =IF(VLOOKUP($C195,REV!$C:$AA,10,0)-'TRADE IN'!$F206=0,"",(VLOOKUP($C195,REV!$C:$AA,10,0)-'TRADE IN'!$F195)) -> 6699 | M195: =IF(VLOOKUP($C195,REV!$C:$AA,11,0)-'TRADE IN'!$F206=0,"",(VLOOKUP($C195,REV!$C:$AA,11,0)-'TRADE IN'!$F195)) -> 6699 | N195: =IF(VLOOKUP($C195,REV!$C:$AA,12,0)-'TRADE IN'!$F206=0,"",(VLOOKUP($C195,REV!$C:$AA,12,0)-'TRADE IN'!$F195)) -> 6699 | O195: =IF(VLOOKUP($C195,REV!$C:$AA,13,0)-'TRADE IN'!$F206=0,"",(VLOOKUP($C195,REV!$C:$AA,13,0)-'TRADE IN'!$F195)) -> 6599 | P195: =IF(VLOOKUP($C195,REV!$C:$AA,14,0)-'TRADE IN'!$F206=0,"",(VLOOKUP($C195,REV!$C:$AA,14,0)-'TRADE IN'!$F195)) -> 6499 | Q195: =IF(VLOOKUP($C195,REV!$C:$AA,15,0)-'TRADE IN'!$F206=0,"",(VLOOKUP($C195,REV!$C:$AA,15,0)-'TRADE IN'!$F195)) -> 6399 | R195: =IF(VLOOKUP($C195,REV!$C:$AA,16,0)-'TRADE IN'!$F206=0,"",(VLOOKUP($C195,REV!$C:$AA,16,0)-'TRADE IN'!$F195)) -> 6599 | S195: =IF(VLOOKUP($C195,REV!$C:$AA,17,0)-'TRADE IN'!$F206=0,"",(VLOOKUP($C195,REV!$C:$AA,17,0)-'TRADE IN'!$F195)) -> 6499 | T195: =IF(VLOOKUP($C195,REV!$C:$AA,18,0)-'TRADE IN'!$F206=0,"",(VLOOKUP($C195,REV!$C:$AA,18,0)-'TRADE IN'!$F195)) -> 6399 | U195: =IF(VLOOKUP($C195,REV!$C:$AA,19,0)-'TRADE IN'!$F206=0,"",(VLOOKUP($C195,REV!$C:$AA,19,0)-'TRADE IN'!$F195)) -> 6399 | V195: =IF(VLOOKUP($C195,REV!$C:$AA,20,0)-'TRADE IN'!$F206=0,"",(VLOOKUP($C195,REV!$C:$AA,20,0)-'TRADE IN'!$F195)) -> 6399 | W195: =IF(VLOOKUP($C195,REV!$C:$AA,21,0)-'TRADE IN'!$F206=0,"",(VLOOKUP($C195,REV!$C:$AA,21,0)-'TRADE IN'!$F195)) -> 6399 | X195: =IF(VLOOKUP($C195,REV!$C:$AA,22,0)-'TRADE IN'!$F206=0,"",(VLOOKUP($C195,REV!$C:$AA,22,0)-'TRADE IN'!$F195)) -> 6299 | Y195: =IF(VLOOKUP($C195,REV!$C:$AA,23,0)-'TRADE IN'!$F206=0,"",(VLOOKUP($C195,REV!$C:$AA,23,0)-'TRADE IN'!$F195)) -> 4999 | Z195: =IF(VLOOKUP($C195,REV!$C:$AA,24,0)-'TRADE IN'!$F206=0,"",(VLOOKUP($C195,REV!$C:$AA,24,0)-'TRADE IN'!$F195)) -> 4999 | AA195: =IF(VLOOKUP($C195,REV!$C:$AA,25,0)-'TRADE IN'!$F206=0,"",(VLOOKUP($C195,REV!$C:$AA,25,0)-'TRADE IN'!$F195)) -> 4999 | AW195: =IF(REV!AW195=0,"",REV!AW195) -> 31.03.2026 | AX195: 5G
A196: Price Oferta | B196: 21X | C196: 4017499 | D196: APPLE IPHONE 17 AIR 256GB | E196: APPLE IPHONE 17 AIR 256GB-AZUL CEU | F196: 1000 | J196: =IF(VLOOKUP($C196,REV!$C:$AA,8,0)-'TRADE IN'!$F196=0,"",(VLOOKUP($C196,REV!$C:$AA,8,0)-'TRADE IN'!$F196)) -> 6699 | K196: =IF(VLOOKUP($C196,REV!$C:$AA,9,0)-'TRADE IN'!$F196=0,"",(VLOOKUP($C196,REV!$C:$AA,9,0)-'TRADE IN'!$F196)) -> 6699 | L196: =IF(VLOOKUP($C196,REV!$C:$AA,10,0)-'TRADE IN'!$F208=0,"",(VLOOKUP($C196,REV!$C:$AA,10,0)-'TRADE IN'!$F196)) -> 6699 | M196: =IF(VLOOKUP($C196,REV!$C:$AA,11,0)-'TRADE IN'!$F208=0,"",(VLOOKUP($C196,REV!$C:$AA,11,0)-'TRADE IN'!$F196)) -> 6699 | N196: =IF(VLOOKUP($C196,REV!$C:$AA,12,0)-'TRADE IN'!$F208=0,"",(VLOOKUP($C196,REV!$C:$AA,12,0)-'TRADE IN'!$F196)) -> 6699 | O196: =IF(VLOOKUP($C196,REV!$C:$AA,13,0)-'TRADE IN'!$F208=0,"",(VLOOKUP($C196,REV!$C:$AA,13,0)-'TRADE IN'!$F196)) -> 6599 | P196: =IF(VLOOKUP($C196,REV!$C:$AA,14,0)-'TRADE IN'!$F208=0,"",(VLOOKUP($C196,REV!$C:$AA,14,0)-'TRADE IN'!$F196)) -> 6499 | Q196: =IF(VLOOKUP($C196,REV!$C:$AA,15,0)-'TRADE IN'!$F208=0,"",(VLOOKUP($C196,REV!$C:$AA,15,0)-'TRADE IN'!$F196)) -> 6399 | R196: =IF(VLOOKUP($C196,REV!$C:$AA,16,0)-'TRADE IN'!$F208=0,"",(VLOOKUP($C196,REV!$C:$AA,16,0)-'TRADE IN'!$F196)) -> 6599 | S196: =IF(VLOOKUP($C196,REV!$C:$AA,17,0)-'TRADE IN'!$F208=0,"",(VLOOKUP($C196,REV!$C:$AA,17,0)-'TRADE IN'!$F196)) -> 6499 | T196: =IF(VLOOKUP($C196,REV!$C:$AA,18,0)-'TRADE IN'!$F208=0,"",(VLOOKUP($C196,REV!$C:$AA,18,0)-'TRADE IN'!$F196)) -> 6399 | U196: =IF(VLOOKUP($C196,REV!$C:$AA,19,0)-'TRADE IN'!$F208=0,"",(VLOOKUP($C196,REV!$C:$AA,19,0)-'TRADE IN'!$F196)) -> 6399 | V196: =IF(VLOOKUP($C196,REV!$C:$AA,20,0)-'TRADE IN'!$F208=0,"",(VLOOKUP($C196,REV!$C:$AA,20,0)-'TRADE IN'!$F196)) -> 6399 | W196: =IF(VLOOKUP($C196,REV!$C:$AA,21,0)-'TRADE IN'!$F208=0,"",(VLOOKUP($C196,REV!$C:$AA,21,0)-'TRADE IN'!$F196)) -> 6399 | X196: =IF(VLOOKUP($C196,REV!$C:$AA,22,0)-'TRADE IN'!$F208=0,"",(VLOOKUP($C196,REV!$C:$AA,22,0)-'TRADE IN'!$F196)) -> 6299 | Y196: =IF(VLOOKUP($C196,REV!$C:$AA,23,0)-'TRADE IN'!$F208=0,"",(VLOOKUP($C196,REV!$C:$AA,23,0)-'TRADE IN'!$F196)) -> 4999 | Z196: =IF(VLOOKUP($C196,REV!$C:$AA,24,0)-'TRADE IN'!$F208=0,"",(VLOOKUP($C196,REV!$C:$AA,24,0)-'TRADE IN'!$F196)) -> 4999 | AA196: =IF(VLOOKUP($C196,REV!$C:$AA,25,0)-'TRADE IN'!$F208=0,"",(VLOOKUP($C196,REV!$C:$AA,25,0)-'TRADE IN'!$F196)) -> 4999 | AW196: =IF(REV!AW196=0,"",REV!AW196) -> 31.03.2026 | AX196: 5G
A197: Price Oferta | B197: 21X | C197: 4017521 | D197: APPLE IPHONE 17 AIR 256GB | E197: APPLE IPHONE 17 AIR 256GB-DOURADO | F197: 1000 | J197: =IF(VLOOKUP($C197,REV!$C:$AA,8,0)-'TRADE IN'!$F197=0,"",(VLOOKUP($C197,REV!$C:$AA,8,0)-'TRADE IN'!$F197)) -> 6699 | K197: =IF(VLOOKUP($C197,REV!$C:$AA,9,0)-'TRADE IN'!$F197=0,"",(VLOOKUP($C197,REV!$C:$AA,9,0)-'TRADE IN'!$F197)) -> 6699 | L197: =IF(VLOOKUP($C197,REV!$C:$AA,10,0)-'TRADE IN'!$F209=0,"",(VLOOKUP($C197,REV!$C:$AA,10,0)-'TRADE IN'!$F197)) -> 6699 | M197: =IF(VLOOKUP($C197,REV!$C:$AA,11,0)-'TRADE IN'!$F209=0,"",(VLOOKUP($C197,REV!$C:$AA,11,0)-'TRADE IN'!$F197)) -> 6699 | N197: =IF(VLOOKUP($C197,REV!$C:$AA,12,0)-'TRADE IN'!$F209=0,"",(VLOOKUP($C197,REV!$C:$AA,12,0)-'TRADE IN'!$F197)) -> 6699 | O197: =IF(VLOOKUP($C197,REV!$C:$AA,13,0)-'TRADE IN'!$F209=0,"",(VLOOKUP($C197,REV!$C:$AA,13,0)-'TRADE IN'!$F197)) -> 6599 | P197: =IF(VLOOKUP($C197,REV!$C:$AA,14,0)-'TRADE IN'!$F209=0,"",(VLOOKUP($C197,REV!$C:$AA,14,0)-'TRADE IN'!$F197)) -> 6499 | Q197: =IF(VLOOKUP($C197,REV!$C:$AA,15,0)-'TRADE IN'!$F209=0,"",(VLOOKUP($C197,REV!$C:$AA,15,0)-'TRADE IN'!$F197)) -> 6399 | R197: =IF(VLOOKUP($C197,REV!$C:$AA,16,0)-'TRADE IN'!$F209=0,"",(VLOOKUP($C197,REV!$C:$AA,16,0)-'TRADE IN'!$F197)) -> 6599 | S197: =IF(VLOOKUP($C197,REV!$C:$AA,17,0)-'TRADE IN'!$F209=0,"",(VLOOKUP($C197,REV!$C:$AA,17,0)-'TRADE IN'!$F197)) -> 6499 | T197: =IF(VLOOKUP($C197,REV!$C:$AA,18,0)-'TRADE IN'!$F209=0,"",(VLOOKUP($C197,REV!$C:$AA,18,0)-'TRADE IN'!$F197)) -> 6399 | U197: =IF(VLOOKUP($C197,REV!$C:$AA,19,0)-'TRADE IN'!$F209=0,"",(VLOOKUP($C197,REV!$C:$AA,19,0)-'TRADE IN'!$F197)) -> 6399 | V197: =IF(VLOOKUP($C197,REV!$C:$AA,20,0)-'TRADE IN'!$F209=0,"",(VLOOKUP($C197,REV!$C:$AA,20,0)-'TRADE IN'!$F197)) -> 6399 | W197: =IF(VLOOKUP($C197,REV!$C:$AA,21,0)-'TRADE IN'!$F209=0,"",(VLOOKUP($C197,REV!$C:$AA,21,0)-'TRADE IN'!$F197)) -> 6399 | X197: =IF(VLOOKUP($C197,REV!$C:$AA,22,0)-'TRADE IN'!$F209=0,"",(VLOOKUP($C197,REV!$C:$AA,22,0)-'TRADE IN'!$F197)) -> 6299 | Y197: =IF(VLOOKUP($C197,REV!$C:$AA,23,0)-'TRADE IN'!$F209=0,"",(VLOOKUP($C197,REV!$C:$AA,23,0)-'TRADE IN'!$F197)) -> 4999 | Z197: =IF(VLOOKUP($C197,REV!$C:$AA,24,0)-'TRADE IN'!$F209=0,"",(VLOOKUP($C197,REV!$C:$AA,24,0)-'TRADE IN'!$F197)) -> 4999 | AA197: =IF(VLOOKUP($C197,REV!$C:$AA,25,0)-'TRADE IN'!$F209=0,"",(VLOOKUP($C197,REV!$C:$AA,25,0)-'TRADE IN'!$F197)) -> 4999 | AW197: =IF(REV!AW197=0,"",REV!AW197) -> 31.03.2026 | AX197: 5G
A198: Price Oferta | B198: 21X | C198: 4017496 | D198: APPLE IPHONE 17 AIR 512GB | E198: APPLE IPHONE 17 AIR 512GB-BRANCO | F198: 1000 | J198: =IF(VLOOKUP($C198,REV!$C:$AA,8,0)-'TRADE IN'!$F198=0,"",(VLOOKUP($C198,REV!$C:$AA,8,0)-'TRADE IN'!$F198)) -> 7999 | K198: =IF(VLOOKUP($C198,REV!$C:$AA,9,0)-'TRADE IN'!$F198=0,"",(VLOOKUP($C198,REV!$C:$AA,9,0)-'TRADE IN'!$F198)) -> 7999 | L198: =IF(VLOOKUP($C198,REV!$C:$AA,10,0)-'TRADE IN'!$F210=0,"",(VLOOKUP($C198,REV!$C:$AA,10,0)-'TRADE IN'!$F198)) -> 7999 | M198: =IF(VLOOKUP($C198,REV!$C:$AA,11,0)-'TRADE IN'!$F210=0,"",(VLOOKUP($C198,REV!$C:$AA,11,0)-'TRADE IN'!$F198)) -> 7999 | N198: =IF(VLOOKUP($C198,REV!$C:$AA,12,0)-'TRADE IN'!$F210=0,"",(VLOOKUP($C198,REV!$C:$AA,12,0)-'TRADE IN'!$F198)) -> 7999 | O198: =IF(VLOOKUP($C198,REV!$C:$AA,13,0)-'TRADE IN'!$F210=0,"",(VLOOKUP($C198,REV!$C:$AA,13,0)-'TRADE IN'!$F198)) -> 7899 | P198: =IF(VLOOKUP($C198,REV!$C:$AA,14,0)-'TRADE IN'!$F210=0,"",(VLOOKUP($C198,REV!$C:$AA,14,0)-'TRADE IN'!$F198)) -> 7799 | Q198: =IF(VLOOKUP($C198,REV!$C:$AA,15,0)-'TRADE IN'!$F210=0,"",(VLOOKUP($C198,REV!$C:$AA,15,0)-'TRADE IN'!$F198)) -> 7499 | R198: =IF(VLOOKUP($C198,REV!$C:$AA,16,0)-'TRADE IN'!$F210=0,"",(VLOOKUP($C198,REV!$C:$AA,16,0)-'TRADE IN'!$F198)) -> 7899 | S198: =IF(VLOOKUP($C198,REV!$C:$AA,17,0)-'TRADE IN'!$F210=0,"",(VLOOKUP($C198,REV!$C:$AA,17,0)-'TRADE IN'!$F198)) -> 7799 | T198: =IF(VLOOKUP($C198,REV!$C:$AA,18,0)-'TRADE IN'!$F210=0,"",(VLOOKUP($C198,REV!$C:$AA,18,0)-'TRADE IN'!$F198)) -> 7499 | U198: =IF(VLOOKUP($C198,REV!$C:$AA,19,0)-'TRADE IN'!$F210=0,"",(VLOOKUP($C198,REV!$C:$AA,19,0)-'TRADE IN'!$F198)) -> 7499 | V198: =IF(VLOOKUP($C198,REV!$C:$AA,20,0)-'TRADE IN'!$F210=0,"",(VLOOKUP($C198,REV!$C:$AA,20,0)-'TRADE IN'!$F198)) -> 7499 | W198: =IF(VLOOKUP($C198,REV!$C:$AA,21,0)-'TRADE IN'!$F210=0,"",(VLOOKUP($C198,REV!$C:$AA,21,0)-'TRADE IN'!$F198)) -> 7499 | X198: =IF(VLOOKUP($C198,REV!$C:$AA,22,0)-'TRADE IN'!$F210=0,"",(VLOOKUP($C198,REV!$C:$AA,22,0)-'TRADE IN'!$F198)) -> 7399 | Y198: =IF(VLOOKUP($C198,REV!$C:$AA,23,0)-'TRADE IN'!$F210=0,"",(VLOOKUP($C198,REV!$C:$AA,23,0)-'TRADE IN'!$F198)) -> 6799 | Z198: =IF(VLOOKUP($C198,REV!$C:$AA,24,0)-'TRADE IN'!$F210=0,"",(VLOOKUP($C198,REV!$C:$AA,24,0)-'TRADE IN'!$F198)) -> 6799 | AA198: =IF(VLOOKUP($C198,REV!$C:$AA,25,0)-'TRADE IN'!$F210=0,"",(VLOOKUP($C198,REV!$C:$AA,25,0)-'TRADE IN'!$F198)) -> 6799 | AW198: =IF(REV!AW198=0,"",REV!AW198) -> 31.03.2026 | AX198: 5G
A199: Price Oferta | B199: 21X | C199: 4017519 | D199: APPLE IPHONE 17 AIR 512GB | E199: APPLE IPHONE 17 AIR 512GB-DOURADO | F199: 1000 | J199: =IF(VLOOKUP($C199,REV!$C:$AA,8,0)-'TRADE IN'!$F199=0,"",(VLOOKUP($C199,REV!$C:$AA,8,0)-'TRADE IN'!$F199)) -> 7999 | K199: =IF(VLOOKUP($C199,REV!$C:$AA,9,0)-'TRADE IN'!$F199=0,"",(VLOOKUP($C199,REV!$C:$AA,9,0)-'TRADE IN'!$F199)) -> 7999 | L199: =IF(VLOOKUP($C199,REV!$C:$AA,10,0)-'TRADE IN'!$F211=0,"",(VLOOKUP($C199,REV!$C:$AA,10,0)-'TRADE IN'!$F199)) -> 7999 | M199: =IF(VLOOKUP($C199,REV!$C:$AA,11,0)-'TRADE IN'!$F211=0,"",(VLOOKUP($C199,REV!$C:$AA,11,0)-'TRADE IN'!$F199)) -> 7999 | N199: =IF(VLOOKUP($C199,REV!$C:$AA,12,0)-'TRADE IN'!$F211=0,"",(VLOOKUP($C199,REV!$C:$AA,12,0)-'TRADE IN'!$F199)) -> 7999 | O199: =IF(VLOOKUP($C199,REV!$C:$AA,13,0)-'TRADE IN'!$F211=0,"",(VLOOKUP($C199,REV!$C:$AA,13,0)-'TRADE IN'!$F199)) -> 7899 | P199: =IF(VLOOKUP($C199,REV!$C:$AA,14,0)-'TRADE IN'!$F211=0,"",(VLOOKUP($C199,REV!$C:$AA,14,0)-'TRADE IN'!$F199)) -> 7799 | Q199: =IF(VLOOKUP($C199,REV!$C:$AA,15,0)-'TRADE IN'!$F211=0,"",(VLOOKUP($C199,REV!$C:$AA,15,0)-'TRADE IN'!$F199)) -> 7499 | R199: =IF(VLOOKUP($C199,REV!$C:$AA,16,0)-'TRADE IN'!$F211=0,"",(VLOOKUP($C199,REV!$C:$AA,16,0)-'TRADE IN'!$F199)) -> 7899 | S199: =IF(VLOOKUP($C199,REV!$C:$AA,17,0)-'TRADE IN'!$F211=0,"",(VLOOKUP($C199,REV!$C:$AA,17,0)-'TRADE IN'!$F199)) -> 7799 | T199: =IF(VLOOKUP($C199,REV!$C:$AA,18,0)-'TRADE IN'!$F211=0,"",(VLOOKUP($C199,REV!$C:$AA,18,0)-'TRADE IN'!$F199)) -> 7499 | U199: =IF(VLOOKUP($C199,REV!$C:$AA,19,0)-'TRADE IN'!$F211=0,"",(VLOOKUP($C199,REV!$C:$AA,19,0)-'TRADE IN'!$F199)) -> 7499 | V199: =IF(VLOOKUP($C199,REV!$C:$AA,20,0)-'TRADE IN'!$F211=0,"",(VLOOKUP($C199,REV!$C:$AA,20,0)-'TRADE IN'!$F199)) -> 7499 | W199: =IF(VLOOKUP($C199,REV!$C:$AA,21,0)-'TRADE IN'!$F211=0,"",(VLOOKUP($C199,REV!$C:$AA,21,0)-'TRADE IN'!$F199)) -> 7499 | X199: =IF(VLOOKUP($C199,REV!$C:$AA,22,0)-'TRADE IN'!$F211=0,"",(VLOOKUP($C199,REV!$C:$AA,22,0)-'TRADE IN'!$F199)) -> 7399 | Y199: =IF(VLOOKUP($C199,REV!$C:$AA,23,0)-'TRADE IN'!$F211=0,"",(VLOOKUP($C199,REV!$C:$AA,23,0)-'TRADE IN'!$F199)) -> 6799 | Z199: =IF(VLOOKUP($C199,REV!$C:$AA,24,0)-'TRADE IN'!$F211=0,"",(VLOOKUP($C199,REV!$C:$AA,24,0)-'TRADE IN'!$F199)) -> 6799 | AA199: =IF(VLOOKUP($C199,REV!$C:$AA,25,0)-'TRADE IN'!$F211=0,"",(VLOOKUP($C199,REV!$C:$AA,25,0)-'TRADE IN'!$F199)) -> 6799 | AW199: =IF(REV!AW199=0,"",REV!AW199) -> 31.03.2026 | AX199: 5G
A200: Price Oferta | B200: 21X | C200: 4017525 | D200: APPLE IPHONE 17 AIR 512GB | E200: APPLE IPHONE 17 AIR 512GB-PRETO | F200: 1000 | J200: =IF(VLOOKUP($C200,REV!$C:$AA,8,0)-'TRADE IN'!$F200=0,"",(VLOOKUP($C200,REV!$C:$AA,8,0)-'TRADE IN'!$F200)) -> 7999 | K200: =IF(VLOOKUP($C200,REV!$C:$AA,9,0)-'TRADE IN'!$F200=0,"",(VLOOKUP($C200,REV!$C:$AA,9,0)-'TRADE IN'!$F200)) -> 7999 | L200: =IF(VLOOKUP($C200,REV!$C:$AA,10,0)-'TRADE IN'!$F212=0,"",(VLOOKUP($C200,REV!$C:$AA,10,0)-'TRADE IN'!$F200)) -> 7999 | M200: =IF(VLOOKUP($C200,REV!$C:$AA,11,0)-'TRADE IN'!$F212=0,"",(VLOOKUP($C200,REV!$C:$AA,11,0)-'TRADE IN'!$F200)) -> 7999 | N200: =IF(VLOOKUP($C200,REV!$C:$AA,12,0)-'TRADE IN'!$F212=0,"",(VLOOKUP($C200,REV!$C:$AA,12,0)-'TRADE IN'!$F200)) -> 7999 | O200: =IF(VLOOKUP($C200,REV!$C:$AA,13,0)-'TRADE IN'!$F212=0,"",(VLOOKUP($C200,REV!$C:$AA,13,0)-'TRADE IN'!$F200)) -> 7899 | P200: =IF(VLOOKUP($C200,REV!$C:$AA,14,0)-'TRADE IN'!$F212=0,"",(VLOOKUP($C200,REV!$C:$AA,14,0)-'TRADE IN'!$F200)) -> 7799 | Q200: =IF(VLOOKUP($C200,REV!$C:$AA,15,0)-'TRADE IN'!$F212=0,"",(VLOOKUP($C200,REV!$C:$AA,15,0)-'TRADE IN'!$F200)) -> 7499 | R200: =IF(VLOOKUP($C200,REV!$C:$AA,16,0)-'TRADE IN'!$F212=0,"",(VLOOKUP($C200,REV!$C:$AA,16,0)-'TRADE IN'!$F200)) -> 7899 | S200: =IF(VLOOKUP($C200,REV!$C:$AA,17,0)-'TRADE IN'!$F212=0,"",(VLOOKUP($C200,REV!$C:$AA,17,0)-'TRADE IN'!$F200)) -> 7799 | T200: =IF(VLOOKUP($C200,REV!$C:$AA,18,0)-'TRADE IN'!$F212=0,"",(VLOOKUP($C200,REV!$C:$AA,18,0)-'TRADE IN'!$F200)) -> 7499 | U200: =IF(VLOOKUP($C200,REV!$C:$AA,19,0)-'TRADE IN'!$F212=0,"",(VLOOKUP($C200,REV!$C:$AA,19,0)-'TRADE IN'!$F200)) -> 7499 | V200: =IF(VLOOKUP($C200,REV!$C:$AA,20,0)-'TRADE IN'!$F212=0,"",(VLOOKUP($C200,REV!$C:$AA,20,0)-'TRADE IN'!$F200)) -> 7499 | W200: =IF(VLOOKUP($C200,REV!$C:$AA,21,0)-'TRADE IN'!$F212=0,"",(VLOOKUP($C200,REV!$C:$AA,21,0)-'TRADE IN'!$F200)) -> 7499 | X200: =IF(VLOOKUP($C200,REV!$C:$AA,22,0)-'TRADE IN'!$F212=0,"",(VLOOKUP($C200,REV!$C:$AA,22,0)-'TRADE IN'!$F200)) -> 7399 | Y200: =IF(VLOOKUP($C200,REV!$C:$AA,23,0)-'TRADE IN'!$F212=0,"",(VLOOKUP($C200,REV!$C:$AA,23,0)-'TRADE IN'!$F200)) -> 6799 | Z200: =IF(VLOOKUP($C200,REV!$C:$AA,24,0)-'TRADE IN'!$F212=0,"",(VLOOKUP($C200,REV!$C:$AA,24,0)-'TRADE IN'!$F200)) -> 6799 | AA200: =IF(VLOOKUP($C200,REV!$C:$AA,25,0)-'TRADE IN'!$F212=0,"",(VLOOKUP($C200,REV!$C:$AA,25,0)-'TRADE IN'!$F200)) -> 6799 | AW200: =IF(REV!AW200=0,"",REV!AW200) -> 31.03.2026 | AX200: 5G
A201: Price Oferta | B201: 21X | C201: 4017518 | D201: APPLE IPHONE 17 AIR 512GB | E201: APPLE IPHONE 17 AIR 512GB-AZUL CEU | F201: 1000 | J201: =IF(VLOOKUP($C201,REV!$C:$AA,8,0)-'TRADE IN'!$F201=0,"",(VLOOKUP($C201,REV!$C:$AA,8,0)-'TRADE IN'!$F201)) -> 7999 | K201: =IF(VLOOKUP($C201,REV!$C:$AA,9,0)-'TRADE IN'!$F201=0,"",(VLOOKUP($C201,REV!$C:$AA,9,0)-'TRADE IN'!$F201)) -> 7999 | L201: =IF(VLOOKUP($C201,REV!$C:$AA,10,0)-'TRADE IN'!$F213=0,"",(VLOOKUP($C201,REV!$C:$AA,10,0)-'TRADE IN'!$F201)) -> 7999 | M201: =IF(VLOOKUP($C201,REV!$C:$AA,11,0)-'TRADE IN'!$F213=0,"",(VLOOKUP($C201,REV!$C:$AA,11,0)-'TRADE IN'!$F201)) -> 7999 | N201: =IF(VLOOKUP($C201,REV!$C:$AA,12,0)-'TRADE IN'!$F213=0,"",(VLOOKUP($C201,REV!$C:$AA,12,0)-'TRADE IN'!$F201)) -> 7999 | O201: =IF(VLOOKUP($C201,REV!$C:$AA,13,0)-'TRADE IN'!$F213=0,"",(VLOOKUP($C201,REV!$C:$AA,13,0)-'TRADE IN'!$F201)) -> 7899 | P201: =IF(VLOOKUP($C201,REV!$C:$AA,14,0)-'TRADE IN'!$F213=0,"",(VLOOKUP($C201,REV!$C:$AA,14,0)-'TRADE IN'!$F201)) -> 7799 | Q201: =IF(VLOOKUP($C201,REV!$C:$AA,15,0)-'TRADE IN'!$F213=0,"",(VLOOKUP($C201,REV!$C:$AA,15,0)-'TRADE IN'!$F201)) -> 7499 | R201: =IF(VLOOKUP($C201,REV!$C:$AA,16,0)-'TRADE IN'!$F213=0,"",(VLOOKUP($C201,REV!$C:$AA,16,0)-'TRADE IN'!$F201)) -> 7899 | S201: =IF(VLOOKUP($C201,REV!$C:$AA,17,0)-'TRADE IN'!$F213=0,"",(VLOOKUP($C201,REV!$C:$AA,17,0)-'TRADE IN'!$F201)) -> 7799 | T201: =IF(VLOOKUP($C201,REV!$C:$AA,18,0)-'TRADE IN'!$F213=0,"",(VLOOKUP($C201,REV!$C:$AA,18,0)-'TRADE IN'!$F201)) -> 7499 | U201: =IF(VLOOKUP($C201,REV!$C:$AA,19,0)-'TRADE IN'!$F213=0,"",(VLOOKUP($C201,REV!$C:$AA,19,0)-'TRADE IN'!$F201)) -> 7499 | V201: =IF(VLOOKUP($C201,REV!$C:$AA,20,0)-'TRADE IN'!$F213=0,"",(VLOOKUP($C201,REV!$C:$AA,20,0)-'TRADE IN'!$F201)) -> 7499 | W201: =IF(VLOOKUP($C201,REV!$C:$AA,21,0)-'TRADE IN'!$F213=0,"",(VLOOKUP($C201,REV!$C:$AA,21,0)-'TRADE IN'!$F201)) -> 7499 | X201: =IF(VLOOKUP($C201,REV!$C:$AA,22,0)-'TRADE IN'!$F213=0,"",(VLOOKUP($C201,REV!$C:$AA,22,0)-'TRADE IN'!$F201)) -> 7399 | Y201: =IF(VLOOKUP($C201,REV!$C:$AA,23,0)-'TRADE IN'!$F213=0,"",(VLOOKUP($C201,REV!$C:$AA,23,0)-'TRADE IN'!$F201)) -> 6799 | Z201: =IF(VLOOKUP($C201,REV!$C:$AA,24,0)-'TRADE IN'!$F213=0,"",(VLOOKUP($C201,REV!$C:$AA,24,0)-'TRADE IN'!$F201)) -> 6799 | AA201: =IF(VLOOKUP($C201,REV!$C:$AA,25,0)-'TRADE IN'!$F213=0,"",(VLOOKUP($C201,REV!$C:$AA,25,0)-'TRADE IN'!$F201)) -> 6799 | AW201: =IF(REV!AW201=0,"",REV!AW201) -> 31.03.2026 | AX201: 5G
A202: Price Oferta | B202: 21X | C202: 4017487 | D202: APPLE IPHONE 17 PRO 256GB | E202: APPLE IPHONE 17 PRO 256GB-AZUL INTENSO | J202: =IF(VLOOKUP($C202,REV!$C:$AA,8,0)-'TRADE IN'!$F202=0,"",(VLOOKUP($C202,REV!$C:$AA,8,0)-'TRADE IN'!$F202)) -> 10799 | K202: =IF(VLOOKUP($C202,REV!$C:$AA,9,0)-'TRADE IN'!$F202=0,"",(VLOOKUP($C202,REV!$C:$AA,9,0)-'TRADE IN'!$F202)) -> 10799 | L202: =IF(VLOOKUP($C202,REV!$C:$AA,10,0)-'TRADE IN'!$F213=0,"",(VLOOKUP($C202,REV!$C:$AA,10,0)-'TRADE IN'!$F202)) -> 10799 | M202: =IF(VLOOKUP($C202,REV!$C:$AA,11,0)-'TRADE IN'!$F213=0,"",(VLOOKUP($C202,REV!$C:$AA,11,0)-'TRADE IN'!$F202)) -> 10799 | N202: =IF(VLOOKUP($C202,REV!$C:$AA,12,0)-'TRADE IN'!$F213=0,"",(VLOOKUP($C202,REV!$C:$AA,12,0)-'TRADE IN'!$F202)) -> 10799 | O202: =IF(VLOOKUP($C202,REV!$C:$AA,13,0)-'TRADE IN'!$F213=0,"",(VLOOKUP($C202,REV!$C:$AA,13,0)-'TRADE IN'!$F202)) -> 10699 | P202: =IF(VLOOKUP($C202,REV!$C:$AA,14,0)-'TRADE IN'!$F213=0,"",(VLOOKUP($C202,REV!$C:$AA,14,0)-'TRADE IN'!$F202)) -> 10599 | Q202: =IF(VLOOKUP($C202,REV!$C:$AA,15,0)-'TRADE IN'!$F213=0,"",(VLOOKUP($C202,REV!$C:$AA,15,0)-'TRADE IN'!$F202)) -> 9799 | R202: =IF(VLOOKUP($C202,REV!$C:$AA,16,0)-'TRADE IN'!$F213=0,"",(VLOOKUP($C202,REV!$C:$AA,16,0)-'TRADE IN'!$F202)) -> 10699 | S202: =IF(VLOOKUP($C202,REV!$C:$AA,17,0)-'TRADE IN'!$F213=0,"",(VLOOKUP($C202,REV!$C:$AA,17,0)-'TRADE IN'!$F202)) -> 10599 | T202: =IF(VLOOKUP($C202,REV!$C:$AA,18,0)-'TRADE IN'!$F213=0,"",(VLOOKUP($C202,REV!$C:$AA,18,0)-'TRADE IN'!$F202)) -> 9799 | U202: =IF(VLOOKUP($C202,REV!$C:$AA,19,0)-'TRADE IN'!$F213=0,"",(VLOOKUP($C202,REV!$C:$AA,19,0)-'TRADE IN'!$F202)) -> 9799 | V202: =IF(VLOOKUP($C202,REV!$C:$AA,20,0)-'TRADE IN'!$F213=0,"",(VLOOKUP($C202,REV!$C:$AA,20,0)-'TRADE IN'!$F202)) -> 9799 | W202: =IF(VLOOKUP($C202,REV!$C:$AA,21,0)-'TRADE IN'!$F213=0,"",(VLOOKUP($C202,REV!$C:$AA,21,0)-'TRADE IN'!$F202)) -> 9699 | X202: =IF(VLOOKUP($C202,REV!$C:$AA,22,0)-'TRADE IN'!$F213=0,"",(VLOOKUP($C202,REV!$C:$AA,22,0)-'TRADE IN'!$F202)) -> 9699 | Y202: =IF(VLOOKUP($C202,REV!$C:$AA,23,0)-'TRADE IN'!$F213=0,"",(VLOOKUP($C202,REV!$C:$AA,23,0)-'TRADE IN'!$F202)) -> 8799 | Z202: =IF(VLOOKUP($C202,REV!$C:$AA,24,0)-'TRADE IN'!$F213=0,"",(VLOOKUP($C202,REV!$C:$AA,24,0)-'TRADE IN'!$F202)) -> 8799 | AA202: =IF(VLOOKUP($C202,REV!$C:$AA,25,0)-'TRADE IN'!$F213=0,"",(VLOOKUP($C202,REV!$C:$AA,25,0)-'TRADE IN'!$F202)) -> 8799 | AW202: =IF(REV!AW202=0,"",REV!AW202) -> 31.03.2026 | AX202: 5G
A203: Price Oferta | B203: 21X | C203: 4017510 | D203: APPLE IPHONE 17 PRO 256GB | E203: APPLE IPHONE 17 PRO 256GB-LARANJA COSMIC | J203: =IF(VLOOKUP($C203,REV!$C:$AA,8,0)-'TRADE IN'!$F203=0,"",(VLOOKUP($C203,REV!$C:$AA,8,0)-'TRADE IN'!$F203)) -> 10799 | K203: =IF(VLOOKUP($C203,REV!$C:$AA,9,0)-'TRADE IN'!$F203=0,"",(VLOOKUP($C203,REV!$C:$AA,9,0)-'TRADE IN'!$F203)) -> 10799 | L203: =IF(VLOOKUP($C203,REV!$C:$AA,10,0)-'TRADE IN'!$F214=0,"",(VLOOKUP($C203,REV!$C:$AA,10,0)-'TRADE IN'!$F203)) -> 10799 | M203: =IF(VLOOKUP($C203,REV!$C:$AA,11,0)-'TRADE IN'!$F214=0,"",(VLOOKUP($C203,REV!$C:$AA,11,0)-'TRADE IN'!$F203)) -> 10799 | N203: =IF(VLOOKUP($C203,REV!$C:$AA,12,0)-'TRADE IN'!$F214=0,"",(VLOOKUP($C203,REV!$C:$AA,12,0)-'TRADE IN'!$F203)) -> 10799 | O203: =IF(VLOOKUP($C203,REV!$C:$AA,13,0)-'TRADE IN'!$F214=0,"",(VLOOKUP($C203,REV!$C:$AA,13,0)-'TRADE IN'!$F203)) -> 10699 | P203: =IF(VLOOKUP($C203,REV!$C:$AA,14,0)-'TRADE IN'!$F214=0,"",(VLOOKUP($C203,REV!$C:$AA,14,0)-'TRADE IN'!$F203)) -> 10599 | Q203: =IF(VLOOKUP($C203,REV!$C:$AA,15,0)-'TRADE IN'!$F214=0,"",(VLOOKUP($C203,REV!$C:$AA,15,0)-'TRADE IN'!$F203)) -> 9799 | R203: =IF(VLOOKUP($C203,REV!$C:$AA,16,0)-'TRADE IN'!$F214=0,"",(VLOOKUP($C203,REV!$C:$AA,16,0)-'TRADE IN'!$F203)) -> 10699 | S203: =IF(VLOOKUP($C203,REV!$C:$AA,17,0)-'TRADE IN'!$F214=0,"",(VLOOKUP($C203,REV!$C:$AA,17,0)-'TRADE IN'!$F203)) -> 10599 | T203: =IF(VLOOKUP($C203,REV!$C:$AA,18,0)-'TRADE IN'!$F214=0,"",(VLOOKUP($C203,REV!$C:$AA,18,0)-'TRADE IN'!$F203)) -> 9799 | U203: =IF(VLOOKUP($C203,REV!$C:$AA,19,0)-'TRADE IN'!$F214=0,"",(VLOOKUP($C203,REV!$C:$AA,19,0)-'TRADE IN'!$F203)) -> 9799 | V203: =IF(VLOOKUP($C203,REV!$C:$AA,20,0)-'TRADE IN'!$F214=0,"",(VLOOKUP($C203,REV!$C:$AA,20,0)-'TRADE IN'!$F203)) -> 9799 | W203: =IF(VLOOKUP($C203,REV!$C:$AA,21,0)-'TRADE IN'!$F214=0,"",(VLOOKUP($C203,REV!$C:$AA,21,0)-'TRADE IN'!$F203)) -> 9699 | X203: =IF(VLOOKUP($C203,REV!$C:$AA,22,0)-'TRADE IN'!$F214=0,"",(VLOOKUP($C203,REV!$C:$AA,22,0)-'TRADE IN'!$F203)) -> 9699 | Y203: =IF(VLOOKUP($C203,REV!$C:$AA,23,0)-'TRADE IN'!$F214=0,"",(VLOOKUP($C203,REV!$C:$AA,23,0)-'TRADE IN'!$F203)) -> 8799 | Z203: =IF(VLOOKUP($C203,REV!$C:$AA,24,0)-'TRADE IN'!$F214=0,"",(VLOOKUP($C203,REV!$C:$AA,24,0)-'TRADE IN'!$F203)) -> 8799 | AA203: =IF(VLOOKUP($C203,REV!$C:$AA,25,0)-'TRADE IN'!$F214=0,"",(VLOOKUP($C203,REV!$C:$AA,25,0)-'TRADE IN'!$F203)) -> 8799 | AW203: =IF(REV!AW203=0,"",REV!AW203) -> 31.03.2026 | AX203: 5G
A204: Price Oferta | B204: 21X | C204: 4017513 | D204: APPLE IPHONE 17 PRO 256GB | E204: APPLE IPHONE 17 PRO 256GB-PRATEADO | J204: =IF(VLOOKUP($C204,REV!$C:$AA,8,0)-'TRADE IN'!$F204=0,"",(VLOOKUP($C204,REV!$C:$AA,8,0)-'TRADE IN'!$F204)) -> 10799 | K204: =IF(VLOOKUP($C204,REV!$C:$AA,9,0)-'TRADE IN'!$F204=0,"",(VLOOKUP($C204,REV!$C:$AA,9,0)-'TRADE IN'!$F204)) -> 10799 | L204: =IF(VLOOKUP($C204,REV!$C:$AA,10,0)-'TRADE IN'!$F215=0,"",(VLOOKUP($C204,REV!$C:$AA,10,0)-'TRADE IN'!$F204)) -> 10799 | M204: =IF(VLOOKUP($C204,REV!$C:$AA,11,0)-'TRADE IN'!$F215=0,"",(VLOOKUP($C204,REV!$C:$AA,11,0)-'TRADE IN'!$F204)) -> 10799 | N204: =IF(VLOOKUP($C204,REV!$C:$AA,12,0)-'TRADE IN'!$F215=0,"",(VLOOKUP($C204,REV!$C:$AA,12,0)-'TRADE IN'!$F204)) -> 10799 | O204: =IF(VLOOKUP($C204,REV!$C:$AA,13,0)-'TRADE IN'!$F215=0,"",(VLOOKUP($C204,REV!$C:$AA,13,0)-'TRADE IN'!$F204)) -> 10699 | P204: =IF(VLOOKUP($C204,REV!$C:$AA,14,0)-'TRADE IN'!$F215=0,"",(VLOOKUP($C204,REV!$C:$AA,14,0)-'TRADE IN'!$F204)) -> 10599 | Q204: =IF(VLOOKUP($C204,REV!$C:$AA,15,0)-'TRADE IN'!$F215=0,"",(VLOOKUP($C204,REV!$C:$AA,15,0)-'TRADE IN'!$F204)) -> 9799 | R204: =IF(VLOOKUP($C204,REV!$C:$AA,16,0)-'TRADE IN'!$F215=0,"",(VLOOKUP($C204,REV!$C:$AA,16,0)-'TRADE IN'!$F204)) -> 10699 | S204: =IF(VLOOKUP($C204,REV!$C:$AA,17,0)-'TRADE IN'!$F215=0,"",(VLOOKUP($C204,REV!$C:$AA,17,0)-'TRADE IN'!$F204)) -> 10599 | T204: =IF(VLOOKUP($C204,REV!$C:$AA,18,0)-'TRADE IN'!$F215=0,"",(VLOOKUP($C204,REV!$C:$AA,18,0)-'TRADE IN'!$F204)) -> 9799 | U204: =IF(VLOOKUP($C204,REV!$C:$AA,19,0)-'TRADE IN'!$F215=0,"",(VLOOKUP($C204,REV!$C:$AA,19,0)-'TRADE IN'!$F204)) -> 9799 | V204: =IF(VLOOKUP($C204,REV!$C:$AA,20,0)-'TRADE IN'!$F215=0,"",(VLOOKUP($C204,REV!$C:$AA,20,0)-'TRADE IN'!$F204)) -> 9799 | W204: =IF(VLOOKUP($C204,REV!$C:$AA,21,0)-'TRADE IN'!$F215=0,"",(VLOOKUP($C204,REV!$C:$AA,21,0)-'TRADE IN'!$F204)) -> 9699 | X204: =IF(VLOOKUP($C204,REV!$C:$AA,22,0)-'TRADE IN'!$F215=0,"",(VLOOKUP($C204,REV!$C:$AA,22,0)-'TRADE IN'!$F204)) -> 9699 | Y204: =IF(VLOOKUP($C204,REV!$C:$AA,23,0)-'TRADE IN'!$F215=0,"",(VLOOKUP($C204,REV!$C:$AA,23,0)-'TRADE IN'!$F204)) -> 8799 | Z204: =IF(VLOOKUP($C204,REV!$C:$AA,24,0)-'TRADE IN'!$F215=0,"",(VLOOKUP($C204,REV!$C:$AA,24,0)-'TRADE IN'!$F204)) -> 8799 | AA204: =IF(VLOOKUP($C204,REV!$C:$AA,25,0)-'TRADE IN'!$F215=0,"",(VLOOKUP($C204,REV!$C:$AA,25,0)-'TRADE IN'!$F204)) -> 8799 | AW204: =IF(REV!AW204=0,"",REV!AW204) -> 31.03.2026 | AX204: 5G
A205: Price Oferta | B205: 21X | C205: 4017488 | D205: APPLE IPHONE 17 PRO 512GB | E205: APPLE IPHONE 17 PRO 512GB-AZUL INTENSO | J205: =IF(VLOOKUP($C205,REV!$C:$AA,8,0)-'TRADE IN'!$F205=0,"",(VLOOKUP($C205,REV!$C:$AA,8,0)-'TRADE IN'!$F205)) -> 12199 | K205: =IF(VLOOKUP($C205,REV!$C:$AA,9,0)-'TRADE IN'!$F205=0,"",(VLOOKUP($C205,REV!$C:$AA,9,0)-'TRADE IN'!$F205)) -> 12199 | L205: =IF(VLOOKUP($C205,REV!$C:$AA,10,0)-'TRADE IN'!$F215=0,"",(VLOOKUP($C205,REV!$C:$AA,10,0)-'TRADE IN'!$F205)) -> 12199 | M205: =IF(VLOOKUP($C205,REV!$C:$AA,11,0)-'TRADE IN'!$F215=0,"",(VLOOKUP($C205,REV!$C:$AA,11,0)-'TRADE IN'!$F205)) -> 12199 | N205: =IF(VLOOKUP($C205,REV!$C:$AA,12,0)-'TRADE IN'!$F215=0,"",(VLOOKUP($C205,REV!$C:$AA,12,0)-'TRADE IN'!$F205)) -> 12199 | O205: =IF(VLOOKUP($C205,REV!$C:$AA,13,0)-'TRADE IN'!$F215=0,"",(VLOOKUP($C205,REV!$C:$AA,13,0)-'TRADE IN'!$F205)) -> 12099 | P205: =IF(VLOOKUP($C205,REV!$C:$AA,14,0)-'TRADE IN'!$F215=0,"",(VLOOKUP($C205,REV!$C:$AA,14,0)-'TRADE IN'!$F205)) -> 11999 | Q205: =IF(VLOOKUP($C205,REV!$C:$AA,15,0)-'TRADE IN'!$F215=0,"",(VLOOKUP($C205,REV!$C:$AA,15,0)-'TRADE IN'!$F205)) -> 11199 | R205: =IF(VLOOKUP($C205,REV!$C:$AA,16,0)-'TRADE IN'!$F215=0,"",(VLOOKUP($C205,REV!$C:$AA,16,0)-'TRADE IN'!$F205)) -> 12099 | S205: =IF(VLOOKUP($C205,REV!$C:$AA,17,0)-'TRADE IN'!$F215=0,"",(VLOOKUP($C205,REV!$C:$AA,17,0)-'TRADE IN'!$F205)) -> 11999 | T205: =IF(VLOOKUP($C205,REV!$C:$AA,18,0)-'TRADE IN'!$F215=0,"",(VLOOKUP($C205,REV!$C:$AA,18,0)-'TRADE IN'!$F205)) -> 11199 | U205: =IF(VLOOKUP($C205,REV!$C:$AA,19,0)-'TRADE IN'!$F215=0,"",(VLOOKUP($C205,REV!$C:$AA,19,0)-'TRADE IN'!$F205)) -> 11199 | V205: =IF(VLOOKUP($C205,REV!$C:$AA,20,0)-'TRADE IN'!$F215=0,"",(VLOOKUP($C205,REV!$C:$AA,20,0)-'TRADE IN'!$F205)) -> 11199 | W205: =IF(VLOOKUP($C205,REV!$C:$AA,21,0)-'TRADE IN'!$F215=0,"",(VLOOKUP($C205,REV!$C:$AA,21,0)-'TRADE IN'!$F205)) -> 11099 | X205: =IF(VLOOKUP($C205,REV!$C:$AA,22,0)-'TRADE IN'!$F215=0,"",(VLOOKUP($C205,REV!$C:$AA,22,0)-'TRADE IN'!$F205)) -> 11099 | Y205: =IF(VLOOKUP($C205,REV!$C:$AA,23,0)-'TRADE IN'!$F215=0,"",(VLOOKUP($C205,REV!$C:$AA,23,0)-'TRADE IN'!$F205)) -> 9999 | Z205: =IF(VLOOKUP($C205,REV!$C:$AA,24,0)-'TRADE IN'!$F215=0,"",(VLOOKUP($C205,REV!$C:$AA,24,0)-'TRADE IN'!$F205)) -> 9999 | AA205: =IF(VLOOKUP($C205,REV!$C:$AA,25,0)-'TRADE IN'!$F215=0,"",(VLOOKUP($C205,REV!$C:$AA,25,0)-'TRADE IN'!$F205)) -> 9899 | AW205: =IF(REV!AW205=0,"",REV!AW205) -> 31.03.2026 | AX205: 5G
A206: Price Oferta | B206: 21X | C206: 4017508 | D206: APPLE IPHONE 17 PRO 512GB | E206: APPLE IPHONE 17 PRO 512GB-LARANJA COSMIC | J206: =IF(VLOOKUP($C206,REV!$C:$AA,8,0)-'TRADE IN'!$F206=0,"",(VLOOKUP($C206,REV!$C:$AA,8,0)-'TRADE IN'!$F206)) -> 12199 | K206: =IF(VLOOKUP($C206,REV!$C:$AA,9,0)-'TRADE IN'!$F206=0,"",(VLOOKUP($C206,REV!$C:$AA,9,0)-'TRADE IN'!$F206)) -> 12199 | L206: =IF(VLOOKUP($C206,REV!$C:$AA,10,0)-'TRADE IN'!$F216=0,"",(VLOOKUP($C206,REV!$C:$AA,10,0)-'TRADE IN'!$F206)) -> 12199 | M206: =IF(VLOOKUP($C206,REV!$C:$AA,11,0)-'TRADE IN'!$F216=0,"",(VLOOKUP($C206,REV!$C:$AA,11,0)-'TRADE IN'!$F206)) -> 12199 | N206: =IF(VLOOKUP($C206,REV!$C:$AA,12,0)-'TRADE IN'!$F216=0,"",(VLOOKUP($C206,REV!$C:$AA,12,0)-'TRADE IN'!$F206)) -> 12199 | O206: =IF(VLOOKUP($C206,REV!$C:$AA,13,0)-'TRADE IN'!$F216=0,"",(VLOOKUP($C206,REV!$C:$AA,13,0)-'TRADE IN'!$F206)) -> 12099 | P206: =IF(VLOOKUP($C206,REV!$C:$AA,14,0)-'TRADE IN'!$F216=0,"",(VLOOKUP($C206,REV!$C:$AA,14,0)-'TRADE IN'!$F206)) -> 11999 | Q206: =IF(VLOOKUP($C206,REV!$C:$AA,15,0)-'TRADE IN'!$F216=0,"",(VLOOKUP($C206,REV!$C:$AA,15,0)-'TRADE IN'!$F206)) -> 11199 | R206: =IF(VLOOKUP($C206,REV!$C:$AA,16,0)-'TRADE IN'!$F216=0,"",(VLOOKUP($C206,REV!$C:$AA,16,0)-'TRADE IN'!$F206)) -> 12099 | S206: =IF(VLOOKUP($C206,REV!$C:$AA,17,0)-'TRADE IN'!$F216=0,"",(VLOOKUP($C206,REV!$C:$AA,17,0)-'TRADE IN'!$F206)) -> 11999 | T206: =IF(VLOOKUP($C206,REV!$C:$AA,18,0)-'TRADE IN'!$F216=0,"",(VLOOKUP($C206,REV!$C:$AA,18,0)-'TRADE IN'!$F206)) -> 11199 | U206: =IF(VLOOKUP($C206,REV!$C:$AA,19,0)-'TRADE IN'!$F216=0,"",(VLOOKUP($C206,REV!$C:$AA,19,0)-'TRADE IN'!$F206)) -> 11199 | V206: =IF(VLOOKUP($C206,REV!$C:$AA,20,0)-'TRADE IN'!$F216=0,"",(VLOOKUP($C206,REV!$C:$AA,20,0)-'TRADE IN'!$F206)) -> 11199 | W206: =IF(VLOOKUP($C206,REV!$C:$AA,21,0)-'TRADE IN'!$F216=0,"",(VLOOKUP($C206,REV!$C:$AA,21,0)-'TRADE IN'!$F206)) -> 11099 | X206: =IF(VLOOKUP($C206,REV!$C:$AA,22,0)-'TRADE IN'!$F216=0,"",(VLOOKUP($C206,REV!$C:$AA,22,0)-'TRADE IN'!$F206)) -> 11099 | Y206: =IF(VLOOKUP($C206,REV!$C:$AA,23,0)-'TRADE IN'!$F216=0,"",(VLOOKUP($C206,REV!$C:$AA,23,0)-'TRADE IN'!$F206)) -> 9999 | Z206: =IF(VLOOKUP($C206,REV!$C:$AA,24,0)-'TRADE IN'!$F216=0,"",(VLOOKUP($C206,REV!$C:$AA,24,0)-'TRADE IN'!$F206)) -> 9999 | AA206: =IF(VLOOKUP($C206,REV!$C:$AA,25,0)-'TRADE IN'!$F216=0,"",(VLOOKUP($C206,REV!$C:$AA,25,0)-'TRADE IN'!$F206)) -> 9899 | AW206: =IF(REV!AW206=0,"",REV!AW206) -> 31.03.2026 | AX206: 5G
A207: Price Oferta | B207: 21X | C207: 4017489 | D207: APPLE IPHONE 17 PRO 512GB | E207: APPLE IPHONE 17 PRO 512GB-PRATEADO | J207: =IF(VLOOKUP($C207,REV!$C:$AA,8,0)-'TRADE IN'!$F207=0,"",(VLOOKUP($C207,REV!$C:$AA,8,0)-'TRADE IN'!$F207)) -> 12199 | K207: =IF(VLOOKUP($C207,REV!$C:$AA,9,0)-'TRADE IN'!$F207=0,"",(VLOOKUP($C207,REV!$C:$AA,9,0)-'TRADE IN'!$F207)) -> 12199 | L207: =IF(VLOOKUP($C207,REV!$C:$AA,10,0)-'TRADE IN'!$F217=0,"",(VLOOKUP($C207,REV!$C:$AA,10,0)-'TRADE IN'!$F207)) -> 12199 | M207: =IF(VLOOKUP($C207,REV!$C:$AA,11,0)-'TRADE IN'!$F217=0,"",(VLOOKUP($C207,REV!$C:$AA,11,0)-'TRADE IN'!$F207)) -> 12199 | N207: =IF(VLOOKUP($C207,REV!$C:$AA,12,0)-'TRADE IN'!$F217=0,"",(VLOOKUP($C207,REV!$C:$AA,12,0)-'TRADE IN'!$F207)) -> 12199 | O207: =IF(VLOOKUP($C207,REV!$C:$AA,13,0)-'TRADE IN'!$F217=0,"",(VLOOKUP($C207,REV!$C:$AA,13,0)-'TRADE IN'!$F207)) -> 12099 | P207: =IF(VLOOKUP($C207,REV!$C:$AA,14,0)-'TRADE IN'!$F217=0,"",(VLOOKUP($C207,REV!$C:$AA,14,0)-'TRADE IN'!$F207)) -> 11999 | Q207: =IF(VLOOKUP($C207,REV!$C:$AA,15,0)-'TRADE IN'!$F217=0,"",(VLOOKUP($C207,REV!$C:$AA,15,0)-'TRADE IN'!$F207)) -> 11199 | R207: =IF(VLOOKUP($C207,REV!$C:$AA,16,0)-'TRADE IN'!$F217=0,"",(VLOOKUP($C207,REV!$C:$AA,16,0)-'TRADE IN'!$F207)) -> 12099 | S207: =IF(VLOOKUP($C207,REV!$C:$AA,17,0)-'TRADE IN'!$F217=0,"",(VLOOKUP($C207,REV!$C:$AA,17,0)-'TRADE IN'!$F207)) -> 11999 | T207: =IF(VLOOKUP($C207,REV!$C:$AA,18,0)-'TRADE IN'!$F217=0,"",(VLOOKUP($C207,REV!$C:$AA,18,0)-'TRADE IN'!$F207)) -> 11199 | U207: =IF(VLOOKUP($C207,REV!$C:$AA,19,0)-'TRADE IN'!$F217=0,"",(VLOOKUP($C207,REV!$C:$AA,19,0)-'TRADE IN'!$F207)) -> 11199 | V207: =IF(VLOOKUP($C207,REV!$C:$AA,20,0)-'TRADE IN'!$F217=0,"",(VLOOKUP($C207,REV!$C:$AA,20,0)-'TRADE IN'!$F207)) -> 11199 | W207: =IF(VLOOKUP($C207,REV!$C:$AA,21,0)-'TRADE IN'!$F217=0,"",(VLOOKUP($C207,REV!$C:$AA,21,0)-'TRADE IN'!$F207)) -> 11099 | X207: =IF(VLOOKUP($C207,REV!$C:$AA,22,0)-'TRADE IN'!$F217=0,"",(VLOOKUP($C207,REV!$C:$AA,22,0)-'TRADE IN'!$F207)) -> 11099 | Y207: =IF(VLOOKUP($C207,REV!$C:$AA,23,0)-'TRADE IN'!$F217=0,"",(VLOOKUP($C207,REV!$C:$AA,23,0)-'TRADE IN'!$F207)) -> 9999 | Z207: =IF(VLOOKUP($C207,REV!$C:$AA,24,0)-'TRADE IN'!$F217=0,"",(VLOOKUP($C207,REV!$C:$AA,24,0)-'TRADE IN'!$F207)) -> 9999 | AA207: =IF(VLOOKUP($C207,REV!$C:$AA,25,0)-'TRADE IN'!$F217=0,"",(VLOOKUP($C207,REV!$C:$AA,25,0)-'TRADE IN'!$F207)) -> 9899 | AW207: =IF(REV!AW207=0,"",REV!AW207) -> 31.03.2026 | AX207: 5G
A208: Price Oferta | B208: 21X | C208: 4017493 | D208: APPLE IPHONE 17 PRO MAX 256GB | E208: APPLE IPHONE 17 PRO MAX 256GB- AZUL INTE | J208: =IF(VLOOKUP($C208,REV!$C:$AA,8,0)-'TRADE IN'!$F208=0,"",(VLOOKUP($C208,REV!$C:$AA,8,0)-'TRADE IN'!$F208)) -> 11699 | K208: =IF(VLOOKUP($C208,REV!$C:$AA,9,0)-'TRADE IN'!$F208=0,"",(VLOOKUP($C208,REV!$C:$AA,9,0)-'TRADE IN'!$F208)) -> 11699 | L208: =IF(VLOOKUP($C208,REV!$C:$AA,10,0)-'TRADE IN'!$F217=0,"",(VLOOKUP($C208,REV!$C:$AA,10,0)-'TRADE IN'!$F208)) -> 11699 | M208: =IF(VLOOKUP($C208,REV!$C:$AA,11,0)-'TRADE IN'!$F217=0,"",(VLOOKUP($C208,REV!$C:$AA,11,0)-'TRADE IN'!$F208)) -> 11699 | N208: =IF(VLOOKUP($C208,REV!$C:$AA,12,0)-'TRADE IN'!$F217=0,"",(VLOOKUP($C208,REV!$C:$AA,12,0)-'TRADE IN'!$F208)) -> 11699 | O208: =IF(VLOOKUP($C208,REV!$C:$AA,13,0)-'TRADE IN'!$F217=0,"",(VLOOKUP($C208,REV!$C:$AA,13,0)-'TRADE IN'!$F208)) -> 11599 | P208: =IF(VLOOKUP($C208,REV!$C:$AA,14,0)-'TRADE IN'!$F217=0,"",(VLOOKUP($C208,REV!$C:$AA,14,0)-'TRADE IN'!$F208)) -> 11499 | Q208: =IF(VLOOKUP($C208,REV!$C:$AA,15,0)-'TRADE IN'!$F217=0,"",(VLOOKUP($C208,REV!$C:$AA,15,0)-'TRADE IN'!$F208)) -> 10699 | R208: =IF(VLOOKUP($C208,REV!$C:$AA,16,0)-'TRADE IN'!$F217=0,"",(VLOOKUP($C208,REV!$C:$AA,16,0)-'TRADE IN'!$F208)) -> 11599 | S208: =IF(VLOOKUP($C208,REV!$C:$AA,17,0)-'TRADE IN'!$F217=0,"",(VLOOKUP($C208,REV!$C:$AA,17,0)-'TRADE IN'!$F208)) -> 11499 | T208: =IF(VLOOKUP($C208,REV!$C:$AA,18,0)-'TRADE IN'!$F217=0,"",(VLOOKUP($C208,REV!$C:$AA,18,0)-'TRADE IN'!$F208)) -> 10699 | U208: =IF(VLOOKUP($C208,REV!$C:$AA,19,0)-'TRADE IN'!$F217=0,"",(VLOOKUP($C208,REV!$C:$AA,19,0)-'TRADE IN'!$F208)) -> 10699 | V208: =IF(VLOOKUP($C208,REV!$C:$AA,20,0)-'TRADE IN'!$F217=0,"",(VLOOKUP($C208,REV!$C:$AA,20,0)-'TRADE IN'!$F208)) -> 10699 | W208: =IF(VLOOKUP($C208,REV!$C:$AA,21,0)-'TRADE IN'!$F217=0,"",(VLOOKUP($C208,REV!$C:$AA,21,0)-'TRADE IN'!$F208)) -> 10599 | X208: =IF(VLOOKUP($C208,REV!$C:$AA,22,0)-'TRADE IN'!$F217=0,"",(VLOOKUP($C208,REV!$C:$AA,22,0)-'TRADE IN'!$F208)) -> 10599 | Y208: =IF(VLOOKUP($C208,REV!$C:$AA,23,0)-'TRADE IN'!$F217=0,"",(VLOOKUP($C208,REV!$C:$AA,23,0)-'TRADE IN'!$F208)) -> 9799 | Z208: =IF(VLOOKUP($C208,REV!$C:$AA,24,0)-'TRADE IN'!$F217=0,"",(VLOOKUP($C208,REV!$C:$AA,24,0)-'TRADE IN'!$F208)) -> 9799 | AA208: =IF(VLOOKUP($C208,REV!$C:$AA,25,0)-'TRADE IN'!$F217=0,"",(VLOOKUP($C208,REV!$C:$AA,25,0)-'TRADE IN'!$F208)) -> 9799 | AW208: =IF(REV!AW208=0,"",REV!AW208) -> 31.03.2026 | AX208: 5G
A209: Price Oferta | B209: 21X | C209: 4017494 | D209: APPLE IPHONE 17 PRO MAX 256GB | E209: APPLE IPHONE 17 PRO MAX 256GB-PRATEADO | J209: =IF(VLOOKUP($C209,REV!$C:$AA,8,0)-'TRADE IN'!$F209=0,"",(VLOOKUP($C209,REV!$C:$AA,8,0)-'TRADE IN'!$F209)) -> 11699 | K209: =IF(VLOOKUP($C209,REV!$C:$AA,9,0)-'TRADE IN'!$F209=0,"",(VLOOKUP($C209,REV!$C:$AA,9,0)-'TRADE IN'!$F209)) -> 11699 | L209: =IF(VLOOKUP($C209,REV!$C:$AA,10,0)-'TRADE IN'!$F220=0,"",(VLOOKUP($C209,REV!$C:$AA,10,0)-'TRADE IN'!$F209)) -> 11699 | M209: =IF(VLOOKUP($C209,REV!$C:$AA,11,0)-'TRADE IN'!$F220=0,"",(VLOOKUP($C209,REV!$C:$AA,11,0)-'TRADE IN'!$F209)) -> 11699 | N209: =IF(VLOOKUP($C209,REV!$C:$AA,12,0)-'TRADE IN'!$F220=0,"",(VLOOKUP($C209,REV!$C:$AA,12,0)-'TRADE IN'!$F209)) -> 11699 | O209: =IF(VLOOKUP($C209,REV!$C:$AA,13,0)-'TRADE IN'!$F220=0,"",(VLOOKUP($C209,REV!$C:$AA,13,0)-'TRADE IN'!$F209)) -> 11599 | P209: =IF(VLOOKUP($C209,REV!$C:$AA,14,0)-'TRADE IN'!$F220=0,"",(VLOOKUP($C209,REV!$C:$AA,14,0)-'TRADE IN'!$F209)) -> 11499 | Q209: =IF(VLOOKUP($C209,REV!$C:$AA,15,0)-'TRADE IN'!$F220=0,"",(VLOOKUP($C209,REV!$C:$AA,15,0)-'TRADE IN'!$F209)) -> 10699 | R209: =IF(VLOOKUP($C209,REV!$C:$AA,16,0)-'TRADE IN'!$F220=0,"",(VLOOKUP($C209,REV!$C:$AA,16,0)-'TRADE IN'!$F209)) -> 11599 | S209: =IF(VLOOKUP($C209,REV!$C:$AA,17,0)-'TRADE IN'!$F220=0,"",(VLOOKUP($C209,REV!$C:$AA,17,0)-'TRADE IN'!$F209)) -> 11499 | T209: =IF(VLOOKUP($C209,REV!$C:$AA,18,0)-'TRADE IN'!$F220=0,"",(VLOOKUP($C209,REV!$C:$AA,18,0)-'TRADE IN'!$F209)) -> 10699 | U209: =IF(VLOOKUP($C209,REV!$C:$AA,19,0)-'TRADE IN'!$F220=0,"",(VLOOKUP($C209,REV!$C:$AA,19,0)-'TRADE IN'!$F209)) -> 10699 | V209: =IF(VLOOKUP($C209,REV!$C:$AA,20,0)-'TRADE IN'!$F220=0,"",(VLOOKUP($C209,REV!$C:$AA,20,0)-'TRADE IN'!$F209)) -> 10699 | W209: =IF(VLOOKUP($C209,REV!$C:$AA,21,0)-'TRADE IN'!$F220=0,"",(VLOOKUP($C209,REV!$C:$AA,21,0)-'TRADE IN'!$F209)) -> 10599 | X209: =IF(VLOOKUP($C209,REV!$C:$AA,22,0)-'TRADE IN'!$F220=0,"",(VLOOKUP($C209,REV!$C:$AA,22,0)-'TRADE IN'!$F209)) -> 10599 | Y209: =IF(VLOOKUP($C209,REV!$C:$AA,23,0)-'TRADE IN'!$F220=0,"",(VLOOKUP($C209,REV!$C:$AA,23,0)-'TRADE IN'!$F209)) -> 9799 | Z209: =IF(VLOOKUP($C209,REV!$C:$AA,24,0)-'TRADE IN'!$F220=0,"",(VLOOKUP($C209,REV!$C:$AA,24,0)-'TRADE IN'!$F209)) -> 9799 | AA209: =IF(VLOOKUP($C209,REV!$C:$AA,25,0)-'TRADE IN'!$F220=0,"",(VLOOKUP($C209,REV!$C:$AA,25,0)-'TRADE IN'!$F209)) -> 9799 | AW209: =IF(REV!AW209=0,"",REV!AW209) -> 31.03.2026 | AX209: 5G
A210: Price Oferta | B210: 21X | C210: 4017514 | D210: APPLE IPHONE 17 PRO MAX 256GB | E210: APPLE IPHONE 17 PRO MAX 256GB-LARANJA CO | J210: =IF(VLOOKUP($C210,REV!$C:$AA,8,0)-'TRADE IN'!$F210=0,"",(VLOOKUP($C210,REV!$C:$AA,8,0)-'TRADE IN'!$F210)) -> 11699 | K210: =IF(VLOOKUP($C210,REV!$C:$AA,9,0)-'TRADE IN'!$F210=0,"",(VLOOKUP($C210,REV!$C:$AA,9,0)-'TRADE IN'!$F210)) -> 11699 | L210: =IF(VLOOKUP($C210,REV!$C:$AA,10,0)-'TRADE IN'!$F221=0,"",(VLOOKUP($C210,REV!$C:$AA,10,0)-'TRADE IN'!$F210)) -> 11699 | M210: =IF(VLOOKUP($C210,REV!$C:$AA,11,0)-'TRADE IN'!$F221=0,"",(VLOOKUP($C210,REV!$C:$AA,11,0)-'TRADE IN'!$F210)) -> 11699 | N210: =IF(VLOOKUP($C210,REV!$C:$AA,12,0)-'TRADE IN'!$F221=0,"",(VLOOKUP($C210,REV!$C:$AA,12,0)-'TRADE IN'!$F210)) -> 11699 | O210: =IF(VLOOKUP($C210,REV!$C:$AA,13,0)-'TRADE IN'!$F221=0,"",(VLOOKUP($C210,REV!$C:$AA,13,0)-'TRADE IN'!$F210)) -> 11599 | P210: =IF(VLOOKUP($C210,REV!$C:$AA,14,0)-'TRADE IN'!$F221=0,"",(VLOOKUP($C210,REV!$C:$AA,14,0)-'TRADE IN'!$F210)) -> 11499 | Q210: =IF(VLOOKUP($C210,REV!$C:$AA,15,0)-'TRADE IN'!$F221=0,"",(VLOOKUP($C210,REV!$C:$AA,15,0)-'TRADE IN'!$F210)) -> 10699 | R210: =IF(VLOOKUP($C210,REV!$C:$AA,16,0)-'TRADE IN'!$F221=0,"",(VLOOKUP($C210,REV!$C:$AA,16,0)-'TRADE IN'!$F210)) -> 11599 | S210: =IF(VLOOKUP($C210,REV!$C:$AA,17,0)-'TRADE IN'!$F221=0,"",(VLOOKUP($C210,REV!$C:$AA,17,0)-'TRADE IN'!$F210)) -> 11499 | T210: =IF(VLOOKUP($C210,REV!$C:$AA,18,0)-'TRADE IN'!$F221=0,"",(VLOOKUP($C210,REV!$C:$AA,18,0)-'TRADE IN'!$F210)) -> 10699 | U210: =IF(VLOOKUP($C210,REV!$C:$AA,19,0)-'TRADE IN'!$F221=0,"",(VLOOKUP($C210,REV!$C:$AA,19,0)-'TRADE IN'!$F210)) -> 10699 | V210: =IF(VLOOKUP($C210,REV!$C:$AA,20,0)-'TRADE IN'!$F221=0,"",(VLOOKUP($C210,REV!$C:$AA,20,0)-'TRADE IN'!$F210)) -> 10699 | W210: =IF(VLOOKUP($C210,REV!$C:$AA,21,0)-'TRADE IN'!$F221=0,"",(VLOOKUP($C210,REV!$C:$AA,21,0)-'TRADE IN'!$F210)) -> 10599 | X210: =IF(VLOOKUP($C210,REV!$C:$AA,22,0)-'TRADE IN'!$F221=0,"",(VLOOKUP($C210,REV!$C:$AA,22,0)-'TRADE IN'!$F210)) -> 10599 | Y210: =IF(VLOOKUP($C210,REV!$C:$AA,23,0)-'TRADE IN'!$F221=0,"",(VLOOKUP($C210,REV!$C:$AA,23,0)-'TRADE IN'!$F210)) -> 9799 | Z210: =IF(VLOOKUP($C210,REV!$C:$AA,24,0)-'TRADE IN'!$F221=0,"",(VLOOKUP($C210,REV!$C:$AA,24,0)-'TRADE IN'!$F210)) -> 9799 | AA210: =IF(VLOOKUP($C210,REV!$C:$AA,25,0)-'TRADE IN'!$F221=0,"",(VLOOKUP($C210,REV!$C:$AA,25,0)-'TRADE IN'!$F210)) -> 9799 | AW210: =IF(REV!AW210=0,"",REV!AW210) -> 31.03.2026 | AX210: 5G
A211: Price Oferta | B211: 21X | C211: 4017503 | D211: APPLE IPHONE 17 PRO MAX 512GB | E211: APPLE IPHONE 17 PRO MAX 512GB-LARANJA CO | J211: =IF(VLOOKUP($C211,REV!$C:$AA,8,0)-'TRADE IN'!$F211=0,"",(VLOOKUP($C211,REV!$C:$AA,8,0)-'TRADE IN'!$F211)) -> 13099 | K211: =IF(VLOOKUP($C211,REV!$C:$AA,9,0)-'TRADE IN'!$F211=0,"",(VLOOKUP($C211,REV!$C:$AA,9,0)-'TRADE IN'!$F211)) -> 13099 | L211: =IF(VLOOKUP($C211,REV!$C:$AA,10,0)-'TRADE IN'!$F222=0,"",(VLOOKUP($C211,REV!$C:$AA,10,0)-'TRADE IN'!$F211)) -> 13099 | M211: =IF(VLOOKUP($C211,REV!$C:$AA,11,0)-'TRADE IN'!$F222=0,"",(VLOOKUP($C211,REV!$C:$AA,11,0)-'TRADE IN'!$F211)) -> 13099 | N211: =IF(VLOOKUP($C211,REV!$C:$AA,12,0)-'TRADE IN'!$F222=0,"",(VLOOKUP($C211,REV!$C:$AA,12,0)-'TRADE IN'!$F211)) -> 13099 | O211: =IF(VLOOKUP($C211,REV!$C:$AA,13,0)-'TRADE IN'!$F222=0,"",(VLOOKUP($C211,REV!$C:$AA,13,0)-'TRADE IN'!$F211)) -> 12999 | P211: =IF(VLOOKUP($C211,REV!$C:$AA,14,0)-'TRADE IN'!$F222=0,"",(VLOOKUP($C211,REV!$C:$AA,14,0)-'TRADE IN'!$F211)) -> 12899 | Q211: =IF(VLOOKUP($C211,REV!$C:$AA,15,0)-'TRADE IN'!$F222=0,"",(VLOOKUP($C211,REV!$C:$AA,15,0)-'TRADE IN'!$F211)) -> 12099 | R211: =IF(VLOOKUP($C211,REV!$C:$AA,16,0)-'TRADE IN'!$F222=0,"",(VLOOKUP($C211,REV!$C:$AA,16,0)-'TRADE IN'!$F211)) -> 12999 | S211: =IF(VLOOKUP($C211,REV!$C:$AA,17,0)-'TRADE IN'!$F222=0,"",(VLOOKUP($C211,REV!$C:$AA,17,0)-'TRADE IN'!$F211)) -> 12899 | T211: =IF(VLOOKUP($C211,REV!$C:$AA,18,0)-'TRADE IN'!$F222=0,"",(VLOOKUP($C211,REV!$C:$AA,18,0)-'TRADE IN'!$F211)) -> 12099 | U211: =IF(VLOOKUP($C211,REV!$C:$AA,19,0)-'TRADE IN'!$F222=0,"",(VLOOKUP($C211,REV!$C:$AA,19,0)-'TRADE IN'!$F211)) -> 12099 | V211: =IF(VLOOKUP($C211,REV!$C:$AA,20,0)-'TRADE IN'!$F222=0,"",(VLOOKUP($C211,REV!$C:$AA,20,0)-'TRADE IN'!$F211)) -> 12099 | W211: =IF(VLOOKUP($C211,REV!$C:$AA,21,0)-'TRADE IN'!$F222=0,"",(VLOOKUP($C211,REV!$C:$AA,21,0)-'TRADE IN'!$F211)) -> 11999 | X211: =IF(VLOOKUP($C211,REV!$C:$AA,22,0)-'TRADE IN'!$F222=0,"",(VLOOKUP($C211,REV!$C:$AA,22,0)-'TRADE IN'!$F211)) -> 11999 | Y211: =IF(VLOOKUP($C211,REV!$C:$AA,23,0)-'TRADE IN'!$F222=0,"",(VLOOKUP($C211,REV!$C:$AA,23,0)-'TRADE IN'!$F211)) -> 10999 | Z211: =IF(VLOOKUP($C211,REV!$C:$AA,24,0)-'TRADE IN'!$F222=0,"",(VLOOKUP($C211,REV!$C:$AA,24,0)-'TRADE IN'!$F211)) -> 10999 | AA211: =IF(VLOOKUP($C211,REV!$C:$AA,25,0)-'TRADE IN'!$F222=0,"",(VLOOKUP($C211,REV!$C:$AA,25,0)-'TRADE IN'!$F211)) -> 10899 | AW211: =IF(REV!AW211=0,"",REV!AW211) -> 31.03.2026 | AX211: 5G
A212: Price Oferta | B212: 21X | C212: 4017520 | D212: APPLE IPHONE 17 PRO MAX 512GB | E212: APPLE IPHONE 17 PRO MAX 512GB-AZUL INTEN | J212: =IF(VLOOKUP($C212,REV!$C:$AA,8,0)-'TRADE IN'!$F212=0,"",(VLOOKUP($C212,REV!$C:$AA,8,0)-'TRADE IN'!$F212)) -> 13099 | K212: =IF(VLOOKUP($C212,REV!$C:$AA,9,0)-'TRADE IN'!$F212=0,"",(VLOOKUP($C212,REV!$C:$AA,9,0)-'TRADE IN'!$F212)) -> 13099 | L212: =IF(VLOOKUP($C212,REV!$C:$AA,10,0)-'TRADE IN'!$F223=0,"",(VLOOKUP($C212,REV!$C:$AA,10,0)-'TRADE IN'!$F212)) -> 13099 | M212: =IF(VLOOKUP($C212,REV!$C:$AA,11,0)-'TRADE IN'!$F223=0,"",(VLOOKUP($C212,REV!$C:$AA,11,0)-'TRADE IN'!$F212)) -> 13099 | N212: =IF(VLOOKUP($C212,REV!$C:$AA,12,0)-'TRADE IN'!$F223=0,"",(VLOOKUP($C212,REV!$C:$AA,12,0)-'TRADE IN'!$F212)) -> 13099 | O212: =IF(VLOOKUP($C212,REV!$C:$AA,13,0)-'TRADE IN'!$F223=0,"",(VLOOKUP($C212,REV!$C:$AA,13,0)-'TRADE IN'!$F212)) -> 12999 | P212: =IF(VLOOKUP($C212,REV!$C:$AA,14,0)-'TRADE IN'!$F223=0,"",(VLOOKUP($C212,REV!$C:$AA,14,0)-'TRADE IN'!$F212)) -> 12899 | Q212: =IF(VLOOKUP($C212,REV!$C:$AA,15,0)-'TRADE IN'!$F223=0,"",(VLOOKUP($C212,REV!$C:$AA,15,0)-'TRADE IN'!$F212)) -> 12099 | R212: =IF(VLOOKUP($C212,REV!$C:$AA,16,0)-'TRADE IN'!$F223=0,"",(VLOOKUP($C212,REV!$C:$AA,16,0)-'TRADE IN'!$F212)) -> 12999 | S212: =IF(VLOOKUP($C212,REV!$C:$AA,17,0)-'TRADE IN'!$F223=0,"",(VLOOKUP($C212,REV!$C:$AA,17,0)-'TRADE IN'!$F212)) -> 12899 | T212: =IF(VLOOKUP($C212,REV!$C:$AA,18,0)-'TRADE IN'!$F223=0,"",(VLOOKUP($C212,REV!$C:$AA,18,0)-'TRADE IN'!$F212)) -> 12099 | U212: =IF(VLOOKUP($C212,REV!$C:$AA,19,0)-'TRADE IN'!$F223=0,"",(VLOOKUP($C212,REV!$C:$AA,19,0)-'TRADE IN'!$F212)) -> 12099 | V212: =IF(VLOOKUP($C212,REV!$C:$AA,20,0)-'TRADE IN'!$F223=0,"",(VLOOKUP($C212,REV!$C:$AA,20,0)-'TRADE IN'!$F212)) -> 12099 | W212: =IF(VLOOKUP($C212,REV!$C:$AA,21,0)-'TRADE IN'!$F223=0,"",(VLOOKUP($C212,REV!$C:$AA,21,0)-'TRADE IN'!$F212)) -> 11999 | X212: =IF(VLOOKUP($C212,REV!$C:$AA,22,0)-'TRADE IN'!$F223=0,"",(VLOOKUP($C212,REV!$C:$AA,22,0)-'TRADE IN'!$F212)) -> 11999 | Y212: =IF(VLOOKUP($C212,REV!$C:$AA,23,0)-'TRADE IN'!$F223=0,"",(VLOOKUP($C212,REV!$C:$AA,23,0)-'TRADE IN'!$F212)) -> 10999 | Z212: =IF(VLOOKUP($C212,REV!$C:$AA,24,0)-'TRADE IN'!$F223=0,"",(VLOOKUP($C212,REV!$C:$AA,24,0)-'TRADE IN'!$F212)) -> 10999 | AA212: =IF(VLOOKUP($C212,REV!$C:$AA,25,0)-'TRADE IN'!$F223=0,"",(VLOOKUP($C212,REV!$C:$AA,25,0)-'TRADE IN'!$F212)) -> 10899 | AW212: =IF(REV!AW212=0,"",REV!AW212) -> 31.03.2026 | AX212: 5G
A213: Price Oferta | B213: 21X | C213: 4017522 | D213: APPLE IPHONE 17 PRO MAX 512GB | E213: APPLE IPHONE 17 PRO MAX 512GB-PRATEADO | J213: =IF(VLOOKUP($C213,REV!$C:$AA,8,0)-'TRADE IN'!$F213=0,"",(VLOOKUP($C213,REV!$C:$AA,8,0)-'TRADE IN'!$F213)) -> 13099 | K213: =IF(VLOOKUP($C213,REV!$C:$AA,9,0)-'TRADE IN'!$F213=0,"",(VLOOKUP($C213,REV!$C:$AA,9,0)-'TRADE IN'!$F213)) -> 13099 | L213: =IF(VLOOKUP($C213,REV!$C:$AA,10,0)-'TRADE IN'!$F224=0,"",(VLOOKUP($C213,REV!$C:$AA,10,0)-'TRADE IN'!$F213)) -> 13099 | M213: =IF(VLOOKUP($C213,REV!$C:$AA,11,0)-'TRADE IN'!$F224=0,"",(VLOOKUP($C213,REV!$C:$AA,11,0)-'TRADE IN'!$F213)) -> 13099 | N213: =IF(VLOOKUP($C213,REV!$C:$AA,12,0)-'TRADE IN'!$F224=0,"",(VLOOKUP($C213,REV!$C:$AA,12,0)-'TRADE IN'!$F213)) -> 13099 | O213: =IF(VLOOKUP($C213,REV!$C:$AA,13,0)-'TRADE IN'!$F224=0,"",(VLOOKUP($C213,REV!$C:$AA,13,0)-'TRADE IN'!$F213)) -> 12999 | P213: =IF(VLOOKUP($C213,REV!$C:$AA,14,0)-'TRADE IN'!$F224=0,"",(VLOOKUP($C213,REV!$C:$AA,14,0)-'TRADE IN'!$F213)) -> 12899 | Q213: =IF(VLOOKUP($C213,REV!$C:$AA,15,0)-'TRADE IN'!$F224=0,"",(VLOOKUP($C213,REV!$C:$AA,15,0)-'TRADE IN'!$F213)) -> 12099 | R213: =IF(VLOOKUP($C213,REV!$C:$AA,16,0)-'TRADE IN'!$F224=0,"",(VLOOKUP($C213,REV!$C:$AA,16,0)-'TRADE IN'!$F213)) -> 12999 | S213: =IF(VLOOKUP($C213,REV!$C:$AA,17,0)-'TRADE IN'!$F224=0,"",(VLOOKUP($C213,REV!$C:$AA,17,0)-'TRADE IN'!$F213)) -> 12899 | T213: =IF(VLOOKUP($C213,REV!$C:$AA,18,0)-'TRADE IN'!$F224=0,"",(VLOOKUP($C213,REV!$C:$AA,18,0)-'TRADE IN'!$F213)) -> 12099 | U213: =IF(VLOOKUP($C213,REV!$C:$AA,19,0)-'TRADE IN'!$F224=0,"",(VLOOKUP($C213,REV!$C:$AA,19,0)-'TRADE IN'!$F213)) -> 12099 | V213: =IF(VLOOKUP($C213,REV!$C:$AA,20,0)-'TRADE IN'!$F224=0,"",(VLOOKUP($C213,REV!$C:$AA,20,0)-'TRADE IN'!$F213)) -> 12099 | W213: =IF(VLOOKUP($C213,REV!$C:$AA,21,0)-'TRADE IN'!$F224=0,"",(VLOOKUP($C213,REV!$C:$AA,21,0)-'TRADE IN'!$F213)) -> 11999 | X213: =IF(VLOOKUP($C213,REV!$C:$AA,22,0)-'TRADE IN'!$F224=0,"",(VLOOKUP($C213,REV!$C:$AA,22,0)-'TRADE IN'!$F213)) -> 11999 | Y213: =IF(VLOOKUP($C213,REV!$C:$AA,23,0)-'TRADE IN'!$F224=0,"",(VLOOKUP($C213,REV!$C:$AA,23,0)-'TRADE IN'!$F213)) -> 10999 | Z213: =IF(VLOOKUP($C213,REV!$C:$AA,24,0)-'TRADE IN'!$F224=0,"",(VLOOKUP($C213,REV!$C:$AA,24,0)-'TRADE IN'!$F213)) -> 10999 | AA213: =IF(VLOOKUP($C213,REV!$C:$AA,25,0)-'TRADE IN'!$F224=0,"",(VLOOKUP($C213,REV!$C:$AA,25,0)-'TRADE IN'!$F213)) -> 10899 | AW213: =IF(REV!AW213=0,"",REV!AW213) -> 31.03.2026 | AX213: 5G
A214: Price Oferta | B214: 21X | C214: 4017020 | D214: JOVI V50 512GB | E214: JOVI V50 512GB-VERMELHO | J214: =IF(VLOOKUP($C214,REV!$C:$AA,8,0)-'TRADE IN'!$F214=0,"",(VLOOKUP($C214,REV!$C:$AA,8,0)-'TRADE IN'!$F214)) -> 3299 | K214: =IF(VLOOKUP($C214,REV!$C:$AA,9,0)-'TRADE IN'!$F214=0,"",(VLOOKUP($C214,REV!$C:$AA,9,0)-'TRADE IN'!$F214)) -> 3299 | L214: =IF(VLOOKUP($C214,REV!$C:$AA,10,0)-'TRADE IN'!$F225=0,"",(VLOOKUP($C214,REV!$C:$AA,10,0)-'TRADE IN'!$F214)) -> 3299 | M214: =IF(VLOOKUP($C214,REV!$C:$AA,11,0)-'TRADE IN'!$F225=0,"",(VLOOKUP($C214,REV!$C:$AA,11,0)-'TRADE IN'!$F214)) -> 3299 | N214: =IF(VLOOKUP($C214,REV!$C:$AA,12,0)-'TRADE IN'!$F225=0,"",(VLOOKUP($C214,REV!$C:$AA,12,0)-'TRADE IN'!$F214)) -> 3299 | O214: =IF(VLOOKUP($C214,REV!$C:$AA,13,0)-'TRADE IN'!$F225=0,"",(VLOOKUP($C214,REV!$C:$AA,13,0)-'TRADE IN'!$F214)) -> 3249 | P214: =IF(VLOOKUP($C214,REV!$C:$AA,14,0)-'TRADE IN'!$F225=0,"",(VLOOKUP($C214,REV!$C:$AA,14,0)-'TRADE IN'!$F214)) -> 3199 | Q214: =IF(VLOOKUP($C214,REV!$C:$AA,15,0)-'TRADE IN'!$F225=0,"",(VLOOKUP($C214,REV!$C:$AA,15,0)-'TRADE IN'!$F214)) -> 2499 | R214: =IF(VLOOKUP($C214,REV!$C:$AA,16,0)-'TRADE IN'!$F225=0,"",(VLOOKUP($C214,REV!$C:$AA,16,0)-'TRADE IN'!$F214)) -> 3249 | S214: =IF(VLOOKUP($C214,REV!$C:$AA,17,0)-'TRADE IN'!$F225=0,"",(VLOOKUP($C214,REV!$C:$AA,17,0)-'TRADE IN'!$F214)) -> 3199 | T214: =IF(VLOOKUP($C214,REV!$C:$AA,18,0)-'TRADE IN'!$F225=0,"",(VLOOKUP($C214,REV!$C:$AA,18,0)-'TRADE IN'!$F214)) -> 2499 | U214: =IF(VLOOKUP($C214,REV!$C:$AA,19,0)-'TRADE IN'!$F225=0,"",(VLOOKUP($C214,REV!$C:$AA,19,0)-'TRADE IN'!$F214)) -> 2499 | V214: =IF(VLOOKUP($C214,REV!$C:$AA,20,0)-'TRADE IN'!$F225=0,"",(VLOOKUP($C214,REV!$C:$AA,20,0)-'TRADE IN'!$F214)) -> 2499 | W214: =IF(VLOOKUP($C214,REV!$C:$AA,21,0)-'TRADE IN'!$F225=0,"",(VLOOKUP($C214,REV!$C:$AA,21,0)-'TRADE IN'!$F214)) -> 2499 | X214: =IF(VLOOKUP($C214,REV!$C:$AA,22,0)-'TRADE IN'!$F225=0,"",(VLOOKUP($C214,REV!$C:$AA,22,0)-'TRADE IN'!$F214)) -> 2399 | Y214: =IF(VLOOKUP($C214,REV!$C:$AA,23,0)-'TRADE IN'!$F225=0,"",(VLOOKUP($C214,REV!$C:$AA,23,0)-'TRADE IN'!$F214)) -> 1799 | Z214: =IF(VLOOKUP($C214,REV!$C:$AA,24,0)-'TRADE IN'!$F225=0,"",(VLOOKUP($C214,REV!$C:$AA,24,0)-'TRADE IN'!$F214)) -> 1799 | AA214: =IF(VLOOKUP($C214,REV!$C:$AA,25,0)-'TRADE IN'!$F225=0,"",(VLOOKUP($C214,REV!$C:$AA,25,0)-'TRADE IN'!$F214)) -> 1799 | AW214: =IF(REV!AW214=0,"",REV!AW214) -> 31.03.2026 | AX214: 5G
A215: Price Oferta | B215: 21X | C215: 4017022 | D215: JOVI V50 512GB | E215: JOVI V50 512GB-PRETO | J215: =IF(VLOOKUP($C215,REV!$C:$AA,8,0)-'TRADE IN'!$F215=0,"",(VLOOKUP($C215,REV!$C:$AA,8,0)-'TRADE IN'!$F215)) -> 3299 | K215: =IF(VLOOKUP($C215,REV!$C:$AA,9,0)-'TRADE IN'!$F215=0,"",(VLOOKUP($C215,REV!$C:$AA,9,0)-'TRADE IN'!$F215)) -> 3299 | L215: =IF(VLOOKUP($C215,REV!$C:$AA,10,0)-'TRADE IN'!$F226=0,"",(VLOOKUP($C215,REV!$C:$AA,10,0)-'TRADE IN'!$F215)) -> 3299 | M215: =IF(VLOOKUP($C215,REV!$C:$AA,11,0)-'TRADE IN'!$F226=0,"",(VLOOKUP($C215,REV!$C:$AA,11,0)-'TRADE IN'!$F215)) -> 3299 | N215: =IF(VLOOKUP($C215,REV!$C:$AA,12,0)-'TRADE IN'!$F226=0,"",(VLOOKUP($C215,REV!$C:$AA,12,0)-'TRADE IN'!$F215)) -> 3299 | O215: =IF(VLOOKUP($C215,REV!$C:$AA,13,0)-'TRADE IN'!$F226=0,"",(VLOOKUP($C215,REV!$C:$AA,13,0)-'TRADE IN'!$F215)) -> 3249 | P215: =IF(VLOOKUP($C215,REV!$C:$AA,14,0)-'TRADE IN'!$F226=0,"",(VLOOKUP($C215,REV!$C:$AA,14,0)-'TRADE IN'!$F215)) -> 3199 | Q215: =IF(VLOOKUP($C215,REV!$C:$AA,15,0)-'TRADE IN'!$F226=0,"",(VLOOKUP($C215,REV!$C:$AA,15,0)-'TRADE IN'!$F215)) -> 2499 | R215: =IF(VLOOKUP($C215,REV!$C:$AA,16,0)-'TRADE IN'!$F226=0,"",(VLOOKUP($C215,REV!$C:$AA,16,0)-'TRADE IN'!$F215)) -> 3249 | S215: =IF(VLOOKUP($C215,REV!$C:$AA,17,0)-'TRADE IN'!$F226=0,"",(VLOOKUP($C215,REV!$C:$AA,17,0)-'TRADE IN'!$F215)) -> 3199 | T215: =IF(VLOOKUP($C215,REV!$C:$AA,18,0)-'TRADE IN'!$F226=0,"",(VLOOKUP($C215,REV!$C:$AA,18,0)-'TRADE IN'!$F215)) -> 2499 | U215: =IF(VLOOKUP($C215,REV!$C:$AA,19,0)-'TRADE IN'!$F226=0,"",(VLOOKUP($C215,REV!$C:$AA,19,0)-'TRADE IN'!$F215)) -> 2499 | V215: =IF(VLOOKUP($C215,REV!$C:$AA,20,0)-'TRADE IN'!$F226=0,"",(VLOOKUP($C215,REV!$C:$AA,20,0)-'TRADE IN'!$F215)) -> 2499 | W215: =IF(VLOOKUP($C215,REV!$C:$AA,21,0)-'TRADE IN'!$F226=0,"",(VLOOKUP($C215,REV!$C:$AA,21,0)-'TRADE IN'!$F215)) -> 2499 | X215: =IF(VLOOKUP($C215,REV!$C:$AA,22,0)-'TRADE IN'!$F226=0,"",(VLOOKUP($C215,REV!$C:$AA,22,0)-'TRADE IN'!$F215)) -> 2399 | Y215: =IF(VLOOKUP($C215,REV!$C:$AA,23,0)-'TRADE IN'!$F226=0,"",(VLOOKUP($C215,REV!$C:$AA,23,0)-'TRADE IN'!$F215)) -> 1799 | Z215: =IF(VLOOKUP($C215,REV!$C:$AA,24,0)-'TRADE IN'!$F226=0,"",(VLOOKUP($C215,REV!$C:$AA,24,0)-'TRADE IN'!$F215)) -> 1799 | AA215: =IF(VLOOKUP($C215,REV!$C:$AA,25,0)-'TRADE IN'!$F226=0,"",(VLOOKUP($C215,REV!$C:$AA,25,0)-'TRADE IN'!$F215)) -> 1799 | AW215: =IF(REV!AW215=0,"",REV!AW215) -> 31.03.2026 | AX215: 5G
A216: Price Oferta | B216: 21X | C216: 4017045 | D216: JOVI V50 LITE 256GB | E216: JOVI V50 LITE 256GB-OURO | J216: =IF(VLOOKUP($C216,REV!$C:$AA,8,0)-'TRADE IN'!$F216=0,"",(VLOOKUP($C216,REV!$C:$AA,8,0)-'TRADE IN'!$F216)) -> 1799 | K216: =IF(VLOOKUP($C216,REV!$C:$AA,9,0)-'TRADE IN'!$F216=0,"",(VLOOKUP($C216,REV!$C:$AA,9,0)-'TRADE IN'!$F216)) -> 1799 | L216: =IF(VLOOKUP($C216,REV!$C:$AA,10,0)-'TRADE IN'!$F227=0,"",(VLOOKUP($C216,REV!$C:$AA,10,0)-'TRADE IN'!$F216)) -> 1799 | M216: =IF(VLOOKUP($C216,REV!$C:$AA,11,0)-'TRADE IN'!$F227=0,"",(VLOOKUP($C216,REV!$C:$AA,11,0)-'TRADE IN'!$F216)) -> 1799 | N216: =IF(VLOOKUP($C216,REV!$C:$AA,12,0)-'TRADE IN'!$F227=0,"",(VLOOKUP($C216,REV!$C:$AA,12,0)-'TRADE IN'!$F216)) -> 1799 | O216: =IF(VLOOKUP($C216,REV!$C:$AA,13,0)-'TRADE IN'!$F227=0,"",(VLOOKUP($C216,REV!$C:$AA,13,0)-'TRADE IN'!$F216)) -> 1699 | P216: =IF(VLOOKUP($C216,REV!$C:$AA,14,0)-'TRADE IN'!$F227=0,"",(VLOOKUP($C216,REV!$C:$AA,14,0)-'TRADE IN'!$F216)) -> 1599 | Q216: =IF(VLOOKUP($C216,REV!$C:$AA,15,0)-'TRADE IN'!$F227=0,"",(VLOOKUP($C216,REV!$C:$AA,15,0)-'TRADE IN'!$F216)) -> 999 | R216: =IF(VLOOKUP($C216,REV!$C:$AA,16,0)-'TRADE IN'!$F227=0,"",(VLOOKUP($C216,REV!$C:$AA,16,0)-'TRADE IN'!$F216)) -> 1699 | S216: =IF(VLOOKUP($C216,REV!$C:$AA,17,0)-'TRADE IN'!$F227=0,"",(VLOOKUP($C216,REV!$C:$AA,17,0)-'TRADE IN'!$F216)) -> 1599 | T216: =IF(VLOOKUP($C216,REV!$C:$AA,18,0)-'TRADE IN'!$F227=0,"",(VLOOKUP($C216,REV!$C:$AA,18,0)-'TRADE IN'!$F216)) -> 999 | U216: =IF(VLOOKUP($C216,REV!$C:$AA,19,0)-'TRADE IN'!$F227=0,"",(VLOOKUP($C216,REV!$C:$AA,19,0)-'TRADE IN'!$F216)) -> 999 | V216: =IF(VLOOKUP($C216,REV!$C:$AA,20,0)-'TRADE IN'!$F227=0,"",(VLOOKUP($C216,REV!$C:$AA,20,0)-'TRADE IN'!$F216)) -> 999 | W216: =IF(VLOOKUP($C216,REV!$C:$AA,21,0)-'TRADE IN'!$F227=0,"",(VLOOKUP($C216,REV!$C:$AA,21,0)-'TRADE IN'!$F216)) -> 999 | X216: =IF(VLOOKUP($C216,REV!$C:$AA,22,0)-'TRADE IN'!$F227=0,"",(VLOOKUP($C216,REV!$C:$AA,22,0)-'TRADE IN'!$F216)) -> 999 | Y216: =IF(VLOOKUP($C216,REV!$C:$AA,23,0)-'TRADE IN'!$F227=0,"",(VLOOKUP($C216,REV!$C:$AA,23,0)-'TRADE IN'!$F216)) -> 799 | Z216: =IF(VLOOKUP($C216,REV!$C:$AA,24,0)-'TRADE IN'!$F227=0,"",(VLOOKUP($C216,REV!$C:$AA,24,0)-'TRADE IN'!$F216)) -> 799 | AA216: =IF(VLOOKUP($C216,REV!$C:$AA,25,0)-'TRADE IN'!$F227=0,"",(VLOOKUP($C216,REV!$C:$AA,25,0)-'TRADE IN'!$F216)) -> 799 | AW216: =IF(REV!AW216=0,"",REV!AW216) -> 31.03.2026 | AX216: 5G
A217: Price Oferta | B217: 21X | C217: 4017047 | D217: JOVI V50 LITE 256GB | E217: JOVI V50 LITE 256GB-PRETO | J217: =IF(VLOOKUP($C217,REV!$C:$AA,8,0)-'TRADE IN'!$F217=0,"",(VLOOKUP($C217,REV!$C:$AA,8,0)-'TRADE IN'!$F217)) -> 1799 | K217: =IF(VLOOKUP($C217,REV!$C:$AA,9,0)-'TRADE IN'!$F217=0,"",(VLOOKUP($C217,REV!$C:$AA,9,0)-'TRADE IN'!$F217)) -> 1799 | L217: =IF(VLOOKUP($C217,REV!$C:$AA,10,0)-'TRADE IN'!$F228=0,"",(VLOOKUP($C217,REV!$C:$AA,10,0)-'TRADE IN'!$F217)) -> 1799 | M217: =IF(VLOOKUP($C217,REV!$C:$AA,11,0)-'TRADE IN'!$F228=0,"",(VLOOKUP($C217,REV!$C:$AA,11,0)-'TRADE IN'!$F217)) -> 1799 | N217: =IF(VLOOKUP($C217,REV!$C:$AA,12,0)-'TRADE IN'!$F228=0,"",(VLOOKUP($C217,REV!$C:$AA,12,0)-'TRADE IN'!$F217)) -> 1799 | O217: =IF(VLOOKUP($C217,REV!$C:$AA,13,0)-'TRADE IN'!$F228=0,"",(VLOOKUP($C217,REV!$C:$AA,13,0)-'TRADE IN'!$F217)) -> 1699 | P217: =IF(VLOOKUP($C217,REV!$C:$AA,14,0)-'TRADE IN'!$F228=0,"",(VLOOKUP($C217,REV!$C:$AA,14,0)-'TRADE IN'!$F217)) -> 1599 | Q217: =IF(VLOOKUP($C217,REV!$C:$AA,15,0)-'TRADE IN'!$F228=0,"",(VLOOKUP($C217,REV!$C:$AA,15,0)-'TRADE IN'!$F217)) -> 999 | R217: =IF(VLOOKUP($C217,REV!$C:$AA,16,0)-'TRADE IN'!$F228=0,"",(VLOOKUP($C217,REV!$C:$AA,16,0)-'TRADE IN'!$F217)) -> 1699 | S217: =IF(VLOOKUP($C217,REV!$C:$AA,17,0)-'TRADE IN'!$F228=0,"",(VLOOKUP($C217,REV!$C:$AA,17,0)-'TRADE IN'!$F217)) -> 1599 | T217: =IF(VLOOKUP($C217,REV!$C:$AA,18,0)-'TRADE IN'!$F228=0,"",(VLOOKUP($C217,REV!$C:$AA,18,0)-'TRADE IN'!$F217)) -> 999 | U217: =IF(VLOOKUP($C217,REV!$C:$AA,19,0)-'TRADE IN'!$F228=0,"",(VLOOKUP($C217,REV!$C:$AA,19,0)-'TRADE IN'!$F217)) -> 999 | V217: =IF(VLOOKUP($C217,REV!$C:$AA,20,0)-'TRADE IN'!$F228=0,"",(VLOOKUP($C217,REV!$C:$AA,20,0)-'TRADE IN'!$F217)) -> 999 | W217: =IF(VLOOKUP($C217,REV!$C:$AA,21,0)-'TRADE IN'!$F228=0,"",(VLOOKUP($C217,REV!$C:$AA,21,0)-'TRADE IN'!$F217)) -> 999 | X217: =IF(VLOOKUP($C217,REV!$C:$AA,22,0)-'TRADE IN'!$F228=0,"",(VLOOKUP($C217,REV!$C:$AA,22,0)-'TRADE IN'!$F217)) -> 999 | Y217: =IF(VLOOKUP($C217,REV!$C:$AA,23,0)-'TRADE IN'!$F228=0,"",(VLOOKUP($C217,REV!$C:$AA,23,0)-'TRADE IN'!$F217)) -> 799 | Z217: =IF(VLOOKUP($C217,REV!$C:$AA,24,0)-'TRADE IN'!$F228=0,"",(VLOOKUP($C217,REV!$C:$AA,24,0)-'TRADE IN'!$F217)) -> 799 | AA217: =IF(VLOOKUP($C217,REV!$C:$AA,25,0)-'TRADE IN'!$F228=0,"",(VLOOKUP($C217,REV!$C:$AA,25,0)-'TRADE IN'!$F217)) -> 799 | AW217: =IF(REV!AW217=0,"",REV!AW217) -> 31.03.2026 | AX217: 5G
A218: Price Oferta | B218: 21X | C218: 4017758 | D218: JOVI V70 5G 512GB | E218: JOVI V70 5G 512GB-AZUL SAFIRA | J218: =IF(VLOOKUP($C218,REV!$C:$AA,8,0)-'TRADE IN'!$F218=0,"",(VLOOKUP($C218,REV!$C:$AA,8,0)-'TRADE IN'!$F218)) -> 2999 | K218: =IF(VLOOKUP($C218,REV!$C:$AA,9,0)-'TRADE IN'!$F218=0,"",(VLOOKUP($C218,REV!$C:$AA,9,0)-'TRADE IN'!$F218)) -> 2999 | L218: =IF(VLOOKUP($C218,REV!$C:$AA,10,0)-'TRADE IN'!$F229=0,"",(VLOOKUP($C218,REV!$C:$AA,10,0)-'TRADE IN'!$F218)) -> 2999 | M218: =IF(VLOOKUP($C218,REV!$C:$AA,11,0)-'TRADE IN'!$F229=0,"",(VLOOKUP($C218,REV!$C:$AA,11,0)-'TRADE IN'!$F218)) -> 2999 | N218: =IF(VLOOKUP($C218,REV!$C:$AA,12,0)-'TRADE IN'!$F229=0,"",(VLOOKUP($C218,REV!$C:$AA,12,0)-'TRADE IN'!$F218)) -> 2999 | O218: =IF(VLOOKUP($C218,REV!$C:$AA,13,0)-'TRADE IN'!$F229=0,"",(VLOOKUP($C218,REV!$C:$AA,13,0)-'TRADE IN'!$F218)) -> 2899 | P218: =IF(VLOOKUP($C218,REV!$C:$AA,14,0)-'TRADE IN'!$F229=0,"",(VLOOKUP($C218,REV!$C:$AA,14,0)-'TRADE IN'!$F218)) -> 2799 | Q218: =IF(VLOOKUP($C218,REV!$C:$AA,15,0)-'TRADE IN'!$F229=0,"",(VLOOKUP($C218,REV!$C:$AA,15,0)-'TRADE IN'!$F218)) -> 2499 | R218: =IF(VLOOKUP($C218,REV!$C:$AA,16,0)-'TRADE IN'!$F229=0,"",(VLOOKUP($C218,REV!$C:$AA,16,0)-'TRADE IN'!$F218)) -> 2899 | S218: =IF(VLOOKUP($C218,REV!$C:$AA,17,0)-'TRADE IN'!$F229=0,"",(VLOOKUP($C218,REV!$C:$AA,17,0)-'TRADE IN'!$F218)) -> 2799 | T218: =IF(VLOOKUP($C218,REV!$C:$AA,18,0)-'TRADE IN'!$F229=0,"",(VLOOKUP($C218,REV!$C:$AA,18,0)-'TRADE IN'!$F218)) -> 2499 | U218: =IF(VLOOKUP($C218,REV!$C:$AA,19,0)-'TRADE IN'!$F229=0,"",(VLOOKUP($C218,REV!$C:$AA,19,0)-'TRADE IN'!$F218)) -> 2499 | V218: =IF(VLOOKUP($C218,REV!$C:$AA,20,0)-'TRADE IN'!$F229=0,"",(VLOOKUP($C218,REV!$C:$AA,20,0)-'TRADE IN'!$F218)) -> 2499 | W218: =IF(VLOOKUP($C218,REV!$C:$AA,21,0)-'TRADE IN'!$F229=0,"",(VLOOKUP($C218,REV!$C:$AA,21,0)-'TRADE IN'!$F218)) -> 2499 | X218: =IF(VLOOKUP($C218,REV!$C:$AA,22,0)-'TRADE IN'!$F229=0,"",(VLOOKUP($C218,REV!$C:$AA,22,0)-'TRADE IN'!$F218)) -> 2399 | Y218: =IF(VLOOKUP($C218,REV!$C:$AA,23,0)-'TRADE IN'!$F229=0,"",(VLOOKUP($C218,REV!$C:$AA,23,0)-'TRADE IN'!$F218)) -> 1999 | Z218: =IF(VLOOKUP($C218,REV!$C:$AA,24,0)-'TRADE IN'!$F229=0,"",(VLOOKUP($C218,REV!$C:$AA,24,0)-'TRADE IN'!$F218)) -> 1999 | AA218: =IF(VLOOKUP($C218,REV!$C:$AA,25,0)-'TRADE IN'!$F229=0,"",(VLOOKUP($C218,REV!$C:$AA,25,0)-'TRADE IN'!$F218)) -> 1999 | AW218: =IF(REV!AW218=0,"",REV!AW218) -> 31.03.2026 | AX218: 5G
A219: Price Oferta | B219: 21X | C219: 4017773 | D219: JOVI V70 5G 512GB | E219: JOVI V70 5G 512GB-LILAS BOREAL | J219: =IF(VLOOKUP($C219,REV!$C:$AA,8,0)-'TRADE IN'!$F219=0,"",(VLOOKUP($C219,REV!$C:$AA,8,0)-'TRADE IN'!$F219)) -> 2999 | K219: =IF(VLOOKUP($C219,REV!$C:$AA,9,0)-'TRADE IN'!$F219=0,"",(VLOOKUP($C219,REV!$C:$AA,9,0)-'TRADE IN'!$F219)) -> 2999 | L219: =IF(VLOOKUP($C219,REV!$C:$AA,10,0)-'TRADE IN'!$F230=0,"",(VLOOKUP($C219,REV!$C:$AA,10,0)-'TRADE IN'!$F219)) -> 2999 | M219: =IF(VLOOKUP($C219,REV!$C:$AA,11,0)-'TRADE IN'!$F230=0,"",(VLOOKUP($C219,REV!$C:$AA,11,0)-'TRADE IN'!$F219)) -> 2999 | N219: =IF(VLOOKUP($C219,REV!$C:$AA,12,0)-'TRADE IN'!$F230=0,"",(VLOOKUP($C219,REV!$C:$AA,12,0)-'TRADE IN'!$F219)) -> 2999 | O219: =IF(VLOOKUP($C219,REV!$C:$AA,13,0)-'TRADE IN'!$F230=0,"",(VLOOKUP($C219,REV!$C:$AA,13,0)-'TRADE IN'!$F219)) -> 2899 | P219: =IF(VLOOKUP($C219,REV!$C:$AA,14,0)-'TRADE IN'!$F230=0,"",(VLOOKUP($C219,REV!$C:$AA,14,0)-'TRADE IN'!$F219)) -> 2799 | Q219: =IF(VLOOKUP($C219,REV!$C:$AA,15,0)-'TRADE IN'!$F230=0,"",(VLOOKUP($C219,REV!$C:$AA,15,0)-'TRADE IN'!$F219)) -> 2499 | R219: =IF(VLOOKUP($C219,REV!$C:$AA,16,0)-'TRADE IN'!$F230=0,"",(VLOOKUP($C219,REV!$C:$AA,16,0)-'TRADE IN'!$F219)) -> 2899 | S219: =IF(VLOOKUP($C219,REV!$C:$AA,17,0)-'TRADE IN'!$F230=0,"",(VLOOKUP($C219,REV!$C:$AA,17,0)-'TRADE IN'!$F219)) -> 2799 | T219: =IF(VLOOKUP($C219,REV!$C:$AA,18,0)-'TRADE IN'!$F230=0,"",(VLOOKUP($C219,REV!$C:$AA,18,0)-'TRADE IN'!$F219)) -> 2499 | U219: =IF(VLOOKUP($C219,REV!$C:$AA,19,0)-'TRADE IN'!$F230=0,"",(VLOOKUP($C219,REV!$C:$AA,19,0)-'TRADE IN'!$F219)) -> 2499 | V219: =IF(VLOOKUP($C219,REV!$C:$AA,20,0)-'TRADE IN'!$F230=0,"",(VLOOKUP($C219,REV!$C:$AA,20,0)-'TRADE IN'!$F219)) -> 2499 | W219: =IF(VLOOKUP($C219,REV!$C:$AA,21,0)-'TRADE IN'!$F230=0,"",(VLOOKUP($C219,REV!$C:$AA,21,0)-'TRADE IN'!$F219)) -> 2499 | X219: =IF(VLOOKUP($C219,REV!$C:$AA,22,0)-'TRADE IN'!$F230=0,"",(VLOOKUP($C219,REV!$C:$AA,22,0)-'TRADE IN'!$F219)) -> 2399 | Y219: =IF(VLOOKUP($C219,REV!$C:$AA,23,0)-'TRADE IN'!$F230=0,"",(VLOOKUP($C219,REV!$C:$AA,23,0)-'TRADE IN'!$F219)) -> 1999 | Z219: =IF(VLOOKUP($C219,REV!$C:$AA,24,0)-'TRADE IN'!$F230=0,"",(VLOOKUP($C219,REV!$C:$AA,24,0)-'TRADE IN'!$F219)) -> 1999 | AA219: =IF(VLOOKUP($C219,REV!$C:$AA,25,0)-'TRADE IN'!$F230=0,"",(VLOOKUP($C219,REV!$C:$AA,25,0)-'TRADE IN'!$F219)) -> 1999 | AW219: =IF(REV!AW219=0,"",REV!AW219) -> 31.03.2026 | AX219: 5G
A220: ADM | B220: 21X | C220: 4017200 | D220: JOVI Y29S 5G 256GB | E220: JOVI Y29S 5G 256GB-PRETO | J220: =IF(VLOOKUP($C220,REV!$C:$AA,8,0)-'TRADE IN'!$F220=0,"",(VLOOKUP($C220,REV!$C:$AA,8,0)-'TRADE IN'!$F220)) -> 1299 | K220: =IF(VLOOKUP($C220,REV!$C:$AA,9,0)-'TRADE IN'!$F220=0,"",(VLOOKUP($C220,REV!$C:$AA,9,0)-'TRADE IN'!$F220)) -> 999 | L220: =IF(VLOOKUP($C220,REV!$C:$AA,10,0)-'TRADE IN'!$F229=0,"",(VLOOKUP($C220,REV!$C:$AA,10,0)-'TRADE IN'!$F220)) -> 999 | M220: =IF(VLOOKUP($C220,REV!$C:$AA,11,0)-'TRADE IN'!$F229=0,"",(VLOOKUP($C220,REV!$C:$AA,11,0)-'TRADE IN'!$F220)) -> 1299 | N220: =IF(VLOOKUP($C220,REV!$C:$AA,12,0)-'TRADE IN'!$F229=0,"",(VLOOKUP($C220,REV!$C:$AA,12,0)-'TRADE IN'!$F220)) -> 999 | O220: =IF(VLOOKUP($C220,REV!$C:$AA,13,0)-'TRADE IN'!$F229=0,"",(VLOOKUP($C220,REV!$C:$AA,13,0)-'TRADE IN'!$F220)) -> 999 | P220: =IF(VLOOKUP($C220,REV!$C:$AA,14,0)-'TRADE IN'!$F229=0,"",(VLOOKUP($C220,REV!$C:$AA,14,0)-'TRADE IN'!$F220)) -> 999 | Q220: =IF(VLOOKUP($C220,REV!$C:$AA,15,0)-'TRADE IN'!$F229=0,"",(VLOOKUP($C220,REV!$C:$AA,15,0)-'TRADE IN'!$F220)) -> 899 | R220: =IF(VLOOKUP($C220,REV!$C:$AA,16,0)-'TRADE IN'!$F229=0,"",(VLOOKUP($C220,REV!$C:$AA,16,0)-'TRADE IN'!$F220)) -> 999 | S220: =IF(VLOOKUP($C220,REV!$C:$AA,17,0)-'TRADE IN'!$F229=0,"",(VLOOKUP($C220,REV!$C:$AA,17,0)-'TRADE IN'!$F220)) -> 999 | T220: =IF(VLOOKUP($C220,REV!$C:$AA,18,0)-'TRADE IN'!$F229=0,"",(VLOOKUP($C220,REV!$C:$AA,18,0)-'TRADE IN'!$F220)) -> 899 | U220: =IF(VLOOKUP($C220,REV!$C:$AA,19,0)-'TRADE IN'!$F229=0,"",(VLOOKUP($C220,REV!$C:$AA,19,0)-'TRADE IN'!$F220)) -> 899 | V220: =IF(VLOOKUP($C220,REV!$C:$AA,20,0)-'TRADE IN'!$F229=0,"",(VLOOKUP($C220,REV!$C:$AA,20,0)-'TRADE IN'!$F220)) -> 899 | W220: =IF(VLOOKUP($C220,REV!$C:$AA,21,0)-'TRADE IN'!$F229=0,"",(VLOOKUP($C220,REV!$C:$AA,21,0)-'TRADE IN'!$F220)) -> 899 | X220: =IF(VLOOKUP($C220,REV!$C:$AA,22,0)-'TRADE IN'!$F229=0,"",(VLOOKUP($C220,REV!$C:$AA,22,0)-'TRADE IN'!$F220)) -> 899 | Y220: =IF(VLOOKUP($C220,REV!$C:$AA,23,0)-'TRADE IN'!$F229=0,"",(VLOOKUP($C220,REV!$C:$AA,23,0)-'TRADE IN'!$F220)) -> 899 | Z220: =IF(VLOOKUP($C220,REV!$C:$AA,24,0)-'TRADE IN'!$F229=0,"",(VLOOKUP($C220,REV!$C:$AA,24,0)-'TRADE IN'!$F220)) -> 899 | AA220: =IF(VLOOKUP($C220,REV!$C:$AA,25,0)-'TRADE IN'!$F229=0,"",(VLOOKUP($C220,REV!$C:$AA,25,0)-'TRADE IN'!$F220)) -> 899 | AW220: =IF(REV!AW220=0,"",REV!AW220) -> 31.03.2026 | AX220: 5G
