Workbook

Sheet REV
A1: OFERTAS VÁLIDAS APENAS PARA PLANOS CONSUMER
B4: Inclusão de Preços
B5: Alteração de Preços
A7: Preços Elegíveis a Price Back
A8: Preços Elegíveis a Price Oferta
A9: CANAL: | B9: REVENDAS
C11: DATA INÍCIO: | D11: 46311 | J11: COM FIDELIZAÇÃO - GROSS / MIGRAÇÃO / UPGRADE / PORTABILIDADE / BASE SEM MOVIMENTAÇÃO | AM11: TIM FIXO | AP11: TIM CASA | AY11: 0.0202 | AZ11: 0.0182 | BA11: 0.0103
A12: Regra Reembolso Pós Fidelizado | B12: CATEGORIA MKT | C12: CÓDIGO | D12: DESCRIÇÃO COMERCIAL | E12: DESCRIÇÃO SAP | F12: PRÉ | G12: PREÇO BASE FATURAMENTO RETAIL | H12: CONTROLE NÃO FIDELIZADO - TODOS (Fatura / Express) | I12: PÓS PAGO NÃO FIDELIZADO - VIDE ABA DE REGRAS | J12: TIM CONTROLE | K12: TIM CONTROLE PLUS | L12: TIM CONTROLE PREMIUM | M12: TIM CONTROLE SMART | N12: TIM CONTROLE REDES SOCIAIS | O12: TIM BLACK | P12: TIM BLACK PLUS | Q12: TIM BLACK PREMIUM | R12: TIM BLACK A (15GB) | S12: TIM BLACK B (20GB) | T12: TIM BLACK C (25GB) | U12: TIM BLACK C ULTRA | V12: TIM BLACK FAMÍLIA | W12: TIM BLACK FAMÍLIA A ONE | X12: TIM BLACK FAMÍLIA PLUS | Y12: TIM BLACK FAMÍLIA PREMIUM | Z12: TIM BLACK FAMÍLIA C ONE | AA12: TIM BLACK FAMÍLIA VIP | AB12: TIM Fibra 400M 24 | AC12: TIM Fibra 500M 24 - 2 | AD12: TIM Fibra 600M 24 - 2 | AE12: TIM Fibra 600M P 24 - 2 | AF12: TIM Fibra 600M M 24 - 2 | AG12: TIM Ultrafibra 800M YT26 | AH12: TIM Fibra 600M GP 25 | AI12: TIM Fibra 1GB 24 | AJ12: TIM Fibra 1GB P 24 | AK12: TIM Fibra 1GB M 24 | AL12: TIM Fibra 2GB 24 | AM12: TIM FIXO LOCAL TOTAL PLUS (Plano Fidelizado) | AN12: TIM FIXO BRASIL TOTAL PLUS (Plano Fidelizado) | AO12: TIM FIXO TOTAL LDI PLUS (Plano Fidelizado) | AP12: TIM LIVE INTERNET 30GB (sem fidelização) | AQ12: TIM LIVE INTERNET 50GB (sem fidelização) | AR12: TIM LIVE INTERNET 80GB (sem fidelização) | AS12: TIM LIVE INTERNET 30GB PLUS | AT12: TIM LIVE INTERNET 50GB PLUS | AU12: TIM LIVE INTERNET 80GB PLUS | AW12: DATA FIM DA OFERTA | AX12: TECNOLOGIA | AY12: Seguro Completo (valor mensal) | AZ12: Roubo e Furto (valor mensal) | BA12: Quebra e danos (valor mensal)
A13: Price Oferta | B13: 21X | C13: 4014380 | D13: APPLE IPHONE 12 64GB | E13: APPLE IPHONE 12 64GB-PRETO NAC | F13: 6499 | G13: 2599 | H13: 999 | I13: 999 | J13: 999 | K13: 999 | L13: 999 | M13: 999 | N13: 999 | O13: 999 | P13: 999 | Q13: 999 | R13: 999 | S13: 999 | T13: 999 | U13: 999 | V13: 999 | W13: 999 | X13: 999 | Y13: 999 | Z13: 999 | AA13: 999 | AW13: 03.11.2026 | AX13: 5G | AY13: =$H13*AY$11 -> 20.1798 | AZ13: =($H13*AZ$11) -> 18.1818 | BA13: =$H13*BA$11 -> 10.2897
A14: Price Oferta | B14: 21X | C14: 4014382 | D14: APPLE IPHONE 12 64GB | E14: APPLE IPHONE 12 64GB-BRANCO NAC | F14: 6499 | G14: 2599 | H14: 999 | I14: 999 | J14: 999 | K14: 999 | L14: 999 | M14: 999 | N14: 999 | O14: 999 | P14: 999 | Q14: 999 | R14: 999 | S14: 999 | T14: 999 | U14: 999 | V14: 999 | W14: 999 | X14: 999 | Y14: 999 | Z14: 999 | AA14: 999 | AW14: 03.11.2026 | AX14: 5G | AY14: =$H14*AY$11 -> 20.1798 | AZ14: =($H14*AZ$11) -> 18.1818 | BA14: =$H14*BA$11 -> 10.2897
A15: Price Oferta | B15: 21X | C15: 4014391 | D15: APPLE IPHONE 12 128GB | E15: APPLE IPHONE 12 128GB-PRETO NAC | F15: 4499 | G15: 2299 | H15: 999 | I15: 999 | J15: 999 | K15: 999 | L15: 999 | M15: 999 | N15: 999 | O15: 999 | P15: 999 | Q15: 999 | R15: 999 | S15: 999 | T15: 999 | U15: 999 | V15: 999 | W15: 999 | X15: 999 | Y15: 999 | Z15: 999 | AA15: 999 | AW15: 03.11.2026 | AX15: 5G | AY15: =$H15*AY$11 -> 20.1798 | AZ15: =($H15*AZ$11) -> 18.1818 | BA15: =$H15*BA$11 -> 10.2897
A16: Price Oferta | B16: 21X | C16: 4014723 | D16: APPLE IPHONE 13 128GB | E16: APPLE IPHONE 13 128GB-PRETO NAC | F16: 6099 | G16: 3199 | H16: 4499 | I16: 4499 | J16: 3599 | K16: 3499 | L16: 3499 | M16: 3599 | N16: 3499 | O16: 3099 | P16: 2999 | Q16: 2499 | R16: 3099 | S16: 2999 | T16: 2499 | U16: 2499 | V16: 2499 | W16: 2499 | X16: 2299 | Y16: 1999 | Z16: 1999 | AA16: 1999 | AW16: 03.11.2026 | AX16: 5G | AY16: =$H16*AY$11 -> 90.8798 | AZ16: =($H16*AZ$11) -> 81.8818 | BA16: =$H16*BA$11 -> 46.3397
A17: Price Oferta | B17: 21X | C17: 4014594 | D17: APPLE IPHONE 13 256GB | E17: APPLE IPHONE 13 256GB-PRETO | F17: 6299 | G17: 2799 | H17: 3899 | I17: 3899 | J17: 3799 | K17: 3799 | L17: 3799 | M17: 3799 | N17: 3799 | O17: 3599 | P17: 3499 | Q17: 2999 | R17: 3599 | S17: 3499 | T17: 2999 | U17: 2999 | V17: 2999 | W17: 2999 | X17: 2799 | Y17: 2499 | Z17: 2499 | AA17: 2499 | AW17: 03.11.2026 | AX17: 5G | AY17: =$H17*AY$11 -> 78.7598 | AZ17: =($H17*AZ$11) -> 70.9618 | BA17: =$H17*BA$11 -> 40.1597
A18: Price Oferta | B18: 21X | C18: 4014837 | D18: APPLE IPHONE 13 256GB | E18: APPLE IPHONE 13 256GB-AZUL NAC | F18: 6299 | G18: 2799 | H18: 3899 | I18: 3899 | J18: 3799 | K18: 3799 | L18: 3799 | M18: 3799 | N18: 3799 | O18: 3599 | P18: 3499 | Q18: 2999 | R18: 3599 | S18: 3499 | T18: 2999 | U18: 2999 | V18: 2999 | W18: 2999 | X18: 2799 | Y18: 2499 | Z18: 2499 | AA18: 2499 | AW18: 03.11.2026 | AX18: 5G | AY18: =$H18*AY$11 -> 78.7598 | AZ18: =($H18*AZ$11) -> 70.9618 | BA18: =$H18*BA$11 -> 40.1597
A19: Price Oferta | B19: 21X | C19: 4014833 | D19: APPLE IPHONE 13 256GB | E19: APPLE IPHONE 13 256GB-PRETO NAC | F19: 6299 | G19: 2799 | H19: 3899 | I19: 3899 | J19: 3799 | K19: 3799 | L19: 3799 | M19: 3799 | N19: 3799 | O19: 3599 | P19: 3499 | Q19: 2999 | R19: 3599 | S19: 3499 | T19: 2999 | U19: 2999 | V19: 2999 | W19: 2999 | X19: 2799 | Y19: 2499 | Z19: 2499 | AA19: 2499 | AW19: 03.11.2026 | AX19: 5G | AY19: =$H19*AY$11 -> 78.7598 | AZ19: =($H19*AZ$11) -> 70.9618 | BA19: =$H19*BA$11 -> 40.1597
A20: Price Oferta | B20: 21X | C20: 4014836 | D20: APPLE IPHONE 13 256GB | E20: APPLE IPHONE 13 256GB-VERMELHO NAC | F20: 6299 | G20: 2799 | H20: 3899 | I20: 3899 | J20: 3799 | K20: 3799 | L20: 3799 | M20: 3799 | N20: 3799 | O20: 3599 | P20: 3499 | Q20: 2999 | R20: 3599 | S20: 3499 | T20: 2999 | U20: 2999 | V20: 2999 | W20: 2999 | X20: 2799 | Y20: 2499 | Z20: 2499 | AA20: 2499 | AW20: 03.11.2026 | AX20: 5G | AY20: =$H20*AY$11 -> 78.7598 | AZ20: =($H20*AZ$11) -> 70.9618 | BA20: =$H20*BA$11 -> 40.1597
A21: Price Oferta | B21: 21X | C21: 4015185 | D21: APPLE IPHONE 14 128GB | E21: APPLE IPHONE 14 128GB-PRETO | F21: 7299 | G21: 3899 | H21: 5299 | I21: 5299 | J21: 4199 | K21: 4199 | L21: 4199 | M21: 4199 | N21: 4199 | O21: 3899 | P21: 3799 | Q21: 3099 | R21: 3899 | S21: 3799 | T21: 3099 | U21: 3099 | V21: 3099 | W21: 3099 | X21: 2999 | Y21: 2499 | Z21: 2499 | AA21: 2499 | AW21: 03.11.2026 | AX21: 5G | AY21: =$H21*AY$11 -> 107.0398 | AZ21: =($H21*AZ$11) -> 96.4418 | BA21: =$H21*BA$11 -> 54.5797
A22: Price Oferta | B22: 21X | C22: 4015262 | D22: APPLE IPHONE 14 128GB | E22: APPLE IPHONE 14 128GB-PRETO NAC | F22: 7299 | G22: 3899 | H22: 5299 | I22: 5299 | J22: 4199 | K22: 4199 | L22: 4199 | M22: 4199 | N22: 4199 | O22: 3899 | P22: 3799 | Q22: 3099 | R22: 3899 | S22: 3799 | T22: 3099 | U22: 3099 | V22: 3099 | W22: 3099 | X22: 2999 | Y22: 2499 | Z22: 2499 | AA22: 2499 | AW22: 03.11.2026 | AX22: 5G | AY22: =$H22*AY$11 -> 107.0398 | AZ22: =($H22*AZ$11) -> 96.4418 | BA22: =$H22*BA$11 -> 54.5797
A23: Price Oferta | B23: 21X | C23: 4015180 | D23: APPLE IPHONE 14 256GB | E23: APPLE IPHONE 14 256GB-BRANCO | F23: 7799 | G23: 2899 | H23: 4399 | I23: 4399 | J23: 4399 | K23: 4399 | L23: 4399 | M23: 4399 | N23: 4399 | O23: 4299 | P23: 4199 | Q23: 3499 | R23: 4299 | S23: 4199 | T23: 3499 | U23: 3499 | V23: 3499 | W23: 3499 | X23: 3399 | Y23: 2499 | Z23: 2499 | AA23: 2449 | AB23: 4399 | AC23: 4399 | AD23: 4399 | AE23: 4199 | AF23: 4199 | AG23: 4199 | AH23: 4199 | AI23: 3499 | AJ23: 3499 | AK23: 3499 | AL23: 2499 | AW23: 03.11.2026 | AX23: 5G | AY23: =$H23*AY$11 -> 88.8598 | AZ23: =($H23*AZ$11) -> 80.0618 | BA23: =$H23*BA$11 -> 45.3097
A24: Price Oferta | B24: 21X | C24: 4015186 | D24: APPLE IPHONE 14 256GB | E24: APPLE IPHONE 14 256GB-PRETO | F24: 7799 | G24: 2899 | H24: 4399 | I24: 4399 | J24: 4399 | K24: 4399 | L24: 4399 | M24: 4399 | N24: 4399 | O24: 4299 | P24: 4199 | Q24: 3499 | R24: 4299 | S24: 4199 | T24: 3499 | U24: 3499 | V24: 3499 | W24: 3499 | X24: 3399 | Y24: 2499 | Z24: 2499 | AA24: 2449 | AB24: 4399 | AC24: 4399 | AD24: 4399 | AE24: 4199 | AF24: 4199 | AG24: 4199 | AH24: 4199 | AI24: 3499 | AJ24: 3499 | AK24: 3499 | AL24: 2499 | AW24: 03.11.2026 | AX24: 5G | AY24: =$H24*AY$11 -> 88.8598 | AZ24: =($H24*AZ$11) -> 80.0618 | BA24: =$H24*BA$11 -> 45.3097
A25: Price Oferta | B25: 21X | C25: 4015267 | D25: APPLE IPHONE 14 256GB | E25: APPLE IPHONE 14 256GB-PRETO NAC | F25: 7799 | G25: 2899 | H25: 4399 | I25: 4399 | J25: 4399 | K25: 4399 | L25: 4399 | M25: 4399 | N25: 4399 | O25: 4299 | P25: 4199 | Q25: 3499 | R25: 4299 | S25: 4199 | T25: 3499 | U25: 3499 | V25: 3499 | W25: 3499 | X25: 3399 | Y25: 2499 | Z25: 2499 | AA25: 2449 | AB25: 4399 | AC25: 4399 | AD25: 4399 | AE25: 4199 | AF25: 4199 | AG25: 4199 | AH25: 4199 | AI25: 3499 | AJ25: 3499 | AK25: 3499 | AL25: 2499 | AW25: 03.11.2026 | AX25: 5G | AY25: =$H25*AY$11 -> 88.8598 | AZ25: =($H25*AZ$11) -> 80.0618 | BA25: =$H25*BA$11 -> 45.3097
A26: Price Oferta | B26: 21X | C26: 4015268 | D26: APPLE IPHONE 14 256GB | E26: APPLE IPHONE 14 256GB-BRANCO NAC | F26: 7799 | G26: 2899 | H26: 4399 | I26: 4399 | J26: 4399 | K26: 4399 | L26: 4399 | M26: 4399 | N26: 4399 | O26: 4299 | P26: 4199 | Q26: 3499 | R26: 4299 | S26: 4199 | T26: 3499 | U26: 3499 | V26: 3499 | W26: 3499 | X26: 3399 | Y26: 2499 | Z26: 2499 | AA26: 2449 | AB26: 4399 | AC26: 4399 | AD26: 4399 | AE26: 4199 | AF26: 4199 | AG26: 4199 | AH26: 4199 | AI26: 3499 | AJ26: 3499 | AK26: 3499 | AL26: 2499 | AW26: 03.11.2026 | AX26: 5G | AY26: =$H26*AY$11 -> 88.8598 | AZ26: =($H26*AZ$11) -> 80.0618 | BA26: =$H26*BA$11 -> 45.3097
A27: Price Oferta | B27: 21X | C27: 4015179 | D27: APPLE IPHONE 14 PLUS 256GB | E27: APPLE IPHONE 14 PLUS 256GB-BRANCO | F27: 7299 | G27: 3899 | H27: 4599 | I27: 4599 | J27: 4499 | K27: 4499 | L27: 4499 | M27: 4499 | N27: 4499 | O27: 4399 | P27: 4299 | Q27: 3499 | R27: 4399 | S27: 4299 | T27: 3499 | U27: 3499 | V27: 3499 | W27: 3499 | X27: 3399 | Y27: 2899 | Z27: 2899 | AA27: 2899 | AW27: 03.11.2026 | AX27: 5G | AY27: =$H27*AY$11 -> 92.8998 | AZ27: =($H27*AZ$11) -> 83.7018 | BA27: =$H27*BA$11 -> 47.3697
A28: Price Oferta | B28: 21X | C28: 4015187 | D28: APPLE IPHONE 14 PLUS 256GB | E28: APPLE IPHONE 14 PLUS 256GB-PRETO | F28: 7299 | G28: 3899 | H28: 4599 | I28: 4599 | J28: 4499 | K28: 4499 | L28: 4499 | M28: 4499 | N28: 4499 | O28: 4399 | P28: 4299 | Q28: 3499 | R28: 4399 | S28: 4299 | T28: 3499 | U28: 3499 | V28: 3499 | W28: 3499 | X28: 3399 | Y28: 2899 | Z28: 2899 | AA28: 2899 | AW28: 03.11.2026 | AX28: 5G | AY28: =$H28*AY$11 -> 92.8998 | AZ28: =($H28*AZ$11) -> 83.7018 | BA28: =$H28*BA$11 -> 47.3697
A29: Price Oferta | B29: 21X | C29: 4015711 | D29: APPLE IPHONE 14 PLUS 256GB | E29: APPLE IPHONE 14 PLUS 256GB-PRETO NAC | F29: 7299 | G29: 3899 | H29: 4599 | I29: 4599 | J29: 4499 | K29: 4499 | L29: 4499 | M29: 4499 | N29: 4499 | O29: 4399 | P29: 4299 | Q29: 3499 | R29: 4399 | S29: 4299 | T29: 3499 | U29: 3499 | V29: 3499 | W29: 3499 | X29: 3399 | Y29: 2899 | Z29: 2899 | AA29: 2899 | AW29: 03.11.2026 | AX29: 5G | AY29: =$H29*AY$11 -> 92.8998 | AZ29: =($H29*AZ$11) -> 83.7018 | BA29: =$H29*BA$11 -> 47.3697
A30: Price Oferta | B30: 21X | C30: 4015162 | D30: APPLE IPHONE 14 PRO MAX 256GB | E30: APPLE IPHONE 14 PRO MAX 256GB-GRAFITE | F30: 11499 | G30: 6899 | H30: 7999 | I30: 7999 | J30: 6399 | K30: 6399 | L30: 6399 | M30: 6399 | N30: 6399 | O30: 6299 | P30: 6199 | Q30: 5999 | R30: 6299 | S30: 6199 | T30: 5999 | U30: 5999 | V30: 5999 | W30: 5999 | X30: 5899 | Y30: 5499 | Z30: 5499 | AA30: 5499 | AW30: 03.11.2026 | AX30: 5G | AY30: =$H30*AY$11 -> 161.5798 | AZ30: =($H30*AZ$11) -> 145.5818 | BA30: =$H30*BA$11 -> 82.3897
A31: Price Oferta | B31: 21X | C31: 4015112 | D31: APPLE IPHONE 14 PRO 256GB | E31: APPLE IPHONE 14 PRO 256GB-GRAFITE | F31: 10499 | G31: 5899 | H31: 6999 | I31: 6999 | J31: 5899 | K31: 5899 | L31: 5899 | M31: 5899 | N31: 5899 | O31: 5799 | P31: 5699 | Q31: 5499 | R31: 5799 | S31: 5699 | T31: 5499 | U31: 5499 | V31: 5499 | W31: 5499 | X31: 5399 | Y31: 4999 | Z31: 4999 | AA31: 4999 | AW31: 03.11.2026 | AX31: 5G | AY31: =$H31*AY$11 -> 141.3798 | AZ31: =($H31*AZ$11) -> 127.3818 | BA31: =$H31*BA$11 -> 72.0897
A32: Price Oferta | B32: 21X | C32: 4015116 | D32: APPLE IPHONE 14 PRO 256GB | E32: APPLE IPHONE 14 PRO 256GB-DOURADO | F32: 10499 | G32: 5899 | H32: 6999 | I32: 6999 | J32: 5899 | K32: 5899 | L32: 5899 | M32: 5899 | N32: 5899 | O32: 5799 | P32: 5699 | Q32: 5499 | R32: 5799 | S32: 5699 | T32: 5499 | U32: 5499 | V32: 5499 | W32: 5499 | X32: 5399 | Y32: 4999 | Z32: 4999 | AA32: 4999 | AW32: 03.11.2026 | AX32: 5G | AY32: =$H32*AY$11 -> 141.3798 | AZ32: =($H32*AZ$11) -> 127.3818 | BA32: =$H32*BA$11 -> 72.0897
A33: Price Oferta | B33: 21X | C33: 4015742 | D33: APPLE IPHONE 15 128GB | E33: APPLE IPHONE 15 128GB-PRETO | F33: 7299 | G33: 5399 | H33: 5699 | I33: 5699 | J33: 4999 | K33: 4899 | L33: 4899 | M33: 4999 | N33: 4899 | O33: 4799 | P33: 4699 | Q33: 4499 | R33: 4799 | S33: 4699 | T33: 4499 | U33: 4399 | V33: 4399 | W33: 4299 | X33: 4199 | Y33: 3499 | Z33: 3499 | AA33: 3499 | AW33: 03.11.2026 | AX33: 5G | AY33: =$H33*AY$11 -> 115.1198 | AZ33: =($H33*AZ$11) -> 103.7218 | BA33: =$H33*BA$11 -> 58.6997
A34: Price Oferta | B34: 21X | C34: 4015725 | D34: APPLE IPHONE 15 128GB | E34: APPLE IPHONE 15 128GB-ROSA | F34: 7299 | G34: 5399 | H34: 5699 | I34: 5699 | J34: 4999 | K34: 4899 | L34: 4899 | M34: 4999 | N34: 4899 | O34: 4799 | P34: 4699 | Q34: 4499 | R34: 4799 | S34: 4699 | T34: 4499 | U34: 4399 | V34: 4399 | W34: 4299 | X34: 4199 | Y34: 3499 | Z34: 3499 | AA34: 3499 | AW34: 03.11.2026 | AX34: 5G | AY34: =$H34*AY$11 -> 115.1198 | AZ34: =($H34*AZ$11) -> 103.7218 | BA34: =$H34*BA$11 -> 58.6997
A35: Price Oferta | B35: 21X | C35: 4015794 | D35: APPLE IPHONE 15 128GB | E35: APPLE IPHONE 15 128GB-VERDE | F35: 7299 | G35: 5399 | H35: 5699 | I35: 5699 | J35: 4999 | K35: 4899 | L35: 4899 | M35: 4999 | N35: 4899 | O35: 4799 | P35: 4699 | Q35: 4499 | R35: 4799 | S35: 4699 | T35: 4499 | U35: 4399 | V35: 4399 | W35: 4299 | X35: 4199 | Y35: 3499 | Z35: 3499 | AA35: 3499 | AW35: 03.11.2026 | AX35: 5G | AY35: =$H35*AY$11 -> 115.1198 | AZ35: =($H35*AZ$11) -> 103.7218 | BA35: =$H35*BA$11 -> 58.6997
A36: Price Oferta | B36: 21X | C36: 4015808 | D36: APPLE IPHONE 15 128GB | E36: APPLE IPHONE 15 128GB-AMARELO | F36: 7299 | G36: 5399 | H36: 5699 | I36: 5699 | J36: 4999 | K36: 4899 | L36: 4899 | M36: 4999 | N36: 4899 | O36: 4799 | P36: 4699 | Q36: 4499 | R36: 4799 | S36: 4699 | T36: 4499 | U36: 4399 | V36: 4399 | W36: 4299 | X36: 4199 | Y36: 3499 | Z36: 3499 | AA36: 3499 | AW36: 03.11.2026 | AX36: 5G | AY36: =$H36*AY$11 -> 115.1198 | AZ36: =($H36*AZ$11) -> 103.7218 | BA36: =$H36*BA$11 -> 58.6997
A37: Price Oferta | B37: 21X | C37: 4015743 | D37: APPLE IPHONE 15 256GB | E37: APPLE IPHONE 15 256GB-PRETO | F37: 8099 | G37: 3899 | H37: 5199 | I37: 5199 | J37: 5099 | K37: 5099 | L37: 5099 | M37: 5099 | N37: 5099 | O37: 4999 | P37: 4899 | Q37: 3999 | R37: 4999 | S37: 4899 | T37: 3999 | U37: 3999 | V37: 3999 | W37: 3999 | X37: 3899 | Y37: 3699 | Z37: 3699 | AA37: 3649 | AW37: 03.11.2026 | AX37: 5G | AY37: =$H37*AY$11 -> 105.0198 | AZ37: =($H37*AZ$11) -> 94.6218 | BA37: =$H37*BA$11 -> 53.5497
A38: Price Oferta | B38: 21X | C38: 4015770 | D38: APPLE IPHONE 15 256GB | E38: APPLE IPHONE 15 256GB-AZUL | F38: 8099 | G38: 3899 | H38: 5199 | I38: 5199 | J38: 5099 | K38: 5099 | L38: 5099 | M38: 5099 | N38: 5099 | O38: 4999 | P38: 4899 | Q38: 3999 | R38: 4999 | S38: 4899 | T38: 3999 | U38: 3999 | V38: 3999 | W38: 3999 | X38: 3899 | Y38: 3699 | Z38: 3699 | AA38: 3649 | AW38: 03.11.2026 | AX38: 5G | AY38: =$H38*AY$11 -> 105.0198 | AZ38: =($H38*AZ$11) -> 94.6218 | BA38: =$H38*BA$11 -> 53.5497
... A85: Price Oferta | B85: 21X | C85: 4016609 | D85: APPLE IPHONE 16 PRO MAX 512GB | E85: APPLE IPHONE 16 PRO MAX 512GB-TITANIO | F85: 13999 | G85: 10799 | H85: 12099 | I85: 12099 | J85: 11999 | K85: 11999 | L85: 11999 | M85: 11999 | N85: 11999 | O85: 11699 | P85: 11599 | Q85: 10999 | R85: 11699 | S85: 11599 | T85: 10999 | U85: 10999 | V85: 10999 | W85: 10999 | X85: 10799 | Y85: 10299 | Z85: 10299 | AA85: 10299 | AW85: 03.11.2026 | AX85: 5G | AY85: =$H85*AY$11 -> 244.3998 | AZ85: =($H85*AZ$11) -> 220.2018 | BA85: =$H85*BA$11 -> 124.6197
A86: Price Oferta | B86: 21X | C86: 4016916 | D86: APPLE IPHONE 16E 256GB | E86: APPLE IPHONE 16E 256GB-PRETO NAC | F86: 6599 | G86: 2299 | H86: 4799 | I86: 4799 | J86: 4799 | K86: 4799 | L86: 4799 | M86: 4799 | N86: 4799 | O86: 4699 | P86: 4599 | Q86: 3599 | R86: 4699 | S86: 4599 | T86: 3599 | U86: 3599 | V86: 3599 | W86: 3599 | X86: 3499 | Y86: 2799 | Z86: 2799 | AA86: 2749 | AB86: 4799 | AC86: 4799 | AD86: 4799 | AE86: 4699 | AF86: 4599 | AG86: 4599 | AH86: 3599 | AI86: 3599 | AJ86: 3599 | AK86: 3599 | AL86: 2799 | AW86: 03.11.2026 | AX86: 5G | AY86: =$H86*AY$11 -> 96.9398 | AZ86: =($H86*AZ$11) -> 87.3418 | BA86: =$H86*BA$11 -> 49.4297
A87: Price Oferta | B87: 21X | C87: 4016917 | D87: APPLE IPHONE 16E 256GB | E87: APPLE IPHONE 16E 256GB-BRANCO NAC | F87: 6599 | G87: 2299 | H87: 4799 | I87: 4799 | J87: 4799 | K87: 4799 | L87: 4799 | M87: 4799 | N87: 4799 | O87: 4699 | P87: 4599 | Q87: 3599 | R87: 4699 | S87: 4599 | T87: 3599 | U87: 3599 | V87: 3599 | W87: 3599 | X87: 3499 | Y87: 2799 | Z87: 2799 | AA87: 2749 | AB87: 4799 | AC87: 4799 | AD87: 4799 | AE87: 4699 | AF87: 4599 | AG87: 4599 | AH87: 3599 | AI87: 3599 | AJ87: 3599 | AK87: 3599 | AL87: 2799 | AW87: 03.11.2026 | AX87: 5G | AY87: =$H87*AY$11 -> 96.9398 | AZ87: =($H87*AZ$11) -> 87.3418 | BA87: =$H87*BA$11 -> 49.4297
A88: Price Oferta | B88: 21X | C88: 4017449 | D88: APPLE IPHONE 17 256GB | E88: APPLE IPHONE 17 256GB-LAVANDA | F88: 7999 | G88: 5399 | H88: 6499 | I88: 6499 | J88: 6399 | K88: 6399 | L88: 6399 | M88: 6399 | N88: 6399 | O88: 6299 | P88: 6199 | Q88: 5499 | R88: 6299 | S88: 6199 | T88: 5499 | U88: 5499 | V88: 5499 | W88: 5499 | X88: 5399 | Y88: 4999 | Z88: 4999 | AA88: 4949 | AB88: 6399 | AC88: 6399 | AD88: 6399 | AE88: 6299 | AF88: 6199 | AG88: 6199 | AH88: 5499 | AI88: 5499 | AJ88: 5499 | AK88: 5499 | AL88: 4999 | AW88: 03.11.2026 | AX88: 5G | AY88: =$H88*AY$11 -> 131.2798 | AZ88: =($H88*AZ$11) -> 118.2818 | BA88: =$H88*BA$11 -> 66.9397
A89: Price Oferta | B89: 21X | C89: 4017897 | D89: APPLE IPHONE 17 256GB | E89: APPLE IPHONE 17 256GB-LAVANDA NAC | F89: 7999 | G89: 5399 | H89: 6499 | I89: 6499 | J89: 6399 | K89: 6399 | L89: 6399 | M89: 6399 | N89: 6399 | O89: 6299 | P89: 6199 | Q89: 5499 | R89: 6299 | S89: 6199 | T89: 5499 | U89: 5499 | V89: 5499 | W89: 5499 | X89: 5399 | Y89: 4999 | Z89: 4999 | AA89: 4949 | AB89: 6399 | AC89: 6399 | AD89: 6399 | AE89: 6299 | AF89: 6199 | AG89: 6199 | AH89: 5499 | AI89: 5499 | AJ89: 5499 | AK89: 5499 | AL89: 4999 | AW89: 03.11.2026 | AX89: 5G | AY89: =$H89*AY$11 -> 131.2798 | AZ89: =($H89*AZ$11) -> 118.2818 | BA89: =$H89*BA$11 -> 66.9397
A90: Price Oferta | B90: 21X | C90: 4017480 | D90: APPLE IPHONE 17 256GB | E90: APPLE IPHONE 17 256GB-AZUL NEVOA | F90: 7999 | G90: 5399 | H90: 6499 | I90: 6499 | J90: 6399 | K90: 6399 | L90: 6399 | M90: 6399 | N90: 6399 | O90: 6299 | P90: 6199 | Q90: 5499 | R90: 6299 | S90: 6199 | T90: 5499 | U90: 5499 | V90: 5499 | W90: 5499 | X90: 5399 | Y90: 4999 | Z90: 4999 | AA90: 4949 | AB90: 6399 | AC90: 6399 | AD90: 6399 | AE90: 6299 | AF90: 6199 | AG90: 6199 | AH90: 5499 | AI90: 5499 | AJ90: 5499 | AK90: 5499 | AL90: 4999 | AW90: 03.11.2026 | AX90: 5G | AY90: =$H90*AY$11 -> 131.2798 | AZ90: =($H90*AZ$11) -> 118.2818 | BA90: =$H90*BA$11 -> 66.9397
A91: Price Oferta | B91: 21X | C91: 4017894 | D91: APPLE IPHONE 17 256GB | E91: APPLE IPHONE 17 256GB-AZUL NEVOA NAC | F91: 7999 | G91: 5399 | H91: 6499 | I91: 6499 | J91: 6399 | K91: 6399 | L91: 6399 | M91: 6399 | N91: 6399 | O91: 6299 | P91: 6199 | Q91: 5499 | R91: 6299 | S91: 6199 | T91: 5499 | U91: 5499 | V91: 5499 | W91: 5499 | X91: 5399 | Y91: 4999 | Z91: 4999 | AA91: 4949 | AB91: 6399 | AC91: 6399 | AD91: 6399 | AE91: 6299 | AF91: 6199 | AG91: 6199 | AH91: 5499 | AI91: 5499 | AJ91: 5499 | AK91: 5499 | AL91: 4999 | AW91: 03.11.2026 | AX91: 5G | AY91: =$H91*AY$11 -> 131.2798 | AZ91: =($H91*AZ$11) -> 118.2818 | BA91: =$H91*BA$11 -> 66.9397
A92: Price Oferta | B92: 21X | C92: 4017485 | D92: APPLE IPHONE 17 256GB | E92: APPLE IPHONE 17 256GB-PRETO | F92: 7999 | G92: 5399 | H92: 6499 | I92: 6499 | J92: 6399 | K92: 6399 | L92: 6399 | M92: 6399 | N92: 6399 | O92: 6299 | P92: 6199 | Q92: 5499 | R92: 6299 | S92: 6199 | T92: 5499 | U92: 5499 | V92: 5499 | W92: 5499 | X92: 5399 | Y92: 4999 | Z92: 4999 | AA92: 4949 | AB92: 6399 | AC92: 6399 | AD92: 6399 | AE92: 6299 | AF92: 6199 | AG92: 6199 | AH92: 5499 | AI92: 5499 | AJ92: 5499 | AK92: 5499 | AL92: 4999 | AW92: 03.11.2026 | AX92: 5G | AY92: =$H92*AY$11 -> 131.2798 | AZ92: =($H92*AZ$11) -> 118.2818 | BA92: =$H92*BA$11 -> 66.9397
A93: Price Oferta | B93: 21X | C93: 4017890 | D93: APPLE IPHONE 17 256GB | E93: APPLE IPHONE 17 256GB-PRETO NAC | F93: 7999 | G93: 5399 | H93: 6499 | I93: 6499 | J93: 6399 | K93: 6399 | L93: 6399 | M93: 6399 | N93: 6399 | O93: 6299 | P93: 6199 | Q93: 5499 | R93: 6299 | S93: 6199 | T93: 5499 | U93: 5499 | V93: 5499 | W93: 5499 | X93: 5399 | Y93: 4999 | Z93: 4999 | AA93: 4949 | AB93: 6399 | AC93: 6399 | AD93: 6399 | AE93: 6299 | AF93: 6199 | AG93: 6199 | AH93: 5499 | AI93: 5499 | AJ93: 5499 | AK93: 5499 | AL93: 4999 | AW93: 03.11.2026 | AX93: 5G | AY93: =$H93*AY$11 -> 131.2798 | AZ93: =($H93*AZ$11) -> 118.2818 | BA93: =$H93*BA$11 -> 66.9397
A94: Price Oferta | B94: 21X | C94: 4017486 | D94: APPLE IPHONE 17 256GB | E94: APPLE IPHONE 17 256GB-BRANCO | F94: 7999 | G94: 5399 | H94: 6499 | I94: 6499 | J94: 6399 | K94: 6399 | L94: 6399 | M94: 6399 | N94: 6399 | O94: 6299 | P94: 6199 | Q94: 5499 | R94: 6299 | S94: 6199 | T94: 5499 | U94: 5499 | V94: 5499 | W94: 5499 | X94: 5399 | Y94: 4999 | Z94: 4999 | AA94: 4949 | AB94: 6399 | AC94: 6399 | AD94: 6399 | AE94: 6299 | AF94: 6199 | AG94: 6199 | AH94: 5499 | AI94: 5499 | AJ94: 5499 | AK94: 5499 | AL94: 4999 | AW94: 03.11.2026 | AX94: 5G | AY94: =$H94*AY$11 -> 131.2798 | AZ94: =($H94*AZ$11) -> 118.2818 | BA94: =$H94*BA$11 -> 66.9397
A95: Price Oferta | B95: 21X | C95: 4017892 | D95: APPLE IPHONE 17 256GB | E95: APPLE IPHONE 17 256GB-BRANCO NAC | F95: 7999 | G95: 5399 | H95: 6499 | I95: 6499 | J95: 6399 | K95: 6399 | L95: 6399 | M95: 6399 | N95: 6399 | O95: 6299 | P95: 6199 | Q95: 5499 | R95: 6299 | S95: 6199 | T95: 5499 | U95: 5499 | V95: 5499 | W95: 5499 | X95: 5399 | Y95: 4999 | Z95: 4999 | AA95: 4949 | AB95: 6399 | AC95: 6399 | AD95: 6399 | AE95: 6299 | AF95: 6199 | AG95: 6199 | AH95: 5499 | AI95: 5499 | AJ95: 5499 | AK95: 5499 | AL95: 4999 | AW95: 03.11.2026 | AX95: 5G | AY95: =$H95*AY$11 -> 131.2798 | AZ95: =($H95*AZ$11) -> 118.2818 | BA95: =$H95*BA$11 -> 66.9397
A96: Price Oferta | B96: 21X | C96: 4017483 | D96: APPLE IPHONE 17 256GB | E96: APPLE IPHONE 17 256GB-SALVIA | F96: 7999 | G96: 5399 | H96: 6499 | I96: 6499 | J96: 6399 | K96: 6399 | L96: 6399 | M96: 6399 | N96: 6399 | O96: 6299 | P96: 6199 | Q96: 5499 | R96: 6299 | S96: 6199 | T96: 5499 | U96: 5499 | V96: 5499 | W96: 5499 | X96: 5399 | Y96: 4999 | Z96: 4999 | AA96: 4949 | AB96: 6399 | AC96: 6399 | AD96: 6399 | AE96: 6299 | AF96: 6199 | AG96: 6199 | AH96: 5499 | AI96: 5499 | AJ96: 5499 | AK96: 5499 | AL96: 4999 | AW96: 03.11.2026 | AX96: 5G | AY96: =$H96*AY$11 -> 131.2798 | AZ96: =($H96*AZ$11) -> 118.2818 | BA96: =$H96*BA$11 -> 66.9397
A97: Price Oferta | B97: 21X | C97: 4017899 | D97: APPLE IPHONE 17 256GB | E97: APPLE IPHONE 17 256GB-SALVIA NAC | F97: 7999 | G97: 5399 | H97: 6499 | I97: 6499 | J97: 6399 | K97: 6399 | L97: 6399 | M97: 6399 | N97: 6399 | O97: 6299 | P97: 6199 | Q97: 5499 | R97: 6299 | S97: 6199 | T97: 5499 | U97: 5499 | V97: 5499 | W97: 5499 | X97: 5399 | Y97: 4999 | Z97: 4999 | AA97: 4949 | AB97: 6399 | AC97: 6399 | AD97: 6399 | AE97: 6299 | AF97: 6199 | AG97: 6199 | AH97: 5499 | AI97: 5499 | AJ97: 5499 | AK97: 5499 | AL97: 4999 | AW97: 03.11.2026 | AX97: 5G | AY97: =$H97*AY$11 -> 131.2798 | AZ97: =($H97*AZ$11) -> 118.2818 | BA97: =$H97*BA$11 -> 66.9397
A98: Price Oferta | B98: 21X | C98: 4017484 | D98: APPLE IPHONE 17 512GB | E98: APPLE IPHONE 17 512GB-BRANCO | F98: 9499 | G98: 7699 | H98: 8199 | I98: 8199 | J98: 8099 | K98: 8099 | L98: 8099 | M98: 8099 | N98: 8099 | O98: 7999 | P98: 7899 | Q98: 7799 | R98: 7999 | S98: 7899 | T98: 7799 | U98: 7799 | V98: 7799 | W98: 7799 | X98: 7699 | Y98: 7499 | Z98: 7499 | AA98: 7499 | AW98: 03.11.2026 | AX98: 5G | AY98: =$H98*AY$11 -> 165.6198 | AZ98: =($H98*AZ$11) -> 149.2218 | BA98: =$H98*BA$11 -> 84.4497
A99: Price Oferta | B99: 21X | C99: 4017506 | D99: APPLE IPHONE 17 512GB | E99: APPLE IPHONE 17 512GB-PRETO | F99: 9499 | G99: 7699 | H99: 8199 | I99: 8199 | J99: 8099 | K99: 8099 | L99: 8099 | M99: 8099 | N99: 8099 | O99: 7999 | P99: 7899 | Q99: 7799 | R99: 7999 | S99: 7899 | T99: 7799 | U99: 7799 | V99: 7799 | W99: 7799 | X99: 7699 | Y99: 7499 | Z99: 7499 | AA99: 7499 | AW99: 03.11.2026 | AX99: 5G | AY99: =$H99*AY$11 -> 165.6198 | AZ99: =($H99*AZ$11) -> 149.2218 | BA99: =$H99*BA$11 -> 84.4497
A100: Price Oferta | B100: 21X | C100: 4017497 | D100: APPLE IPHONE AIR 256GB | E100: APPLE IPHONE AIR 256GB-PRETO | F100: 10499 | G100: 7299 | H100: 7799 | I100: 7799 | J100: 7699 | K100: 7699 | L100: 7699 | M100: 7699 | N100: 7699 | O100: 7599 | P100: 7499 | Q100: 7399 | R100: 7599 | S100: 7499 | T100: 7399 | U100: 7399 | V100: 7399 | W100: 7399 | X100: 7299 | Y100: 6499 | Z100: 6499 | AA100: 5499 | AW100: 03.11.2026 | AX100: 5G | AY100: =$H100*AY$11 -> 157.5398 | AZ100: =($H100*AZ$11) -> 141.9418 | BA100: =$H100*BA$11 -> 80.3297
A101: Price Oferta | B101: 21X | C101: 4017498 | D101: APPLE IPHONE AIR 256GB | E101: APPLE IPHONE AIR 256GB-BRANCO | F101: 10499 | G101: 7299 | H101: 7799 | I101: 7799 | J101: 7699 | K101: 7699 | L101: 7699 | M101: 7699 | N101: 7699 | O101: 7599 | P101: 7499 | Q101: 7399 | R101: 7599 | S101: 7499 | T101: 7399 | U101: 7399 | V101: 7399 | W101: 7399 | X101: 7299 | Y101: 6499 | Z101: 6499 | AA101: 5499 | AW101: 03.11.2026 | AX101: 5G | AY101: =$H101*AY$11 -> 157.5398 | AZ101: =($H101*AZ$11) -> 141.9418 | BA101: =$H101*BA$11 -> 80.3297
A102: Price Oferta | B102: 21X | C102: 4017499 | D102: APPLE IPHONE AIR 256GB | E102: APPLE IPHONE AIR 256GB-AZUL CEU | F102: 10499 | G102: 7299 | H102: 7799 | I102: 7799 | J102: 7699 | K102: 7699 | L102: 7699 | M102: 7699 | N102: 7699 | O102: 7599 | P102: 7499 | Q102: 7399 | R102: 7599 | S102: 7499 | T102: 7399 | U102: 7399 | V102: 7399 | W102: 7399 | X102: 7299 | Y102: 6499 | Z102: 6499 | AA102: 5499 | AW102: 03.11.2026 | AX102: 5G | AY102: =$H102*AY$11 -> 157.5398 | AZ102: =($H102*AZ$11) -> 141.9418 | BA102: =$H102*BA$11 -> 80.3297
A103: Price Oferta | B103: 21X | C103: 4017521 | D103: APPLE IPHONE AIR 256GB | E103: APPLE IPHONE AIR 256GB-DOURADO | F103: 10499 | G103: 7299 | H103: 7799 | I103: 7799 | J103: 7699 | K103: 7699 | L103: 7699 | M103: 7699 | N103: 7699 | O103: 7599 | P103: 7499 | Q103: 7399 | R103: 7599 | S103: 7499 | T103: 7399 | U103: 7399 | V103: 7399 | W103: 7399 | X103: 7299 | Y103: 6499 | Z103: 6499 | AA103: 5499 | AW103: 03.11.2026 | AX103: 5G | AY103: =$H103*AY$11 -> 157.5398 | AZ103: =($H103*AZ$11) -> 141.9418 | BA103: =$H103*BA$11 -> 80.3297
A104: Price Oferta | B104: 21X | C104: 4017496 | D104: APPLE IPHONE AIR 512GB | E104: APPLE IPHONE AIR 512GB-BRANCO | F104: 11999 | G104: 8399 | H104: 9099 | I104: 9099 | J104: 8999 | K104: 8999 | L104: 8999 | M104: 8999 | N104: 8999 | O104: 8899 | P104: 8799 | Q104: 8499 | R104: 8899 | S104: 8799 | T104: 8499 | U104: 8499 | V104: 8499 | W104: 8499 | X104: 8399 | Y104: 7799 | Z104: 7799 | AA104: 6799 | AW104: 03.11.2026 | AX104: 5G | AY104: =$H104*AY$11 -> 183.7998 | AZ104: =($H104*AZ$11) -> 165.6018 | BA104: =$H104*BA$11 -> 93.7197
A105: Price Oferta | B105: 21X | C105: 4017519 | D105: APPLE IPHONE AIR 512GB | E105: APPLE IPHONE AIR 512GB-DOURADO | F105: 11999 | G105: 8399 | H105: 9099 | I105: 9099 | J105: 8999 | K105: 8999 | L105: 8999 | M105: 8999 | N105: 8999 | O105: 8899 | P105: 8799 | Q105: 8499 | R105: 8899 | S105: 8799 | T105: 8499 | U105: 8499 | V105: 8499 | W105: 8499 | X105: 8399 | Y105: 7799 | Z105: 7799 | AA105: 6799 | AW105: 03.11.2026 | AX105: 5G | AY105: =$H105*AY$11 -> 183.7998 | AZ105: =($H105*AZ$11) -> 165.6018 | BA105: =$H105*BA$11 -> 93.7197
A106: Price Oferta | B106: 21X | C106: 4017525 | D106: APPLE IPHONE AIR 512GB | E106: APPLE IPHONE AIR 512GB-PRETO | F106: 11999 | G106: 8399 | H106: 9099 | I106: 9099 | J106: 8999 | K106: 8999 | L106: 8999 | M106: 8999 | N106: 8999 | O106: 8899 | P106: 8799 | Q106: 8499 | R106: 8899 | S106: 8799 | T106: 8499 | U106: 8499 | V106: 8499 | W106: 8499 | X106: 8399 | Y106: 7799 | Z106: 7799 | AA106: 6799 | AW106: 03.11.2026 | AX106: 5G | AY106: =$H106*AY$11 -> 183.7998 | AZ106: =($H106*AZ$11) -> 165.6018 | BA106: =$H106*BA$11 -> 93.7197
A107: Price Oferta | B107: 21X | C107: 4017518 | D107: APPLE IPHONE AIR 512GB | E107: APPLE IPHONE AIR 512GB-AZUL CEU | F107: 11999 | G107: 8399 | H107: 9099 | I107: 9099 | J107: 8999 | K107: 8999 | L107: 8999 | M107: 8999 | N107: 8999 | O107: 8899 | P107: 8799 | Q107: 8499 | R107: 8899 | S107: 8799 | T107: 8499 | U107: 8499 | V107: 8499 | W107: 8499 | X107: 8399 | Y107: 7799 | Z107: 7799 | AA107: 6799 | AW107: 03.11.2026 | AX107: 5G | AY107: =$H107*AY$11 -> 183.7998 | AZ107: =($H107*AZ$11) -> 165.6018 | BA107: =$H107*BA$11 -> 93.7197
A108: Price Oferta | B108: 21X | C108: 4017487 | D108: APPLE IPHONE 17 PRO 256GB | E108: APPLE IPHONE 17 PRO 256GB-AZUL INTENSO | F108: 11499 | G108: 8799 | H108: 10799 | I108: 10799 | J108: 10799 | K108: 10799 | L108: 10799 | M108: 10799 | N108: 10799 | O108: 10699 | P108: 10599 | Q108: 9799 | R108: 10699 | S108: 10599 | T108: 9799 | U108: 9799 | V108: 9799 | W108: 9699 | X108: 9699 | Y108: 8799 | Z108: 8799 | AA108: 8799 | AW108: 03.11.2026 | AX108: 5G | AY108: =$H108*AY$11 -> 218.1398 | AZ108: =($H108*AZ$11) -> 196.5418 | BA108: =$H108*BA$11 -> 111.2297
A109: Price Oferta | B109: 21X | C109: 4017510 | D109: APPLE IPHONE 17 PRO 256GB | E109: APPLE IPHONE 17 PRO 256GB-LARANJA COSMIC | F109: 11499 | G109: 8799 | H109: 10799 | I109: 10799 | J109: 10799 | K109: 10799 | L109: 10799 | M109: 10799 | N109: 10799 | O109: 10699 | P109: 10599 | Q109: 9799 | R109: 10699 | S109: 10599 | T109: 9799 | U109: 9799 | V109: 9799 | W109: 9699 | X109: 9699 | Y109: 8799 | Z109: 8799 | AA109: 8799 | AW109: 03.11.2026 | AX109: 5G | AY109: =$H109*AY$11 -> 218.1398 | AZ109: =($H109*AZ$11) -> 196.5418 | BA109: =$H109*BA$11 -> 111.2297
... A119: Price Oferta | B119: 21X | C119: 4017522 | D119: APPLE IPHONE 17 PRO MAX 512GB | E119: APPLE IPHONE 17 PRO MAX 512GB-PRATEADO | F119: 13999 | G119: 10999 | H119: 13099 | I119: 13099 | J119: 13099 | K119: 13099 | L119: 13099 | M119: 13099 | N119: 13099 | O119: 12999 | P119: 12899 | Q119: 12099 | R119: 12999 | S119: 12899 | T119: 12099 | U119: 12099 | V119: 12099 | W119: 11999 | X119: 11999 | Y119: 10999 | Z119: 10999 | AA119: 10899 | AW119: 03.11.2026 | AX119: 5G | AY119: =$H119*AY$11 -> 264.5998 | AZ119: =($H119*AZ$11) -> 238.4018 | BA119: =$H119*BA$11 -> 134.9197
A120: Price Oferta | B120: 21X | C120: 4017845 | D120: APPLE IPHONE 17E 256GB | E120: APPLE IPHONE 17E 256GB-BRANCO | F120: 5799 | G120: 3099 | H120: 5199 | I120: 5199 | J120: 5099 | K120: 5099 | L120: 5099 | M120: 5099 | N120: 5099 | O120: 4999 | P120: 4899 | Q120: 4499 | R120: 4999 | S120: 4899 | T120: 4499 | U120: 4499 | V120: 4499 | W120: 4499 | X120: 4399 | Y120: 3799 | Z120: 3799 | AA120: 3749 | AB120: 5099 | AC120: 5099 | AD120: 5099 | AE120: 4999 | AF120: 4899 | AG120: 4899 | AH120: 4499 | AI120: 4499 | AJ120: 4499 | AK120: 4499 | AL120: 3799 | AW120: 03.11.2026 | AX120: 5G | AY120: =$H120*AY$11 -> 105.0198 | AZ120: =($H120*AZ$11) -> 94.6218 | BA120: =$H120*BA$11 -> 53.5497
A121: Price Oferta | B121: 21X | C121: 4017841 | D121: APPLE IPHONE 17E 256GB | E121: APPLE IPHONE 17E 256GB-PRETO | F121: 5799 | G121: 3099 | H121: 5199 | I121: 5199 | J121: 5099 | K121: 5099 | L121: 5099 | M121: 5099 | N121: 5099 | O121: 4999 | P121: 4899 | Q121: 4499 | R121: 4999 | S121: 4899 | T121: 4499 | U121: 4499 | V121: 4499 | W121: 4499 | X121: 4399 | Y121: 3799 | Z121: 3799 | AA121: 3749 | AB121: 5099 | AC121: 5099 | AD121: 5099 | AE121: 4999 | AF121: 4899 | AG121: 4899 | AH121: 4499 | AI121: 4499 | AJ121: 4499 | AK121: 4499 | AL121: 3799 | AW121: 03.11.2026 | AX121: 5G | AY121: =$H121*AY$11 -> 105.0198 | AZ121: =($H121*AZ$11) -> 94.6218 | BA121: =$H121*BA$11 -> 53.5497
A122: Price Oferta | B122: 21X | C122: 4017846 | D122: APPLE IPHONE 17E 256GB | E122: APPLE IPHONE 17E 256GB-ROSA PALIDO | F122: 5799 | G122: 3099 | H122: 5199 | I122: 5199 | J122: 5099 | K122: 5099 | L122: 5099 | M122: 5099 | N122: 5099 | O122: 4999 | P122: 4899 | Q122: 4499 | R122: 4999 | S122: 4899 | T122: 4499 | U122: 4499 | V122: 4499 | W122: 4499 | X122: 4399 | Y122: 3799 | Z122: 3799 | AA122: 3749 | AB122: 5099 | AC122: 5099 | AD122: 5099 | AE122: 4999 | AF122: 4899 | AG122: 4899 | AH122: 4499 | AI122: 4499 | AJ122: 4499 | AK122: 4499 | AL122: 3799 | AW122: 03.11.2026 | AX122: 5G | AY122: =$H122*AY$11 -> 105.0198 | AZ122: =($H122*AZ$11) -> 94.6218 | BA122: =$H122*BA$11 -> 53.5497
A123: Price Oferta | B123: 21X | C123: 4017981 | D123: APPLE IPHONE 17E 256GB | E123: APPLE IPHONE 17E 256GB-BRANCO NAC | F123: 5799 | G123: 3099 | H123: 5199 | I123: 5199 | J123: 5099 | K123: 5099 | L123: 5099 | M123: 5099 | N123: 5099 | O123: 4999 | P123: 4899 | Q123: 4499 | R123: 4999 | S123: 4899 | T123: 4499 | U123: 4499 | V123: 4499 | W123: 4499 | X123: 4399 | Y123: 3799 | Z123: 3799 | AA123: 3749 | AB123: 5099 | AC123: 5099 | AD123: 5099 | AE123: 4999 | AF123: 4899 | AG123: 4899 | AH123: 4499 | AI123: 4499 | AJ123: 4499 | AK123: 4499 | AL123: 3799 | AW123: 03.11.2026 | AX123: 5G | AY123: =$H123*AY$11 -> 105.0198 | AZ123: =($H123*AZ$11) -> 94.6218 | BA123: =$H123*BA$11 -> 53.5497
A124: Price Oferta | B124: 21X | C124: 4017980 | D124: APPLE IPHONE 17E 256GB | E124: APPLE IPHONE 17E 256GB-PRETO NAC | F124: 5799 | G124: 3099 | H124: 5199 | I124: 5199 | J124: 5099 | K124: 5099 | L124: 5099 | M124: 5099 | N124: 5099 | O124: 4999 | P124: 4899 | Q124: 4499 | R124: 4999 | S124: 4899 | T124: 4499 | U124: 4499 | V124: 4499 | W124: 4499 | X124: 4399 | Y124: 3799 | Z124: 3799 | AA124: 3749 | AB124: 5099 | AC124: 5099 | AD124: 5099 | AE124: 4999 | AF124: 4899 | AG124: 4899 | AH124: 4499 | AI124: 4499 | AJ124: 4499 | AK124: 4499 | AL124: 3799 | AW124: 03.11.2026 | AX124: 5G | AY124: =$H124*AY$11 -> 105.0198 | AZ124: =($H124*AZ$11) -> 94.6218 | BA124: =$H124*BA$11 -> 53.5497
A125: Price Oferta | B125: 21X | C125: 4017985 | D125: APPLE IPHONE 17E 256GB | E125: APPLE IPHONE 17E 256GB-ROSA PALIDO NAC | F125: 5799 | G125: 3099 | H125: 5199 | I125: 5199 | J125: 5099 | K125: 5099 | L125: 5099 | M125: 5099 | N125: 5099 | O125: 4999 | P125: 4899 | Q125: 4499 | R125: 4999 | S125: 4899 | T125: 4499 | U125: 4499 | V125: 4499 | W125: 4499 | X125: 4399 | Y125: 3799 | Z125: 3799 | AA125: 3749 | AB125: 5099 | AC125: 5099 | AD125: 5099 | AE125: 4999 | AF125: 4899 | AG125: 4899 | AH125: 4499 | AI125: 4499 | AJ125: 4499 | AK125: 4499 | AL125: 3799 | AW125: 03.11.2026 | AX125: 5G | AY125: =$H125*AY$11 -> 105.0198 | AZ125: =($H125*AZ$11) -> 94.6218 | BA125: =$H125*BA$11 -> 53.5497
A126: Price Oferta | B126: 21X | C126: 4018280 | D126: APPLE IPHONE 18 PRO 256GB | E126: APPLE IPHONE 18 PRO 256GB-PRETO | F126: 11999 | G126: 9899 | H126: 10999 | I126: 10999 | J126: 10899 | K126: 10899 | L126: 10899 | M126: 10899 | N126: 10899 | O126: 10799 | P126: 10699 | Q126: 9999 | R126: 10799 | S126: 10699 | T126: 9999 | U126: 9999 | V126: 9999 | W126: 9999 | X126: 9899 | Y126: 9499 | Z126: 9499 | AA126: 9299 | AB126: 10899 | AC126: 10899 | AD126: 10899 | AE126: 10899 | AF126: 10799 | AG126: 10699 | AH126: 9999 | AI126: 9999 | AJ126: 9999 | AK126: 9999 | AL126: 9499 | AW126: 03.11.2026 | AX126: 5G | AY126: =$H126*AY$11 -> 222.1798 | AZ126: =($H126*AZ$11) -> 200.1818 | BA126: =$H126*BA$11 -> 113.2897
A127: Price Oferta | B127: 21X | C127: 4018283 | D127: APPLE IPHONE 18 PRO 256GB | E127: APPLE IPHONE 18 PRO 256GB-BORDO | F127: 11999 | G127: 9899 | H127: 10999 | I127: 10999 | J127: 10899 | K127: 10899 | L127: 10899 | M127: 10899 | N127: 10899 | O127: 10799 | P127: 10699 | Q127: 9999 | R127: 10799 | S127: 10699 | T127: 9999 | U127: 9999 | V127: 9999 | W127: 9999 | X127: 9899 | Y127: 9499 | Z127: 9499 | AA127: 9299 | AB127: 10899 | AC127: 10899 | AD127: 10899 | AE127: 10899 | AF127: 10799 | AG127: 10699 | AH127: 9999 | AI127: 9999 | AJ127: 9999 | AK127: 9999 | AL127: 9499 | AW127: 03.11.2026 | AX127: 5G | AY127: =$H127*AY$11 -> 222.1798 | AZ127: =($H127*AZ$11) -> 200.1818 | BA127: =$H127*BA$11 -> 113.2897
A128: Price Oferta | B128: 21X | C128: 4018301 | D128: APPLE IPHONE 18 PRO 256GB | E128: APPLE IPHONE 18 PRO 256GB-GLACIAL | F128: 11999 | G128: 9899 | H128: 10999 | I128: 10999 | J128: 10899 | K128: 10899 | L128: 10899 | M128: 10899 | N128: 10899 | O128: 10799 | P128: 10699 | Q128: 9999 | R128: 10799 | S128: 10699 | T128: 9999 | U128: 9999 | V128: 9999 | W128: 9999 | X128: 9899 | Y128: 9499 | Z128: 9499 | AA128: 9299 | AB128: 10899 | AC128: 10899 | AD128: 10899 | AE128: 10899 | AF128: 10799 | AG128: 10699 | AH128: 9999 | AI128: 9999 | AJ128: 9999 | AK128: 9999 | AL128: 9499 | AW128: 03.11.2026 | AX128: 5G | AY128: =$H128*AY$11 -> 222.1798 | AZ128: =($H128*AZ$11) -> 200.1818 | BA128: =$H128*BA$11 -> 113.2897
A129: Price Oferta | B129: 21X | C129: 4018282 | D129: APPLE IPHONE 18 PRO 512GB | E129: APPLE IPHONE 18 PRO 512GB-PRETO | F129: 13499 | G129: 11299 | H129: 12399 | I129: 12399 | J129: 12299 | K129: 12299 | L129: 12299 | M129: 12299 | N129: 12299 | O129: 12199 | P129: 12099 | Q129: 11399 | R129: 12199 | S129: 12099 | T129: 11399 | U129: 11399 | V129: 11399 | W129: 11399 | X129: 11299 | Y129: 10799 | Z129: 10799 | AA129: 10499 | AB129: 12299 | AC129: 12299 | AD129: 12299 | AE129: 12299 | AF129: 12199 | AG129: 12099 | AH129: 11399 | AI129: 11399 | AJ129: 11399 | AK129: 11399 | AL129: 10799 | AW129: 03.11.2026 | AX129: 5G | AY129: =$H129*AY$11 -> 250.4598 | AZ129: =($H129*AZ$11) -> 225.6618 | BA129: =$H129*BA$11 -> 127.7097
A130: Price Oferta | B130: 21X | C130: 4018281 | D130: APPLE IPHONE 18 PRO 512GB | E130: APPLE IPHONE 18 PRO 512GB-BORDO | F130: 13499 | G130: 11299 | H130: 12399 | I130: 12399 | J130: 12299 | K130: 12299 | L130: 12299 | M130: 12299 | N130: 12299 | O130: 12199 | P130: 12099 | Q130: 11399 | R130: 12199 | S130: 12099 | T130: 11399 | U130: 11399 | V130: 11399 | W130: 11399 | X130: 11299 | Y130: 10799 | Z130: 10799 | AA130: 10499 | AB130: 12299 | AC130: 12299 | AD130: 12299 | AE130: 12299 | AF130: 12199 | AG130: 12099 | AH130: 11399 | AI130: 11399 | AJ130: 11399 | AK130: 11399 | AL130: 10799 | AW130: 03.11.2026 | AX130: 5G | AY130: =$H130*AY$11 -> 250.4598 | AZ130: =($H130*AZ$11) -> 225.6618 | BA130: =$H130*BA$11 -> 127.7097
A131: Price Oferta | B131: 21X | C131: 4018300 | D131: APPLE IPHONE 18 PRO 512GB | E131: APPLE IPHONE 18 PRO 512GB-GLACIAL | F131: 13499 | G131: 11299 | H131: 12399 | I131: 12399 | J131: 12299 | K131: 12299 | L131: 12299 | M131: 12299 | N131: 12299 | O131: 12199 | P131: 12099 | Q131: 11399 | R131: 12199 | S131: 12099 | T131: 11399 | U131: 11399 | V131: 11399 | W131: 11399 | X131: 11299 | Y131: 10799 | Z131: 10799 | AA131: 10499 | AB131: 12299 | AC131: 12299 | AD131: 12299 | AE131: 12299 | AF131: 12199 | AG131: 12099 | AH131: 11399 | AI131: 11399 | AJ131: 11399 | AK131: 11399 | AL131: 10799 | AW131: 03.11.2026 | AX131: 5G | AY131: =$H131*AY$11 -> 250.4598 | AZ131: =($H131*AZ$11) -> 225.6618 | BA131: =$H131*BA$11 -> 127.7097
... A139: Price Oferta | B139: 21X | C139: 4018309 | D139: APPLE IPHONE 18 PRO MAX 512GB | E139: APPLE IPHONE 18 PRO MAX 512GB-GLACIAL | F139: 14499 | G139: 12299 | H139: 13399 | I139: 13399 | J139: 13299 | K139: 13299 | L139: 13299 | M139: 13299 | N139: 13299 | O139: 13199 | P139: 13099 | Q139: 12399 | R139: 13199 | S139: 13099 | T139: 12399 | U139: 12399 | V139: 12399 | W139: 12399 | X139: 12299 | Y139: 11699 | Z139: 11699 | AA139: 11499 | AB139: 13299 | AC139: 13299 | AD139: 13299 | AE139: 13299 | AF139: 13199 | AG139: 13099 | AH139: 12399 | AI139: 12399 | AJ139: 12399 | AK139: 12399 | AL139: 11699 | AW139: 03.11.2026 | AX139: 5G | AY139: =$H139*AY$11 -> 270.6598 | AZ139: =($H139*AZ$11) -> 243.8618 | BA139: =$H139*BA$11 -> 138.0097
A140: Price Oferta | B140: 21X | C140: 4017020 | D140: JOVI V50 512GB | E140: JOVI V50 512GB-VERMELHO | F140: 4999 | G140: 2399 | H140: 3399 | I140: 3399 | J140: 2499 | K140: 2299 | L140: 2299 | M140: 2499 | N140: 2299 | O140: 2199 | P140: 2099 | Q140: 1799 | R140: 2199 | S140: 2099 | T140: 1799 | U140: 1799 | V140: 1799 | W140: 1799 | X140: 1699 | Y140: 1299 | Z140: 1299 | AA140: 1299 | AW140: 03.11.2026 | AX140: 5G | AY140: =$H140*AY$11 -> 68.6598 | AZ140: =($H140*AZ$11) -> 61.8618 | BA140: =$H140*BA$11 -> 35.0097
A141: Price Oferta | B141: 21X | C141: 4017022 | D141: JOVI V50 512GB | E141: JOVI V50 512GB-PRETO | F141: 4999 | G141: 2399 | H141: 3399 | I141: 3399 | J141: 2499 | K141: 2299 | L141: 2299 | M141: 2499 | N141: 2299 | O141: 2199 | P141: 2099 | Q141: 1799 | R141: 2199 | S141: 2099 | T141: 1799 | U141: 1799 | V141: 1799 | W141: 1799 | X141: 1699 | Y141: 1299 | Z141: 1299 | AA141: 1299 | AW141: 03.11.2026 | AX141: 5G | AY141: =$H141*AY$11 -> 68.6598 | AZ141: =($H141*AZ$11) -> 61.8618 | BA141: =$H141*BA$11 -> 35.0097
A142: Price Oferta | B142: 21X | C142: 4017045 | D142: JOVI V50 LITE 256GB | E142: JOVI V50 LITE 256GB-OURO | F142: 3199 | G142: 999 | H142: 1919 | I142: 1919 | J142: 1499 | K142: 1499 | L142: 1499 | M142: 1499 | N142: 1499 | O142: 1449 | P142: 1399 | Q142: 799 | R142: 1449 | S142: 1399 | T142: 799 | U142: 799 | V142: 799 | W142: 799 | X142: 799 | Y142: 699 | Z142: 699 | AA142: 699 | AW142: 03.11.2026 | AX142: 5G | AY142: =$H142*AY$11 -> 38.7638 | AZ142: =($H142*AZ$11) -> 34.9258 | BA142: =$H142*BA$11 -> 19.7657
A143: Price Oferta | B143: 21X | C143: 4017047 | D143: JOVI V50 LITE 256GB | E143: JOVI V50 LITE 256GB-PRETO | F143: 3199 | G143: 999 | H143: 1919 | I143: 1919 | J143: 1499 | K143: 1499 | L143: 1499 | M143: 1499 | N143: 1499 | O143: 1449 | P143: 1399 | Q143: 799 | R143: 1449 | S143: 1399 | T143: 799 | U143: 799 | V143: 799 | W143: 799 | X143: 799 | Y143: 699 | Z143: 699 | AA143: 699 | AW143: 03.11.2026 | AX143: 5G | AY143: =$H143*AY$11 -> 38.7638 | AZ143: =($H143*AZ$11) -> 34.9258 | BA143: =$H143*BA$11 -> 19.7657
A144: Price Oferta | B144: 21X | C144: 4017758 | D144: JOVI V70 5G 512GB | E144: JOVI V70 5G 512GB-AZUL SAFIRA | F144: 3999 | G144: 1999 | H144: 2799 | I144: 2799 | J144: 2699 | K144: 2699 | L144: 2699 | M144: 2699 | N144: 2699 | O144: 2599 | P144: 2499 | Q144: 1999 | R144: 2599 | S144: 2499 | T144: 1999 | U144: 1999 | V144: 1999 | W144: 1999 | X144: 1899 | Y144: 1499 | Z144: 1499 | AA144: 1399 | AW144: 03.11.2026 | AX144: 5G | AY144: =$H144*AY$11 -> 56.5398 | AZ144: =($H144*AZ$11) -> 50.9418 | BA144: =$H144*BA$11 -> 28.8297
A145: Price Oferta | B145: 21X | C145: 4017773 | D145: JOVI V70 5G 512GB | E145: JOVI V70 5G 512GB-LILAS BOREAL | F145: 3999 | G145: 1999 | H145: 2799 | I145: 2799 | J145: 2699 | K145: 2699 | L145: 2699 | M145: 2699 | N145: 2699 | O145: 2599 | P145: 2499 | Q145: 1999 | R145: 2599 | S145: 2499 | T145: 1999 | U145: 1999 | V145: 1999 | W145: 1999 | X145: 1899 | Y145: 1499 | Z145: 1499 | AA145: 1399 | AW145: 03.11.2026 | AX145: 5G | AY145: =$H145*AY$11 -> 56.5398 | AZ145: =($H145*AZ$11) -> 50.9418 | BA145: =$H145*BA$11 -> 28.8297
A146: ADM | B146: 21X | C146: 4017737 | D146: JOVI Y21 5G 256GB | E146: JOVI Y21 5G 256GB-AZUL | F146: 2299 | G146: 1599 | H146: 1599 | I146: 1599 | J146: 1399 | K146: 1399 | L146: 1399 | M146: 1399 | N146: 1399 | O146: 1299 | P146: 1249 | Q146: 1199 | R146: 1299 | S146: 1249 | T146: 1199 | U146: 1199 | V146: 1199 | W146: 1199 | X146: 1199 | Y146: 1199 | Z146: 1199 | AA146: 1199 | AW146: 03.11.2026 | AX146: 5G | AY146: =$H146*AY$11 -> 32.2998 | AZ146: =($H146*AZ$11) -> 29.1018 | BA146: =$H146*BA$11 -> 16.4697
A147: ADM | B147: 21X | C147: 4017770 | D147: JOVI Y21 5G 256GB | E147: JOVI Y21 5G 256GB-DOURADO | F147: 2299 | G147: 1599 | H147: 1599 | I147: 1599 | J147: 1399 | K147: 1399 | L147: 1399 | M147: 1399 | N147: 1399 | O147: 1299 | P147: 1249 | Q147: 1199 | R147: 1299 | S147: 1249 | T147: 1199 | U147: 1199 | V147: 1199 | W147: 1199 | X147: 1199 | Y147: 1199 | Z147: 1199 | AA147: 1199 | AW147: 03.11.2026 | AX147: 5G | AY147: =$H147*AY$11 -> 32.2998 | AZ147: =($H147*AZ$11) -> 29.1018 | BA147: =$H147*BA$11 -> 16.4697
A148: ADM | B148: 21X | C148: 4018220 | D148: JOVI Y21E 4G 4RAM 128GB | E148: JOVI Y21E 4G 4RAM 128GB-AZUL | F148: 1699 | G148: 1149 | H148: 1149 | I148: 1149 | J148: 999 | K148: 999 | L148: 999 | M148: 999 | N148: 999 | O148: 899 | P148: 899 | Q148: 799 | R148: 899 | S148: 899 | T148: 799 | U148: 799 | V148: 799 | W148: 799 | X148: 799 | Y148: 799 | Z148: 799 | AA148: 799 | AW148: 03.11.2026 | AX148: 4G | AY148: =$H148*AY$11 -> 23.2098 | AZ148: =($H148*AZ$11) -> 20.9118 | BA148: =$H148*BA$11 -> 11.8347
A149: ADM | B149: 21X | C149: 4018221 | D149: JOVI Y21E 4G 4RAM 128GB | E149: JOVI Y21E 4G 4RAM 128GB-DOURADO | F149: 1699 | G149: 1149 | H149: 1149 | I149: 1149 | J149: 999 | K149: 999 | L149: 999 | M149: 999 | N149: 999 | O149: 899 | P149: 899 | Q149: 799 | R149: 899 | S149: 899 | T149: 799 | U149: 799 | V149: 799 | W149: 799 | X149: 799 | Y149: 799 | Z149: 799 | AA149: 799 | AW149: 03.11.2026 | AX149: 4G | AY149: =$H149*AY$11 -> 23.2098 | AZ149: =($H149*AZ$11) -> 20.9118 | BA149: =$H149*BA$11 -> 11.8347
A150: ADM | B150: 21X | C150: 4017200 | D150: JOVI Y29S 5G 256GB | E150: JOVI Y29S 5G 256GB-PRETO | F150: 2099 | G150: 1419 | H150: 1419 | I150: 1419 | J150: 1299 | K150: 999 | L150: 999 | M150: 1299 | N150: 999 | O150: 999 | P150: 999 | Q150: 899 | R150: 999 | S150: 999 | T150: 899 | U150: 899 | V150: 899 | W150: 899 | X150: 899 | Y150: 899 | Z150: 899 | AA150: 899 | AW150: 03.11.2026 | AX150: 5G | AY150: =$H150*AY$11 -> 28.6638 | AZ150: =($H150*AZ$11) -> 25.8258 | BA150: =$H150*BA$11 -> 14.6157
A151: ADM | B151: 21X | C151: 4018137 | D151: JOVI Y31 4G 8RAM 256GB | E151: JOVI Y31 4G 8RAM 256GB-BRANCO | F151: 2799 | G151: 1999 | H151: 1999 | I151: 1999 | J151: 1899 | K151: 1899 | L151: 1899 | M151: 1899 | N151: 1899 | O151: 1799 | P151: 1699 | Q151: 1499 | R151: 1799 | S151: 1699 | T151: 1499 | U151: 1499 | V151: 1499 | W151: 1499 | X151: 1399 | Y151: 1299 | Z151: 1299 | AA151: 1299 | AW151: 03.11.2026 | AX151: 4G | AY151: =$H151*AY$11 -> 40.3798 | AZ151: =($H151*AZ$11) -> 36.3818 | BA151: =$H151*BA$11 -> 20.5897
... A156: Price Oferta | B156: 21X | C156: 4018016 | D156: JOVI X300 ULTRA 5G 512GB | E156: JOVI X300 ULTRA 5G 512GB-VERDE | F156: 19999 | G156: 14199 | H156: 14899 | I156: 14899 | J156: 14799 | K156: 14799 | L156: 14799 | M156: 14799 | N156: 14799 | O156: 14599 | P156: 14499 | Q156: 14299 | R156: 14599 | S156: 14499 | T156: 14299 | U156: 14299 | V156: 14299 | W156: 14299 | X156: 14199 | Y156: 13699 | Z156: 13699 | AA156: 13499 | AW156: 03.11.2026 | AX156: 5G | AY156: =$H156*AY$11 -> 300.9598 | AZ156: =($H156*AZ$11) -> 271.1618 | BA156: =$H156*BA$11 -> 153.4597
A157: ADM | B157: 21X | C157: 4015390 | D157: MOTOROLA MOTO E13 64GB | E157: MOTOROLA MOTO E13 64GB-GRAFITE | F157: 799 | G157: 549 | H157: 549 | I157: 549 | J157: =M157 -> 449 | K157: =M157 -> 449 | L157: =N157 -> 449 | M157: 449 | N157: 449 | O157: =R157 -> 399 | P157: =S157 -> 349 | Q157: =T157 -> 299 | R157: 399 | S157: 349 | T157: 299 | U157: 299 | V157: 299 | W157: 299 | X157: 299 | Y157: 299 | Z157: 299 | AA157: 299 | AW157: 03.11.2026 | AX157: 4G | AY157: =$H157*AY$11 -> 11.0898 | AZ157: =($H157*AZ$11) -> 9.9918 | BA157: =$H157*BA$11 -> 5.6547
A158: Price Oferta | B158: 21X | C158: 4015070 | D158: MOTOROLA EDGE 30 NEO 5G | E158: MOTOROLA EDGE 30 NEO 5G-PRETO | F158: 3499 | G158: 799 | H158: 1099 | I158: 1099 | J158: 899 | K158: 799 | L158: 799 | M158: 899 | N158: 899 | O158: 749 | P158: 749 | Q158: 749 | R158: 749 | S158: 749 | T158: 749 | U158: 749 | V158: 749 | W158: 749 | X158: 749 | Y158: 749 | Z158: 749 | AA158: 749 | AW158: 03.11.2026 | AX158: 5G | AY158: =$H158*AY$11 -> 22.1998 | AZ158: =($H158*AZ$11) -> 20.0018 | BA158: =$H158*BA$11 -> 11.3197
A159: Price Oferta | B159: 21X | C159: 4014800 | D159: MOTOROLA EDGE 30 PRO | E159: MOTOROLA EDGE 30 PRO-AZUL | F159: 6499 | G159: 1399 | H159: 2499 | I159: 2499 | J159: =M159 -> 2299 | K159: =M159 -> 2299 | L159: =N159 -> 2299 | M159: 2299 | N159: 2299 | O159: =R159 -> 1899 | P159: =S159 -> 1799 | Q159: =T159 -> 1499 | R159: 1899 | S159: 1799 | T159: 1499 | U159: 1499 | V159: 1499 | W159: 1499 | X159: 1399 | Y159: 999 | Z159: 999 | AA159: 949 | AW159: 03.11.2026 | AX159: 5G | AY159: =$H159*AY$11 -> 50.4798 | AZ159: =($H159*AZ$11) -> 45.4818 | BA159: =$H159*BA$11 -> 25.7397
A160: Price Oferta | B160: 21X | C160: 4015553 | D160: MOTOROLA EDGE 40 | E160: MOTOROLA EDGE 40-PRETO | F160: 3699 | G160: 1279 | H160: 2299 | I160: 2299 | J160: 1599 | K160: 1499 | L160: 1499 | M160: 1599 | N160: 1599 | O160: 1399 | P160: 1299 | Q160: 1099 | R160: 1399 | S160: 1299 | T160: 1099 | U160: 1099 | V160: 1099 | W160: 1099 | X160: 999 | Y160: 899 | Z160: 899 | AA160: 899 | AW160: 03.11.2026 | AX160: 5G | AY160: =$H160*AY$11 -> 46.4398 | AZ160: =($H160*AZ$11) -> 41.8418 | BA160: =$H160*BA$11 -> 23.6797
A161: Price Oferta | B161: 21X | C161: 4015555 | D161: MOTOROLA EDGE 40 | E161: MOTOROLA EDGE 40-MAGENTA | F161: 3699 | G161: 1279 | H161: 2299 | I161: 2299 | J161: 1599 | K161: 1499 | L161: 1499 | M161: 1599 | N161: 1599 | O161: 1399 | P161: 1299 | Q161: 1099 | R161: 1399 | S161: 1299 | T161: 1099 | U161: 1099 | V161: 1099 | W161: 1099 | X161: 999 | Y161: 899 | Z161: 899 | AA161: 899 | AW161: 03.11.2026 | AX161: 5G | AY161: =$H161*AY$11 -> 46.4398 | AZ161: =($H161*AZ$11) -> 41.8418 | BA161: =$H161*BA$11 -> 23.6797
A162: Price Oferta | B162: 21X | C162: 4015692 | D162: MOTOROLA EDGE 40 NEO | E162: MOTOROLA EDGE 40 NEO-PRETO | F162: 2999 | G162: 1099 | H162: 2099 | I162: 2099 | J162: 1499 | K162: 1399 | L162: 1399 | M162: 1499 | N162: 1499 | O162: 1299 | P162: 1199 | Q162: 1099 | R162: 1299 | S162: 1199 | T162: 1099 | U162: 1099 | V162: 1099 | W162: 1099 | X162: 999 | Y162: 899 | Z162: 899 | AA162: 899 | AW162: 03.11.2026 | AX162: 5G | AY162: =$H162*AY$11 -> 42.3998 | AZ162: =($H162*AZ$11) -> 38.2018 | BA162: =$H162*BA$11 -> 21.6197
A163: Price Oferta | B163: 21X | C163: 4016016 | D163: MOTOROLA EDGE 40 NEO | E163: MOTOROLA EDGE 40 NEO-PEACH FUZZ | F163: 2999 | G163: 1099 | H163: 2099 | I163: 2099 | J163: 1499 | K163: 1399 | L163: 1399 | M163: 1499 | N163: 1499 | O163: 1299 | P163: 1199 | Q163: 1099 | R163: 1299 | S163: 1199 | T163: 1099 | U163: 1099 | V163: 1099 | W163: 1099 | X163: 999 | Y163: 899 | Z163: 899 | AA163: 899 | AW163: 03.11.2026 | AX163: 5G | AY163: =$H163*AY$11 -> 42.3998 | AZ163: =($H163*AZ$11) -> 38.2018 | BA163: =$H163*BA$11 -> 21.6197
A164: Price Oferta | B164: 21X | C164: 4016501 | D164: MOTOROLA EDGE 50 256GB | E164: MOTOROLA EDGE 50 256GB-CINZA | F164: 3299 | G164: 1399 | H164: 1999 | I164: 1999 | J164: 1799 | K164: 1799 | L164: 1799 | M164: 1799 | N164: 1799 | O164: 1699 | P164: 1599 | Q164: 599 | R164: 1699 | S164: 1599 | T164: 599 | U164: 599 | V164: 599 | W164: 599 | X164: 599 | Y164: 599 | Z164: 599 | AA164: 599 | AW164: 03.11.2026 | AX164: 5G | AY164: =$H164*AY$11 -> 40.3798 | AZ164: =($H164*AZ$11) -> 36.3818 | BA164: =$H164*BA$11 -> 20.5897
A165: Price Oferta | B165: 21X | C165: 4016503 | D165: MOTOROLA EDGE 50 256GB | E165: MOTOROLA EDGE 50 256GB-VERDE | F165: 3299 | G165: 1399 | H165: 1999 | I165: 1999 | J165: 1799 | K165: 1799 | L165: 1799 | M165: 1799 | N165: 1799 | O165: 1699 | P165: 1599 | Q165: 599 | R165: 1699 | S165: 1599 | T165: 599 | U165: 599 | V165: 599 | W165: 599 | X165: 599 | Y165: 599 | Z165: 599 | AA165: 599 | AW165: 03.11.2026 | AX165: 5G | AY165: =$H165*AY$11 -> 40.3798 | AZ165: =($H165*AZ$11) -> 36.3818 | BA165: =$H165*BA$11 -> 20.5897
A166: Price Oferta | B166: 21X | C166: 4016505 | D166: MOTOROLA EDGE 50 256GB | E166: MOTOROLA EDGE 50 256GB-PEACH FUZZ | F166: 3299 | G166: 1399 | H166: 1999 | I166: 1999 | J166: 1799 | K166: 1799 | L166: 1799 | M166: 1799 | N166: 1799 | O166: 1699 | P166: 1599 | Q166: 599 | R166: 1699 | S166: 1599 | T166: 599 | U166: 599 | V166: 599 | W166: 599 | X166: 599 | Y166: 599 | Z166: 599 | AA166: 599 | AW166: 03.11.2026 | AX166: 5G | AY166: =$H166*AY$11 -> 40.3798 | AZ166: =($H166*AZ$11) -> 36.3818 | BA166: =$H166*BA$11 -> 20.5897
A167: Price Oferta | B167: 21X | C167: 4016284 | D167: MOTOROLA EDGE 50 FUSION 256GB | E167: MOTOROLA EDGE 50 FUSION 256GB-AZUL MARIN | F167: 2999 | G167: 1199 | H167: 2299 | I167: 2299 | J167: 1799 | K167: 1799 | L167: 1799 | M167: 1799 | N167: 1799 | O167: 1699 | P167: 1649 | Q167: 1299 | R167: 1699 | S167: 1649 | T167: 1299 | U167: 1299 | V167: 1299 | W167: 1299 | X167: 1199 | Y167: 1199 | Z167: 1199 | AA167: 1199 | AW167: 03.11.2026 | AX167: 5G | AY167: =$H167*AY$11 -> 46.4398 | AZ167: =($H167*AZ$11) -> 41.8418 | BA167: =$H167*BA$11 -> 23.6797
A168: Price Oferta | B168: 21X | C168: 4016285 | D168: MOTOROLA EDGE 50 FUSION 256GB | E168: MOTOROLA EDGE 50 FUSION 256GB-AZUL CLARO | F168: 2999 | G168: 1199 | H168: 2299 | I168: 2299 | J168: 1799 | K168: 1799 | L168: 1799 | M168: 1799 | N168: 1799 | O168: 1699 | P168: 1649 | Q168: 1299 | R168: 1699 | S168: 1649 | T168: 1299 | U168: 1299 | V168: 1299 | W168: 1299 | X168: 1199 | Y168: 1199 | Z168: 1199 | AA168: 1199 | AW168: 03.11.2026 | AX168: 5G | AY168: =$H168*AY$11 -> 46.4398 | AZ168: =($H168*AZ$11) -> 41.8418 | BA168: =$H168*BA$11 -> 23.6797
A169: Price Oferta | B169: 21X | C169: 4016922 | D169: MOTOROLA EDGE 60 FUSION 256GB | E169: MOTOROLA EDGE 60 FUSION 256GB-CINZA | F169: 2999 | G169: 1499 | H169: 2199 | I169: 2199 | J169: 1999 | K169: 1999 | L169: 1999 | M169: 1999 | N169: 1999 | O169: 1899 | P169: 1799 | Q169: 799 | R169: 1899 | S169: 1799 | T169: 799 | U169: 799 | V169: 799 | W169: 799 | X169: 799 | Y169: 799 | Z169: 799 | AA169: 799 | AW169: 03.11.2026 | AX169: 5G | AY169: =$H169*AY$11 -> 44.4198 | AZ169: =($H169*AZ$11) -> 40.0218 | BA169: =$H169*BA$11 -> 22.6497
A170: Price Oferta | B170: 21X | C170: 4016923 | D170: MOTOROLA EDGE 60 FUSION 256GB | E170: MOTOROLA EDGE 60 FUSION 256GB-ROSA | F170: 2999 | G170: 1499 | H170: 2199 | I170: 2199 | J170: 1999 | K170: 1999 | L170: 1999 | M170: 1999 | N170: 1999 | O170: 1899 | P170: 1799 | Q170: 799 | R170: 1899 | S170: 1799 | T170: 799 | U170: 799 | V170: 799 | W170: 799 | X170: 799 | Y170: 799 | Z170: 799 | AA170: 799 | AW170: 03.11.2026 | AX170: 5G | AY170: =$H170*AY$11 -> 44.4198 | AZ170: =($H170*AZ$11) -> 40.0218 | BA170: =$H170*BA$11 -> 22.6497
...

Sheet ACESSÓRIOS REV
B1: TABELA DE PREÇOS - ACESSÓRIOS
B3: CANAL: | C3: REVENDAS
B4: Inclusão de Preço
B5: Alteração de Preço
C6: DATA INÍCIO: | D6: =REV!D11 -> 46311
B7: CATEGORIA MKT | C7: CÓDIGO | D7: DESCRIÇÃO COMERCIAL | E7: DESCRIÇÃO SAP | F7: PRÉ | G7: PREÇO BASE FATURAMENTO RETAIL | H7: CONTROLE NÃO FIDELIZADO - TODOS (Fatura / Express) | I7: PÓS PAGO NÃO FIDELIZADO - VIDE ABA DE REGRAS | J7: TIM CONTROLE | K7: TIM CONTROLE PLUS | L7: TIM CONTROLE PREMIUM | M7: TIM CONTROLE SMART | N7: TIM CONTROLE REDES SOCIAIS | O7: TIM BLACK | P7: TIM BLACK PLUS | Q7: TIM BLACK PREMIUM | R7: TIM BLACK A (15GB) | S7: TIM BLACK B (20GB) | T7: TIM BLACK C (25GB) | U7: TIM BLACK C ULTRA | V7: TIM BLACK FAMÍLIA | W7: TIM BLACK FAMÍLIA A ONE | X7: TIM BLACK FAMÍLIA PLUS | Y7: TIM BLACK FAMÍLIA PREMIUM | Z7: TIM BLACK FAMÍLIA C ONE | AA7: TIM BLACK FAMÍLIA VIP | AB7: TIM Fibra 400M 24 | AC7: TIM Fibra 500M 24 - 2 | AD7: TIM Fibra 600M 24 - 2 | AE7: TIM Fibra 600M P 24 - 2 | AF7: TIM Fibra 600M M 24 - 2 | AG7: TIM Ultrafibra 800M YT26 | AH7: TIM Fibra 600M GP 25 | AI7: TIM Fibra 1GB 24 | AJ7: TIM Fibra 1GB P 24 | AK7: TIM Fibra 1GB M 24 | AL7: TIM Fibra 2GB 24 | AM7: DATA FIM DA OFERTA
B8: SMARTHOME | C8: 4014927 | D8: BALANCA INTELIGENTE GEONAV | E8: BALANCA INTELIGENTE GEONAV-BRANCO | F8: 199 | G8: 199 | AB8: 169 | AC8: 169 | AD8: 169 | AE8: 169 | AF8: 169 | AG8: 169 | AH8: 169 | AI8: 169 | AJ8: 169 | AK8: 169 | AL8: 169 | AM8: 31.12.9999
B9: GAMER | C9: 4016500 | D9: BASE DE CARREGAMENTO SONY DUALSENSE | E9: BASE DE CARREGAMENTO SONY DUALSENSE-BRAN | F9: 199 | G9: 199 | AM9: 31.12.9999
B10: MUSICA | C10: 4014444 | D10: CAIXA DE SOM BT JBL CHARGE 5 | E10: CAIXA DE SOM BT JBL CHARGE 5-PRETO | F10: 799 | G10: 799 | H10: 799 | I10: 799 | J10: 749 | K10: 749 | L10: 749 | M10: 749 | N10: 749 | O10: 699 | P10: 599 | Q10: 449 | R10: 699 | S10: 599 | T10: 449 | U10: 449 | V10: 449 | W10: 449 | X10: 449 | Y10: 449 | Z10: 449 | AA10: 449 | AM10: 31.12.9999
B11: MUSICA | C11: 4017142 | D11: CAIXA DE SOM BT JBL CHARGE 6 | E11: CAIXA DE SOM BT JBL CHARGE 6-AZUL | F11: 999 | G11: 999 | H11: 999 | I11: 999 | J11: 949 | K11: 949 | L11: 949 | M11: 949 | N11: 949 | O11: 899 | P11: 799 | Q11: 599 | R11: 899 | S11: 799 | T11: 599 | U11: 599 | V11: 599 | W11: 599 | X11: 549 | Y11: 549 | Z11: 549 | AA11: 549 | AM11: 31.12.9999
B12: MUSICA | C12: 4014958 | D12: CAIXA DE SOM BT JBL FLIP 6 | E12: CAIXA DE SOM BT JBL FLIP 6-PRETO | F12: 299 | G12: 399 | AM12: 31.12.9999
B13: MÚSICA | C13: 4017062 | D13: CAIXA DE SOM BT JBL FLIP 7 | E13: CAIXA DE SOM BT JBL FLIP 7-PRETO | F13: 899 | G13: 899 | H13: 899 | I13: 899 | J13: 849 | K13: 849 | L13: 849 | M13: 849 | N13: 849 | O13: 799 | P13: 699 | Q13: 499 | R13: 799 | S13: 699 | T13: 499 | U13: 499 | V13: 499 | W13: 499 | X13: 499 | Y13: 499 | Z13: 499 | AA13: 499 | AM13: 31.12.9999
B14: MUSICA | C14: 4016330 | D14: CAIXA DE SOM BT JBL GO4 | E14: CAIXA DE SOM BT JBL GO4-PRETO | F14: 199 | G14: 199 | H14: 199 | I14: 199 | J14: 149 | K14: 149 | L14: 149 | M14: 149 | N14: 149 | O14: 149 | P14: 149 | Q14: 149 | R14: 149 | S14: 149 | T14: 149 | U14: 149 | V14: 149 | W14: 149 | X14: 149 | Y14: 149 | Z14: 149 | AA14: 149 | AB14: 149 | AC14: 149 | AD14: 149 | AE14: 149 | AF14: 149 | AG14: 149 | AH14: 149 | AI14: 149 | AJ14: 149 | AK14: 149 | AL14: 149 | AM14: 31.12.9999
B15: INFOTECH | C15: 4018060 | D15: CAIXA DE SOM BT JBL GO5 | E15: CAIXA DE SOM BT JBL GO5-PRETO | F15: 359 | G15: 299 | H15: 359 | I15: 359 | J15: 199 | K15: 199 | L15: 199 | M15: 199 | N15: 199 | O15: 199 | P15: 199 | Q15: 99 | R15: 199 | S15: 199 | T15: 99 | U15: 99 | V15: 99 | W15: 99 | X15: 99 | Y15: 99 | Z15: 99 | AA15: 99 | AB15: 199 | AC15: 199 | AD15: 199 | AE15: 199 | AF15: 199 | AG15: 199 | AH15: 199 | AI15: 99 | AJ15: 99 | AK15: 99 | AL15: 99 | AM15: 31.12.9999
B16: MUSICA | C16: 4015270 | D16: CAIXA DE SOM JBL BOOMBOX 3 | E16: CAIXA DE SOM JBL BOOMBOX 3-PRETO | F16: 1999 | G16: 1999 | H16: 1999 | I16: 1999 | J16: 1949 | K16: 1949 | L16: 1949 | M16: 1949 | N16: 1949 | O16: 1899 | P16: 1799 | Q16: 1599 | R16: 1899 | S16: 1799 | T16: 1599 | U16: 1599 | V16: 1599 | W16: 1599 | X16: 1499 | Y16: 1199 | Z16: 1199 | AA16: 1149 | AM16: 31.12.9999
B17: MUSICA | C17: 4015688 | D17: CAIXA DE SOM JBL BOOMBOX 3 | E17: CAIXA DE SOM JBL BOOMBOX 3-PRETO AM | F17: 1999 | G17: 1999 | H17: 1999 | I17: 1999 | J17: 1949 | K17: 1949 | L17: 1949 | M17: 1949 | N17: 1949 | O17: 1899 | P17: 1799 | Q17: 1599 | R17: 1899 | S17: 1799 | T17: 1599 | U17: 1599 | V17: 1599 | W17: 1599 | X17: 1499 | Y17: 1199 | Z17: 1199 | AA17: 1149 | AM17: 31.12.9999
B18: CAIXA DE SOM | C18: 4017260 | D18: CAIXA DE SOM JBL BOOMBOX 4 | E18: CAIXA DE SOM JBL BOOMBOX 4-PRETO | F18: 2599 | G18: 1999 | H18: 2599 | I18: 2599 | J18: 2549 | K18: 2549 | L18: 2549 | M18: 2549 | N18: 2549 | O18: 2499 | P18: 2399 | Q18: 2199 | R18: 2499 | S18: 2399 | T18: 2199 | U18: 2199 | V18: 2199 | W18: 2199 | X18: 2099 | Y18: 1799 | Z18: 1799 | AA18: 1749 | AB18: 2549 | AC18: 2549 | AD18: 2549 | AE18: 2549 | AF18: 2499 | AG18: 2499 | AH18: 2499 | AI18: 2199 | AJ18: 2199 | AK18: 2199 | AL18: 1799 | AM18: 31.12.9999
B19: CAIXA DE SOM | C19: 4018025 | D19: CAIXA DE SOM JBL BOOMBOX 4 | E19: CAIXA DE SOM JBL BOOMBOX 4-PRETO AM | F19: 2599 | G19: 1999 | H19: 2599 | I19: 2599 | J19: 2549 | K19: 2549 | L19: 2549 | M19: 2549 | N19: 2549 | O19: 2499 | P19: 2399 | Q19: 2199 | R19: 2499 | S19: 2399 | T19: 2199 | U19: 2199 | V19: 2199 | W19: 2199 | X19: 2099 | Y19: 1799 | Z19: 1799 | AA19: 1749 | AB19: 2549 | AC19: 2549 | AD19: 2549 | AE19: 2549 | AF19: 2499 | AG19: 2499 | AH19: 2499 | AI19: 2199 | AJ19: 2199 | AK19: 2199 | AL19: 1799 | AM19: 31.12.9999
B20: MÚSICA | C20: 4016358 | D20: CAIXA DE SOM JBL CLIP 5 | E20: CAIXA DE SOM JBL CLIP 5-PRETO | F20: 399 | G20: 399 | H20: 399 | I20: 399 | J20: 349 | K20: 349 | L20: 349 | M20: 349 | N20: 349 | O20: 299 | P20: 299 | Q20: 299 | R20: 299 | S20: 299 | T20: 299 | U20: 299 | V20: 299 | W20: 299 | X20: 299 | Y20: 299 | Z20: 299 | AA20: 299 | AM20: 31.12.9999
B21: MUSICA | C21: 4016341 | D21: CAIXA DE SOM JBL ENCORE ESSENTIAL | E21: CAIXA DE SOM JBL ENCORE ESSENTIAL-PRE AM | F21: 1199 | G21: 1199 | AM21: 31.12.9999
B22: MUSICA | C22: 4015273 | D22: CAIXA DE SOM JBL ENCORE ESSENTIAL | E22: CAIXA DE SOM JBL ENCORE ESSENTIAL-PRETO | F22: 1199 | G22: 1199 | AM22: 31.12.9999
B23: MUSICA | C23: 4017250 | D23: CAIXA DE SOM JBL ENCORE ESSENTIAL 2 | E23: CAIXA DE SOM JBL ENCORE ESSENTIAL 2-PRET | F23: 1499 | G23: 999 | H23: 1499 | I23: 1499 | J23: 1449 | K23: 1449 | L23: 1449 | M23: 1449 | N23: 1449 | O23: 1399 | P23: 1299 | Q23: 999 | R23: 1399 | S23: 1299 | T23: 1099 | U23: 1099 | V23: 999 | W23: 999 | X23: 999 | Y23: 899 | Z23: 899 | AA23: 899 | AB23: 1449 | AC23: 1449 | AD23: 1449 | AE23: 1399 | AF23: 1399 | AG23: 1399 | AH23: 1399 | AI23: 999 | AJ23: 999 | AK23: 999 | AL23: 899 | AM23: 31.12.9999
B24: CAIXA DE SOM | C24: 4017944 | D24: CAIXA DE SOM JBL ENCORE 2 2MIC | E24: CAIXA DE SOM JBL ENCORE 2 2MIC-PRETO AM | F24: 2699 | G24: 1899 | H24: 2699 | I24: 2699 | J24: 2649 | K24: 2649 | L24: 2649 | M24: 2649 | N24: 2649 | O24: 2599 | P24: 2499 | Q24: 2299 | R24: 2599 | S24: 2499 | T24: 2299 | U24: 2299 | V24: 2299 | W24: 2299 | X24: 2199 | Y24: 1899 | Z24: 1899 | AA24: 1849 | AM24: 31.12.9999
B25: CAIXA DE SOM | C25: 4018027 | D25: CAIXA JBL ENCORE ESSENTIAL 2 | E25: CAIXA JBL ENCORE ESSENTIAL 2-PRETO AM | F25: 1699 | G25: 899 | H25: 1699 | I25: 1699 | J25: 1649 | K25: 1649 | L25: 1649 | M25: 1649 | N25: 1649 | O25: 1599 | P25: 1499 | Q25: 1299 | R25: 1599 | S25: 1499 | T25: 1299 | U25: 1299 | V25: 1299 | W25: 1299 | X25: 1199 | Y25: 899 | Z25: 899 | AA25: 899 | AM25: 31.12.9999
B26: CAIXA DE SOM | C26: 4017581 | D26: CAIXA DE SOM JBL GO ESSENTIAL 2 | E26: CAIXA DE SOM JBL GO ESSENTIAL 2-PRETO | F26: 219 | G26: 219 | AM26: 31.12.9999
B27: MÚSICA | C27: 4017638 | D27: CAIXA DE SOM JBL GRIP 16W | E27: CAIXA DE SOM JBL GRIP 16W-PRETO | F27: 549 | G27: 549 | H27: 549 | I27: 549 | J27: 499 | K27: 499 | L27: 499 | M27: 499 | N27: 499 | O27: 449 | P27: 399 | Q27: 399 | R27: 449 | S27: 399 | T27: 399 | U27: 399 | V27: 399 | W27: 399 | X27: 399 | Y27: 399 | Z27: 399 | AA27: 399 | AM27: 31.12.9999
B28: MUSICA | C28: 4016351 | D28: CAIXA DE SOM JBL XTREME 4 | E28: CAIXA DE SOM JBL XTREME 4 | F28: 799 | G28: 999 | H28: 799 | I28: 799 | J28: 749 | K28: 749 | L28: 749 | M28: 749 | N28: 749 | O28: 699 | P28: 599 | Q28: 449 | R28: 699 | S28: 599 | T28: 449 | U28: 449 | V28: 449 | W28: 449 | X28: 449 | Y28: 449 | Z28: 449 | AA28: 449 | AM28: 31.12.9999
B29: BASICO | C29: 4016004 | D29: CAPA CLEAR GALAXY S24 | E29: CAPA CLEAR GALAXY S24-TRANSPARENTE | F29: 129 | G29: 129 | AM29: 31.12.9999
B30: BASICO | C30: 4016005 | D30: CAPA CLEAR GALAXY S24 PLUS | E30: CAPA CLEAR GALAXY S24 PLUS-TRANSPARENTE | F30: 129 | G30: 129 | AM30: 31.12.9999
B31: BASICO | C31: 4016006 | D31: CAPA CLEAR GALAXY S24 ULTRA | E31: CAPA CLEAR GALAXY S24 ULTRA-TRANSPARENTE | F31: 129 | G31: 129 | AM31: 31.12.9999
B32: BASICO | C32: 4015729 | D32: CAPA PROTECTIC COVER GALAXY S23 FE | E32: CAPA PROTECTIC COVER GALAXY S23 FE-TRANS | F32: 10 | G32: 10 | AM32: 31.12.9999
B33: BASICO | C33: 4013975 | D33: CARREGADOR APPLE USB-C 20W | E33: CARREGADOR APPLE USB-C 20W-BRANCO | F33: 219 | G33: 219 | AM33: 31.12.9999
B34: CARREGADOR | C34: 4016254 | D34: CARREGADOR APPLE USB-C 20W 2024 | E34: CARREGADOR APPLE USB-C 20W 2024-BRANCO | F34: 219 | G34: 219 | AM34: 31.12.9999
B35: GAMES | C35: 4018040 | D35: CONTROLE PS5 DUALSENSE 2026 | E35: CONTROLE PS5 DUALSENSE 2026-BRANCO | F35: 499 | G35: 399 | H35: 499 | I35: 499 | J35: 399 | K35: 399 | L35: 399 | M35: 399 | N35: 399 | O35: 349 | P35: 249 | Q35: 249 | R35: 349 | S35: 249 | T35: 249 | U35: 249 | V35: 249 | W35: 249 | X35: 249 | Y35: 249 | Z35: 249 | AA35: 249 | AB35: 399 | AC35: 399 | AD35: 399 | AE35: 399 | AF35: 299 | AG35: 299 | AH35: 299 | AI35: 249 | AJ35: 249 | AK35: 249 | AL35: 249 | AM35: 31.12.9999
B36: GAMES | C36: 4017939 | D36: CONTROLE PS5 DUALSENSE 2026 | E36: CONTROLE PS5 DUALSENSE 2026-AZUL | F36: 499 | G36: 399 | H36: 499 | I36: 499 | J36: 399 | K36: 399 | L36: 399 | M36: 399 | N36: 399 | O36: 349 | P36: 249 | Q36: 249 | R36: 349 | S36: 249 | T36: 249 | U36: 249 | V36: 249 | W36: 249 | X36: 249 | Y36: 249 | Z36: 249 | AA36: 249 | AB36: 399 | AC36: 399 | AD36: 399 | AE36: 399 | AF36: 299 | AG36: 299 | AH36: 299 | AI36: 249 | AJ36: 249 | AK36: 249 | AL36: 249 | AM36: 31.12.9999
B37: GAMER | C37: 4017938 | D37: CONTROLE PS5 DUALSENSE 2026 | E37: CONTROLE PS5 DUALSENSE 2026-PRETO | F37: 499 | G37: 399 | H37: 499 | I37: 499 | J37: 399 | K37: 399 | L37: 399 | M37: 399 | N37: 399 | O37: 349 | P37: 249 | Q37: 249 | R37: 349 | S37: 249 | T37: 249 | U37: 249 | V37: 249 | W37: 249 | X37: 249 | Y37: 249 | Z37: 249 | AA37: 249 | AB37: 399 | AC37: 399 | AD37: 399 | AE37: 399 | AF37: 299 | AG37: 299 | AH37: 299 | AI37: 249 | AJ37: 249 | AK37: 249 | AL37: 249 | AM37: 31.12.9999
B38: GAMER | C38: 4018041 | D38: CONTROLE PS5 DUALSENSE 2026 | E38: CONTROLE PS5 DUALSENSE 2026-CAMUFLADO | F38: 499 | G38: 399 | H38: 499 | I38: 499 | J38: 399 | K38: 399 | L38: 399 | M38: 399 | N38: 399 | O38: 349 | P38: 249 | Q38: 249 | R38: 349 | S38: 249 | T38: 249 | U38: 249 | V38: 249 | W38: 249 | X38: 249 | Y38: 249 | Z38: 249 | AA38: 249 | AB38: 399 | AC38: 399 | AD38: 399 | AE38: 399 | AF38: 299 | AG38: 299 | AH38: 299 | AI38: 249 | AJ38: 249 | AK38: 249 | AL38: 249 | AM38: 31.12.9999
B39: GAMER | C39: 4016340 | D39: CONTROLE SEM FIO PS5 DUALSENSE | E39: CONTROLE SEM FIO PS5 DUALSENSE-BRANCO | F39: 499 | G39: 399 | H39: 499 | I39: 499 | J39: 399 | K39: 399 | L39: 399 | M39: 399 | N39: 399 | O39: 349 | P39: 249 | Q39: 249 | R39: 349 | S39: 249 | T39: 249 | U39: 249 | V39: 249 | W39: 249 | X39: 249 | Y39: 249 | Z39: 249 | AA39: 249 | AB39: 399 | AC39: 399 | AD39: 399 | AE39: 399 | AF39: 299 | AG39: 299 | AH39: 299 | AI39: 249 | AJ39: 249 | AK39: 249 | AL39: 249 | AM39: 31.12.9999
B40: GAMER | C40: 4016494 | D40: CONTROLE SEM FIO PS5 DUALSENSE | E40: CONTROLE SEM FIO PS5 DUALSENSE-PRETO | F40: 499 | G40: 399 | H40: 499 | I40: 499 | J40: 399 | K40: 399 | L40: 399 | M40: 399 | N40: 399 | O40: 349 | P40: 249 | Q40: 249 | R40: 349 | S40: 249 | T40: 249 | U40: 249 | V40: 249 | W40: 249 | X40: 249 | Y40: 249 | Z40: 249 | AA40: 249 | AB40: 399 | AC40: 399 | AD40: 399 | AE40: 399 | AF40: 299 | AG40: 299 | AH40: 299 | AI40: 249 | AJ40: 249 | AK40: 249 | AL40: 249 | AM40: 31.12.9999
B41: GAMER | C41: 4017140 | D41: CONTROLE SEM FIO PS5 DUALSENSE | E41: CONTROLE SEM FIO PS5 DUALSENSE-CAMUFLADO | F41: 499 | G41: 399 | H41: 499 | I41: 499 | J41: 399 | K41: 399 | L41: 399 | M41: 399 | N41: 399 | O41: 349 | P41: 249 | Q41: 249 | R41: 349 | S41: 249 | T41: 249 | U41: 249 | V41: 249 | W41: 249 | X41: 249 | Y41: 249 | Z41: 249 | AA41: 249 | AB41: 399 | AC41: 399 | AD41: 399 | AE41: 399 | AF41: 299 | AG41: 299 | AH41: 299 | AI41: 249 | AJ41: 249 | AK41: 249 | AL41: 249 | AM41: 31.12.9999
B42: GAMES | C42: 4016959 | D42: CONTROLE SEM FIO PS5 DUALSENSE CHROMA INDIGO | E42: CONTROLE SEM FIO PS5 DUALSENSE-INDIGO | F42: 499 | G42: 399 | H42: 499 | I42: 499 | J42: 399 | K42: 399 | L42: 399 | M42: 399 | N42: 399 | O42: 349 | P42: 249 | Q42: 249 | R42: 349 | S42: 249 | T42: 249 | U42: 249 | V42: 249 | W42: 249 | X42: 249 | Y42: 249 | Z42: 249 | AA42: 249 | AB42: 399 | AC42: 399 | AD42: 399 | AE42: 399 | AF42: 299 | AG42: 299 | AH42: 299 | AI42: 249 | AJ42: 249 | AK42: 249 | AL42: 249 | AM42: 31.12.9999
B43: GAMER | C43: 4015506 | D43: CONTROLE SEM FIO XBOX SERIES | E43: CONTROLE SEM FIO XBOX SERIES-BRANCO | F43: 299 | G43: 299 | H43: 299 | I43: 299 | J43: 249 | K43: 249 | L43: 249 | M43: 249 | N43: 249 | O43: 199 | P43: 199 | Q43: 199 | R43: 199 | S43: 199 | T43: 199 | U43: 199 | V43: 199 | W43: 199 | X43: 199 | Y43: 199 | Z43: 199 | AA43: 199 | AM43: 31.12.9999
B44: GADGETS | C44: 4015637 | D44: ESTABILIZADOR DJI OSMO MOBILE SE | E44: ESTABILIZADOR DJI OSMO MOBILE SE-CINZA | F44: 999 | G44: 999 | H44: 999 | I44: 999 | J44: 949 | K44: 949 | L44: 949 | M44: 949 | N44: 949 | O44: 899 | P44: 799 | Q44: 599 | R44: 899 | S44: 799 | T44: 599 | U44: 599 | V44: 599 | W44: 599 | X44: 549 | Y44: 549 | Z44: 549 | AA44: 549 | AM44: 31.12.9999
B45: GADGETS | C45: 4015591 | D45: FILME INSTAX MINI 10 FOTOS | E45: FILME INSTAX MINI 10 FOTOS-BRANCO | F45: 49 | G45: 49 | AM45: 31.12.9999
B46: GADGETS | C46: 4015592 | D46: FILME INSTAX MINI 20 FOTOS | E46: FILME INSTAX MINI 20 FOTOS-BRANCO | F46: 89 | G46: 89 | AM46: 31.12.9999
B47: FONE DE OUVIDO | C47: 4013141 | D47: FONE APPLE EARPODS | E47: FONE APPLE EARPODS-BRANCO | F47: 199 | G47: 199 | AM47: 31.12.9999
B48: FONE DE OUVIDO | C48: 4015880 | D48: FONE APPLE EARPODS USBC | E48: FONE APPLE EARPODS USBC-BRANCO | F48: 199 | G48: 199 | AM48: 31.12.9999
B49: FONE DE OUVIDO | C49: 4016971 | D49: FONE APPLE EARPODS USBC 2024 | E49: FONE APPLE EARPODS USBC 2024-BRANCO | F49: 199 | G49: 199 | AM49: 31.12.9999
B50: FONE DE OUVIDO | C50: 4016096 | D50: FONE COM FIO GEONAV USB-C | E50: FONE COM FIO GEONAV USB-C-CINZA | F50: 49 | G50: 99 | AM50: 31.12.9999
B51: FONE DE OUVIDO | C51: 4013617 | D51: FONE JBL TUNE 110 | E51: FONE JBL TUNE 110-PRETO | F51: 99 | G51: 99 | H51: 99 | I51: 99 | J51: 99 | K51: 99 | L51: 99 | M51: 99 | N51: 99 | O51: 99 | P51: 99 | Q51: 99 | R51: 99 | S51: 99 | T51: 99 | U51: 99 | V51: 99 | W51: 99 | X51: 99 | Y51: 99 | Z51: 99 | AA51: 99 | AM51: 31.12.9999
B52: FONE DE OUVIDO | C52: 4014261 | D52: FONE JBL TUNE 125BT | E52: FONE JBL TUNE 125BT-PRETO | F52: 149 | G52: 149 | AM52: 31.12.9999
B53: FONE DE OUVIDO | C53: 4015696 | D53: FONE SAMSUNG GALAXY BUDS FE | E53: FONE SAMSUNG GALAXY BUDS FE-GRAFITE | F53: 199 | G53: 199 | H53: 199 | I53: 199 | J53: 149 | K53: 149 | L53: 149 | M53: 149 | N53: 149 | O53: 99 | P53: 99 | Q53: 99 | R53: 99 | S53: 99 | T53: 99 | U53: 99 | V53: 99 | W53: 99 | X53: 99 | Y53: 99 | Z53: 99 | AA53: 99 | AM53: 31.12.9999
B54: FONE DE OUVIDO | C54: 4016533 | D54: FONE TWS GALAXY BUDS 3 2024 | E54: FONE TWS GALAXY BUDS 3 2024-BRANCO | F54: 599 | G54: 799 | H54: 599 | I54: 599 | J54: 549 | K54: 549 | L54: 549 | M54: 549 | N54: 549 | O54: 499 | P54: 399 | Q54: 349 | R54: 499 | S54: 399 | T54: 349 | U54: 349 | V54: 349 | W54: 349 | X54: 349 | Y54: 349 | Z54: 349 | AA54: 349 | AM54: 31.12.9999
B55: FONE DE OUVIDO | C55: 4016531 | D55: FONE TWS GALAXY BUDS 3 2024 | E55: FONE TWS GALAXY BUDS 3 2024-CINZA | F55: 599 | G55: 799 | H55: 599 | I55: 599 | J55: 549 | K55: 549 | L55: 549 | M55: 549 | N55: 549 | O55: 499 | P55: 399 | Q55: 349 | R55: 499 | S55: 399 | T55: 349 | U55: 349 | V55: 349 | W55: 349 | X55: 349 | Y55: 349 | Z55: 349 | AA55: 349 | AM55: 31.12.9999
B56: FONE DE OUVIDO | C56: 4017404 | D56: FONE TWS GALAXY BUDS 3 FE | E56: FONE TWS GALAXY BUDS 3 FE-PRETO | F56: 1099 | G56: 1099 | H56: 1099 | I56: 1099 | J56: 1049 | K56: 1049 | L56: 1049 | M56: 1049 | N56: 1049 | O56: 999 | P56: 899 | Q56: 699 | R56: 999 | S56: 899 | T56: 699 | U56: 699 | V56: 699 | W56: 699 | X56: 599 | Y56: 599 | Z56: 599 | AA56: 599 | AM56: 31.12.9999
B57: FONE DE OUVIDO | C57: 4016537 | D57: FONE TWS GALAXY BUDS 3 PRO 2024 | E57: FONE TWS GALAXY BUDS 3 PRO 2024-CINZA | F57: 1199 | G57: 1199 | H57: 1199 | I57: 1199 | J57: 1149 | K57: 1149 | L57: 1149 | M57: 1149 | N57: 1149 | O57: 1099 | P57: 999 | Q57: 799 | R57: 1099 | S57: 999 | T57: 799 | U57: 799 | V57: 799 | W57: 799 | X57: 799 | Y57: 799 | Z57: 799 | AA57: 799 | AM57: 31.12.9999
B58: FONE DE OUVIDO | C58: 4017785 | D58: FONE TWS GALAXY BUDS 4 | E58: FONE TWS GALAXY BUDS 4-PRETO | F58: 1399 | G58: 1399 | H58: 1399 | I58: 1399 | J58: 1349 | K58: 1349 | L58: 1349 | M58: 1349 | N58: 1349 | O58: 1299 | P58: 1199 | Q58: 999 | R58: 1299 | S58: 1199 | T58: 999 | U58: 999 | V58: 999 | W58: 999 | X58: 899 | Y58: 749 | Z58: 749 | AA58: 749 | AM58: 31.12.9999
B59: FONE DE OUVIDO | C59: 4017780 | D59: FONE TWS GALAXY BUDS 4 PRO | E59: FONE TWS GALAXY BUDS 4 PRO-PRETO | F59: 1699 | G59: 1699 | H59: 1699 | I59: 1699 | J59: 1649 | K59: 1649 | L59: 1649 | M59: 1649 | N59: 1649 | O59: 1599 | P59: 1499 | Q59: 1299 | R59: 1599 | S59: 1499 | T59: 1299 | U59: 1299 | V59: 1299 | W59: 1299 | X59: 1199 | Y59: 899 | Z59: 899 | AA59: 899 | AM59: 31.12.9999
B60: FONE DE OUVIDO | C60: 4017339 | D60: FONE TWS GALAXY BUDS CORE | E60: FONE TWS GALAXY BUDS CORE-PRETO | F60: 299 | G60: 299 | H60: 299 | I60: 299 | J60: 249 | K60: 249 | L60: 249 | M60: 249 | N60: 249 | O60: 199 | P60: 199 | Q60: 199 | R60: 199 | S60: 199 | T60: 199 | U60: 199 | V60: 199 | W60: 199 | X60: 199 | Y60: 199 | Z60: 199 | AA60: 199 | AM60: 31.12.9999
B61: FONE DE OUVIDO | C61: 4017398 | D61: FONE TWS GALAXY BUDS CORE | E61: FONE TWS GALAXY BUDS CORE-BRANCO | F61: 299 | G61: 299 | H61: 299 | I61: 299 | J61: 249 | K61: 249 | L61: 249 | M61: 249 | N61: 249 | O61: 199 | P61: 199 | Q61: 199 | R61: 199 | S61: 199 | T61: 199 | U61: 199 | V61: 199 | W61: 199 | X61: 199 | Y61: 199 | Z61: 199 | AA61: 199 | AM61: 31.12.9999
B62: FONE DE OUVIDO | C62: 4016523 | D62: FONE TWS GALAXY BUDS FE 2024 | E62: FONE TWS GALAXY BUDS FE 2024-GRAFITE | F62: 199 | G62: 199 | H62: 199 | I62: 199 | J62: 149 | K62: 149 | L62: 149 | M62: 149 | N62: 149 | O62: 99 | P62: 99 | Q62: 99 | R62: 99 | S62: 99 | T62: 99 | U62: 99 | V62: 99 | W62: 99 | X62: 99 | Y62: 99 | Z62: 99 | AA62: 99 | AM62: 31.12.9999
B63: FONE DE OUVIDO | C63: 4017661 | D63: FONE TWS JBL SENSE LITE | E63: FONE TWS JBL SENSE LITE-PRETO | F63: 499 | G63: 499 | H63: 499 | I63: 499 | J63: 449 | K63: 449 | L63: 449 | M63: 449 | N63: 449 | O63: 399 | P63: 299 | Q63: 299 | R63: 399 | S63: 299 | T63: 299 | U63: 299 | V63: 299 | W63: 299 | X63: 299 | Y63: 299 | Z63: 299 | AA63: 299 | AM63: 31.12.9999
B64: FONE DE OUVIDO | C64: 4016484 | D64: FONE TWS JBL WAVE BEAM 2 | E64: FONE TWS JBL WAVE BEAM 2-PRETO | F64: 299 | G64: 299 | H64: 299 | I64: 299 | J64: 249 | K64: 249 | L64: 249 | M64: 249 | N64: 249 | O64: 199 | P64: 199 | Q64: 199 | R64: 199 | S64: 199 | T64: 199 | U64: 199 | V64: 199 | W64: 199 | X64: 199 | Y64: 199 | Z64: 199 | AA64: 199 | AM64: 31.12.9999
B65: FONE DE OUVIDO | C65: 4016483 | D65: FONE TWS JBL WAVE BUDS 2 | E65: FONE TWS JBL WAVE BUDS 2-PRETO | F65: 299 | G65: 299 | H65: 299 | I65: 299 | J65: 199 | K65: 199 | L65: 199 | M65: 199 | N65: 199 | O65: 199 | P65: 199 | Q65: 199 | R65: 199 | S65: 199 | T65: 199 | U65: 199 | V65: 199 | W65: 199 | X65: 199 | Y65: 199 | Z65: 199 | AA65: 199 | AB65: 199 | AC65: 199 | AD65: 199 | AE65: 199 | AF65: 199 | AG65: 199 | AH65: 199 | AI65: 199 | AJ65: 199 | AK65: 199 | AL65: 199 | AM65: 31.12.9999
B66: FONE DE OUVIDO | C66: 4016310 | D66: FONE TWS MOTO BUDS | E66: FONE TWS MOTO BUDS-AZUL ESCURO | F66: 399 | G66: 399 | H66: 399 | I66: 399 | J66: 349 | K66: 349 | L66: 349 | M66: 349 | N66: 349 | O66: 299 | P66: 299 | Q66: 249 | R66: 299 | S66: 249 | T66: 249 | U66: 249 | V66: 249 | W66: 249 | X66: 249 | Y66: 249 | Z66: 249 | AA66: 249 | AM66: 31.12.9999
B67: FONE DE OUVIDO | C67: 4016311 | D67: FONE TWS MOTO BUDS | E67: FONE TWS MOTO BUDS-AZUL CLARO | F67: 399 | G67: 399 | H67: 399 | I67: 399 | J67: 349 | K67: 349 | L67: 349 | M67: 349 | N67: 349 | O67: 299 | P67: 299 | Q67: 249 | R67: 299 | S67: 249 | T67: 249 | U67: 249 | V67: 249 | W67: 249 | X67: 249 | Y67: 249 | Z67: 249 | AA67: 249 | AM67: 31.12.9999
B68: MUSICA | C68: 4016544 | D68: FONE TWS MOTO BUDS 65 2024 | E68: FONE TWS MOTO BUDS 65 2024-PRETO | F68: 199 | G68: 199 | H68: 199 | I68: 199 | J68: 99 | K68: 99 | L68: 99 | M68: 99 | N68: 99 | O68: 99 | P68: 99 | Q68: 99 | R68: 99 | S68: 99 | T68: 99 | U68: 99 | V68: 99 | W68: 99 | X68: 99 | Y68: 99 | Z68: 99 | AA68: 99 | AM68: 31.12.9999
B69: GADGETS | C69: 4016406 | D69: FONE TWS SAMSUNG GALAXY BUDS 3 | E69: FONE TWS SAMSUNG GALAXY BUDS 3-BRANCO | F69: 599 | G69: 799 | H69: 599 | I69: 599 | J69: 549 | K69: 549 | L69: 549 | M69: 549 | N69: 549 | O69: 499 | P69: 399 | Q69: 349 | R69: 499 | S69: 399 | T69: 349 | U69: 349 | V69: 349 | W69: 349 | X69: 349 | Y69: 349 | Z69: 349 | AA69: 349 | AM69: 31.12.9999
B70: GADGETS | C70: 4016403 | D70: FONE TWS SAMSUNG GALAXY BUDS 3 | E70: FONE TWS SAMSUNG GALAXY BUDS 3-CINZA | F70: 599 | G70: 799 | H70: 599 | I70: 599 | J70: 549 | K70: 549 | L70: 549 | M70: 549 | N70: 549 | O70: 499 | P70: 399 | Q70: 349 | R70: 499 | S70: 399 | T70: 349 | U70: 349 | V70: 349 | W70: 349 | X70: 349 | Y70: 349 | Z70: 349 | AA70: 349 | AM70: 31.12.9999
B71: FONE DE OUVIDO | C71: 4016367 | D71: FONE USB-C JBL 310C | E71: FONE USB-C JBL 310C-PRETO | F71: 129 | G71: 129 | H71: 129 | I71: 129 | J71: 99 | K71: 99 | L71: 99 | M71: 99 | N71: 99 | O71: 99 | P71: 99 | Q71: 99 | R71: 99 | S71: 99 | T71: 99 | U71: 99 | V71: 99 | W71: 99 | X71: 99 | Y71: 99 | Z71: 99 | AA71: 99 | AM71: 31.12.9999
B72: INFOTECH | C72: 4016410 | D72: GALAXY BOOK4 I3 8GB 256GB | E72: GALAXY BOOK4 I3 8GB 256GB-GRAFITE | F72: 2999 | G72: 2199 | H72: 2999 | I72: 2999 | J72: 2949 | K72: 2949 | L72: 2949 | M72: 2949 | N72: 2949 | O72: 2899 | P72: 2799 | Q72: 2599 | R72: 2899 | S72: 2799 | T72: 2599 | U72: 2599 | V72: 2599 | W72: 2599 | X72: 2499 | Y72: 2199 | Z72: 2199 | AA72: 2149 | AM72: 31.12.9999
B73: MUSICA | C73: 4015498 | D73: HEADPHONE BT JBL TUNE 520 | E73: HEADPHONE BT JBL TUNE 520-PRETO | F73: 149 | G73: 199 | H73: 0 | I73: 0 | J73: 0 | K73: 0 | L73: 0 | M73: 0 | N73: 0 | O73: 0 | P73: 0 | Q73: 0 | R73: 0 | S73: 0 | T73: 0 | U73: 0 | V73: 0 | W73: 0 | X73: 0 | Y73: 0 | Z73: 0 | AA73: 0 | AM73: 31.12.9999
B74: FONE DE OUVIDO | C74: 4017807 | D74: HEADPHONE BT JBL TUNE 530 | E74: HEADPHONE BT JBL TUNE 530-PRETO | F74: 219 | G74: 219 | H74: 219 | I74: 219 | J74: 149 | K74: 149 | L74: 149 | M74: 149 | N74: 149 | O74: 149 | P74: 149 | Q74: 149 | R74: 149 | S74: 149 | T74: 149 | U74: 149 | V74: 149 | W74: 149 | X74: 149 | Y74: 149 | Z74: 149 | AA74: 149 | AB74: 149 | AC74: 149 | AD74: 149 | AE74: 149 | AF74: 149 | AG74: 149 | AH74: 149 | AI74: 149 | AJ74: 149 | AK74: 149 | AL74: 149 | AM74: 31.12.9999
B75: MUSICA | C75: 4016014 | D75: HEADPHONE BT JBL TUNE 720 | E75: HEADPHONE BT JBL TUNE 720-PRETO | F75: 399 | G75: 399 | H75: 399 | I75: 399 | J75: 349 | K75: 349 | L75: 349 | M75: 349 | N75: 349 | O75: 299 | P75: 299 | Q75: 249 | R75: 299 | S75: 249 | T75: 249 | U75: 249 | V75: 249 | W75: 249 | X75: 249 | Y75: 249 | Z75: 249 | AA75: 249 | AM75: 31.12.9999
B76: FONE DE OUVIDO | C76: 4017808 | D76: HEADPHONE BT JBL TUNE 730 | E76: HEADPHONE BT JBL TUNE 730-PRETO | F76: 399 | G76: 399 | H76: 399 | I76: 399 | J76: 349 | K76: 349 | L76: 349 | M76: 349 | N76: 349 | O76: 299 | P76: 249 | Q76: 249 | R76: 299 | S76: 249 | T76: 249 | U76: 249 | V76: 249 | W76: 249 | X76: 249 | Y76: 249 | Z76: 249 | AA76: 249 | AM76: 31.12.9999
B77: GAMER | C77: 4016400 | D77: HEADSET RAZER BLACKSHARK V2 | E77: HEADSET RAZER BLACKSHARK V2-PRETO | F77: 299 | G77: 299 | H77: 299 | I77: 299 | J77: 249 | K77: 249 | L77: 249 | M77: 249 | N77: 249 | O77: 199 | P77: 199 | Q77: 199 | R77: 199 | S77: 199 | T77: 199 | U77: 199 | V77: 199 | W77: 199 | X77: 199 | Y77: 199 | Z77: 199 | AA77: 199 | AM77: 31.12.9999
B78: GAMER | C78: 4016502 | D78: HEADSET SEM FIO SONY PULSE 3D | E78: HEADSET SEM FIO SONY PULSE 3D-BRANCO | F78: 599 | G78: 599 | H78: 599 | I78: 599 | J78: 549 | K78: 549 | L78: 549 | M78: 549 | N78: 549 | O78: 499 | P78: 399 | Q78: 349 | R78: 499 | S78: 399 | T78: 349 | U78: 349 | V78: 349 | W78: 349 | X78: 349 | Y78: 349 | Z78: 349 | AA78: 349 | AM78: 31.12.9999
B79: FOTOGRAFIA | C79: 4015538 | D79: IMPRESSORA INSTAX MINI LINK 2 | E79: IMPRESSORA INSTAX MINI LINK 2-BRANCO | F79: 699 | G79: 699 | H79: 699 | I79: 699 | J79: 649 | K79: 649 | L79: 649 | M79: 649 | N79: 649 | O79: 599 | P79: 599 | Q79: 399 | R79: 599 | S79: 499 | T79: 399 | U79: 399 | V79: 399 | W79: 399 | X79: 399 | Y79: 399 | Z79: 399 | AA79: 399 | AM79: 31.12.9999
B80: FOTOGRAFIA | C80: 4016434 | D80: IMPRESSORA INSTAX MINI LINK 2 2024 | E80: IMPRESSORA INSTAX MINI LINK 2 2024-BRANC | F80: 699 | G80: 699 | H80: 699 | I80: 699 | J80: 649 | K80: 649 | L80: 649 | M80: 649 | N80: 649 | O80: 599 | P80: 599 | Q80: 399 | R80: 599 | S80: 499 | T80: 399 | U80: 399 | V80: 399 | W80: 399 | X80: 399 | Y80: 399 | Z80: 399 | AA80: 399 | AM80: 31.12.9999
B81: CAPA | C81: 4018205 | D81: KIT PROTECAO DEVIA IPHONE 18 PRO | E81: KIT PROTECAO DEVIA IPHONE 18 PRO-TRANSP | F81: 299 | G81: 299 | AM81: 31.12.9999
B82: GADGETS | C82: 4018208 | D82: KIT PROTECAO DEVIA IPHONE 18 PRO MAX | E82: KIT PROTECAO DEVIA IPHONE 18 PRO MAX-TRA | F82: 399 | G82: 399 | AM82: 31.12.9999
B83: SMARTHOME | C83: 4014960 | D83: LUMINARIA INTELIGENTE GEONAV | E83: LUMINARIA INTELIGENTE GEONAV-BRANCO | F83: 299 | G83: 299 | AB83: 289 | AC83: 289 | AD83: 289 | AE83: 289 | AF83: 289 | AG83: 289 | AH83: 289 | AI83: 289 | AJ83: 289 | AK83: 289 | AL83: 289 | AM83: 31.12.9999
B84: GAMER | C84: 4015580 | D84: MICROSOFT XBOX SERIES S 512GB | E84: MICROSOFT XBOX SERIES S 512GB-BRANCO | F84: 2499 | G84: 2499 | H84: 2499 | I84: 2499 | J84: 2449 | K84: 2449 | L84: 2449 | M84: 2449 | N84: 2449 | O84: 2399 | P84: 2399 | Q84: 2099 | R84: 2399 | S84: 2299 | T84: 2099 | U84: 2099 | V84: 2099 | W84: 2099 | X84: 1999 | Y84: 1699 | Z84: 1699 | AA84: 1649 | AM84: 31.12.9999
B85: GADGETS | C85: 4016307 | D85: OCULOS BT JBL SOUNDGEAR | E85: OCULOS BT JBL SOUNDGEAR-PEROLA | F85: 699 | G85: 699 | H85: 699 | I85: 699 | J85: 649 | K85: 649 | L85: 649 | M85: 649 | N85: 649 | O85: 599 | P85: 599 | Q85: 399 | R85: 599 | S85: 499 | T85: 399 | U85: 399 | V85: 399 | W85: 399 | X85: 399 | Y85: 399 | Z85: 399 | AA85: 399 | AM85: 31.12.9999
B86: GADGETS | C86: 4016308 | D86: OCULOS BT JBL SOUNDGEAR | E86: OCULOS BT JBL SOUNDGEAR-ONIX | F86: 699 | G86: 699 | H86: 699 | I86: 699 | J86: 649 | K86: 649 | L86: 649 | M86: 649 | N86: 649 | O86: 599 | P86: 599 | Q86: 399 | R86: 599 | S86: 499 | T86: 399 | U86: 399 | V86: 399 | W86: 399 | X86: 399 | Y86: 399 | Z86: 399 | AA86: 399 | AM86: 31.12.9999
B87: INFOTECH | C87: 4016180 | D87: POSITIVO VISION C15 4GB 128GB | E87: POSITIVO VISION C15 4GB 128GB-CINZA | F87: 999 | G87: 999 | H87: 999 | I87: 999 | J87: 949 | K87: 949 | L87: 949 | M87: 949 | N87: 949 | O87: 899 | P87: 799 | Q87: 599 | R87: 899 | S87: 799 | T87: 599 | U87: 599 | V87: 599 | W87: 599 | X87: 549 | Y87: 549 | Z87: 549 | AA87: 549 | AM87: 31.12.9999
B88: GAMES | C88: 4017353 | D88: PS5 SLIM DIGI ASTRO BOT E GT7 2025 | E88: PS5 SLIM DIGI ASTRO BOT E GT7 2025-BRANC | F88: 4599 | G88: 2999 | H88: 4599 | I88: 4599 | J88: 4549 | K88: 4549 | L88: 4549 | M88: 4549 | N88: 4549 | O88: 4499 | P88: 4399 | Q88: 4199 | R88: 4499 | S88: 4399 | T88: 4199 | U88: 4199 | V88: 4199 | W88: 4199 | X88: 4099 | Y88: 3599 | Z88: 3599 | AA88: 3599 | AB88: 4549 | AC88: 4549 | AD88: 4549 | AE88: 4499 | AF88: 4499 | AG88: 4499 | AH88: 4499 | AI88: 4199 | AJ88: 4199 | AK88: 4199 | AL88: 3599 | AM88: 31.12.9999
B89: GAMER | C89: 4016511 | D89: PS5 SLIM DIGITAL 1TB 2 JOGOS | E89: PS5 SLIM DIGITAL 1TB 2 JOGOS-BRANCO | F89: 4599 | G89: 2999 | H89: 4599 | I89: 4599 | J89: 4549 | K89: 4549 | L89: 4549 | M89: 4549 | N89: 4549 | O89: 4499 | P89: 4399 | Q89: 4199 | R89: 4499 | S89: 4399 | T89: 4199 | U89: 4199 | V89: 4199 | W89: 4199 | X89: 4099 | Y89: 3599 | Z89: 3599 | AA89: 3599 | AB89: 4549 | AC89: 4549 | AD89: 4549 | AE89: 4499 | AF89: 4499 | AG89: 4499 | AH89: 4499 | AI89: 4199 | AJ89: 4199 | AK89: 4199 | AL89: 3599 | AM89: 31.12.9999
B90: GAMER | C90: 4016960 | D90: PS5 SLIM DIGITAL 1TB 2 JOGOS 2025 | E90: PS5 SLIM DIGITAL 1TB 2 JOGOS 2025-BRANCO | F90: 4599 | G90: 2999 | H90: 4599 | I90: 4599 | J90: 4549 | K90: 4549 | L90: 4549 | M90: 4549 | N90: 4549 | O90: 4499 | P90: 4399 | Q90: 4199 | R90: 4499 | S90: 4399 | T90: 4199 | U90: 4199 | V90: 4199 | W90: 4199 | X90: 4099 | Y90: 3599 | Z90: 3599 | AA90: 3599 | AB90: 4549 | AC90: 4549 | AD90: 4549 | AE90: 4499 | AF90: 4499 | AG90: 4499 | AH90: 4499 | AI90: 4199 | AJ90: 4199 | AK90: 4199 | AL90: 3599 | AM90: 31.12.9999
B91: GAMER | C91: 4017129 | D91: PS5 SLIM DIGITAL ASTRO BOT E GT7 | E91: PS5 SLIM DIGITAL ASTRO BOT E GT7-BRANCO | F91: 4599 | G91: 2999 | H91: 4599 | I91: 4599 | J91: 4549 | K91: 4549 | L91: 4549 | M91: 4549 | N91: 4549 | O91: 4499 | P91: 4399 | Q91: 4199 | R91: 4499 | S91: 4399 | T91: 4199 | U91: 4199 | V91: 4199 | W91: 4199 | X91: 4099 | Y91: 3599 | Z91: 3599 | AA91: 3599 | AB91: 4549 | AC91: 4549 | AD91: 4549 | AE91: 4499 | AF91: 4499 | AG91: 4499 | AH91: 4499 | AI91: 4199 | AJ91: 4199 | AK91: 4199 | AL91: 3599 | AM91: 31.12.9999
B92: GAMER | C92: 4016309 | D92: PS5 SLIM DISK 1TB 2 JOGOS | E92: PS5 SLIM DISK 1TB 2 JOGOS-BRANCO | F92: 5099 | G92: 3999 | H92: 5099 | I92: 5099 | J92: 5049 | K92: 5049 | L92: 5049 | M92: 5049 | N92: 5049 | O92: 4999 | P92: 4899 | Q92: 4699 | R92: 4999 | S92: 4899 | T92: 4699 | U92: 4699 | V92: 4699 | W92: 4699 | X92: 4599 | Y92: 3999 | Z92: 3999 | AA92: 3999 | AB92: 5049 | AC92: 5049 | AD92: 5049 | AE92: 4999 | AF92: 4999 | AG92: 4999 | AH92: 4999 | AI92: 4699 | AJ92: 4699 | AK92: 4699 | AL92: 3999 | AM92: 31.12.9999
B93: GAMES | C93: 4016958 | D93: PS5 SLIM DISK 1TB 2 JOGOS 2025 | E93: PS5 SLIM DISK 1TB 2 JOGOS 2025-BRANCO | F93: 5099 | G93: 3999 | H93: 5099 | I93: 5099 | J93: 5049 | K93: 5049 | L93: 5049 | M93: 5049 | N93: 5049 | O93: 4999 | P93: 4899 | Q93: 4699 | R93: 4999 | S93: 4899 | T93: 4699 | U93: 4699 | V93: 4699 | W93: 4699 | X93: 4599 | Y93: 3999 | Z93: 3999 | AA93: 3999 | AB93: 5049 | AC93: 5049 | AD93: 5049 | AE93: 4999 | AF93: 4999 | AG93: 4999 | AH93: 4999 | AI93: 4699 | AJ93: 4699 | AK93: 4699 | AL93: 3999 | AM93: 31.12.9999
B94: GAMER | C94: 4017128 | D94: PS5 SLIM DISK ASTRO BOT E GT7 | E94: PS5 SLIM DISK ASTRO BOT E GT7-BRANCO | F94: 5099 | G94: 3999 | H94: 5099 | I94: 5099 | J94: 5049 | K94: 5049 | L94: 5049 | M94: 5049 | N94: 5049 | O94: 4999 | P94: 4899 | Q94: 4699 | R94: 4999 | S94: 4899 | T94: 4699 | U94: 4699 | V94: 4699 | W94: 4699 | X94: 4599 | Y94: 3999 | Z94: 3999 | AA94: 3999 | AB94: 5049 | AC94: 5049 | AD94: 5049 | AE94: 4999 | AF94: 4999 | AG94: 4999 | AH94: 4999 | AI94: 4699 | AJ94: 4699 | AK94: 4699 | AL94: 3999 | AM94: 31.12.9999
B95: GAMES | C95: 4017326 | D95: PS5 SLIM DISK ASTRO BOT E GT7 2025 | E95: PS5 SLIM DISK ASTRO BOT E GT7 2025-BRANC | F95: 5099 | G95: 3999 | H95: 5099 | I95: 5099 | J95: 5049 | K95: 5049 | L95: 5049 | M95: 5049 | N95: 5049 | O95: 4999 | P95: 4899 | Q95: 4699 | R95: 4999 | S95: 4899 | T95: 4699 | U95: 4699 | V95: 4699 | W95: 4699 | X95: 4599 | Y95: 3999 | Z95: 3999 | AA95: 3999 | AB95: 5049 | AC95: 5049 | AD95: 5049 | AE95: 4999 | AF95: 4999 | AG95: 4999 | AH95: 4999 | AI95: 4699 | AJ95: 4699 | AK95: 4699 | AL95: 3999 | AM95: 31.12.9999
B96: SMARTHOME | C96: 4016298 | D96: ROBÔ ASPIRADOR POSITIVO WI-FI | E96: ROBÔ ASPIRADOR POSITIVO WI-FI | F96: 649 | G96: 649 | H96: 649 | I96: 649 | J96: 599 | K96: 599 | L96: 599 | M96: 599 | N96: 599 | O96: 549 | P96: 449 | Q96: 349 | R96: 549 | S96: 449 | T96: 349 | U96: 349 | V96: 349 | W96: 349 | X96: 349 | Y96: 349 | Z96: 349 | AA96: 349 | AM96: 31.12.9999
B97: GADGETS | C97: 4015924 | D97: SAMSUNG GALAXY FIT3 | E97: SAMSUNG GALAXY FIT3-ROSE | F97: 299 | G97: 399 | H97: 299 | I97: 299 | J97: 249 | K97: 249 | L97: 249 | M97: 249 | N97: 249 | O97: 199 | P97: 199 | Q97: 199 | R97: 199 | S97: 199 | T97: 199 | U97: 199 | V97: 199 | W97: 199 | X97: 199 | Y97: 199 | Z97: 199 | AA97: 199 | AB97: 249 | AC97: 249 | AD97: 249 | AE97: 199 | AF97: 199 | AG97: 199 | AH97: 199 | AI97: 199 | AJ97: 199 | AK97: 199 | AL97: 199 | AM97: 31.12.9999
B98: GADGETS | C98: 4015922 | D98: SAMSUNG GALAXY FIT3 | E98: SAMSUNG GALAXY FIT3-GRAFITE | F98: 299 | G98: 399 | H98: 299 | I98: 299 | J98: 249 | K98: 249 | L98: 249 | M98: 249 | N98: 249 | O98: 199 | P98: 199 | Q98: 199 | R98: 199 | S98: 199 | T98: 199 | U98: 199 | V98: 199 | W98: 199 | X98: 199 | Y98: 199 | Z98: 199 | AA98: 199 | AB98: 249 | AC98: 249 | AD98: 249 | AE98: 199 | AF98: 199 | AG98: 199 | AH98: 199 | AI98: 199 | AJ98: 199 | AK98: 199 | AL98: 199 | AM98: 31.12.9999
B99: GADGETS | C99: 4017419 | D99: SAMSUNG GALAXY FIT3 2025 | E99: SAMSUNG GALAXY FIT3 2025-GRAFITE | F99: 299 | G99: 399 | H99: 299 | I99: 299 | J99: 249 | K99: 249 | L99: 249 | M99: 249 | N99: 249 | O99: 199 | P99: 199 | Q99: 199 | R99: 199 | S99: 199 | T99: 199 | U99: 199 | V99: 199 | W99: 199 | X99: 199 | Y99: 199 | Z99: 199 | AA99: 199 | AB99: 249 | AC99: 249 | AD99: 249 | AE99: 199 | AF99: 199 | AG99: 199 | AH99: 199 | AI99: 199 | AJ99: 199 | AK99: 199 | AL99: 199 | AM99: 31.12.9999
B100: GADGETS | C100: 4017414 | D100: SAMSUNG GALAXY FIT3 2025 | E100: SAMSUNG GALAXY FIT3 2025-ROSE | F100: 299 | G100: 399 | H100: 299 | I100: 299 | J100: 249 | K100: 249 | L100: 249 | M100: 249 | N100: 249 | O100: 199 | P100: 199 | Q100: 199 | R100: 199 | S100: 199 | T100: 199 | U100: 199 | V100: 199 | W100: 199 | X100: 199 | Y100: 199 | Z100: 199 | AA100: 199 | AB100: 249 | AC100: 249 | AD100: 249 | AE100: 199 | AF100: 199 | AG100: 199 | AH100: 199 | AI100: 199 | AJ100: 199 | AK100: 199 | AL100: 199 | AM100: 31.12.9999
B101: GADGETS | C101: 4015728 | D101: SAMSUNG GALAXY SMARTTAG 2 | E101: TRACKER SAMSUNG GALAXY SMARTTAG 2-PRETO | F101: 199 | G101: 199 | AM101: 31.12.9999
...

Sheet TRADE IN
A1: OFERTAS VÁLIDAS APENAS PARA PLANOS CONSUMER
B4: Inclusão de Preços
B5: Alteração de Preços
A7: Preços Elegíveis a Price Back
A8: Preços Elegíveis a Price Oferta
A9: CANAL: | B9: REVENDAS
C11: DATA INÍCIO: | D11: =REV!D11 -> 46311 | J11: COM FIDELIZAÇÃO - GROSS / MIGRAÇÃO / UPGRADE / PORTABILIDADE / BASE SEM MOVIMENTAÇÃO | AM11: TIM FIXO | AP11: TIM CASA
A12: Regra Reembolso Pós Fidelizado | B12: CATEGORIA MKT | C12: CÓDIGO | D12: DESCRIÇÃO COMERCIAL | E12: DESCRIÇÃO SAP | F12: BOOST TRADE IN | G12: PREÇO BASE FATURAMENTO RETAIL | H12: CONTROLE NÃO FIDELIZADO - TODOS (Fatura / Express) | I12: PÓS PAGO NÃO FIDELIZADO - VIDE ABA DE REGRAS | J12: TIM CONTROLE | K12: TIM CONTROLE PLUS | L12: TIM CONTROLE PREMIUM | M12: TIM CONTROLE SMART | N12: TIM CONTROLE REDES SOCIAIS | O12: TIM BLACK | P12: TIM BLACK PLUS | Q12: TIM BLACK PREMIUM | R12: TIM BLACK A (15GB) | S12: TIM BLACK B (20GB) | T12: TIM BLACK C (25GB) | U12: TIM BLACK C ULTRA | V12: TIM BLACK FAMÍLIA | W12: TIM BLACK FAMÍLIA A ONE | X12: TIM BLACK FAMÍLIA PLUS | Y12: TIM BLACK FAMÍLIA PREMIUM | Z12: TIM BLACK FAMÍLIA C ONE | AA12: TIM BLACK FAMÍLIA VIP | AB12: TIM Fibra 400M 24 | AC12: TIM Fibra 500M 24 - 2 | AD12: TIM Fibra 600M 24 - 2 | AE12: TIM Fibra 600M P 24 - 2 | AF12: TIM Fibra 600M M 24 - 2 | AG12: TIM Ultrafibra 800M YT26 | AH12: TIM Fibra 600M GP 25 | AI12: TIM Fibra 1GB 24 | AJ12: TIM Fibra 1GB P 24 | AK12: TIM Fibra 1GB M 24 | AL12: TIM Fibra 2GB 24 | AM12: TIM FIXO LOCAL TOTAL PLUS (Plano Fidelizado) | AN12: TIM FIXO BRASIL TOTAL PLUS (Plano Fidelizado) | AO12: TIM FIXO TOTAL LDI PLUS (Plano Fidelizado) | AP12: TIM LIVE INTERNET 30GB (sem fidelização) | AQ12: TIM LIVE INTERNET 50GB (sem fidelização) | AR12: TIM LIVE INTERNET 80GB (sem fidelização) | AS12: TIM LIVE INTERNET 30GB PLUS | AT12: TIM LIVE INTERNET 50GB PLUS | AU12: TIM LIVE INTERNET 80GB PLUS | AW12: DATA FIM DA OFERTA | AX12: TECNOLOGIA
A13: Price Oferta | B13: 21X | C13: 4014380 | D13: APPLE IPHONE 12 64GB | E13: APPLE IPHONE 12 64GB-PRETO NAC | J13: =IF(VLOOKUP($C13,REV!$C:$AA,8,0)-'TRADE IN'!$F13=0,"",(VLOOKUP($C13,REV!$C:$AA,8,0)-'TRADE IN'!$F13)) -> 999 | K13: =IF(VLOOKUP($C13,REV!$C:$AA,9,0)-'TRADE IN'!$F13=0,"",(VLOOKUP($C13,REV!$C:$AA,9,0)-'TRADE IN'!$F13)) -> 999 | L13: =IF(VLOOKUP($C13,REV!$C:$AA,10,0)-'TRADE IN'!$F13=0,"",(VLOOKUP($C13,REV!$C:$AA,10,0)-'TRADE IN'!$F13)) -> 999 | M13: =IF(VLOOKUP($C13,REV!$C:$AA,11,0)-'TRADE IN'!$F13=0,"",(VLOOKUP($C13,REV!$C:$AA,11,0)-'TRADE IN'!$F13)) -> 999 | N13: =IF(VLOOKUP($C13,REV!$C:$AA,12,0)-'TRADE IN'!$F13=0,"",(VLOOKUP($C13,REV!$C:$AA,12,0)-'TRADE IN'!$F13)) -> 999 | O13: =IF(VLOOKUP($C13,REV!$C:$AA,13,0)-'TRADE IN'!$F13=0,"",(VLOOKUP($C13,REV!$C:$AA,13,0)-'TRADE IN'!$F13)) -> 999 | P13: =IF(VLOOKUP($C13,REV!$C:$AA,14,0)-'TRADE IN'!$F13=0,"",(VLOOKUP($C13,REV!$C:$AA,14,0)-'TRADE IN'!$F13)) -> 999 | Q13: =IF(VLOOKUP($C13,REV!$C:$AA,15,0)-'TRADE IN'!$F13=0,"",(VLOOKUP($C13,REV!$C:$AA,15,0)-'TRADE IN'!$F13)) -> 999 | R13: =IF(VLOOKUP($C13,REV!$C:$AA,16,0)-'TRADE IN'!$F13=0,"",(VLOOKUP($C13,REV!$C:$AA,16,0)-'TRADE IN'!$F13)) -> 999 | S13: =IF(VLOOKUP($C13,REV!$C:$AA,17,0)-'TRADE IN'!$F13=0,"",(VLOOKUP($C13,REV!$C:$AA,17,0)-'TRADE IN'!$F13)) -> 999 | T13: =IF(VLOOKUP($C13,REV!$C:$AA,18,0)-'TRADE IN'!$F13=0,"",(VLOOKUP($C13,REV!$C:$AA,18,0)-'TRADE IN'!$F13)) -> 999 | U13: =IF(VLOOKUP($C13,REV!$C:$AA,19,0)-'TRADE IN'!$F13=0,"",(VLOOKUP($C13,REV!$C:$AA,19,0)-'TRADE IN'!$F13)) -> 999 | V13: =IF(VLOOKUP($C13,REV!$C:$AA,20,0)-'TRADE IN'!$F13=0,"",(VLOOKUP($C13,REV!$C:$AA,20,0)-'TRADE IN'!$F13)) -> 999 | W13: =IF(VLOOKUP($C13,REV!$C:$AA,21,0)-'TRADE IN'!$F13=0,"",(VLOOKUP($C13,REV!$C:$AA,21,0)-'TRADE IN'!$F13)) -> 999 | X13: =IF(VLOOKUP($C13,REV!$C:$AA,22,0)-'TRADE IN'!$F13=0,"",(VLOOKUP($C13,REV!$C:$AA,22,0)-'TRADE IN'!$F13)) -> 999 | Y13: =IF(VLOOKUP($C13,REV!$C:$AA,23,0)-'TRADE IN'!$F13=0,"",(VLOOKUP($C13,REV!$C:$AA,23,0)-'TRADE IN'!$F13)) -> 999 | Z13: =IF(VLOOKUP($C13,REV!$C:$AA,24,0)-'TRADE IN'!$F13=0,"",(VLOOKUP($C13,REV!$C:$AA,24,0)-'TRADE IN'!$F13)) -> 999 | AA13: =IF(VLOOKUP($C13,REV!$C:$AA,25,0)-'TRADE IN'!$F13=0,"",(VLOOKUP($C13,REV!$C:$AA,25,0)-'TRADE IN'!$F13)) -> 999 | AW13: =REV!AW13 -> 03.11.2026 | AX13: =VLOOKUP(C13,REV!C:AX,48,0) -> 5G
A14: Price Oferta | B14: 21X | C14: 4014382 | D14: APPLE IPHONE 12 64GB | E14: APPLE IPHONE 12 64GB-BRANCO NAC | J14: =IF(VLOOKUP($C14,REV!$C:$AA,8,0)-'TRADE IN'!$F14=0,"",(VLOOKUP($C14,REV!$C:$AA,8,0)-'TRADE IN'!$F14)) -> 999 | K14: =IF(VLOOKUP($C14,REV!$C:$AA,9,0)-'TRADE IN'!$F14=0,"",(VLOOKUP($C14,REV!$C:$AA,9,0)-'TRADE IN'!$F14)) -> 999 | L14: =IF(VLOOKUP($C14,REV!$C:$AA,10,0)-'TRADE IN'!$F14=0,"",(VLOOKUP($C14,REV!$C:$AA,10,0)-'TRADE IN'!$F14)) -> 999 | M14: =IF(VLOOKUP($C14,REV!$C:$AA,11,0)-'TRADE IN'!$F14=0,"",(VLOOKUP($C14,REV!$C:$AA,11,0)-'TRADE IN'!$F14)) -> 999 | N14: =IF(VLOOKUP($C14,REV!$C:$AA,12,0)-'TRADE IN'!$F14=0,"",(VLOOKUP($C14,REV!$C:$AA,12,0)-'TRADE IN'!$F14)) -> 999 | O14: =IF(VLOOKUP($C14,REV!$C:$AA,13,0)-'TRADE IN'!$F14=0,"",(VLOOKUP($C14,REV!$C:$AA,13,0)-'TRADE IN'!$F14)) -> 999 | P14: =IF(VLOOKUP($C14,REV!$C:$AA,14,0)-'TRADE IN'!$F14=0,"",(VLOOKUP($C14,REV!$C:$AA,14,0)-'TRADE IN'!$F14)) -> 999 | Q14: =IF(VLOOKUP($C14,REV!$C:$AA,15,0)-'TRADE IN'!$F14=0,"",(VLOOKUP($C14,REV!$C:$AA,15,0)-'TRADE IN'!$F14)) -> 999 | R14: =IF(VLOOKUP($C14,REV!$C:$AA,16,0)-'TRADE IN'!$F14=0,"",(VLOOKUP($C14,REV!$C:$AA,16,0)-'TRADE IN'!$F14)) -> 999 | S14: =IF(VLOOKUP($C14,REV!$C:$AA,17,0)-'TRADE IN'!$F14=0,"",(VLOOKUP($C14,REV!$C:$AA,17,0)-'TRADE IN'!$F14)) -> 999 | T14: =IF(VLOOKUP($C14,REV!$C:$AA,18,0)-'TRADE IN'!$F14=0,"",(VLOOKUP($C14,REV!$C:$AA,18,0)-'TRADE IN'!$F14)) -> 999 | U14: =IF(VLOOKUP($C14,REV!$C:$AA,19,0)-'TRADE IN'!$F14=0,"",(VLOOKUP($C14,REV!$C:$AA,19,0)-'TRADE IN'!$F14)) -> 999 | V14: =IF(VLOOKUP($C14,REV!$C:$AA,20,0)-'TRADE IN'!$F14=0,"",(VLOOKUP($C14,REV!$C:$AA,20,0)-'TRADE IN'!$F14)) -> 999 | W14: =IF(VLOOKUP($C14,REV!$C:$AA,21,0)-'TRADE IN'!$F14=0,"",(VLOOKUP($C14,REV!$C:$AA,21,0)-'TRADE IN'!$F14)) -> 999 | X14: =IF(VLOOKUP($C14,REV!$C:$AA,22,0)-'TRADE IN'!$F14=0,"",(VLOOKUP($C14,REV!$C:$AA,22,0)-'TRADE IN'!$F14)) -> 999 | Y14: =IF(VLOOKUP($C14,REV!$C:$AA,23,0)-'TRADE IN'!$F14=0,"",(VLOOKUP($C14,REV!$C:$AA,23,0)-'TRADE IN'!$F14)) -> 999 | Z14: =IF(VLOOKUP($C14,REV!$C:$AA,24,0)-'TRADE IN'!$F14=0,"",(VLOOKUP($C14,REV!$C:$AA,24,0)-'TRADE IN'!$F14)) -> 999 | AA14: =IF(VLOOKUP($C14,REV!$C:$AA,25,0)-'TRADE IN'!$F14=0,"",(VLOOKUP($C14,REV!$C:$AA,25,0)-'TRADE IN'!$F14)) -> 999 | AW14: =REV!AW14 -> 03.11.2026 | AX14: =VLOOKUP(C14,REV!C:AX,48,0) -> 5G
A15: Price Oferta | B15: 21X | C15: 4014391 | D15: APPLE IPHONE 12 128GB | E15: APPLE IPHONE 12 128GB-PRETO NAC | J15: =IF(VLOOKUP($C15,REV!$C:$AA,8,0)-'TRADE IN'!$F15=0,"",(VLOOKUP($C15,REV!$C:$AA,8,0)-'TRADE IN'!$F15)) -> 999 | K15: =IF(VLOOKUP($C15,REV!$C:$AA,9,0)-'TRADE IN'!$F15=0,"",(VLOOKUP($C15,REV!$C:$AA,9,0)-'TRADE IN'!$F15)) -> 999 | L15: =IF(VLOOKUP($C15,REV!$C:$AA,10,0)-'TRADE IN'!$F15=0,"",(VLOOKUP($C15,REV!$C:$AA,10,0)-'TRADE IN'!$F15)) -> 999 | M15: =IF(VLOOKUP($C15,REV!$C:$AA,11,0)-'TRADE IN'!$F15=0,"",(VLOOKUP($C15,REV!$C:$AA,11,0)-'TRADE IN'!$F15)) -> 999 | N15: =IF(VLOOKUP($C15,REV!$C:$AA,12,0)-'TRADE IN'!$F15=0,"",(VLOOKUP($C15,REV!$C:$AA,12,0)-'TRADE IN'!$F15)) -> 999 | O15: =IF(VLOOKUP($C15,REV!$C:$AA,13,0)-'TRADE IN'!$F15=0,"",(VLOOKUP($C15,REV!$C:$AA,13,0)-'TRADE IN'!$F15)) -> 999 | P15: =IF(VLOOKUP($C15,REV!$C:$AA,14,0)-'TRADE IN'!$F15=0,"",(VLOOKUP($C15,REV!$C:$AA,14,0)-'TRADE IN'!$F15)) -> 999 | Q15: =IF(VLOOKUP($C15,REV!$C:$AA,15,0)-'TRADE IN'!$F15=0,"",(VLOOKUP($C15,REV!$C:$AA,15,0)-'TRADE IN'!$F15)) -> 999 | R15: =IF(VLOOKUP($C15,REV!$C:$AA,16,0)-'TRADE IN'!$F15=0,"",(VLOOKUP($C15,REV!$C:$AA,16,0)-'TRADE IN'!$F15)) -> 999 | S15: =IF(VLOOKUP($C15,REV!$C:$AA,17,0)-'TRADE IN'!$F15=0,"",(VLOOKUP($C15,REV!$C:$AA,17,0)-'TRADE IN'!$F15)) -> 999 | T15: =IF(VLOOKUP($C15,REV!$C:$AA,18,0)-'TRADE IN'!$F15=0,"",(VLOOKUP($C15,REV!$C:$AA,18,0)-'TRADE IN'!$F15)) -> 999 | U15: =IF(VLOOKUP($C15,REV!$C:$AA,19,0)-'TRADE IN'!$F15=0,"",(VLOOKUP($C15,REV!$C:$AA,19,0)-'TRADE IN'!$F15)) -> 999 | V15: =IF(VLOOKUP($C15,REV!$C:$AA,20,0)-'TRADE IN'!$F15=0,"",(VLOOKUP($C15,REV!$C:$AA,20,0)-'TRADE IN'!$F15)) -> 999 | W15: =IF(VLOOKUP($C15,REV!$C:$AA,21,0)-'TRADE IN'!$F15=0,"",(VLOOKUP($C15,REV!$C:$AA,21,0)-'TRADE IN'!$F15)) -> 999 | X15: =IF(VLOOKUP($C15,REV!$C:$AA,22,0)-'TRADE IN'!$F15=0,"",(VLOOKUP($C15,REV!$C:$AA,22,0)-'TRADE IN'!$F15)) -> 999 | Y15: =IF(VLOOKUP($C15,REV!$C:$AA,23,0)-'TRADE IN'!$F15=0,"",(VLOOKUP($C15,REV!$C:$AA,23,0)-'TRADE IN'!$F15)) -> 999 | Z15: =IF(VLOOKUP($C15,REV!$C:$AA,24,0)-'TRADE IN'!$F15=0,"",(VLOOKUP($C15,REV!$C:$AA,24,0)-'TRADE IN'!$F15)) -> 999 | AA15: =IF(VLOOKUP($C15,REV!$C:$AA,25,0)-'TRADE IN'!$F15=0,"",(VLOOKUP($C15,REV!$C:$AA,25,0)-'TRADE IN'!$F15)) -> 999 | AW15: =REV!AW15 -> 03.11.2026 | AX15: =VLOOKUP(C15,REV!C:AX,48,0) -> 5G
A16: Price Oferta | B16: 21X | C16: 4014723 | D16: APPLE IPHONE 13 128GB | E16: APPLE IPHONE 13 128GB-PRETO NAC | J16: =IF(VLOOKUP($C16,REV!$C:$AA,8,0)-'TRADE IN'!$F16=0,"",(VLOOKUP($C16,REV!$C:$AA,8,0)-'TRADE IN'!$F16)) -> 3599 | K16: =IF(VLOOKUP($C16,REV!$C:$AA,9,0)-'TRADE IN'!$F16=0,"",(VLOOKUP($C16,REV!$C:$AA,9,0)-'TRADE IN'!$F16)) -> 3499 | L16: =IF(VLOOKUP($C16,REV!$C:$AA,10,0)-'TRADE IN'!$F16=0,"",(VLOOKUP($C16,REV!$C:$AA,10,0)-'TRADE IN'!$F16)) -> 3499 | M16: =IF(VLOOKUP($C16,REV!$C:$AA,11,0)-'TRADE IN'!$F16=0,"",(VLOOKUP($C16,REV!$C:$AA,11,0)-'TRADE IN'!$F16)) -> 3599 | N16: =IF(VLOOKUP($C16,REV!$C:$AA,12,0)-'TRADE IN'!$F16=0,"",(VLOOKUP($C16,REV!$C:$AA,12,0)-'TRADE IN'!$F16)) -> 3499 | O16: =IF(VLOOKUP($C16,REV!$C:$AA,13,0)-'TRADE IN'!$F16=0,"",(VLOOKUP($C16,REV!$C:$AA,13,0)-'TRADE IN'!$F16)) -> 3099 | P16: =IF(VLOOKUP($C16,REV!$C:$AA,14,0)-'TRADE IN'!$F16=0,"",(VLOOKUP($C16,REV!$C:$AA,14,0)-'TRADE IN'!$F16)) -> 2999 | Q16: =IF(VLOOKUP($C16,REV!$C:$AA,15,0)-'TRADE IN'!$F16=0,"",(VLOOKUP($C16,REV!$C:$AA,15,0)-'TRADE IN'!$F16)) -> 2499 | R16: =IF(VLOOKUP($C16,REV!$C:$AA,16,0)-'TRADE IN'!$F16=0,"",(VLOOKUP($C16,REV!$C:$AA,16,0)-'TRADE IN'!$F16)) -> 3099 | S16: =IF(VLOOKUP($C16,REV!$C:$AA,17,0)-'TRADE IN'!$F16=0,"",(VLOOKUP($C16,REV!$C:$AA,17,0)-'TRADE IN'!$F16)) -> 2999 | T16: =IF(VLOOKUP($C16,REV!$C:$AA,18,0)-'TRADE IN'!$F16=0,"",(VLOOKUP($C16,REV!$C:$AA,18,0)-'TRADE IN'!$F16)) -> 2499 | U16: =IF(VLOOKUP($C16,REV!$C:$AA,19,0)-'TRADE IN'!$F16=0,"",(VLOOKUP($C16,REV!$C:$AA,19,0)-'TRADE IN'!$F16)) -> 2499 | V16: =IF(VLOOKUP($C16,REV!$C:$AA,20,0)-'TRADE IN'!$F16=0,"",(VLOOKUP($C16,REV!$C:$AA,20,0)-'TRADE IN'!$F16)) -> 2499 | W16: =IF(VLOOKUP($C16,REV!$C:$AA,21,0)-'TRADE IN'!$F16=0,"",(VLOOKUP($C16,REV!$C:$AA,21,0)-'TRADE IN'!$F16)) -> 2499 | X16: =IF(VLOOKUP($C16,REV!$C:$AA,22,0)-'TRADE IN'!$F16=0,"",(VLOOKUP($C16,REV!$C:$AA,22,0)-'TRADE IN'!$F16)) -> 2299 | Y16: =IF(VLOOKUP($C16,REV!$C:$AA,23,0)-'TRADE IN'!$F16=0,"",(VLOOKUP($C16,REV!$C:$AA,23,0)-'TRADE IN'!$F16)) -> 1999 | Z16: =IF(VLOOKUP($C16,REV!$C:$AA,24,0)-'TRADE IN'!$F16=0,"",(VLOOKUP($C16,REV!$C:$AA,24,0)-'TRADE IN'!$F16)) -> 1999 | AA16: =IF(VLOOKUP($C16,REV!$C:$AA,25,0)-'TRADE IN'!$F16=0,"",(VLOOKUP($C16,REV!$C:$AA,25,0)-'TRADE IN'!$F16)) -> 1999 | AW16: =REV!AW16 -> 03.11.2026 | AX16: =VLOOKUP(C16,REV!C:AX,48,0) -> 5G
A17: Price Oferta | B17: 21X | C17: 4014594 | D17: APPLE IPHONE 13 256GB | E17: APPLE IPHONE 13 256GB-PRETO | J17: =IF(VLOOKUP($C17,REV!$C:$AA,8,0)-'TRADE IN'!$F17=0,"",(VLOOKUP($C17,REV!$C:$AA,8,0)-'TRADE IN'!$F17)) -> 3799 | K17: =IF(VLOOKUP($C17,REV!$C:$AA,9,0)-'TRADE IN'!$F17=0,"",(VLOOKUP($C17,REV!$C:$AA,9,0)-'TRADE IN'!$F17)) -> 3799 | L17: =IF(VLOOKUP($C17,REV!$C:$AA,10,0)-'TRADE IN'!$F17=0,"",(VLOOKUP($C17,REV!$C:$AA,10,0)-'TRADE IN'!$F17)) -> 3799 | M17: =IF(VLOOKUP($C17,REV!$C:$AA,11,0)-'TRADE IN'!$F17=0,"",(VLOOKUP($C17,REV!$C:$AA,11,0)-'TRADE IN'!$F17)) -> 3799 | N17: =IF(VLOOKUP($C17,REV!$C:$AA,12,0)-'TRADE IN'!$F17=0,"",(VLOOKUP($C17,REV!$C:$AA,12,0)-'TRADE IN'!$F17)) -> 3799 | O17: =IF(VLOOKUP($C17,REV!$C:$AA,13,0)-'TRADE IN'!$F17=0,"",(VLOOKUP($C17,REV!$C:$AA,13,0)-'TRADE IN'!$F17)) -> 3599 | P17: =IF(VLOOKUP($C17,REV!$C:$AA,14,0)-'TRADE IN'!$F17=0,"",(VLOOKUP($C17,REV!$C:$AA,14,0)-'TRADE IN'!$F17)) -> 3499 | Q17: =IF(VLOOKUP($C17,REV!$C:$AA,15,0)-'TRADE IN'!$F17=0,"",(VLOOKUP($C17,REV!$C:$AA,15,0)-'TRADE IN'!$F17)) -> 2999 | R17: =IF(VLOOKUP($C17,REV!$C:$AA,16,0)-'TRADE IN'!$F17=0,"",(VLOOKUP($C17,REV!$C:$AA,16,0)-'TRADE IN'!$F17)) -> 3599 | S17: =IF(VLOOKUP($C17,REV!$C:$AA,17,0)-'TRADE IN'!$F17=0,"",(VLOOKUP($C17,REV!$C:$AA,17,0)-'TRADE IN'!$F17)) -> 3499 | T17: =IF(VLOOKUP($C17,REV!$C:$AA,18,0)-'TRADE IN'!$F17=0,"",(VLOOKUP($C17,REV!$C:$AA,18,0)-'TRADE IN'!$F17)) -> 2999 | U17: =IF(VLOOKUP($C17,REV!$C:$AA,19,0)-'TRADE IN'!$F17=0,"",(VLOOKUP($C17,REV!$C:$AA,19,0)-'TRADE IN'!$F17)) -> 2999 | V17: =IF(VLOOKUP($C17,REV!$C:$AA,20,0)-'TRADE IN'!$F17=0,"",(VLOOKUP($C17,REV!$C:$AA,20,0)-'TRADE IN'!$F17)) -> 2999 | W17: =IF(VLOOKUP($C17,REV!$C:$AA,21,0)-'TRADE IN'!$F17=0,"",(VLOOKUP($C17,REV!$C:$AA,21,0)-'TRADE IN'!$F17)) -> 2999 | X17: =IF(VLOOKUP($C17,REV!$C:$AA,22,0)-'TRADE IN'!$F17=0,"",(VLOOKUP($C17,REV!$C:$AA,22,0)-'TRADE IN'!$F17)) -> 2799 | Y17: =IF(VLOOKUP($C17,REV!$C:$AA,23,0)-'TRADE IN'!$F17=0,"",(VLOOKUP($C17,REV!$C:$AA,23,0)-'TRADE IN'!$F17)) -> 2499 | Z17: =IF(VLOOKUP($C17,REV!$C:$AA,24,0)-'TRADE IN'!$F17=0,"",(VLOOKUP($C17,REV!$C:$AA,24,0)-'TRADE IN'!$F17)) -> 2499 | AA17: =IF(VLOOKUP($C17,REV!$C:$AA,25,0)-'TRADE IN'!$F17=0,"",(VLOOKUP($C17,REV!$C:$AA,25,0)-'TRADE IN'!$F17)) -> 2499 | AW17: =REV!AW17 -> 03.11.2026 | AX17: =VLOOKUP(C17,REV!C:AX,48,0) -> 5G
A18: Price Oferta | B18: 21X | C18: 4014837 | D18: APPLE IPHONE 13 256GB | E18: APPLE IPHONE 13 256GB-AZUL NAC | J18: =IF(VLOOKUP($C18,REV!$C:$AA,8,0)-'TRADE IN'!$F18=0,"",(VLOOKUP($C18,REV!$C:$AA,8,0)-'TRADE IN'!$F18)) -> 3799 | K18: =IF(VLOOKUP($C18,REV!$C:$AA,9,0)-'TRADE IN'!$F18=0,"",(VLOOKUP($C18,REV!$C:$AA,9,0)-'TRADE IN'!$F18)) -> 3799 | L18: =IF(VLOOKUP($C18,REV!$C:$AA,10,0)-'TRADE IN'!$F18=0,"",(VLOOKUP($C18,REV!$C:$AA,10,0)-'TRADE IN'!$F18)) -> 3799 | M18: =IF(VLOOKUP($C18,REV!$C:$AA,11,0)-'TRADE IN'!$F18=0,"",(VLOOKUP($C18,REV!$C:$AA,11,0)-'TRADE IN'!$F18)) -> 3799 | N18: =IF(VLOOKUP($C18,REV!$C:$AA,12,0)-'TRADE IN'!$F18=0,"",(VLOOKUP($C18,REV!$C:$AA,12,0)-'TRADE IN'!$F18)) -> 3799 | O18: =IF(VLOOKUP($C18,REV!$C:$AA,13,0)-'TRADE IN'!$F18=0,"",(VLOOKUP($C18,REV!$C:$AA,13,0)-'TRADE IN'!$F18)) -> 3599 | P18: =IF(VLOOKUP($C18,REV!$C:$AA,14,0)-'TRADE IN'!$F18=0,"",(VLOOKUP($C18,REV!$C:$AA,14,0)-'TRADE IN'!$F18)) -> 3499 | Q18: =IF(VLOOKUP($C18,REV!$C:$AA,15,0)-'TRADE IN'!$F18=0,"",(VLOOKUP($C18,REV!$C:$AA,15,0)-'TRADE IN'!$F18)) -> 2999 | R18: =IF(VLOOKUP($C18,REV!$C:$AA,16,0)-'TRADE IN'!$F18=0,"",(VLOOKUP($C18,REV!$C:$AA,16,0)-'TRADE IN'!$F18)) -> 3599 | S18: =IF(VLOOKUP($C18,REV!$C:$AA,17,0)-'TRADE IN'!$F18=0,"",(VLOOKUP($C18,REV!$C:$AA,17,0)-'TRADE IN'!$F18)) -> 3499 | T18: =IF(VLOOKUP($C18,REV!$C:$AA,18,0)-'TRADE IN'!$F18=0,"",(VLOOKUP($C18,REV!$C:$AA,18,0)-'TRADE IN'!$F18)) -> 2999 | U18: =IF(VLOOKUP($C18,REV!$C:$AA,19,0)-'TRADE IN'!$F18=0,"",(VLOOKUP($C18,REV!$C:$AA,19,0)-'TRADE IN'!$F18)) -> 2999 | V18: =IF(VLOOKUP($C18,REV!$C:$AA,20,0)-'TRADE IN'!$F18=0,"",(VLOOKUP($C18,REV!$C:$AA,20,0)-'TRADE IN'!$F18)) -> 2999 | W18: =IF(VLOOKUP($C18,REV!$C:$AA,21,0)-'TRADE IN'!$F18=0,"",(VLOOKUP($C18,REV!$C:$AA,21,0)-'TRADE IN'!$F18)) -> 2999 | X18: =IF(VLOOKUP($C18,REV!$C:$AA,22,0)-'TRADE IN'!$F18=0,"",(VLOOKUP($C18,REV!$C:$AA,22,0)-'TRADE IN'!$F18)) -> 2799 | Y18: =IF(VLOOKUP($C18,REV!$C:$AA,23,0)-'TRADE IN'!$F18=0,"",(VLOOKUP($C18,REV!$C:$AA,23,0)-'TRADE IN'!$F18)) -> 2499 | Z18: =IF(VLOOKUP($C18,REV!$C:$AA,24,0)-'TRADE IN'!$F18=0,"",(VLOOKUP($C18,REV!$C:$AA,24,0)-'TRADE IN'!$F18)) -> 2499 | AA18: =IF(VLOOKUP($C18,REV!$C:$AA,25,0)-'TRADE IN'!$F18=0,"",(VLOOKUP($C18,REV!$C:$AA,25,0)-'TRADE IN'!$F18)) -> 2499 | AW18: =REV!AW18 -> 03.11.2026 | AX18: =VLOOKUP(C18,REV!C:AX,48,0) -> 5G
A19: Price Oferta | B19: 21X | C19: 4014833 | D19: APPLE IPHONE 13 256GB | E19: APPLE IPHONE 13 256GB-PRETO NAC | J19: =IF(VLOOKUP($C19,REV!$C:$AA,8,0)-'TRADE IN'!$F19=0,"",(VLOOKUP($C19,REV!$C:$AA,8,0)-'TRADE IN'!$F19)) -> 3799 | K19: =IF(VLOOKUP($C19,REV!$C:$AA,9,0)-'TRADE IN'!$F19=0,"",(VLOOKUP($C19,REV!$C:$AA,9,0)-'TRADE IN'!$F19)) -> 3799 | L19: =IF(VLOOKUP($C19,REV!$C:$AA,10,0)-'TRADE IN'!$F19=0,"",(VLOOKUP($C19,REV!$C:$AA,10,0)-'TRADE IN'!$F19)) -> 3799 | M19: =IF(VLOOKUP($C19,REV!$C:$AA,11,0)-'TRADE IN'!$F19=0,"",(VLOOKUP($C19,REV!$C:$AA,11,0)-'TRADE IN'!$F19)) -> 3799 | N19: =IF(VLOOKUP($C19,REV!$C:$AA,12,0)-'TRADE IN'!$F19=0,"",(VLOOKUP($C19,REV!$C:$AA,12,0)-'TRADE IN'!$F19)) -> 3799 | O19: =IF(VLOOKUP($C19,REV!$C:$AA,13,0)-'TRADE IN'!$F19=0,"",(VLOOKUP($C19,REV!$C:$AA,13,0)-'TRADE IN'!$F19)) -> 3599 | P19: =IF(VLOOKUP($C19,REV!$C:$AA,14,0)-'TRADE IN'!$F19=0,"",(VLOOKUP($C19,REV!$C:$AA,14,0)-'TRADE IN'!$F19)) -> 3499 | Q19: =IF(VLOOKUP($C19,REV!$C:$AA,15,0)-'TRADE IN'!$F19=0,"",(VLOOKUP($C19,REV!$C:$AA,15,0)-'TRADE IN'!$F19)) -> 2999 | R19: =IF(VLOOKUP($C19,REV!$C:$AA,16,0)-'TRADE IN'!$F19=0,"",(VLOOKUP($C19,REV!$C:$AA,16,0)-'TRADE IN'!$F19)) -> 3599 | S19: =IF(VLOOKUP($C19,REV!$C:$AA,17,0)-'TRADE IN'!$F19=0,"",(VLOOKUP($C19,REV!$C:$AA,17,0)-'TRADE IN'!$F19)) -> 3499 | T19: =IF(VLOOKUP($C19,REV!$C:$AA,18,0)-'TRADE IN'!$F19=0,"",(VLOOKUP($C19,REV!$C:$AA,18,0)-'TRADE IN'!$F19)) -> 2999 | U19: =IF(VLOOKUP($C19,REV!$C:$AA,19,0)-'TRADE IN'!$F19=0,"",(VLOOKUP($C19,REV!$C:$AA,19,0)-'TRADE IN'!$F19)) -> 2999 | V19: =IF(VLOOKUP($C19,REV!$C:$AA,20,0)-'TRADE IN'!$F19=0,"",(VLOOKUP($C19,REV!$C:$AA,20,0)-'TRADE IN'!$F19)) -> 2999 | W19: =IF(VLOOKUP($C19,REV!$C:$AA,21,0)-'TRADE IN'!$F19=0,"",(VLOOKUP($C19,REV!$C:$AA,21,0)-'TRADE IN'!$F19)) -> 2999 | X19: =IF(VLOOKUP($C19,REV!$C:$AA,22,0)-'TRADE IN'!$F19=0,"",(VLOOKUP($C19,REV!$C:$AA,22,0)-'TRADE IN'!$F19)) -> 2799 | Y19: =IF(VLOOKUP($C19,REV!$C:$AA,23,0)-'TRADE IN'!$F19=0,"",(VLOOKUP($C19,REV!$C:$AA,23,0)-'TRADE IN'!$F19)) -> 2499 | Z19: =IF(VLOOKUP($C19,REV!$C:$AA,24,0)-'TRADE IN'!$F19=0,"",(VLOOKUP($C19,REV!$C:$AA,24,0)-'TRADE IN'!$F19)) -> 2499 | AA19: =IF(VLOOKUP($C19,REV!$C:$AA,25,0)-'TRADE IN'!$F19=0,"",(VLOOKUP($C19,REV!$C:$AA,25,0)-'TRADE IN'!$F19)) -> 2499 | AW19: =REV!AW19 -> 03.11.2026 | AX19: =VLOOKUP(C19,REV!C:AX,48,0) -> 5G
A20: Price Oferta | B20: 21X | C20: 4014836 | D20: APPLE IPHONE 13 256GB | E20: APPLE IPHONE 13 256GB-VERMELHO NAC | J20: =IF(VLOOKUP($C20,REV!$C:$AA,8,0)-'TRADE IN'!$F20=0,"",(VLOOKUP($C20,REV!$C:$AA,8,0)-'TRADE IN'!$F20)) -> 3799 | K20: =IF(VLOOKUP($C20,REV!$C:$AA,9,0)-'TRADE IN'!$F20=0,"",(VLOOKUP($C20,REV!$C:$AA,9,0)-'TRADE IN'!$F20)) -> 3799 | L20: =IF(VLOOKUP($C20,REV!$C:$AA,10,0)-'TRADE IN'!$F20=0,"",(VLOOKUP($C20,REV!$C:$AA,10,0)-'TRADE IN'!$F20)) -> 3799 | M20: =IF(VLOOKUP($C20,REV!$C:$AA,11,0)-'TRADE IN'!$F20=0,"",(VLOOKUP($C20,REV!$C:$AA,11,0)-'TRADE IN'!$F20)) -> 3799 | N20: =IF(VLOOKUP($C20,REV!$C:$AA,12,0)-'TRADE IN'!$F20=0,"",(VLOOKUP($C20,REV!$C:$AA,12,0)-'TRADE IN'!$F20)) -> 3799 | O20: =IF(VLOOKUP($C20,REV!$C:$AA,13,0)-'TRADE IN'!$F20=0,"",(VLOOKUP($C20,REV!$C:$AA,13,0)-'TRADE IN'!$F20)) -> 3599 | P20: =IF(VLOOKUP($C20,REV!$C:$AA,14,0)-'TRADE IN'!$F20=0,"",(VLOOKUP($C20,REV!$C:$AA,14,0)-'TRADE IN'!$F20)) -> 3499 | Q20: =IF(VLOOKUP($C20,REV!$C:$AA,15,0)-'TRADE IN'!$F20=0,"",(VLOOKUP($C20,REV!$C:$AA,15,0)-'TRADE IN'!$F20)) -> 2999 | R20: =IF(VLOOKUP($C20,REV!$C:$AA,16,0)-'TRADE IN'!$F20=0,"",(VLOOKUP($C20,REV!$C:$AA,16,0)-'TRADE IN'!$F20)) -> 3599 | S20: =IF(VLOOKUP($C20,REV!$C:$AA,17,0)-'TRADE IN'!$F20=0,"",(VLOOKUP($C20,REV!$C:$AA,17,0)-'TRADE IN'!$F20)) -> 3499 | T20: =IF(VLOOKUP($C20,REV!$C:$AA,18,0)-'TRADE IN'!$F20=0,"",(VLOOKUP($C20,REV!$C:$AA,18,0)-'TRADE IN'!$F20)) -> 2999 | U20: =IF(VLOOKUP($C20,REV!$C:$AA,19,0)-'TRADE IN'!$F20=0,"",(VLOOKUP($C20,REV!$C:$AA,19,0)-'TRADE IN'!$F20)) -> 2999 | V20: =IF(VLOOKUP($C20,REV!$C:$AA,20,0)-'TRADE IN'!$F20=0,"",(VLOOKUP($C20,REV!$C:$AA,20,0)-'TRADE IN'!$F20)) -> 2999 | W20: =IF(VLOOKUP($C20,REV!$C:$AA,21,0)-'TRADE IN'!$F20=0,"",(VLOOKUP($C20,REV!$C:$AA,21,0)-'TRADE IN'!$F20)) -> 2999 | X20: =IF(VLOOKUP($C20,REV!$C:$AA,22,0)-'TRADE IN'!$F20=0,"",(VLOOKUP($C20,REV!$C:$AA,22,0)-'TRADE IN'!$F20)) -> 2799 | Y20: =IF(VLOOKUP($C20,REV!$C:$AA,23,0)-'TRADE IN'!$F20=0,"",(VLOOKUP($C20,REV!$C:$AA,23,0)-'TRADE IN'!$F20)) -> 2499 | Z20: =IF(VLOOKUP($C20,REV!$C:$AA,24,0)-'TRADE IN'!$F20=0,"",(VLOOKUP($C20,REV!$C:$AA,24,0)-'TRADE IN'!$F20)) -> 2499 | AA20: =IF(VLOOKUP($C20,REV!$C:$AA,25,0)-'TRADE IN'!$F20=0,"",(VLOOKUP($C20,REV!$C:$AA,25,0)-'TRADE IN'!$F20)) -> 2499 | AW20: =REV!AW20 -> 03.11.2026 | AX20: =VLOOKUP(C20,REV!C:AX,48,0) -> 5G
A21: Price Oferta | B21: 21X | C21: 4015185 | D21: APPLE IPHONE 14 128GB | E21: APPLE IPHONE 14 128GB-PRETO | J21: =IF(VLOOKUP($C21,REV!$C:$AA,8,0)-'TRADE IN'!$F21=0,"",(VLOOKUP($C21,REV!$C:$AA,8,0)-'TRADE IN'!$F21)) -> 4199 | K21: =IF(VLOOKUP($C21,REV!$C:$AA,9,0)-'TRADE IN'!$F21=0,"",(VLOOKUP($C21,REV!$C:$AA,9,0)-'TRADE IN'!$F21)) -> 4199 | L21: =IF(VLOOKUP($C21,REV!$C:$AA,10,0)-'TRADE IN'!$F21=0,"",(VLOOKUP($C21,REV!$C:$AA,10,0)-'TRADE IN'!$F21)) -> 4199 | M21: =IF(VLOOKUP($C21,REV!$C:$AA,11,0)-'TRADE IN'!$F21=0,"",(VLOOKUP($C21,REV!$C:$AA,11,0)-'TRADE IN'!$F21)) -> 4199 | N21: =IF(VLOOKUP($C21,REV!$C:$AA,12,0)-'TRADE IN'!$F21=0,"",(VLOOKUP($C21,REV!$C:$AA,12,0)-'TRADE IN'!$F21)) -> 4199 | O21: =IF(VLOOKUP($C21,REV!$C:$AA,13,0)-'TRADE IN'!$F21=0,"",(VLOOKUP($C21,REV!$C:$AA,13,0)-'TRADE IN'!$F21)) -> 3899 | P21: =IF(VLOOKUP($C21,REV!$C:$AA,14,0)-'TRADE IN'!$F21=0,"",(VLOOKUP($C21,REV!$C:$AA,14,0)-'TRADE IN'!$F21)) -> 3799 | Q21: =IF(VLOOKUP($C21,REV!$C:$AA,15,0)-'TRADE IN'!$F21=0,"",(VLOOKUP($C21,REV!$C:$AA,15,0)-'TRADE IN'!$F21)) -> 3099 | R21: =IF(VLOOKUP($C21,REV!$C:$AA,16,0)-'TRADE IN'!$F21=0,"",(VLOOKUP($C21,REV!$C:$AA,16,0)-'TRADE IN'!$F21)) -> 3899 | S21: =IF(VLOOKUP($C21,REV!$C:$AA,17,0)-'TRADE IN'!$F21=0,"",(VLOOKUP($C21,REV!$C:$AA,17,0)-'TRADE IN'!$F21)) -> 3799 | T21: =IF(VLOOKUP($C21,REV!$C:$AA,18,0)-'TRADE IN'!$F21=0,"",(VLOOKUP($C21,REV!$C:$AA,18,0)-'TRADE IN'!$F21)) -> 3099 | U21: =IF(VLOOKUP($C21,REV!$C:$AA,19,0)-'TRADE IN'!$F21=0,"",(VLOOKUP($C21,REV!$C:$AA,19,0)-'TRADE IN'!$F21)) -> 3099 | V21: =IF(VLOOKUP($C21,REV!$C:$AA,20,0)-'TRADE IN'!$F21=0,"",(VLOOKUP($C21,REV!$C:$AA,20,0)-'TRADE IN'!$F21)) -> 3099 | W21: =IF(VLOOKUP($C21,REV!$C:$AA,21,0)-'TRADE IN'!$F21=0,"",(VLOOKUP($C21,REV!$C:$AA,21,0)-'TRADE IN'!$F21)) -> 3099 | X21: =IF(VLOOKUP($C21,REV!$C:$AA,22,0)-'TRADE IN'!$F21=0,"",(VLOOKUP($C21,REV!$C:$AA,22,0)-'TRADE IN'!$F21)) -> 2999 | Y21: =IF(VLOOKUP($C21,REV!$C:$AA,23,0)-'TRADE IN'!$F21=0,"",(VLOOKUP($C21,REV!$C:$AA,23,0)-'TRADE IN'!$F21)) -> 2499 | Z21: =IF(VLOOKUP($C21,REV!$C:$AA,24,0)-'TRADE IN'!$F21=0,"",(VLOOKUP($C21,REV!$C:$AA,24,0)-'TRADE IN'!$F21)) -> 2499 | AA21: =IF(VLOOKUP($C21,REV!$C:$AA,25,0)-'TRADE IN'!$F21=0,"",(VLOOKUP($C21,REV!$C:$AA,25,0)-'TRADE IN'!$F21)) -> 2499 | AW21: =REV!AW21 -> 03.11.2026 | AX21: =VLOOKUP(C21,REV!C:AX,48,0) -> 5G
A22: Price Oferta | B22: 21X | C22: 4015262 | D22: APPLE IPHONE 14 128GB | E22: APPLE IPHONE 14 128GB-PRETO NAC | J22: =IF(VLOOKUP($C22,REV!$C:$AA,8,0)-'TRADE IN'!$F22=0,"",(VLOOKUP($C22,REV!$C:$AA,8,0)-'TRADE IN'!$F22)) -> 4199 | K22: =IF(VLOOKUP($C22,REV!$C:$AA,9,0)-'TRADE IN'!$F22=0,"",(VLOOKUP($C22,REV!$C:$AA,9,0)-'TRADE IN'!$F22)) -> 4199 | L22: =IF(VLOOKUP($C22,REV!$C:$AA,10,0)-'TRADE IN'!$F22=0,"",(VLOOKUP($C22,REV!$C:$AA,10,0)-'TRADE IN'!$F22)) -> 4199 | M22: =IF(VLOOKUP($C22,REV!$C:$AA,11,0)-'TRADE IN'!$F22=0,"",(VLOOKUP($C22,REV!$C:$AA,11,0)-'TRADE IN'!$F22)) -> 4199 | N22: =IF(VLOOKUP($C22,REV!$C:$AA,12,0)-'TRADE IN'!$F22=0,"",(VLOOKUP($C22,REV!$C:$AA,12,0)-'TRADE IN'!$F22)) -> 4199 | O22: =IF(VLOOKUP($C22,REV!$C:$AA,13,0)-'TRADE IN'!$F22=0,"",(VLOOKUP($C22,REV!$C:$AA,13,0)-'TRADE IN'!$F22)) -> 3899 | P22: =IF(VLOOKUP($C22,REV!$C:$AA,14,0)-'TRADE IN'!$F22=0,"",(VLOOKUP($C22,REV!$C:$AA,14,0)-'TRADE IN'!$F22)) -> 3799 | Q22: =IF(VLOOKUP($C22,REV!$C:$AA,15,0)-'TRADE IN'!$F22=0,"",(VLOOKUP($C22,REV!$C:$AA,15,0)-'TRADE IN'!$F22)) -> 3099 | R22: =IF(VLOOKUP($C22,REV!$C:$AA,16,0)-'TRADE IN'!$F22=0,"",(VLOOKUP($C22,REV!$C:$AA,16,0)-'TRADE IN'!$F22)) -> 3899 | S22: =IF(VLOOKUP($C22,REV!$C:$AA,17,0)-'TRADE IN'!$F22=0,"",(VLOOKUP($C22,REV!$C:$AA,17,0)-'TRADE IN'!$F22)) -> 3799 | T22: =IF(VLOOKUP($C22,REV!$C:$AA,18,0)-'TRADE IN'!$F22=0,"",(VLOOKUP($C22,REV!$C:$AA,18,0)-'TRADE IN'!$F22)) -> 3099 | U22: =IF(VLOOKUP($C22,REV!$C:$AA,19,0)-'TRADE IN'!$F22=0,"",(VLOOKUP($C22,REV!$C:$AA,19,0)-'TRADE IN'!$F22)) -> 3099 | V22: =IF(VLOOKUP($C22,REV!$C:$AA,20,0)-'TRADE IN'!$F22=0,"",(VLOOKUP($C22,REV!$C:$AA,20,0)-'TRADE IN'!$F22)) -> 3099 | W22: =IF(VLOOKUP($C22,REV!$C:$AA,21,0)-'TRADE IN'!$F22=0,"",(VLOOKUP($C22,REV!$C:$AA,21,0)-'TRADE IN'!$F22)) -> 3099 | X22: =IF(VLOOKUP($C22,REV!$C:$AA,22,0)-'TRADE IN'!$F22=0,"",(VLOOKUP($C22,REV!$C:$AA,22,0)-'TRADE IN'!$F22)) -> 2999 | Y22: =IF(VLOOKUP($C22,REV!$C:$AA,23,0)-'TRADE IN'!$F22=0,"",(VLOOKUP($C22,REV!$C:$AA,23,0)-'TRADE IN'!$F22)) -> 2499 | Z22: =IF(VLOOKUP($C22,REV!$C:$AA,24,0)-'TRADE IN'!$F22=0,"",(VLOOKUP($C22,REV!$C:$AA,24,0)-'TRADE IN'!$F22)) -> 2499 | AA22: =IF(VLOOKUP($C22,REV!$C:$AA,25,0)-'TRADE IN'!$F22=0,"",(VLOOKUP($C22,REV!$C:$AA,25,0)-'TRADE IN'!$F22)) -> 2499 | AW22: =REV!AW22 -> 03.11.2026 | AX22: =VLOOKUP(C22,REV!C:AX,48,0) -> 5G
A23: Price Oferta | B23: 21X | C23: 4015180 | D23: APPLE IPHONE 14 256GB | E23: APPLE IPHONE 14 256GB-BRANCO | J23: =IF(VLOOKUP($C23,REV!$C:$AA,8,0)-'TRADE IN'!$F23=0,"",(VLOOKUP($C23,REV!$C:$AA,8,0)-'TRADE IN'!$F23)) -> 4399 | K23: =IF(VLOOKUP($C23,REV!$C:$AA,9,0)-'TRADE IN'!$F23=0,"",(VLOOKUP($C23,REV!$C:$AA,9,0)-'TRADE IN'!$F23)) -> 4399 | L23: =IF(VLOOKUP($C23,REV!$C:$AA,10,0)-'TRADE IN'!$F23=0,"",(VLOOKUP($C23,REV!$C:$AA,10,0)-'TRADE IN'!$F23)) -> 4399 | M23: =IF(VLOOKUP($C23,REV!$C:$AA,11,0)-'TRADE IN'!$F23=0,"",(VLOOKUP($C23,REV!$C:$AA,11,0)-'TRADE IN'!$F23)) -> 4399 | N23: =IF(VLOOKUP($C23,REV!$C:$AA,12,0)-'TRADE IN'!$F23=0,"",(VLOOKUP($C23,REV!$C:$AA,12,0)-'TRADE IN'!$F23)) -> 4399 | O23: =IF(VLOOKUP($C23,REV!$C:$AA,13,0)-'TRADE IN'!$F23=0,"",(VLOOKUP($C23,REV!$C:$AA,13,0)-'TRADE IN'!$F23)) -> 4299 | P23: =IF(VLOOKUP($C23,REV!$C:$AA,14,0)-'TRADE IN'!$F23=0,"",(VLOOKUP($C23,REV!$C:$AA,14,0)-'TRADE IN'!$F23)) -> 4199 | Q23: =IF(VLOOKUP($C23,REV!$C:$AA,15,0)-'TRADE IN'!$F23=0,"",(VLOOKUP($C23,REV!$C:$AA,15,0)-'TRADE IN'!$F23)) -> 3499 | R23: =IF(VLOOKUP($C23,REV!$C:$AA,16,0)-'TRADE IN'!$F23=0,"",(VLOOKUP($C23,REV!$C:$AA,16,0)-'TRADE IN'!$F23)) -> 4299 | S23: =IF(VLOOKUP($C23,REV!$C:$AA,17,0)-'TRADE IN'!$F23=0,"",(VLOOKUP($C23,REV!$C:$AA,17,0)-'TRADE IN'!$F23)) -> 4199 | T23: =IF(VLOOKUP($C23,REV!$C:$AA,18,0)-'TRADE IN'!$F23=0,"",(VLOOKUP($C23,REV!$C:$AA,18,0)-'TRADE IN'!$F23)) -> 3499 | U23: =IF(VLOOKUP($C23,REV!$C:$AA,19,0)-'TRADE IN'!$F23=0,"",(VLOOKUP($C23,REV!$C:$AA,19,0)-'TRADE IN'!$F23)) -> 3499 | V23: =IF(VLOOKUP($C23,REV!$C:$AA,20,0)-'TRADE IN'!$F23=0,"",(VLOOKUP($C23,REV!$C:$AA,20,0)-'TRADE IN'!$F23)) -> 3499 | W23: =IF(VLOOKUP($C23,REV!$C:$AA,21,0)-'TRADE IN'!$F23=0,"",(VLOOKUP($C23,REV!$C:$AA,21,0)-'TRADE IN'!$F23)) -> 3499 | X23: =IF(VLOOKUP($C23,REV!$C:$AA,22,0)-'TRADE IN'!$F23=0,"",(VLOOKUP($C23,REV!$C:$AA,22,0)-'TRADE IN'!$F23)) -> 3399 | Y23: =IF(VLOOKUP($C23,REV!$C:$AA,23,0)-'TRADE IN'!$F23=0,"",(VLOOKUP($C23,REV!$C:$AA,23,0)-'TRADE IN'!$F23)) -> 2499 | Z23: =IF(VLOOKUP($C23,REV!$C:$AA,24,0)-'TRADE IN'!$F23=0,"",(VLOOKUP($C23,REV!$C:$AA,24,0)-'TRADE IN'!$F23)) -> 2499 | AA23: =IF(VLOOKUP($C23,REV!$C:$AA,25,0)-'TRADE IN'!$F23=0,"",(VLOOKUP($C23,REV!$C:$AA,25,0)-'TRADE IN'!$F23)) -> 2449 | AB23: =IF(VLOOKUP($C23,REV!$C:$AL,27,0)-'TRADE IN'!$F23=0,"",(VLOOKUP($C23,REV!$C:$AL,27,0)-'TRADE IN'!$F23)) -> 4399 | AC23: =IF(VLOOKUP($C23,REV!$C:$AL,28,0)-'TRADE IN'!$F23=0,"",(VLOOKUP($C23,REV!$C:$AL,28,0)-'TRADE IN'!$F23)) -> 4399 | AD23: =IF(VLOOKUP($C23,REV!$C:$AL,29,0)-'TRADE IN'!$F23=0,"",(VLOOKUP($C23,REV!$C:$AL,29,0)-'TRADE IN'!$F23)) -> 4199 | AE23: =IF(VLOOKUP($C23,REV!$C:$AL,30,0)-'TRADE IN'!$F23=0,"",(VLOOKUP($C23,REV!$C:$AL,30,0)-'TRADE IN'!$F23)) -> 4199 | AF23: =IF(VLOOKUP($C23,REV!$C:$AL,31,0)-'TRADE IN'!$F23=0,"",(VLOOKUP($C23,REV!$C:$AL,31,0)-'TRADE IN'!$F23)) -> 4199 | AG23: =IF(VLOOKUP($C23,REV!$C:$AL,31,0)-'TRADE IN'!$F23=0,"",(VLOOKUP($C23,REV!$C:$AL,31,0)-'TRADE IN'!$F23)) -> 4199 | AH23: =IF(VLOOKUP($C23,REV!$C:$AL,32,0)-'TRADE IN'!$F23=0,"",(VLOOKUP($C23,REV!$C:$AL,32,0)-'TRADE IN'!$F23)) -> 4199 | AI23: =IF(VLOOKUP($C23,REV!$C:$AL,33,0)-'TRADE IN'!$F23=0,"",(VLOOKUP($C23,REV!$C:$AL,33,0)-'TRADE IN'!$F23)) -> 3499 | AJ23: =IF(VLOOKUP($C23,REV!$C:$AL,34,0)-'TRADE IN'!$F23=0,"",(VLOOKUP($C23,REV!$C:$AL,34,0)-'TRADE IN'!$F23)) -> 3499 | AK23: =IF(VLOOKUP($C23,REV!$C:$AL,35,0)-'TRADE IN'!$F23=0,"",(VLOOKUP($C23,REV!$C:$AL,35,0)-'TRADE IN'!$F23)) -> 3499 | AL23: =IF(VLOOKUP($C23,REV!$C:$AL,36,0)-'TRADE IN'!$F23=0,"",(VLOOKUP($C23,REV!$C:$AL,36,0)-'TRADE IN'!$F23)) -> 2499 | AW23: =REV!AW23 -> 03.11.2026 | AX23: =VLOOKUP(C23,REV!C:AX,48,0) -> 5G
A24: Price Oferta | B24: 21X | C24: 4015186 | D24: APPLE IPHONE 14 256GB | E24: APPLE IPHONE 14 256GB-PRETO | J24: =IF(VLOOKUP($C24,REV!$C:$AA,8,0)-'TRADE IN'!$F24=0,"",(VLOOKUP($C24,REV!$C:$AA,8,0)-'TRADE IN'!$F24)) -> 4399 | K24: =IF(VLOOKUP($C24,REV!$C:$AA,9,0)-'TRADE IN'!$F24=0,"",(VLOOKUP($C24,REV!$C:$AA,9,0)-'TRADE IN'!$F24)) -> 4399 | L24: =IF(VLOOKUP($C24,REV!$C:$AA,10,0)-'TRADE IN'!$F24=0,"",(VLOOKUP($C24,REV!$C:$AA,10,0)-'TRADE IN'!$F24)) -> 4399 | M24: =IF(VLOOKUP($C24,REV!$C:$AA,11,0)-'TRADE IN'!$F24=0,"",(VLOOKUP($C24,REV!$C:$AA,11,0)-'TRADE IN'!$F24)) -> 4399 | N24: =IF(VLOOKUP($C24,REV!$C:$AA,12,0)-'TRADE IN'!$F24=0,"",(VLOOKUP($C24,REV!$C:$AA,12,0)-'TRADE IN'!$F24)) -> 4399 | O24: =IF(VLOOKUP($C24,REV!$C:$AA,13,0)-'TRADE IN'!$F24=0,"",(VLOOKUP($C24,REV!$C:$AA,13,0)-'TRADE IN'!$F24)) -> 4299 | P24: =IF(VLOOKUP($C24,REV!$C:$AA,14,0)-'TRADE IN'!$F24=0,"",(VLOOKUP($C24,REV!$C:$AA,14,0)-'TRADE IN'!$F24)) -> 4199 | Q24: =IF(VLOOKUP($C24,REV!$C:$AA,15,0)-'TRADE IN'!$F24=0,"",(VLOOKUP($C24,REV!$C:$AA,15,0)-'TRADE IN'!$F24)) -> 3499 | R24: =IF(VLOOKUP($C24,REV!$C:$AA,16,0)-'TRADE IN'!$F24=0,"",(VLOOKUP($C24,REV!$C:$AA,16,0)-'TRADE IN'!$F24)) -> 4299 | S24: =IF(VLOOKUP($C24,REV!$C:$AA,17,0)-'TRADE IN'!$F24=0,"",(VLOOKUP($C24,REV!$C:$AA,17,0)-'TRADE IN'!$F24)) -> 4199 | T24: =IF(VLOOKUP($C24,REV!$C:$AA,18,0)-'TRADE IN'!$F24=0,"",(VLOOKUP($C24,REV!$C:$AA,18,0)-'TRADE IN'!$F24)) -> 3499 | U24: =IF(VLOOKUP($C24,REV!$C:$AA,19,0)-'TRADE IN'!$F24=0,"",(VLOOKUP($C24,REV!$C:$AA,19,0)-'TRADE IN'!$F24)) -> 3499 | V24: =IF(VLOOKUP($C24,REV!$C:$AA,20,0)-'TRADE IN'!$F24=0,"",(VLOOKUP($C24,REV!$C:$AA,20,0)-'TRADE IN'!$F24)) -> 3499 | W24: =IF(VLOOKUP($C24,REV!$C:$AA,21,0)-'TRADE IN'!$F24=0,"",(VLOOKUP($C24,REV!$C:$AA,21,0)-'TRADE IN'!$F24)) -> 3499 | X24: =IF(VLOOKUP($C24,REV!$C:$AA,22,0)-'TRADE IN'!$F24=0,"",(VLOOKUP($C24,REV!$C:$AA,22,0)-'TRADE IN'!$F24)) -> 3399 | Y24: =IF(VLOOKUP($C24,REV!$C:$AA,23,0)-'TRADE IN'!$F24=0,"",(VLOOKUP($C24,REV!$C:$AA,23,0)-'TRADE IN'!$F24)) -> 2499 | Z24: =IF(VLOOKUP($C24,REV!$C:$AA,24,0)-'TRADE IN'!$F24=0,"",(VLOOKUP($C24,REV!$C:$AA,24,0)-'TRADE IN'!$F24)) -> 2499 | AA24: =IF(VLOOKUP($C24,REV!$C:$AA,25,0)-'TRADE IN'!$F24=0,"",(VLOOKUP($C24,REV!$C:$AA,25,0)-'TRADE IN'!$F24)) -> 2449 | AB24: =IF(VLOOKUP($C24,REV!$C:$AL,27,0)-'TRADE IN'!$F24=0,"",(VLOOKUP($C24,REV!$C:$AL,27,0)-'TRADE IN'!$F24)) -> 4399 | AC24: =IF(VLOOKUP($C24,REV!$C:$AL,28,0)-'TRADE IN'!$F24=0,"",(VLOOKUP($C24,REV!$C:$AL,28,0)-'TRADE IN'!$F24)) -> 4399 | AD24: =IF(VLOOKUP($C24,REV!$C:$AL,29,0)-'TRADE IN'!$F24=0,"",(VLOOKUP($C24,REV!$C:$AL,29,0)-'TRADE IN'!$F24)) -> 4199 | AE24: =IF(VLOOKUP($C24,REV!$C:$AL,30,0)-'TRADE IN'!$F24=0,"",(VLOOKUP($C24,REV!$C:$AL,30,0)-'TRADE IN'!$F24)) -> 4199 | AF24: =IF(VLOOKUP($C24,REV!$C:$AL,31,0)-'TRADE IN'!$F24=0,"",(VLOOKUP($C24,REV!$C:$AL,31,0)-'TRADE IN'!$F24)) -> 4199 | AG24: =IF(VLOOKUP($C24,REV!$C:$AL,31,0)-'TRADE IN'!$F24=0,"",(VLOOKUP($C24,REV!$C:$AL,31,0)-'TRADE IN'!$F24)) -> 4199 | AH24: =IF(VLOOKUP($C24,REV!$C:$AL,32,0)-'TRADE IN'!$F24=0,"",(VLOOKUP($C24,REV!$C:$AL,32,0)-'TRADE IN'!$F24)) -> 4199 | AI24: =IF(VLOOKUP($C24,REV!$C:$AL,33,0)-'TRADE IN'!$F24=0,"",(VLOOKUP($C24,REV!$C:$AL,33,0)-'TRADE IN'!$F24)) -> 3499 | AJ24: =IF(VLOOKUP($C24,REV!$C:$AL,34,0)-'TRADE IN'!$F24=0,"",(VLOOKUP($C24,REV!$C:$AL,34,0)-'TRADE IN'!$F24)) -> 3499 | AK24: =IF(VLOOKUP($C24,REV!$C:$AL,35,0)-'TRADE IN'!$F24=0,"",(VLOOKUP($C24,REV!$C:$AL,35,0)-'TRADE IN'!$F24)) -> 3499 | AL24: =IF(VLOOKUP($C24,REV!$C:$AL,36,0)-'TRADE IN'!$F24=0,"",(VLOOKUP($C24,REV!$C:$AL,36,0)-'TRADE IN'!$F24)) -> 2499 | AW24: =REV!AW24 -> 03.11.2026 | AX24: =VLOOKUP(C24,REV!C:AX,48,0) -> 5G
A25: Price Oferta | B25: 21X | C25: 4015267 | D25: APPLE IPHONE 14 256GB | E25: APPLE IPHONE 14 256GB-PRETO NAC | J25: =IF(VLOOKUP($C25,REV!$C:$AA,8,0)-'TRADE IN'!$F25=0,"",(VLOOKUP($C25,REV!$C:$AA,8,0)-'TRADE IN'!$F25)) -> 4399 | K25: =IF(VLOOKUP($C25,REV!$C:$AA,9,0)-'TRADE IN'!$F25=0,"",(VLOOKUP($C25,REV!$C:$AA,9,0)-'TRADE IN'!$F25)) -> 4399 | L25: =IF(VLOOKUP($C25,REV!$C:$AA,10,0)-'TRADE IN'!$F25=0,"",(VLOOKUP($C25,REV!$C:$AA,10,0)-'TRADE IN'!$F25)) -> 4399 | M25: =IF(VLOOKUP($C25,REV!$C:$AA,11,0)-'TRADE IN'!$F25=0,"",(VLOOKUP($C25,REV!$C:$AA,11,0)-'TRADE IN'!$F25)) -> 4399 | N25: =IF(VLOOKUP($C25,REV!$C:$AA,12,0)-'TRADE IN'!$F25=0,"",(VLOOKUP($C25,REV!$C:$AA,12,0)-'TRADE IN'!$F25)) -> 4399 | O25: =IF(VLOOKUP($C25,REV!$C:$AA,13,0)-'TRADE IN'!$F25=0,"",(VLOOKUP($C25,REV!$C:$AA,13,0)-'TRADE IN'!$F25)) -> 4299 | P25: =IF(VLOOKUP($C25,REV!$C:$AA,14,0)-'TRADE IN'!$F25=0,"",(VLOOKUP($C25,REV!$C:$AA,14,0)-'TRADE IN'!$F25)) -> 4199 | Q25: =IF(VLOOKUP($C25,REV!$C:$AA,15,0)-'TRADE IN'!$F25=0,"",(VLOOKUP($C25,REV!$C:$AA,15,0)-'TRADE IN'!$F25)) -> 3499 | R25: =IF(VLOOKUP($C25,REV!$C:$AA,16,0)-'TRADE IN'!$F25=0,"",(VLOOKUP($C25,REV!$C:$AA,16,0)-'TRADE IN'!$F25)) -> 4299 | S25: =IF(VLOOKUP($C25,REV!$C:$AA,17,0)-'TRADE IN'!$F25=0,"",(VLOOKUP($C25,REV!$C:$AA,17,0)-'TRADE IN'!$F25)) -> 4199 | T25: =IF(VLOOKUP($C25,REV!$C:$AA,18,0)-'TRADE IN'!$F25=0,"",(VLOOKUP($C25,REV!$C:$AA,18,0)-'TRADE IN'!$F25)) -> 3499 | U25: =IF(VLOOKUP($C25,REV!$C:$AA,19,0)-'TRADE IN'!$F25=0,"",(VLOOKUP($C25,REV!$C:$AA,19,0)-'TRADE IN'!$F25)) -> 3499 | V25: =IF(VLOOKUP($C25,REV!$C:$AA,20,0)-'TRADE IN'!$F25=0,"",(VLOOKUP($C25,REV!$C:$AA,20,0)-'TRADE IN'!$F25)) -> 3499 | W25: =IF(VLOOKUP($C25,REV!$C:$AA,21,0)-'TRADE IN'!$F25=0,"",(VLOOKUP($C25,REV!$C:$AA,21,0)-'TRADE IN'!$F25)) -> 3499 | X25: =IF(VLOOKUP($C25,REV!$C:$AA,22,0)-'TRADE IN'!$F25=0,"",(VLOOKUP($C25,REV!$C:$AA,22,0)-'TRADE IN'!$F25)) -> 3399 | Y25: =IF(VLOOKUP($C25,REV!$C:$AA,23,0)-'TRADE IN'!$F25=0,"",(VLOOKUP($C25,REV!$C:$AA,23,0)-'TRADE IN'!$F25)) -> 2499 | Z25: =IF(VLOOKUP($C25,REV!$C:$AA,24,0)-'TRADE IN'!$F25=0,"",(VLOOKUP($C25,REV!$C:$AA,24,0)-'TRADE IN'!$F25)) -> 2499 | AA25: =IF(VLOOKUP($C25,REV!$C:$AA,25,0)-'TRADE IN'!$F25=0,"",(VLOOKUP($C25,REV!$C:$AA,25,0)-'TRADE IN'!$F25)) -> 2449 | AB25: =IF(VLOOKUP($C25,REV!$C:$AL,27,0)-'TRADE IN'!$F25=0,"",(VLOOKUP($C25,REV!$C:$AL,27,0)-'TRADE IN'!$F25)) -> 4399 | AC25: =IF(VLOOKUP($C25,REV!$C:$AL,28,0)-'TRADE IN'!$F25=0,"",(VLOOKUP($C25,REV!$C:$AL,28,0)-'TRADE IN'!$F25)) -> 4399 | AD25: =IF(VLOOKUP($C25,REV!$C:$AL,29,0)-'TRADE IN'!$F25=0,"",(VLOOKUP($C25,REV!$C:$AL,29,0)-'TRADE IN'!$F25)) -> 4199 | AE25: =IF(VLOOKUP($C25,REV!$C:$AL,30,0)-'TRADE IN'!$F25=0,"",(VLOOKUP($C25,REV!$C:$AL,30,0)-'TRADE IN'!$F25)) -> 4199 | AF25: =IF(VLOOKUP($C25,REV!$C:$AL,31,0)-'TRADE IN'!$F25=0,"",(VLOOKUP($C25,REV!$C:$AL,31,0)-'TRADE IN'!$F25)) -> 4199 | AG25: =IF(VLOOKUP($C25,REV!$C:$AL,31,0)-'TRADE IN'!$F25=0,"",(VLOOKUP($C25,REV!$C:$AL,31,0)-'TRADE IN'!$F25)) -> 4199 | AH25: =IF(VLOOKUP($C25,REV!$C:$AL,32,0)-'TRADE IN'!$F25=0,"",(VLOOKUP($C25,REV!$C:$AL,32,0)-'TRADE IN'!$F25)) -> 4199 | AI25: =IF(VLOOKUP($C25,REV!$C:$AL,33,0)-'TRADE IN'!$F25=0,"",(VLOOKUP($C25,REV!$C:$AL,33,0)-'TRADE IN'!$F25)) -> 3499 | AJ25: =IF(VLOOKUP($C25,REV!$C:$AL,34,0)-'TRADE IN'!$F25=0,"",(VLOOKUP($C25,REV!$C:$AL,34,0)-'TRADE IN'!$F25)) -> 3499 | AK25: =IF(VLOOKUP($C25,REV!$C:$AL,35,0)-'TRADE IN'!$F25=0,"",(VLOOKUP($C25,REV!$C:$AL,35,0)-'TRADE IN'!$F25)) -> 3499 | AL25: =IF(VLOOKUP($C25,REV!$C:$AL,36,0)-'TRADE IN'!$F25=0,"",(VLOOKUP($C25,REV!$C:$AL,36,0)-'TRADE IN'!$F25)) -> 2499 | AW25: =REV!AW25 -> 03.11.2026 | AX25: =VLOOKUP(C25,REV!C:AX,48,0) -> 5G
A26: Price Oferta | B26: 21X | C26: 4015268 | D26: APPLE IPHONE 14 256GB | E26: APPLE IPHONE 14 256GB-BRANCO NAC | J26: =IF(VLOOKUP($C26,REV!$C:$AA,8,0)-'TRADE IN'!$F26=0,"",(VLOOKUP($C26,REV!$C:$AA,8,0)-'TRADE IN'!$F26)) -> 4399 | K26: =IF(VLOOKUP($C26,REV!$C:$AA,9,0)-'TRADE IN'!$F26=0,"",(VLOOKUP($C26,REV!$C:$AA,9,0)-'TRADE IN'!$F26)) -> 4399 | L26: =IF(VLOOKUP($C26,REV!$C:$AA,10,0)-'TRADE IN'!$F26=0,"",(VLOOKUP($C26,REV!$C:$AA,10,0)-'TRADE IN'!$F26)) -> 4399 | M26: =IF(VLOOKUP($C26,REV!$C:$AA,11,0)-'TRADE IN'!$F26=0,"",(VLOOKUP($C26,REV!$C:$AA,11,0)-'TRADE IN'!$F26)) -> 4399 | N26: =IF(VLOOKUP($C26,REV!$C:$AA,12,0)-'TRADE IN'!$F26=0,"",(VLOOKUP($C26,REV!$C:$AA,12,0)-'TRADE IN'!$F26)) -> 4399 | O26: =IF(VLOOKUP($C26,REV!$C:$AA,13,0)-'TRADE IN'!$F26=0,"",(VLOOKUP($C26,REV!$C:$AA,13,0)-'TRADE IN'!$F26)) -> 4299 | P26: =IF(VLOOKUP($C26,REV!$C:$AA,14,0)-'TRADE IN'!$F26=0,"",(VLOOKUP($C26,REV!$C:$AA,14,0)-'TRADE IN'!$F26)) -> 4199 | Q26: =IF(VLOOKUP($C26,REV!$C:$AA,15,0)-'TRADE IN'!$F26=0,"",(VLOOKUP($C26,REV!$C:$AA,15,0)-'TRADE IN'!$F26)) -> 3499 | R26: =IF(VLOOKUP($C26,REV!$C:$AA,16,0)-'TRADE IN'!$F26=0,"",(VLOOKUP($C26,REV!$C:$AA,16,0)-'TRADE IN'!$F26)) -> 4299 | S26: =IF(VLOOKUP($C26,REV!$C:$AA,17,0)-'TRADE IN'!$F26=0,"",(VLOOKUP($C26,REV!$C:$AA,17,0)-'TRADE IN'!$F26)) -> 4199 | T26: =IF(VLOOKUP($C26,REV!$C:$AA,18,0)-'TRADE IN'!$F26=0,"",(VLOOKUP($C26,REV!$C:$AA,18,0)-'TRADE IN'!$F26)) -> 3499 | U26: =IF(VLOOKUP($C26,REV!$C:$AA,19,0)-'TRADE IN'!$F26=0,"",(VLOOKUP($C26,REV!$C:$AA,19,0)-'TRADE IN'!$F26)) -> 3499 | V26: =IF(VLOOKUP($C26,REV!$C:$AA,20,0)-'TRADE IN'!$F26=0,"",(VLOOKUP($C26,REV!$C:$AA,20,0)-'TRADE IN'!$F26)) -> 3499 | W26: =IF(VLOOKUP($C26,REV!$C:$AA,21,0)-'TRADE IN'!$F26=0,"",(VLOOKUP($C26,REV!$C:$AA,21,0)-'TRADE IN'!$F26)) -> 3499 | X26: =IF(VLOOKUP($C26,REV!$C:$AA,22,0)-'TRADE IN'!$F26=0,"",(VLOOKUP($C26,REV!$C:$AA,22,0)-'TRADE IN'!$F26)) -> 3399 | Y26: =IF(VLOOKUP($C26,REV!$C:$AA,23,0)-'TRADE IN'!$F26=0,"",(VLOOKUP($C26,REV!$C:$AA,23,0)-'TRADE IN'!$F26)) -> 2499 | Z26: =IF(VLOOKUP($C26,REV!$C:$AA,24,0)-'TRADE IN'!$F26=0,"",(VLOOKUP($C26,REV!$C:$AA,24,0)-'TRADE IN'!$F26)) -> 2499 | AA26: =IF(VLOOKUP($C26,REV!$C:$AA,25,0)-'TRADE IN'!$F26=0,"",(VLOOKUP($C26,REV!$C:$AA,25,0)-'TRADE IN'!$F26)) -> 2449 | AB26: =IF(VLOOKUP($C26,REV!$C:$AL,27,0)-'TRADE IN'!$F26=0,"",(VLOOKUP($C26,REV!$C:$AL,27,0)-'TRADE IN'!$F26)) -> 4399 | AC26: =IF(VLOOKUP($C26,REV!$C:$AL,28,0)-'TRADE IN'!$F26=0,"",(VLOOKUP($C26,REV!$C:$AL,28,0)-'TRADE IN'!$F26)) -> 4399 | AD26: =IF(VLOOKUP($C26,REV!$C:$AL,29,0)-'TRADE IN'!$F26=0,"",(VLOOKUP($C26,REV!$C:$AL,29,0)-'TRADE IN'!$F26)) -> 4199 | AE26: =IF(VLOOKUP($C26,REV!$C:$AL,30,0)-'TRADE IN'!$F26=0,"",(VLOOKUP($C26,REV!$C:$AL,30,0)-'TRADE IN'!$F26)) -> 4199 | AF26: =IF(VLOOKUP($C26,REV!$C:$AL,31,0)-'TRADE IN'!$F26=0,"",(VLOOKUP($C26,REV!$C:$AL,31,0)-'TRADE IN'!$F26)) -> 4199 | AG26: =IF(VLOOKUP($C26,REV!$C:$AL,31,0)-'TRADE IN'!$F26=0,"",(VLOOKUP($C26,REV!$C:$AL,31,0)-'TRADE IN'!$F26)) -> 4199 | AH26: =IF(VLOOKUP($C26,REV!$C:$AL,32,0)-'TRADE IN'!$F26=0,"",(VLOOKUP($C26,REV!$C:$AL,32,0)-'TRADE IN'!$F26)) -> 4199 | AI26: =IF(VLOOKUP($C26,REV!$C:$AL,33,0)-'TRADE IN'!$F26=0,"",(VLOOKUP($C26,REV!$C:$AL,33,0)-'TRADE IN'!$F26)) -> 3499 | AJ26: =IF(VLOOKUP($C26,REV!$C:$AL,34,0)-'TRADE IN'!$F26=0,"",(VLOOKUP($C26,REV!$C:$AL,34,0)-'TRADE IN'!$F26)) -> 3499 | AK26: =IF(VLOOKUP($C26,REV!$C:$AL,35,0)-'TRADE IN'!$F26=0,"",(VLOOKUP($C26,REV!$C:$AL,35,0)-'TRADE IN'!$F26)) -> 3499 | AL26: =IF(VLOOKUP($C26,REV!$C:$AL,36,0)-'TRADE IN'!$F26=0,"",(VLOOKUP($C26,REV!$C:$AL,36,0)-'TRADE IN'!$F26)) -> 2499 | AW26: =REV!AW26 -> 03.11.2026 | AX26: =VLOOKUP(C26,REV!C:AX,48,0) -> 5G
A27: Price Oferta | B27: 21X | C27: 4015179 | D27: APPLE IPHONE 14 PLUS 256GB | E27: APPLE IPHONE 14 PLUS 256GB-BRANCO | J27: =IF(VLOOKUP($C27,REV!$C:$AA,8,0)-'TRADE IN'!$F27=0,"",(VLOOKUP($C27,REV!$C:$AA,8,0)-'TRADE IN'!$F27)) -> 4499 | K27: =IF(VLOOKUP($C27,REV!$C:$AA,9,0)-'TRADE IN'!$F27=0,"",(VLOOKUP($C27,REV!$C:$AA,9,0)-'TRADE IN'!$F27)) -> 4499 | L27: =IF(VLOOKUP($C27,REV!$C:$AA,10,0)-'TRADE IN'!$F27=0,"",(VLOOKUP($C27,REV!$C:$AA,10,0)-'TRADE IN'!$F27)) -> 4499 | M27: =IF(VLOOKUP($C27,REV!$C:$AA,11,0)-'TRADE IN'!$F27=0,"",(VLOOKUP($C27,REV!$C:$AA,11,0)-'TRADE IN'!$F27)) -> 4499 | N27: =IF(VLOOKUP($C27,REV!$C:$AA,12,0)-'TRADE IN'!$F27=0,"",(VLOOKUP($C27,REV!$C:$AA,12,0)-'TRADE IN'!$F27)) -> 4499 | O27: =IF(VLOOKUP($C27,REV!$C:$AA,13,0)-'TRADE IN'!$F27=0,"",(VLOOKUP($C27,REV!$C:$AA,13,0)-'TRADE IN'!$F27)) -> 4399 | P27: =IF(VLOOKUP($C27,REV!$C:$AA,14,0)-'TRADE IN'!$F27=0,"",(VLOOKUP($C27,REV!$C:$AA,14,0)-'TRADE IN'!$F27)) -> 4299 | Q27: =IF(VLOOKUP($C27,REV!$C:$AA,15,0)-'TRADE IN'!$F27=0,"",(VLOOKUP($C27,REV!$C:$AA,15,0)-'TRADE IN'!$F27)) -> 3499 | R27: =IF(VLOOKUP($C27,REV!$C:$AA,16,0)-'TRADE IN'!$F27=0,"",(VLOOKUP($C27,REV!$C:$AA,16,0)-'TRADE IN'!$F27)) -> 4399 | S27: =IF(VLOOKUP($C27,REV!$C:$AA,17,0)-'TRADE IN'!$F27=0,"",(VLOOKUP($C27,REV!$C:$AA,17,0)-'TRADE IN'!$F27)) -> 4299 | T27: =IF(VLOOKUP($C27,REV!$C:$AA,18,0)-'TRADE IN'!$F27=0,"",(VLOOKUP($C27,REV!$C:$AA,18,0)-'TRADE IN'!$F27)) -> 3499 | U27: =IF(VLOOKUP($C27,REV!$C:$AA,19,0)-'TRADE IN'!$F27=0,"",(VLOOKUP($C27,REV!$C:$AA,19,0)-'TRADE IN'!$F27)) -> 3499 | V27: =IF(VLOOKUP($C27,REV!$C:$AA,20,0)-'TRADE IN'!$F27=0,"",(VLOOKUP($C27,REV!$C:$AA,20,0)-'TRADE IN'!$F27)) -> 3499 | W27: =IF(VLOOKUP($C27,REV!$C:$AA,21,0)-'TRADE IN'!$F27=0,"",(VLOOKUP($C27,REV!$C:$AA,21,0)-'TRADE IN'!$F27)) -> 3499 | X27: =IF(VLOOKUP($C27,REV!$C:$AA,22,0)-'TRADE IN'!$F27=0,"",(VLOOKUP($C27,REV!$C:$AA,22,0)-'TRADE IN'!$F27)) -> 3399 | Y27: =IF(VLOOKUP($C27,REV!$C:$AA,23,0)-'TRADE IN'!$F27=0,"",(VLOOKUP($C27,REV!$C:$AA,23,0)-'TRADE IN'!$F27)) -> 2899 | Z27: =IF(VLOOKUP($C27,REV!$C:$AA,24,0)-'TRADE IN'!$F27=0,"",(VLOOKUP($C27,REV!$C:$AA,24,0)-'TRADE IN'!$F27)) -> 2899 | AA27: =IF(VLOOKUP($C27,REV!$C:$AA,25,0)-'TRADE IN'!$F27=0,"",(VLOOKUP($C27,REV!$C:$AA,25,0)-'TRADE IN'!$F27)) -> 2899 | AW27: =REV!AW27 -> 03.11.2026 | AX27: =VLOOKUP(C27,REV!C:AX,48,0) -> 5G
A28: Price Oferta | B28: 21X | C28: 4015187 | D28: APPLE IPHONE 14 PLUS 256GB | E28: APPLE IPHONE 14 PLUS 256GB-PRETO | J28: =IF(VLOOKUP($C28,REV!$C:$AA,8,0)-'TRADE IN'!$F28=0,"",(VLOOKUP($C28,REV!$C:$AA,8,0)-'TRADE IN'!$F28)) -> 4499 | K28: =IF(VLOOKUP($C28,REV!$C:$AA,9,0)-'TRADE IN'!$F28=0,"",(VLOOKUP($C28,REV!$C:$AA,9,0)-'TRADE IN'!$F28)) -> 4499 | L28: =IF(VLOOKUP($C28,REV!$C:$AA,10,0)-'TRADE IN'!$F28=0,"",(VLOOKUP($C28,REV!$C:$AA,10,0)-'TRADE IN'!$F28)) -> 4499 | M28: =IF(VLOOKUP($C28,REV!$C:$AA,11,0)-'TRADE IN'!$F28=0,"",(VLOOKUP($C28,REV!$C:$AA,11,0)-'TRADE IN'!$F28)) -> 4499 | N28: =IF(VLOOKUP($C28,REV!$C:$AA,12,0)-'TRADE IN'!$F28=0,"",(VLOOKUP($C28,REV!$C:$AA,12,0)-'TRADE IN'!$F28)) -> 4499 | O28: =IF(VLOOKUP($C28,REV!$C:$AA,13,0)-'TRADE IN'!$F28=0,"",(VLOOKUP($C28,REV!$C:$AA,13,0)-'TRADE IN'!$F28)) -> 4399 | P28: =IF(VLOOKUP($C28,REV!$C:$AA,14,0)-'TRADE IN'!$F28=0,"",(VLOOKUP($C28,REV!$C:$AA,14,0)-'TRADE IN'!$F28)) -> 4299 | Q28: =IF(VLOOKUP($C28,REV!$C:$AA,15,0)-'TRADE IN'!$F28=0,"",(VLOOKUP($C28,REV!$C:$AA,15,0)-'TRADE IN'!$F28)) -> 3499 | R28: =IF(VLOOKUP($C28,REV!$C:$AA,16,0)-'TRADE IN'!$F28=0,"",(VLOOKUP($C28,REV!$C:$AA,16,0)-'TRADE IN'!$F28)) -> 4399 | S28: =IF(VLOOKUP($C28,REV!$C:$AA,17,0)-'TRADE IN'!$F28=0,"",(VLOOKUP($C28,REV!$C:$AA,17,0)-'TRADE IN'!$F28)) -> 4299 | T28: =IF(VLOOKUP($C28,REV!$C:$AA,18,0)-'TRADE IN'!$F28=0,"",(VLOOKUP($C28,REV!$C:$AA,18,0)-'TRADE IN'!$F28)) -> 3499 | U28: =IF(VLOOKUP($C28,REV!$C:$AA,19,0)-'TRADE IN'!$F28=0,"",(VLOOKUP($C28,REV!$C:$AA,19,0)-'TRADE IN'!$F28)) -> 3499 | V28: =IF(VLOOKUP($C28,REV!$C:$AA,20,0)-'TRADE IN'!$F28=0,"",(VLOOKUP($C28,REV!$C:$AA,20,0)-'TRADE IN'!$F28)) -> 3499 | W28: =IF(VLOOKUP($C28,REV!$C:$AA,21,0)-'TRADE IN'!$F28=0,"",(VLOOKUP($C28,REV!$C:$AA,21,0)-'TRADE IN'!$F28)) -> 3499 | X28: =IF(VLOOKUP($C28,REV!$C:$AA,22,0)-'TRADE IN'!$F28=0,"",(VLOOKUP($C28,REV!$C:$AA,22,0)-'TRADE IN'!$F28)) -> 3399 | Y28: =IF(VLOOKUP($C28,REV!$C:$AA,23,0)-'TRADE IN'!$F28=0,"",(VLOOKUP($C28,REV!$C:$AA,23,0)-'TRADE IN'!$F28)) -> 2899 | Z28: =IF(VLOOKUP($C28,REV!$C:$AA,24,0)-'TRADE IN'!$F28=0,"",(VLOOKUP($C28,REV!$C:$AA,24,0)-'TRADE IN'!$F28)) -> 2899 | AA28: =IF(VLOOKUP($C28,REV!$C:$AA,25,0)-'TRADE IN'!$F28=0,"",(VLOOKUP($C28,REV!$C:$AA,25,0)-'TRADE IN'!$F28)) -> 2899 | AW28: =REV!AW28 -> 03.11.2026 | AX28: =VLOOKUP(C28,REV!C:AX,48,0) -> 5G
A29: Price Oferta | B29: 21X | C29: 4015711 | D29: APPLE IPHONE 14 PLUS 256GB | E29: APPLE IPHONE 14 PLUS 256GB-PRETO NAC | J29: =IF(VLOOKUP($C29,REV!$C:$AA,8,0)-'TRADE IN'!$F29=0,"",(VLOOKUP($C29,REV!$C:$AA,8,0)-'TRADE IN'!$F29)) -> 4499 | K29: =IF(VLOOKUP($C29,REV!$C:$AA,9,0)-'TRADE IN'!$F29=0,"",(VLOOKUP($C29,REV!$C:$AA,9,0)-'TRADE IN'!$F29)) -> 4499 | L29: =IF(VLOOKUP($C29,REV!$C:$AA,10,0)-'TRADE IN'!$F29=0,"",(VLOOKUP($C29,REV!$C:$AA,10,0)-'TRADE IN'!$F29)) -> 4499 | M29: =IF(VLOOKUP($C29,REV!$C:$AA,11,0)-'TRADE IN'!$F29=0,"",(VLOOKUP($C29,REV!$C:$AA,11,0)-'TRADE IN'!$F29)) -> 4499 | N29: =IF(VLOOKUP($C29,REV!$C:$AA,12,0)-'TRADE IN'!$F29=0,"",(VLOOKUP($C29,REV!$C:$AA,12,0)-'TRADE IN'!$F29)) -> 4499 | O29: =IF(VLOOKUP($C29,REV!$C:$AA,13,0)-'TRADE IN'!$F29=0,"",(VLOOKUP($C29,REV!$C:$AA,13,0)-'TRADE IN'!$F29)) -> 4399 | P29: =IF(VLOOKUP($C29,REV!$C:$AA,14,0)-'TRADE IN'!$F29=0,"",(VLOOKUP($C29,REV!$C:$AA,14,0)-'TRADE IN'!$F29)) -> 4299 | Q29: =IF(VLOOKUP($C29,REV!$C:$AA,15,0)-'TRADE IN'!$F29=0,"",(VLOOKUP($C29,REV!$C:$AA,15,0)-'TRADE IN'!$F29)) -> 3499 | R29: =IF(VLOOKUP($C29,REV!$C:$AA,16,0)-'TRADE IN'!$F29=0,"",(VLOOKUP($C29,REV!$C:$AA,16,0)-'TRADE IN'!$F29)) -> 4399 | S29: =IF(VLOOKUP($C29,REV!$C:$AA,17,0)-'TRADE IN'!$F29=0,"",(VLOOKUP($C29,REV!$C:$AA,17,0)-'TRADE IN'!$F29)) -> 4299 | T29: =IF(VLOOKUP($C29,REV!$C:$AA,18,0)-'TRADE IN'!$F29=0,"",(VLOOKUP($C29,REV!$C:$AA,18,0)-'TRADE IN'!$F29)) -> 3499 | U29: =IF(VLOOKUP($C29,REV!$C:$AA,19,0)-'TRADE IN'!$F29=0,"",(VLOOKUP($C29,REV!$C:$AA,19,0)-'TRADE IN'!$F29)) -> 3499 | V29: =IF(VLOOKUP($C29,REV!$C:$AA,20,0)-'TRADE IN'!$F29=0,"",(VLOOKUP($C29,REV!$C:$AA,20,0)-'TRADE IN'!$F29)) -> 3499 | W29: =IF(VLOOKUP($C29,REV!$C:$AA,21,0)-'TRADE IN'!$F29=0,"",(VLOOKUP($C29,REV!$C:$AA,21,0)-'TRADE IN'!$F29)) -> 3499 | X29: =IF(VLOOKUP($C29,REV!$C:$AA,22,0)-'TRADE IN'!$F29=0,"",(VLOOKUP($C29,REV!$C:$AA,22,0)-'TRADE IN'!$F29)) -> 3399 | Y29: =IF(VLOOKUP($C29,REV!$C:$AA,23,0)-'TRADE IN'!$F29=0,"",(VLOOKUP($C29,REV!$C:$AA,23,0)-'TRADE IN'!$F29)) -> 2899 | Z29: =IF(VLOOKUP($C29,REV!$C:$AA,24,0)-'TRADE IN'!$F29=0,"",(VLOOKUP($C29,REV!$C:$AA,24,0)-'TRADE IN'!$F29)) -> 2899 | AA29: =IF(VLOOKUP($C29,REV!$C:$AA,25,0)-'TRADE IN'!$F29=0,"",(VLOOKUP($C29,REV!$C:$AA,25,0)-'TRADE IN'!$F29)) -> 2899 | AW29: =REV!AW29 -> 03.11.2026 | AX29: =VLOOKUP(C29,REV!C:AX,48,0) -> 5G
A30: Price Oferta | B30: 21X | C30: 4015162 | D30: APPLE IPHONE 14 PRO MAX 256GB | E30: APPLE IPHONE 14 PRO MAX 256GB-GRAFITE | J30: =IF(VLOOKUP($C30,REV!$C:$AA,8,0)-'TRADE IN'!$F30=0,"",(VLOOKUP($C30,REV!$C:$AA,8,0)-'TRADE IN'!$F30)) -> 6399 | K30: =IF(VLOOKUP($C30,REV!$C:$AA,9,0)-'TRADE IN'!$F30=0,"",(VLOOKUP($C30,REV!$C:$AA,9,0)-'TRADE IN'!$F30)) -> 6399 | L30: =IF(VLOOKUP($C30,REV!$C:$AA,10,0)-'TRADE IN'!$F30=0,"",(VLOOKUP($C30,REV!$C:$AA,10,0)-'TRADE IN'!$F30)) -> 6399 | M30: =IF(VLOOKUP($C30,REV!$C:$AA,11,0)-'TRADE IN'!$F30=0,"",(VLOOKUP($C30,REV!$C:$AA,11,0)-'TRADE IN'!$F30)) -> 6399 | N30: =IF(VLOOKUP($C30,REV!$C:$AA,12,0)-'TRADE IN'!$F30=0,"",(VLOOKUP($C30,REV!$C:$AA,12,0)-'TRADE IN'!$F30)) -> 6399 | O30: =IF(VLOOKUP($C30,REV!$C:$AA,13,0)-'TRADE IN'!$F30=0,"",(VLOOKUP($C30,REV!$C:$AA,13,0)-'TRADE IN'!$F30)) -> 6299 | P30: =IF(VLOOKUP($C30,REV!$C:$AA,14,0)-'TRADE IN'!$F30=0,"",(VLOOKUP($C30,REV!$C:$AA,14,0)-'TRADE IN'!$F30)) -> 6199 | Q30: =IF(VLOOKUP($C30,REV!$C:$AA,15,0)-'TRADE IN'!$F30=0,"",(VLOOKUP($C30,REV!$C:$AA,15,0)-'TRADE IN'!$F30)) -> 5999 | R30: =IF(VLOOKUP($C30,REV!$C:$AA,16,0)-'TRADE IN'!$F30=0,"",(VLOOKUP($C30,REV!$C:$AA,16,0)-'TRADE IN'!$F30)) -> 6299 | S30: =IF(VLOOKUP($C30,REV!$C:$AA,17,0)-'TRADE IN'!$F30=0,"",(VLOOKUP($C30,REV!$C:$AA,17,0)-'TRADE IN'!$F30)) -> 6199 | T30: =IF(VLOOKUP($C30,REV!$C:$AA,18,0)-'TRADE IN'!$F30=0,"",(VLOOKUP($C30,REV!$C:$AA,18,0)-'TRADE IN'!$F30)) -> 5999 | U30: =IF(VLOOKUP($C30,REV!$C:$AA,19,0)-'TRADE IN'!$F30=0,"",(VLOOKUP($C30,REV!$C:$AA,19,0)-'TRADE IN'!$F30)) -> 5999 | V30: =IF(VLOOKUP($C30,REV!$C:$AA,20,0)-'TRADE IN'!$F30=0,"",(VLOOKUP($C30,REV!$C:$AA,20,0)-'TRADE IN'!$F30)) -> 5999 | W30: =IF(VLOOKUP($C30,REV!$C:$AA,21,0)-'TRADE IN'!$F30=0,"",(VLOOKUP($C30,REV!$C:$AA,21,0)-'TRADE IN'!$F30)) -> 5999 | X30: =IF(VLOOKUP($C30,REV!$C:$AA,22,0)-'TRADE IN'!$F30=0,"",(VLOOKUP($C30,REV!$C:$AA,22,0)-'TRADE IN'!$F30)) -> 5899 | Y30: =IF(VLOOKUP($C30,REV!$C:$AA,23,0)-'TRADE IN'!$F30=0,"",(VLOOKUP($C30,REV!$C:$AA,23,0)-'TRADE IN'!$F30)) -> 5499 | Z30: =IF(VLOOKUP($C30,REV!$C:$AA,24,0)-'TRADE IN'!$F30=0,"",(VLOOKUP($C30,REV!$C:$AA,24,0)-'TRADE IN'!$F30)) -> 5499 | AA30: =IF(VLOOKUP($C30,REV!$C:$AA,25,0)-'TRADE IN'!$F30=0,"",(VLOOKUP($C30,REV!$C:$AA,25,0)-'TRADE IN'!$F30)) -> 5499 | AW30: =REV!AW30 -> 03.11.2026 | AX30: =VLOOKUP(C30,REV!C:AX,48,0) -> 5G
A31: Price Oferta | B31: 21X | C31: 4015112 | D31: APPLE IPHONE 14 PRO 256GB | E31: APPLE IPHONE 14 PRO 256GB-GRAFITE | J31: =IF(VLOOKUP($C31,REV!$C:$AA,8,0)-'TRADE IN'!$F31=0,"",(VLOOKUP($C31,REV!$C:$AA,8,0)-'TRADE IN'!$F31)) -> 5899 | K31: =IF(VLOOKUP($C31,REV!$C:$AA,9,0)-'TRADE IN'!$F31=0,"",(VLOOKUP($C31,REV!$C:$AA,9,0)-'TRADE IN'!$F31)) -> 5899 | L31: =IF(VLOOKUP($C31,REV!$C:$AA,10,0)-'TRADE IN'!$F31=0,"",(VLOOKUP($C31,REV!$C:$AA,10,0)-'TRADE IN'!$F31)) -> 5899 | M31: =IF(VLOOKUP($C31,REV!$C:$AA,11,0)-'TRADE IN'!$F31=0,"",(VLOOKUP($C31,REV!$C:$AA,11,0)-'TRADE IN'!$F31)) -> 5899 | N31: =IF(VLOOKUP($C31,REV!$C:$AA,12,0)-'TRADE IN'!$F31=0,"",(VLOOKUP($C31,REV!$C:$AA,12,0)-'TRADE IN'!$F31)) -> 5899 | O31: =IF(VLOOKUP($C31,REV!$C:$AA,13,0)-'TRADE IN'!$F31=0,"",(VLOOKUP($C31,REV!$C:$AA,13,0)-'TRADE IN'!$F31)) -> 5799 | P31: =IF(VLOOKUP($C31,REV!$C:$AA,14,0)-'TRADE IN'!$F31=0,"",(VLOOKUP($C31,REV!$C:$AA,14,0)-'TRADE IN'!$F31)) -> 5699 | Q31: =IF(VLOOKUP($C31,REV!$C:$AA,15,0)-'TRADE IN'!$F31=0,"",(VLOOKUP($C31,REV!$C:$AA,15,0)-'TRADE IN'!$F31)) -> 5499 | R31: =IF(VLOOKUP($C31,REV!$C:$AA,16,0)-'TRADE IN'!$F31=0,"",(VLOOKUP($C31,REV!$C:$AA,16,0)-'TRADE IN'!$F31)) -> 5799 | S31: =IF(VLOOKUP($C31,REV!$C:$AA,17,0)-'TRADE IN'!$F31=0,"",(VLOOKUP($C31,REV!$C:$AA,17,0)-'TRADE IN'!$F31)) -> 5699 | T31: =IF(VLOOKUP($C31,REV!$C:$AA,18,0)-'TRADE IN'!$F31=0,"",(VLOOKUP($C31,REV!$C:$AA,18,0)-'TRADE IN'!$F31)) -> 5499 | U31: =IF(VLOOKUP($C31,REV!$C:$AA,19,0)-'TRADE IN'!$F31=0,"",(VLOOKUP($C31,REV!$C:$AA,19,0)-'TRADE IN'!$F31)) -> 5499 | V31: =IF(VLOOKUP($C31,REV!$C:$AA,20,0)-'TRADE IN'!$F31=0,"",(VLOOKUP($C31,REV!$C:$AA,20,0)-'TRADE IN'!$F31)) -> 5499 | W31: =IF(VLOOKUP($C31,REV!$C:$AA,21,0)-'TRADE IN'!$F31=0,"",(VLOOKUP($C31,REV!$C:$AA,21,0)-'TRADE IN'!$F31)) -> 5499 | X31: =IF(VLOOKUP($C31,REV!$C:$AA,22,0)-'TRADE IN'!$F31=0,"",(VLOOKUP($C31,REV!$C:$AA,22,0)-'TRADE IN'!$F31)) -> 5399 | Y31: =IF(VLOOKUP($C31,REV!$C:$AA,23,0)-'TRADE IN'!$F31=0,"",(VLOOKUP($C31,REV!$C:$AA,23,0)-'TRADE IN'!$F31)) -> 4999 | Z31: =IF(VLOOKUP($C31,REV!$C:$AA,24,0)-'TRADE IN'!$F31=0,"",(VLOOKUP($C31,REV!$C:$AA,24,0)-'TRADE IN'!$F31)) -> 4999 | AA31: =IF(VLOOKUP($C31,REV!$C:$AA,25,0)-'TRADE IN'!$F31=0,"",(VLOOKUP($C31,REV!$C:$AA,25,0)-'TRADE IN'!$F31)) -> 4999 | AW31: =REV!AW31 -> 03.11.2026 | AX31: =VLOOKUP(C31,REV!C:AX,48,0) -> 5G
A32: Price Oferta | B32: 21X | C32: 4015116 | D32: APPLE IPHONE 14 PRO 256GB | E32: APPLE IPHONE 14 PRO 256GB-DOURADO | J32: =IF(VLOOKUP($C32,REV!$C:$AA,8,0)-'TRADE IN'!$F32=0,"",(VLOOKUP($C32,REV!$C:$AA,8,0)-'TRADE IN'!$F32)) -> 5899 | K32: =IF(VLOOKUP($C32,REV!$C:$AA,9,0)-'TRADE IN'!$F32=0,"",(VLOOKUP($C32,REV!$C:$AA,9,0)-'TRADE IN'!$F32)) -> 5899 | L32: =IF(VLOOKUP($C32,REV!$C:$AA,10,0)-'TRADE IN'!$F32=0,"",(VLOOKUP($C32,REV!$C:$AA,10,0)-'TRADE IN'!$F32)) -> 5899 | M32: =IF(VLOOKUP($C32,REV!$C:$AA,11,0)-'TRADE IN'!$F32=0,"",(VLOOKUP($C32,REV!$C:$AA,11,0)-'TRADE IN'!$F32)) -> 5899 | N32: =IF(VLOOKUP($C32,REV!$C:$AA,12,0)-'TRADE IN'!$F32=0,"",(VLOOKUP($C32,REV!$C:$AA,12,0)-'TRADE IN'!$F32)) -> 5899 | O32: =IF(VLOOKUP($C32,REV!$C:$AA,13,0)-'TRADE IN'!$F32=0,"",(VLOOKUP($C32,REV!$C:$AA,13,0)-'TRADE IN'!$F32)) -> 5799 | P32: =IF(VLOOKUP($C32,REV!$C:$AA,14,0)-'TRADE IN'!$F32=0,"",(VLOOKUP($C32,REV!$C:$AA,14,0)-'TRADE IN'!$F32)) -> 5699 | Q32: =IF(VLOOKUP($C32,REV!$C:$AA,15,0)-'TRADE IN'!$F32=0,"",(VLOOKUP($C32,REV!$C:$AA,15,0)-'TRADE IN'!$F32)) -> 5499 | R32: =IF(VLOOKUP($C32,REV!$C:$AA,16,0)-'TRADE IN'!$F32=0,"",(VLOOKUP($C32,REV!$C:$AA,16,0)-'TRADE IN'!$F32)) -> 5799 | S32: =IF(VLOOKUP($C32,REV!$C:$AA,17,0)-'TRADE IN'!$F32=0,"",(VLOOKUP($C32,REV!$C:$AA,17,0)-'TRADE IN'!$F32)) -> 5699 | T32: =IF(VLOOKUP($C32,REV!$C:$AA,18,0)-'TRADE IN'!$F32=0,"",(VLOOKUP($C32,REV!$C:$AA,18,0)-'TRADE IN'!$F32)) -> 5499 | U32: =IF(VLOOKUP($C32,REV!$C:$AA,19,0)-'TRADE IN'!$F32=0,"",(VLOOKUP($C32,REV!$C:$AA,19,0)-'TRADE IN'!$F32)) -> 5499 | V32: =IF(VLOOKUP($C32,REV!$C:$AA,20,0)-'TRADE IN'!$F32=0,"",(VLOOKUP($C32,REV!$C:$AA,20,0)-'TRADE IN'!$F32)) -> 5499 | W32: =IF(VLOOKUP($C32,REV!$C:$AA,21,0)-'TRADE IN'!$F32=0,"",(VLOOKUP($C32,REV!$C:$AA,21,0)-'TRADE IN'!$F32)) -> 5499 | X32: =IF(VLOOKUP($C32,REV!$C:$AA,22,0)-'TRADE IN'!$F32=0,"",(VLOOKUP($C32,REV!$C:$AA,22,0)-'TRADE IN'!$F32)) -> 5399 | Y32: =IF(VLOOKUP($C32,REV!$C:$AA,23,0)-'TRADE IN'!$F32=0,"",(VLOOKUP($C32,REV!$C:$AA,23,0)-'TRADE IN'!$F32)) -> 4999 | Z32: =IF(VLOOKUP($C32,REV!$C:$AA,24,0)-'TRADE IN'!$F32=0,"",(VLOOKUP($C32,REV!$C:$AA,24,0)-'TRADE IN'!$F32)) -> 4999 | AA32: =IF(VLOOKUP($C32,REV!$C:$AA,25,0)-'TRADE IN'!$F32=0,"",(VLOOKUP($C32,REV!$C:$AA,25,0)-'TRADE IN'!$F32)) -> 4999 | AW32: =REV!AW32 -> 03.11.2026 | AX32: =VLOOKUP(C32,REV!C:AX,48,0) -> 5G
A33: Price Oferta | B33: 21X | C33: 4015742 | D33: APPLE IPHONE 15 128GB | E33: APPLE IPHONE 15 128GB-PRETO | J33: =IF(VLOOKUP($C33,REV!$C:$AA,8,0)-'TRADE IN'!$F33=0,"",(VLOOKUP($C33,REV!$C:$AA,8,0)-'TRADE IN'!$F33)) -> 4999 | K33: =IF(VLOOKUP($C33,REV!$C:$AA,9,0)-'TRADE IN'!$F33=0,"",(VLOOKUP($C33,REV!$C:$AA,9,0)-'TRADE IN'!$F33)) -> 4899 | L33: =IF(VLOOKUP($C33,REV!$C:$AA,10,0)-'TRADE IN'!$F33=0,"",(VLOOKUP($C33,REV!$C:$AA,10,0)-'TRADE IN'!$F33)) -> 4899 | M33: =IF(VLOOKUP($C33,REV!$C:$AA,11,0)-'TRADE IN'!$F33=0,"",(VLOOKUP($C33,REV!$C:$AA,11,0)-'TRADE IN'!$F33)) -> 4999 | N33: =IF(VLOOKUP($C33,REV!$C:$AA,12,0)-'TRADE IN'!$F33=0,"",(VLOOKUP($C33,REV!$C:$AA,12,0)-'TRADE IN'!$F33)) -> 4899 | O33: =IF(VLOOKUP($C33,REV!$C:$AA,13,0)-'TRADE IN'!$F33=0,"",(VLOOKUP($C33,REV!$C:$AA,13,0)-'TRADE IN'!$F33)) -> 4799 | P33: =IF(VLOOKUP($C33,REV!$C:$AA,14,0)-'TRADE IN'!$F33=0,"",(VLOOKUP($C33,REV!$C:$AA,14,0)-'TRADE IN'!$F33)) -> 4699 | Q33: =IF(VLOOKUP($C33,REV!$C:$AA,15,0)-'TRADE IN'!$F33=0,"",(VLOOKUP($C33,REV!$C:$AA,15,0)-'TRADE IN'!$F33)) -> 4499 | R33: =IF(VLOOKUP($C33,REV!$C:$AA,16,0)-'TRADE IN'!$F33=0,"",(VLOOKUP($C33,REV!$C:$AA,16,0)-'TRADE IN'!$F33)) -> 4799 | S33: =IF(VLOOKUP($C33,REV!$C:$AA,17,0)-'TRADE IN'!$F33=0,"",(VLOOKUP($C33,REV!$C:$AA,17,0)-'TRADE IN'!$F33)) -> 4699 | T33: =IF(VLOOKUP($C33,REV!$C:$AA,18,0)-'TRADE IN'!$F33=0,"",(VLOOKUP($C33,REV!$C:$AA,18,0)-'TRADE IN'!$F33)) -> 4499 | U33: =IF(VLOOKUP($C33,REV!$C:$AA,19,0)-'TRADE IN'!$F33=0,"",(VLOOKUP($C33,REV!$C:$AA,19,0)-'TRADE IN'!$F33)) -> 4399 | V33: =IF(VLOOKUP($C33,REV!$C:$AA,20,0)-'TRADE IN'!$F33=0,"",(VLOOKUP($C33,REV!$C:$AA,20,0)-'TRADE IN'!$F33)) -> 4399 | W33: =IF(VLOOKUP($C33,REV!$C:$AA,21,0)-'TRADE IN'!$F33=0,"",(VLOOKUP($C33,REV!$C:$AA,21,0)-'TRADE IN'!$F33)) -> 4299 | X33: =IF(VLOOKUP($C33,REV!$C:$AA,22,0)-'TRADE IN'!$F33=0,"",(VLOOKUP($C33,REV!$C:$AA,22,0)-'TRADE IN'!$F33)) -> 4199 | Y33: =IF(VLOOKUP($C33,REV!$C:$AA,23,0)-'TRADE IN'!$F33=0,"",(VLOOKUP($C33,REV!$C:$AA,23,0)-'TRADE IN'!$F33)) -> 3499 | Z33: =IF(VLOOKUP($C33,REV!$C:$AA,24,0)-'TRADE IN'!$F33=0,"",(VLOOKUP($C33,REV!$C:$AA,24,0)-'TRADE IN'!$F33)) -> 3499 | AA33: =IF(VLOOKUP($C33,REV!$C:$AA,25,0)-'TRADE IN'!$F33=0,"",(VLOOKUP($C33,REV!$C:$AA,25,0)-'TRADE IN'!$F33)) -> 3499 | AW33: =REV!AW33 -> 03.11.2026 | AX33: =VLOOKUP(C33,REV!C:AX,48,0) -> 5G
A34: Price Oferta | B34: 21X | C34: 4015725 | D34: APPLE IPHONE 15 128GB | E34: APPLE IPHONE 15 128GB-ROSA | J34: =IF(VLOOKUP($C34,REV!$C:$AA,8,0)-'TRADE IN'!$F34=0,"",(VLOOKUP($C34,REV!$C:$AA,8,0)-'TRADE IN'!$F34)) -> 4999 | K34: =IF(VLOOKUP($C34,REV!$C:$AA,9,0)-'TRADE IN'!$F34=0,"",(VLOOKUP($C34,REV!$C:$AA,9,0)-'TRADE IN'!$F34)) -> 4899 | L34: =IF(VLOOKUP($C34,REV!$C:$AA,10,0)-'TRADE IN'!$F34=0,"",(VLOOKUP($C34,REV!$C:$AA,10,0)-'TRADE IN'!$F34)) -> 4899 | M34: =IF(VLOOKUP($C34,REV!$C:$AA,11,0)-'TRADE IN'!$F34=0,"",(VLOOKUP($C34,REV!$C:$AA,11,0)-'TRADE IN'!$F34)) -> 4999 | N34: =IF(VLOOKUP($C34,REV!$C:$AA,12,0)-'TRADE IN'!$F34=0,"",(VLOOKUP($C34,REV!$C:$AA,12,0)-'TRADE IN'!$F34)) -> 4899 | O34: =IF(VLOOKUP($C34,REV!$C:$AA,13,0)-'TRADE IN'!$F34=0,"",(VLOOKUP($C34,REV!$C:$AA,13,0)-'TRADE IN'!$F34)) -> 4799 | P34: =IF(VLOOKUP($C34,REV!$C:$AA,14,0)-'TRADE IN'!$F34=0,"",(VLOOKUP($C34,REV!$C:$AA,14,0)-'TRADE IN'!$F34)) -> 4699 | Q34: =IF(VLOOKUP($C34,REV!$C:$AA,15,0)-'TRADE IN'!$F34=0,"",(VLOOKUP($C34,REV!$C:$AA,15,0)-'TRADE IN'!$F34)) -> 4499 | R34: =IF(VLOOKUP($C34,REV!$C:$AA,16,0)-'TRADE IN'!$F34=0,"",(VLOOKUP($C34,REV!$C:$AA,16,0)-'TRADE IN'!$F34)) -> 4799 | S34: =IF(VLOOKUP($C34,REV!$C:$AA,17,0)-'TRADE IN'!$F34=0,"",(VLOOKUP($C34,REV!$C:$AA,17,0)-'TRADE IN'!$F34)) -> 4699 | T34: =IF(VLOOKUP($C34,REV!$C:$AA,18,0)-'TRADE IN'!$F34=0,"",(VLOOKUP($C34,REV!$C:$AA,18,0)-'TRADE IN'!$F34)) -> 4499 | U34: =IF(VLOOKUP($C34,REV!$C:$AA,19,0)-'TRADE IN'!$F34=0,"",(VLOOKUP($C34,REV!$C:$AA,19,0)-'TRADE IN'!$F34)) -> 4399 | V34: =IF(VLOOKUP($C34,REV!$C:$AA,20,0)-'TRADE IN'!$F34=0,"",(VLOOKUP($C34,REV!$C:$AA,20,0)-'TRADE IN'!$F34)) -> 4399 | W34: =IF(VLOOKUP($C34,REV!$C:$AA,21,0)-'TRADE IN'!$F34=0,"",(VLOOKUP($C34,REV!$C:$AA,21,0)-'TRADE IN'!$F34)) -> 4299 | X34: =IF(VLOOKUP($C34,REV!$C:$AA,22,0)-'TRADE IN'!$F34=0,"",(VLOOKUP($C34,REV!$C:$AA,22,0)-'TRADE IN'!$F34)) -> 4199 | Y34: =IF(VLOOKUP($C34,REV!$C:$AA,23,0)-'TRADE IN'!$F34=0,"",(VLOOKUP($C34,REV!$C:$AA,23,0)-'TRADE IN'!$F34)) -> 3499 | Z34: =IF(VLOOKUP($C34,REV!$C:$AA,24,0)-'TRADE IN'!$F34=0,"",(VLOOKUP($C34,REV!$C:$AA,24,0)-'TRADE IN'!$F34)) -> 3499 | AA34: =IF(VLOOKUP($C34,REV!$C:$AA,25,0)-'TRADE IN'!$F34=0,"",(VLOOKUP($C34,REV!$C:$AA,25,0)-'TRADE IN'!$F34)) -> 3499 | AW34: =REV!AW34 -> 03.11.2026 | AX34: =VLOOKUP(C34,REV!C:AX,48,0) -> 5G
A35: Price Oferta | B35: 21X | C35: 4015794 | D35: APPLE IPHONE 15 128GB | E35: APPLE IPHONE 15 128GB-VERDE | J35: =IF(VLOOKUP($C35,REV!$C:$AA,8,0)-'TRADE IN'!$F35=0,"",(VLOOKUP($C35,REV!$C:$AA,8,0)-'TRADE IN'!$F35)) -> 4999 | K35: =IF(VLOOKUP($C35,REV!$C:$AA,9,0)-'TRADE IN'!$F35=0,"",(VLOOKUP($C35,REV!$C:$AA,9,0)-'TRADE IN'!$F35)) -> 4899 | L35: =IF(VLOOKUP($C35,REV!$C:$AA,10,0)-'TRADE IN'!$F35=0,"",(VLOOKUP($C35,REV!$C:$AA,10,0)-'TRADE IN'!$F35)) -> 4899 | M35: =IF(VLOOKUP($C35,REV!$C:$AA,11,0)-'TRADE IN'!$F35=0,"",(VLOOKUP($C35,REV!$C:$AA,11,0)-'TRADE IN'!$F35)) -> 4999 | N35: =IF(VLOOKUP($C35,REV!$C:$AA,12,0)-'TRADE IN'!$F35=0,"",(VLOOKUP($C35,REV!$C:$AA,12,0)-'TRADE IN'!$F35)) -> 4899 | O35: =IF(VLOOKUP($C35,REV!$C:$AA,13,0)-'TRADE IN'!$F35=0,"",(VLOOKUP($C35,REV!$C:$AA,13,0)-'TRADE IN'!$F35)) -> 4799 | P35: =IF(VLOOKUP($C35,REV!$C:$AA,14,0)-'TRADE IN'!$F35=0,"",(VLOOKUP($C35,REV!$C:$AA,14,0)-'TRADE IN'!$F35)) -> 4699 | Q35: =IF(VLOOKUP($C35,REV!$C:$AA,15,0)-'TRADE IN'!$F35=0,"",(VLOOKUP($C35,REV!$C:$AA,15,0)-'TRADE IN'!$F35)) -> 4499 | R35: =IF(VLOOKUP($C35,REV!$C:$AA,16,0)-'TRADE IN'!$F35=0,"",(VLOOKUP($C35,REV!$C:$AA,16,0)-'TRADE IN'!$F35)) -> 4799 | S35: =IF(VLOOKUP($C35,REV!$C:$AA,17,0)-'TRADE IN'!$F35=0,"",(VLOOKUP($C35,REV!$C:$AA,17,0)-'TRADE IN'!$F35)) -> 4699 | T35: =IF(VLOOKUP($C35,REV!$C:$AA,18,0)-'TRADE IN'!$F35=0,"",(VLOOKUP($C35,REV!$C:$AA,18,0)-'TRADE IN'!$F35)) -> 4499 | U35: =IF(VLOOKUP($C35,REV!$C:$AA,19,0)-'TRADE IN'!$F35=0,"",(VLOOKUP($C35,REV!$C:$AA,19,0)-'TRADE IN'!$F35)) -> 4399 | V35: =IF(VLOOKUP($C35,REV!$C:$AA,20,0)-'TRADE IN'!$F35=0,"",(VLOOKUP($C35,REV!$C:$AA,20,0)-'TRADE IN'!$F35)) -> 4399 | W35: =IF(VLOOKUP($C35,REV!$C:$AA,21,0)-'TRADE IN'!$F35=0,"",(VLOOKUP($C35,REV!$C:$AA,21,0)-'TRADE IN'!$F35)) -> 4299 | X35: =IF(VLOOKUP($C35,REV!$C:$AA,22,0)-'TRADE IN'!$F35=0,"",(VLOOKUP($C35,REV!$C:$AA,22,0)-'TRADE IN'!$F35)) -> 4199 | Y35: =IF(VLOOKUP($C35,REV!$C:$AA,23,0)-'TRADE IN'!$F35=0,"",(VLOOKUP($C35,REV!$C:$AA,23,0)-'TRADE IN'!$F35)) -> 3499 | Z35: =IF(VLOOKUP($C35,REV!$C:$AA,24,0)-'TRADE IN'!$F35=0,"",(VLOOKUP($C35,REV!$C:$AA,24,0)-'TRADE IN'!$F35)) -> 3499 | AA35: =IF(VLOOKUP($C35,REV!$C:$AA,25,0)-'TRADE IN'!$F35=0,"",(VLOOKUP($C35,REV!$C:$AA,25,0)-'TRADE IN'!$F35)) -> 3499 | AW35: =REV!AW35 -> 03.11.2026 | AX35: =VLOOKUP(C35,REV!C:AX,48,0) -> 5G
A36: Price Oferta | B36: 21X | C36: 4015808 | D36: APPLE IPHONE 15 128GB | E36: APPLE IPHONE 15 128GB-AMARELO | J36: =IF(VLOOKUP($C36,REV!$C:$AA,8,0)-'TRADE IN'!$F36=0,"",(VLOOKUP($C36,REV!$C:$AA,8,0)-'TRADE IN'!$F36)) -> 4999 | K36: =IF(VLOOKUP($C36,REV!$C:$AA,9,0)-'TRADE IN'!$F36=0,"",(VLOOKUP($C36,REV!$C:$AA,9,0)-'TRADE IN'!$F36)) -> 4899 | L36: =IF(VLOOKUP($C36,REV!$C:$AA,10,0)-'TRADE IN'!$F36=0,"",(VLOOKUP($C36,REV!$C:$AA,10,0)-'TRADE IN'!$F36)) -> 4899 | M36: =IF(VLOOKUP($C36,REV!$C:$AA,11,0)-'TRADE IN'!$F36=0,"",(VLOOKUP($C36,REV!$C:$AA,11,0)-'TRADE IN'!$F36)) -> 4999 | N36: =IF(VLOOKUP($C36,REV!$C:$AA,12,0)-'TRADE IN'!$F36=0,"",(VLOOKUP($C36,REV!$C:$AA,12,0)-'TRADE IN'!$F36)) -> 4899 | O36: =IF(VLOOKUP($C36,REV!$C:$AA,13,0)-'TRADE IN'!$F36=0,"",(VLOOKUP($C36,REV!$C:$AA,13,0)-'TRADE IN'!$F36)) -> 4799 | P36: =IF(VLOOKUP($C36,REV!$C:$AA,14,0)-'TRADE IN'!$F36=0,"",(VLOOKUP($C36,REV!$C:$AA,14,0)-'TRADE IN'!$F36)) -> 4699 | Q36: =IF(VLOOKUP($C36,REV!$C:$AA,15,0)-'TRADE IN'!$F36=0,"",(VLOOKUP($C36,REV!$C:$AA,15,0)-'TRADE IN'!$F36)) -> 4499 | R36: =IF(VLOOKUP($C36,REV!$C:$AA,16,0)-'TRADE IN'!$F36=0,"",(VLOOKUP($C36,REV!$C:$AA,16,0)-'TRADE IN'!$F36)) -> 4799 | S36: =IF(VLOOKUP($C36,REV!$C:$AA,17,0)-'TRADE IN'!$F36=0,"",(VLOOKUP($C36,REV!$C:$AA,17,0)-'TRADE IN'!$F36)) -> 4699 | T36: =IF(VLOOKUP($C36,REV!$C:$AA,18,0)-'TRADE IN'!$F36=0,"",(VLOOKUP($C36,REV!$C:$AA,18,0)-'TRADE IN'!$F36)) -> 4499 | U36: =IF(VLOOKUP($C36,REV!$C:$AA,19,0)-'TRADE IN'!$F36=0,"",(VLOOKUP($C36,REV!$C:$AA,19,0)-'TRADE IN'!$F36)) -> 4399 | V36: =IF(VLOOKUP($C36,REV!$C:$AA,20,0)-'TRADE IN'!$F36=0,"",(VLOOKUP($C36,REV!$C:$AA,20,0)-'TRADE IN'!$F36)) -> 4399 | W36: =IF(VLOOKUP($C36,REV!$C:$AA,21,0)-'TRADE IN'!$F36=0,"",(VLOOKUP($C36,REV!$C:$AA,21,0)-'TRADE IN'!$F36)) -> 4299 | X36: =IF(VLOOKUP($C36,REV!$C:$AA,22,0)-'TRADE IN'!$F36=0,"",(VLOOKUP($C36,REV!$C:$AA,22,0)-'TRADE IN'!$F36)) -> 4199 | Y36: =IF(VLOOKUP($C36,REV!$C:$AA,23,0)-'TRADE IN'!$F36=0,"",(VLOOKUP($C36,REV!$C:$AA,23,0)-'TRADE IN'!$F36)) -> 3499 | Z36: =IF(VLOOKUP($C36,REV!$C:$AA,24,0)-'TRADE IN'!$F36=0,"",(VLOOKUP($C36,REV!$C:$AA,24,0)-'TRADE IN'!$F36)) -> 3499 | AA36: =IF(VLOOKUP($C36,REV!$C:$AA,25,0)-'TRADE IN'!$F36=0,"",(VLOOKUP($C36,REV!$C:$AA,25,0)-'TRADE IN'!$F36)) -> 3499 | AW36: =REV!AW36 -> 03.11.2026 | AX36: =VLOOKUP(C36,REV!C:AX,48,0) -> 5G
A37: Price Oferta | B37: 21X | C37: 4015743 | D37: APPLE IPHONE 15 256GB | E37: APPLE IPHONE 15 256GB-PRETO | J37: =IF(VLOOKUP($C37,REV!$C:$AA,8,0)-'TRADE IN'!$F37=0,"",(VLOOKUP($C37,REV!$C:$AA,8,0)-'TRADE IN'!$F37)) -> 5099 | K37: =IF(VLOOKUP($C37,REV!$C:$AA,9,0)-'TRADE IN'!$F37=0,"",(VLOOKUP($C37,REV!$C:$AA,9,0)-'TRADE IN'!$F37)) -> 5099 | L37: =IF(VLOOKUP($C37,REV!$C:$AA,10,0)-'TRADE IN'!$F37=0,"",(VLOOKUP($C37,REV!$C:$AA,10,0)-'TRADE IN'!$F37)) -> 5099 | M37: =IF(VLOOKUP($C37,REV!$C:$AA,11,0)-'TRADE IN'!$F37=0,"",(VLOOKUP($C37,REV!$C:$AA,11,0)-'TRADE IN'!$F37)) -> 5099 | N37: =IF(VLOOKUP($C37,REV!$C:$AA,12,0)-'TRADE IN'!$F37=0,"",(VLOOKUP($C37,REV!$C:$AA,12,0)-'TRADE IN'!$F37)) -> 5099 | O37: =IF(VLOOKUP($C37,REV!$C:$AA,13,0)-'TRADE IN'!$F37=0,"",(VLOOKUP($C37,REV!$C:$AA,13,0)-'TRADE IN'!$F37)) -> 4999 | P37: =IF(VLOOKUP($C37,REV!$C:$AA,14,0)-'TRADE IN'!$F37=0,"",(VLOOKUP($C37,REV!$C:$AA,14,0)-'TRADE IN'!$F37)) -> 4899 | Q37: =IF(VLOOKUP($C37,REV!$C:$AA,15,0)-'TRADE IN'!$F37=0,"",(VLOOKUP($C37,REV!$C:$AA,15,0)-'TRADE IN'!$F37)) -> 3999 | R37: =IF(VLOOKUP($C37,REV!$C:$AA,16,0)-'TRADE IN'!$F37=0,"",(VLOOKUP($C37,REV!$C:$AA,16,0)-'TRADE IN'!$F37)) -> 4999 | S37: =IF(VLOOKUP($C37,REV!$C:$AA,17,0)-'TRADE IN'!$F37=0,"",(VLOOKUP($C37,REV!$C:$AA,17,0)-'TRADE IN'!$F37)) -> 4899 | T37: =IF(VLOOKUP($C37,REV!$C:$AA,18,0)-'TRADE IN'!$F37=0,"",(VLOOKUP($C37,REV!$C:$AA,18,0)-'TRADE IN'!$F37)) -> 3999 | U37: =IF(VLOOKUP($C37,REV!$C:$AA,19,0)-'TRADE IN'!$F37=0,"",(VLOOKUP($C37,REV!$C:$AA,19,0)-'TRADE IN'!$F37)) -> 3999 | V37: =IF(VLOOKUP($C37,REV!$C:$AA,20,0)-'TRADE IN'!$F37=0,"",(VLOOKUP($C37,REV!$C:$AA,20,0)-'TRADE IN'!$F37)) -> 3999 | W37: =IF(VLOOKUP($C37,REV!$C:$AA,21,0)-'TRADE IN'!$F37=0,"",(VLOOKUP($C37,REV!$C:$AA,21,0)-'TRADE IN'!$F37)) -> 3999 | X37: =IF(VLOOKUP($C37,REV!$C:$AA,22,0)-'TRADE IN'!$F37=0,"",(VLOOKUP($C37,REV!$C:$AA,22,0)-'TRADE IN'!$F37)) -> 3899 | Y37: =IF(VLOOKUP($C37,REV!$C:$AA,23,0)-'TRADE IN'!$F37=0,"",(VLOOKUP($C37,REV!$C:$AA,23,0)-'TRADE IN'!$F37)) -> 3699 | Z37: =IF(VLOOKUP($C37,REV!$C:$AA,24,0)-'TRADE IN'!$F37=0,"",(VLOOKUP($C37,REV!$C:$AA,24,0)-'TRADE IN'!$F37)) -> 3699 | AA37: =IF(VLOOKUP($C37,REV!$C:$AA,25,0)-'TRADE IN'!$F37=0,"",(VLOOKUP($C37,REV!$C:$AA,25,0)-'TRADE IN'!$F37)) -> 3649 | AW37: =REV!AW37 -> 03.11.2026 | AX37: =VLOOKUP(C37,REV!C:AX,48,0) -> 5G
A38: Price Oferta | B38: 21X | C38: 4015770 | D38: APPLE IPHONE 15 256GB | E38: APPLE IPHONE 15 256GB-AZUL | J38: =IF(VLOOKUP($C38,REV!$C:$AA,8,0)-'TRADE IN'!$F38=0,"",(VLOOKUP($C38,REV!$C:$AA,8,0)-'TRADE IN'!$F38)) -> 5099 | K38: =IF(VLOOKUP($C38,REV!$C:$AA,9,0)-'TRADE IN'!$F38=0,"",(VLOOKUP($C38,REV!$C:$AA,9,0)-'TRADE IN'!$F38)) -> 5099 | L38: =IF(VLOOKUP($C38,REV!$C:$AA,10,0)-'TRADE IN'!$F38=0,"",(VLOOKUP($C38,REV!$C:$AA,10,0)-'TRADE IN'!$F38)) -> 5099 | M38: =IF(VLOOKUP($C38,REV!$C:$AA,11,0)-'TRADE IN'!$F38=0,"",(VLOOKUP($C38,REV!$C:$AA,11,0)-'TRADE IN'!$F38)) -> 5099 | N38: =IF(VLOOKUP($C38,REV!$C:$AA,12,0)-'TRADE IN'!$F38=0,"",(VLOOKUP($C38,REV!$C:$AA,12,0)-'TRADE IN'!$F38)) -> 5099 | O38: =IF(VLOOKUP($C38,REV!$C:$AA,13,0)-'TRADE IN'!$F38=0,"",(VLOOKUP($C38,REV!$C:$AA,13,0)-'TRADE IN'!$F38)) -> 4999 | P38: =IF(VLOOKUP($C38,REV!$C:$AA,14,0)-'TRADE IN'!$F38=0,"",(VLOOKUP($C38,REV!$C:$AA,14,0)-'TRADE IN'!$F38)) -> 4899 | Q38: =IF(VLOOKUP($C38,REV!$C:$AA,15,0)-'TRADE IN'!$F38=0,"",(VLOOKUP($C38,REV!$C:$AA,15,0)-'TRADE IN'!$F38)) -> 3999 | R38: =IF(VLOOKUP($C38,REV!$C:$AA,16,0)-'TRADE IN'!$F38=0,"",(VLOOKUP($C38,REV!$C:$AA,16,0)-'TRADE IN'!$F38)) -> 4999 | S38: =IF(VLOOKUP($C38,REV!$C:$AA,17,0)-'TRADE IN'!$F38=0,"",(VLOOKUP($C38,REV!$C:$AA,17,0)-'TRADE IN'!$F38)) -> 4899 | T38: =IF(VLOOKUP($C38,REV!$C:$AA,18,0)-'TRADE IN'!$F38=0,"",(VLOOKUP($C38,REV!$C:$AA,18,0)-'TRADE IN'!$F38)) -> 3999 | U38: =IF(VLOOKUP($C38,REV!$C:$AA,19,0)-'TRADE IN'!$F38=0,"",(VLOOKUP($C38,REV!$C:$AA,19,0)-'TRADE IN'!$F38)) -> 3999 | V38: =IF(VLOOKUP($C38,REV!$C:$AA,20,0)-'TRADE IN'!$F38=0,"",(VLOOKUP($C38,REV!$C:$AA,20,0)-'TRADE IN'!$F38)) -> 3999 | W38: =IF(VLOOKUP($C38,REV!$C:$AA,21,0)-'TRADE IN'!$F38=0,"",(VLOOKUP($C38,REV!$C:$AA,21,0)-'TRADE IN'!$F38)) -> 3999 | X38: =IF(VLOOKUP($C38,REV!$C:$AA,22,0)-'TRADE IN'!$F38=0,"",(VLOOKUP($C38,REV!$C:$AA,22,0)-'TRADE IN'!$F38)) -> 3899 | Y38: =IF(VLOOKUP($C38,REV!$C:$AA,23,0)-'TRADE IN'!$F38=0,"",(VLOOKUP($C38,REV!$C:$AA,23,0)-'TRADE IN'!$F38)) -> 3699 | Z38: =IF(VLOOKUP($C38,REV!$C:$AA,24,0)-'TRADE IN'!$F38=0,"",(VLOOKUP($C38,REV!$C:$AA,24,0)-'TRADE IN'!$F38)) -> 3699 | AA38: =IF(VLOOKUP($C38,REV!$C:$AA,25,0)-'TRADE IN'!$F38=0,"",(VLOOKUP($C38,REV!$C:$AA,25,0)-'TRADE IN'!$F38)) -> 3649 | AW38: =REV!AW38 -> 03.11.2026 | AX38: =VLOOKUP(C38,REV!C:AX,48,0) -> 5G
... A85: Price Oferta | B85: 21X | C85: 4016609 | D85: APPLE IPHONE 16 PRO MAX 512GB | E85: APPLE IPHONE 16 PRO MAX 512GB-TITANIO | J85: =IF(VLOOKUP($C85,REV!$C:$AA,8,0)-'TRADE IN'!$F85=0,"",(VLOOKUP($C85,REV!$C:$AA,8,0)-'TRADE IN'!$F85)) -> 11999 | K85: =IF(VLOOKUP($C85,REV!$C:$AA,9,0)-'TRADE IN'!$F85=0,"",(VLOOKUP($C85,REV!$C:$AA,9,0)-'TRADE IN'!$F85)) -> 11999 | L85: =IF(VLOOKUP($C85,REV!$C:$AA,10,0)-'TRADE IN'!$F85=0,"",(VLOOKUP($C85,REV!$C:$AA,10,0)-'TRADE IN'!$F85)) -> 11999 | M85: =IF(VLOOKUP($C85,REV!$C:$AA,11,0)-'TRADE IN'!$F85=0,"",(VLOOKUP($C85,REV!$C:$AA,11,0)-'TRADE IN'!$F85)) -> 11999 | N85: =IF(VLOOKUP($C85,REV!$C:$AA,12,0)-'TRADE IN'!$F85=0,"",(VLOOKUP($C85,REV!$C:$AA,12,0)-'TRADE IN'!$F85)) -> 11999 | O85: =IF(VLOOKUP($C85,REV!$C:$AA,13,0)-'TRADE IN'!$F85=0,"",(VLOOKUP($C85,REV!$C:$AA,13,0)-'TRADE IN'!$F85)) -> 11699 | P85: =IF(VLOOKUP($C85,REV!$C:$AA,14,0)-'TRADE IN'!$F85=0,"",(VLOOKUP($C85,REV!$C:$AA,14,0)-'TRADE IN'!$F85)) -> 11599 | Q85: =IF(VLOOKUP($C85,REV!$C:$AA,15,0)-'TRADE IN'!$F85=0,"",(VLOOKUP($C85,REV!$C:$AA,15,0)-'TRADE IN'!$F85)) -> 10999 | R85: =IF(VLOOKUP($C85,REV!$C:$AA,16,0)-'TRADE IN'!$F85=0,"",(VLOOKUP($C85,REV!$C:$AA,16,0)-'TRADE IN'!$F85)) -> 11699 | S85: =IF(VLOOKUP($C85,REV!$C:$AA,17,0)-'TRADE IN'!$F85=0,"",(VLOOKUP($C85,REV!$C:$AA,17,0)-'TRADE IN'!$F85)) -> 11599 | T85: =IF(VLOOKUP($C85,REV!$C:$AA,18,0)-'TRADE IN'!$F85=0,"",(VLOOKUP($C85,REV!$C:$AA,18,0)-'TRADE IN'!$F85)) -> 10999 | U85: =IF(VLOOKUP($C85,REV!$C:$AA,19,0)-'TRADE IN'!$F85=0,"",(VLOOKUP($C85,REV!$C:$AA,19,0)-'TRADE IN'!$F85)) -> 10999 | V85: =IF(VLOOKUP($C85,REV!$C:$AA,20,0)-'TRADE IN'!$F85=0,"",(VLOOKUP($C85,REV!$C:$AA,20,0)-'TRADE IN'!$F85)) -> 10999 | W85: =IF(VLOOKUP($C85,REV!$C:$AA,21,0)-'TRADE IN'!$F85=0,"",(VLOOKUP($C85,REV!$C:$AA,21,0)-'TRADE IN'!$F85)) -> 10999 | X85: =IF(VLOOKUP($C85,REV!$C:$AA,22,0)-'TRADE IN'!$F85=0,"",(VLOOKUP($C85,REV!$C:$AA,22,0)-'TRADE IN'!$F85)) -> 10799 | Y85: =IF(VLOOKUP($C85,REV!$C:$AA,23,0)-'TRADE IN'!$F85=0,"",(VLOOKUP($C85,REV!$C:$AA,23,0)-'TRADE IN'!$F85)) -> 10299 | Z85: =IF(VLOOKUP($C85,REV!$C:$AA,24,0)-'TRADE IN'!$F85=0,"",(VLOOKUP($C85,REV!$C:$AA,24,0)-'TRADE IN'!$F85)) -> 10299 | AA85: =IF(VLOOKUP($C85,REV!$C:$AA,25,0)-'TRADE IN'!$F85=0,"",(VLOOKUP($C85,REV!$C:$AA,25,0)-'TRADE IN'!$F85)) -> 10299 | AW85: =REV!AW85 -> 03.11.2026 | AX85: =VLOOKUP(C85,REV!C:AX,48,0) -> 5G
A86: Price Oferta | B86: 21X | C86: 4016916 | D86: APPLE IPHONE 16E 256GB | E86: APPLE IPHONE 16E 256GB-PRETO NAC | J86: =IF(VLOOKUP($C86,REV!$C:$AA,8,0)-'TRADE IN'!$F86=0,"",(VLOOKUP($C86,REV!$C:$AA,8,0)-'TRADE IN'!$F86)) -> 4799 | K86: =IF(VLOOKUP($C86,REV!$C:$AA,9,0)-'TRADE IN'!$F86=0,"",(VLOOKUP($C86,REV!$C:$AA,9,0)-'TRADE IN'!$F86)) -> 4799 | L86: =IF(VLOOKUP($C86,REV!$C:$AA,10,0)-'TRADE IN'!$F86=0,"",(VLOOKUP($C86,REV!$C:$AA,10,0)-'TRADE IN'!$F86)) -> 4799 | M86: =IF(VLOOKUP($C86,REV!$C:$AA,11,0)-'TRADE IN'!$F86=0,"",(VLOOKUP($C86,REV!$C:$AA,11,0)-'TRADE IN'!$F86)) -> 4799 | N86: =IF(VLOOKUP($C86,REV!$C:$AA,12,0)-'TRADE IN'!$F86=0,"",(VLOOKUP($C86,REV!$C:$AA,12,0)-'TRADE IN'!$F86)) -> 4799 | O86: =IF(VLOOKUP($C86,REV!$C:$AA,13,0)-'TRADE IN'!$F86=0,"",(VLOOKUP($C86,REV!$C:$AA,13,0)-'TRADE IN'!$F86)) -> 4699 | P86: =IF(VLOOKUP($C86,REV!$C:$AA,14,0)-'TRADE IN'!$F86=0,"",(VLOOKUP($C86,REV!$C:$AA,14,0)-'TRADE IN'!$F86)) -> 4599 | Q86: =IF(VLOOKUP($C86,REV!$C:$AA,15,0)-'TRADE IN'!$F86=0,"",(VLOOKUP($C86,REV!$C:$AA,15,0)-'TRADE IN'!$F86)) -> 3599 | R86: =IF(VLOOKUP($C86,REV!$C:$AA,16,0)-'TRADE IN'!$F86=0,"",(VLOOKUP($C86,REV!$C:$AA,16,0)-'TRADE IN'!$F86)) -> 4699 | S86: =IF(VLOOKUP($C86,REV!$C:$AA,17,0)-'TRADE IN'!$F86=0,"",(VLOOKUP($C86,REV!$C:$AA,17,0)-'TRADE IN'!$F86)) -> 4599 | T86: =IF(VLOOKUP($C86,REV!$C:$AA,18,0)-'TRADE IN'!$F86=0,"",(VLOOKUP($C86,REV!$C:$AA,18,0)-'TRADE IN'!$F86)) -> 3599 | U86: =IF(VLOOKUP($C86,REV!$C:$AA,19,0)-'TRADE IN'!$F86=0,"",(VLOOKUP($C86,REV!$C:$AA,19,0)-'TRADE IN'!$F86)) -> 3599 | V86: =IF(VLOOKUP($C86,REV!$C:$AA,20,0)-'TRADE IN'!$F86=0,"",(VLOOKUP($C86,REV!$C:$AA,20,0)-'TRADE IN'!$F86)) -> 3599 | W86: =IF(VLOOKUP($C86,REV!$C:$AA,21,0)-'TRADE IN'!$F86=0,"",(VLOOKUP($C86,REV!$C:$AA,21,0)-'TRADE IN'!$F86)) -> 3599 | X86: =IF(VLOOKUP($C86,REV!$C:$AA,22,0)-'TRADE IN'!$F86=0,"",(VLOOKUP($C86,REV!$C:$AA,22,0)-'TRADE IN'!$F86)) -> 3499 | Y86: =IF(VLOOKUP($C86,REV!$C:$AA,23,0)-'TRADE IN'!$F86=0,"",(VLOOKUP($C86,REV!$C:$AA,23,0)-'TRADE IN'!$F86)) -> 2799 | Z86: =IF(VLOOKUP($C86,REV!$C:$AA,24,0)-'TRADE IN'!$F86=0,"",(VLOOKUP($C86,REV!$C:$AA,24,0)-'TRADE IN'!$F86)) -> 2799 | AA86: =IF(VLOOKUP($C86,REV!$C:$AA,25,0)-'TRADE IN'!$F86=0,"",(VLOOKUP($C86,REV!$C:$AA,25,0)-'TRADE IN'!$F86)) -> 2749 | AB86: =IF(VLOOKUP($C86,REV!$C:$AL,27,0)-'TRADE IN'!$F86=0,"",(VLOOKUP($C86,REV!$C:$AL,27,0)-'TRADE IN'!$F86)) -> 4799 | AC86: =IF(VLOOKUP($C86,REV!$C:$AL,28,0)-'TRADE IN'!$F86=0,"",(VLOOKUP($C86,REV!$C:$AL,28,0)-'TRADE IN'!$F86)) -> 4799 | AD86: =IF(VLOOKUP($C86,REV!$C:$AL,29,0)-'TRADE IN'!$F86=0,"",(VLOOKUP($C86,REV!$C:$AL,29,0)-'TRADE IN'!$F86)) -> 4699 | AE86: =IF(VLOOKUP($C86,REV!$C:$AL,30,0)-'TRADE IN'!$F86=0,"",(VLOOKUP($C86,REV!$C:$AL,30,0)-'TRADE IN'!$F86)) -> 4599 | AF86: =IF(VLOOKUP($C86,REV!$C:$AL,31,0)-'TRADE IN'!$F86=0,"",(VLOOKUP($C86,REV!$C:$AL,31,0)-'TRADE IN'!$F86)) -> 4599 | AG86: =IF(VLOOKUP($C86,REV!$C:$AL,31,0)-'TRADE IN'!$F86=0,"",(VLOOKUP($C86,REV!$C:$AL,31,0)-'TRADE IN'!$F86)) -> 4599 | AH86: =IF(VLOOKUP($C86,REV!$C:$AL,32,0)-'TRADE IN'!$F86=0,"",(VLOOKUP($C86,REV!$C:$AL,32,0)-'TRADE IN'!$F86)) -> 3599 | AI86: =IF(VLOOKUP($C86,REV!$C:$AL,33,0)-'TRADE IN'!$F86=0,"",(VLOOKUP($C86,REV!$C:$AL,33,0)-'TRADE IN'!$F86)) -> 3599 | AJ86: =IF(VLOOKUP($C86,REV!$C:$AL,34,0)-'TRADE IN'!$F86=0,"",(VLOOKUP($C86,REV!$C:$AL,34,0)-'TRADE IN'!$F86)) -> 3599 | AK86: =IF(VLOOKUP($C86,REV!$C:$AL,35,0)-'TRADE IN'!$F86=0,"",(VLOOKUP($C86,REV!$C:$AL,35,0)-'TRADE IN'!$F86)) -> 3599 | AL86: =IF(VLOOKUP($C86,REV!$C:$AL,36,0)-'TRADE IN'!$F86=0,"",(VLOOKUP($C86,REV!$C:$AL,36,0)-'TRADE IN'!$F86)) -> 2799 | AW86: =REV!AW86 -> 03.11.2026 | AX86: =VLOOKUP(C86,REV!C:AX,48,0) -> 5G
A87: Price Oferta | B87: 21X | C87: 4016917 | D87: APPLE IPHONE 16E 256GB | E87: APPLE IPHONE 16E 256GB-BRANCO NAC | J87: =IF(VLOOKUP($C87,REV!$C:$AA,8,0)-'TRADE IN'!$F87=0,"",(VLOOKUP($C87,REV!$C:$AA,8,0)-'TRADE IN'!$F87)) -> 4799 | K87: =IF(VLOOKUP($C87,REV!$C:$AA,9,0)-'TRADE IN'!$F87=0,"",(VLOOKUP($C87,REV!$C:$AA,9,0)-'TRADE IN'!$F87)) -> 4799 | L87: =IF(VLOOKUP($C87,REV!$C:$AA,10,0)-'TRADE IN'!$F87=0,"",(VLOOKUP($C87,REV!$C:$AA,10,0)-'TRADE IN'!$F87)) -> 4799 | M87: =IF(VLOOKUP($C87,REV!$C:$AA,11,0)-'TRADE IN'!$F87=0,"",(VLOOKUP($C87,REV!$C:$AA,11,0)-'TRADE IN'!$F87)) -> 4799 | N87: =IF(VLOOKUP($C87,REV!$C:$AA,12,0)-'TRADE IN'!$F87=0,"",(VLOOKUP($C87,REV!$C:$AA,12,0)-'TRADE IN'!$F87)) -> 4799 | O87: =IF(VLOOKUP($C87,REV!$C:$AA,13,0)-'TRADE IN'!$F87=0,"",(VLOOKUP($C87,REV!$C:$AA,13,0)-'TRADE IN'!$F87)) -> 4699 | P87: =IF(VLOOKUP($C87,REV!$C:$AA,14,0)-'TRADE IN'!$F87=0,"",(VLOOKUP($C87,REV!$C:$AA,14,0)-'TRADE IN'!$F87)) -> 4599 | Q87: =IF(VLOOKUP($C87,REV!$C:$AA,15,0)-'TRADE IN'!$F87=0,"",(VLOOKUP($C87,REV!$C:$AA,15,0)-'TRADE IN'!$F87)) -> 3599 | R87: =IF(VLOOKUP($C87,REV!$C:$AA,16,0)-'TRADE IN'!$F87=0,"",(VLOOKUP($C87,REV!$C:$AA,16,0)-'TRADE IN'!$F87)) -> 4699 | S87: =IF(VLOOKUP($C87,REV!$C:$AA,17,0)-'TRADE IN'!$F87=0,"",(VLOOKUP($C87,REV!$C:$AA,17,0)-'TRADE IN'!$F87)) -> 4599 | T87: =IF(VLOOKUP($C87,REV!$C:$AA,18,0)-'TRADE IN'!$F87=0,"",(VLOOKUP($C87,REV!$C:$AA,18,0)-'TRADE IN'!$F87)) -> 3599 | U87: =IF(VLOOKUP($C87,REV!$C:$AA,19,0)-'TRADE IN'!$F87=0,"",(VLOOKUP($C87,REV!$C:$AA,19,0)-'TRADE IN'!$F87)) -> 3599 | V87: =IF(VLOOKUP($C87,REV!$C:$AA,20,0)-'TRADE IN'!$F87=0,"",(VLOOKUP($C87,REV!$C:$AA,20,0)-'TRADE IN'!$F87)) -> 3599 | W87: =IF(VLOOKUP($C87,REV!$C:$AA,21,0)-'TRADE IN'!$F87=0,"",(VLOOKUP($C87,REV!$C:$AA,21,0)-'TRADE IN'!$F87)) -> 3599 | X87: =IF(VLOOKUP($C87,REV!$C:$AA,22,0)-'TRADE IN'!$F87=0,"",(VLOOKUP($C87,REV!$C:$AA,22,0)-'TRADE IN'!$F87)) -> 3499 | Y87: =IF(VLOOKUP($C87,REV!$C:$AA,23,0)-'TRADE IN'!$F87=0,"",(VLOOKUP($C87,REV!$C:$AA,23,0)-'TRADE IN'!$F87)) -> 2799 | Z87: =IF(VLOOKUP($C87,REV!$C:$AA,24,0)-'TRADE IN'!$F87=0,"",(VLOOKUP($C87,REV!$C:$AA,24,0)-'TRADE IN'!$F87)) -> 2799 | AA87: =IF(VLOOKUP($C87,REV!$C:$AA,25,0)-'TRADE IN'!$F87=0,"",(VLOOKUP($C87,REV!$C:$AA,25,0)-'TRADE IN'!$F87)) -> 2749 | AB87: =IF(VLOOKUP($C87,REV!$C:$AL,27,0)-'TRADE IN'!$F87=0,"",(VLOOKUP($C87,REV!$C:$AL,27,0)-'TRADE IN'!$F87)) -> 4799 | AC87: =IF(VLOOKUP($C87,REV!$C:$AL,28,0)-'TRADE IN'!$F87=0,"",(VLOOKUP($C87,REV!$C:$AL,28,0)-'TRADE IN'!$F87)) -> 4799 | AD87: =IF(VLOOKUP($C87,REV!$C:$AL,29,0)-'TRADE IN'!$F87=0,"",(VLOOKUP($C87,REV!$C:$AL,29,0)-'TRADE IN'!$F87)) -> 4699 | AE87: =IF(VLOOKUP($C87,REV!$C:$AL,30,0)-'TRADE IN'!$F87=0,"",(VLOOKUP($C87,REV!$C:$AL,30,0)-'TRADE IN'!$F87)) -> 4599 | AF87: =IF(VLOOKUP($C87,REV!$C:$AL,31,0)-'TRADE IN'!$F87=0,"",(VLOOKUP($C87,REV!$C:$AL,31,0)-'TRADE IN'!$F87)) -> 4599 | AG87: =IF(VLOOKUP($C87,REV!$C:$AL,31,0)-'TRADE IN'!$F87=0,"",(VLOOKUP($C87,REV!$C:$AL,31,0)-'TRADE IN'!$F87)) -> 4599 | AH87: =IF(VLOOKUP($C87,REV!$C:$AL,32,0)-'TRADE IN'!$F87=0,"",(VLOOKUP($C87,REV!$C:$AL,32,0)-'TRADE IN'!$F87)) -> 3599 | AI87: =IF(VLOOKUP($C87,REV!$C:$AL,33,0)-'TRADE IN'!$F87=0,"",(VLOOKUP($C87,REV!$C:$AL,33,0)-'TRADE IN'!$F87)) -> 3599 | AJ87: =IF(VLOOKUP($C87,REV!$C:$AL,34,0)-'TRADE IN'!$F87=0,"",(VLOOKUP($C87,REV!$C:$AL,34,0)-'TRADE IN'!$F87)) -> 3599 | AK87: =IF(VLOOKUP($C87,REV!$C:$AL,35,0)-'TRADE IN'!$F87=0,"",(VLOOKUP($C87,REV!$C:$AL,35,0)-'TRADE IN'!$F87)) -> 3599 | AL87: =IF(VLOOKUP($C87,REV!$C:$AL,36,0)-'TRADE IN'!$F87=0,"",(VLOOKUP($C87,REV!$C:$AL,36,0)-'TRADE IN'!$F87)) -> 2799 | AW87: =REV!AW87 -> 03.11.2026 | AX87: =VLOOKUP(C87,REV!C:AX,48,0) -> 5G
A88: Price Oferta | B88: 21X | C88: 4017449 | D88: APPLE IPHONE 17 256GB | E88: APPLE IPHONE 17 256GB-LAVANDA | J88: =IF(VLOOKUP($C88,REV!$C:$AA,8,0)-'TRADE IN'!$F88=0,"",(VLOOKUP($C88,REV!$C:$AA,8,0)-'TRADE IN'!$F88)) -> 6399 | K88: =IF(VLOOKUP($C88,REV!$C:$AA,9,0)-'TRADE IN'!$F88=0,"",(VLOOKUP($C88,REV!$C:$AA,9,0)-'TRADE IN'!$F88)) -> 6399 | L88: =IF(VLOOKUP($C88,REV!$C:$AA,10,0)-'TRADE IN'!$F88=0,"",(VLOOKUP($C88,REV!$C:$AA,10,0)-'TRADE IN'!$F88)) -> 6399 | M88: =IF(VLOOKUP($C88,REV!$C:$AA,11,0)-'TRADE IN'!$F88=0,"",(VLOOKUP($C88,REV!$C:$AA,11,0)-'TRADE IN'!$F88)) -> 6399 | N88: =IF(VLOOKUP($C88,REV!$C:$AA,12,0)-'TRADE IN'!$F88=0,"",(VLOOKUP($C88,REV!$C:$AA,12,0)-'TRADE IN'!$F88)) -> 6399 | O88: =IF(VLOOKUP($C88,REV!$C:$AA,13,0)-'TRADE IN'!$F88=0,"",(VLOOKUP($C88,REV!$C:$AA,13,0)-'TRADE IN'!$F88)) -> 6299 | P88: =IF(VLOOKUP($C88,REV!$C:$AA,14,0)-'TRADE IN'!$F88=0,"",(VLOOKUP($C88,REV!$C:$AA,14,0)-'TRADE IN'!$F88)) -> 6199 | Q88: =IF(VLOOKUP($C88,REV!$C:$AA,15,0)-'TRADE IN'!$F88=0,"",(VLOOKUP($C88,REV!$C:$AA,15,0)-'TRADE IN'!$F88)) -> 5499 | R88: =IF(VLOOKUP($C88,REV!$C:$AA,16,0)-'TRADE IN'!$F88=0,"",(VLOOKUP($C88,REV!$C:$AA,16,0)-'TRADE IN'!$F88)) -> 6299 | S88: =IF(VLOOKUP($C88,REV!$C:$AA,17,0)-'TRADE IN'!$F88=0,"",(VLOOKUP($C88,REV!$C:$AA,17,0)-'TRADE IN'!$F88)) -> 6199 | T88: =IF(VLOOKUP($C88,REV!$C:$AA,18,0)-'TRADE IN'!$F88=0,"",(VLOOKUP($C88,REV!$C:$AA,18,0)-'TRADE IN'!$F88)) -> 5499 | U88: =IF(VLOOKUP($C88,REV!$C:$AA,19,0)-'TRADE IN'!$F88=0,"",(VLOOKUP($C88,REV!$C:$AA,19,0)-'TRADE IN'!$F88)) -> 5499 | V88: =IF(VLOOKUP($C88,REV!$C:$AA,20,0)-'TRADE IN'!$F88=0,"",(VLOOKUP($C88,REV!$C:$AA,20,0)-'TRADE IN'!$F88)) -> 5499 | W88: =IF(VLOOKUP($C88,REV!$C:$AA,21,0)-'TRADE IN'!$F88=0,"",(VLOOKUP($C88,REV!$C:$AA,21,0)-'TRADE IN'!$F88)) -> 5499 | X88: =IF(VLOOKUP($C88,REV!$C:$AA,22,0)-'TRADE IN'!$F88=0,"",(VLOOKUP($C88,REV!$C:$AA,22,0)-'TRADE IN'!$F88)) -> 5399 | Y88: =IF(VLOOKUP($C88,REV!$C:$AA,23,0)-'TRADE IN'!$F88=0,"",(VLOOKUP($C88,REV!$C:$AA,23,0)-'TRADE IN'!$F88)) -> 4999 | Z88: =IF(VLOOKUP($C88,REV!$C:$AA,24,0)-'TRADE IN'!$F88=0,"",(VLOOKUP($C88,REV!$C:$AA,24,0)-'TRADE IN'!$F88)) -> 4999 | AA88: =IF(VLOOKUP($C88,REV!$C:$AA,25,0)-'TRADE IN'!$F88=0,"",(VLOOKUP($C88,REV!$C:$AA,25,0)-'TRADE IN'!$F88)) -> 4949 | AB88: =IF(VLOOKUP($C88,REV!$C:$AL,27,0)-'TRADE IN'!$F88=0,"",(VLOOKUP($C88,REV!$C:$AL,27,0)-'TRADE IN'!$F88)) -> 6399 | AC88: =IF(VLOOKUP($C88,REV!$C:$AL,28,0)-'TRADE IN'!$F88=0,"",(VLOOKUP($C88,REV!$C:$AL,28,0)-'TRADE IN'!$F88)) -> 6399 | AD88: =IF(VLOOKUP($C88,REV!$C:$AL,29,0)-'TRADE IN'!$F88=0,"",(VLOOKUP($C88,REV!$C:$AL,29,0)-'TRADE IN'!$F88)) -> 6299 | AE88: =IF(VLOOKUP($C88,REV!$C:$AL,30,0)-'TRADE IN'!$F88=0,"",(VLOOKUP($C88,REV!$C:$AL,30,0)-'TRADE IN'!$F88)) -> 6199 | AF88: =IF(VLOOKUP($C88,REV!$C:$AL,31,0)-'TRADE IN'!$F88=0,"",(VLOOKUP($C88,REV!$C:$AL,31,0)-'TRADE IN'!$F88)) -> 6199 | AG88: =IF(VLOOKUP($C88,REV!$C:$AL,31,0)-'TRADE IN'!$F88=0,"",(VLOOKUP($C88,REV!$C:$AL,31,0)-'TRADE IN'!$F88)) -> 6199 | AH88: =IF(VLOOKUP($C88,REV!$C:$AL,32,0)-'TRADE IN'!$F88=0,"",(VLOOKUP($C88,REV!$C:$AL,32,0)-'TRADE IN'!$F88)) -> 5499 | AI88: =IF(VLOOKUP($C88,REV!$C:$AL,33,0)-'TRADE IN'!$F88=0,"",(VLOOKUP($C88,REV!$C:$AL,33,0)-'TRADE IN'!$F88)) -> 5499 | AJ88: =IF(VLOOKUP($C88,REV!$C:$AL,34,0)-'TRADE IN'!$F88=0,"",(VLOOKUP($C88,REV!$C:$AL,34,0)-'TRADE IN'!$F88)) -> 5499 | AK88: =IF(VLOOKUP($C88,REV!$C:$AL,35,0)-'TRADE IN'!$F88=0,"",(VLOOKUP($C88,REV!$C:$AL,35,0)-'TRADE IN'!$F88)) -> 5499 | AL88: =IF(VLOOKUP($C88,REV!$C:$AL,36,0)-'TRADE IN'!$F88=0,"",(VLOOKUP($C88,REV!$C:$AL,36,0)-'TRADE IN'!$F88)) -> 4999 | AW88: =REV!AW88 -> 03.11.2026 | AX88: =VLOOKUP(C88,REV!C:AX,48,0) -> 5G
A89: Price Oferta | B89: 21X | C89: 4017897 | D89: APPLE IPHONE 17 256GB | E89: APPLE IPHONE 17 256GB-LAVANDA NAC | J89: =IF(VLOOKUP($C89,REV!$C:$AA,8,0)-'TRADE IN'!$F89=0,"",(VLOOKUP($C89,REV!$C:$AA,8,0)-'TRADE IN'!$F89)) -> 6399 | K89: =IF(VLOOKUP($C89,REV!$C:$AA,9,0)-'TRADE IN'!$F89=0,"",(VLOOKUP($C89,REV!$C:$AA,9,0)-'TRADE IN'!$F89)) -> 6399 | L89: =IF(VLOOKUP($C89,REV!$C:$AA,10,0)-'TRADE IN'!$F89=0,"",(VLOOKUP($C89,REV!$C:$AA,10,0)-'TRADE IN'!$F89)) -> 6399 | M89: =IF(VLOOKUP($C89,REV!$C:$AA,11,0)-'TRADE IN'!$F89=0,"",(VLOOKUP($C89,REV!$C:$AA,11,0)-'TRADE IN'!$F89)) -> 6399 | N89: =IF(VLOOKUP($C89,REV!$C:$AA,12,0)-'TRADE IN'!$F89=0,"",(VLOOKUP($C89,REV!$C:$AA,12,0)-'TRADE IN'!$F89)) -> 6399 | O89: =IF(VLOOKUP($C89,REV!$C:$AA,13,0)-'TRADE IN'!$F89=0,"",(VLOOKUP($C89,REV!$C:$AA,13,0)-'TRADE IN'!$F89)) -> 6299 | P89: =IF(VLOOKUP($C89,REV!$C:$AA,14,0)-'TRADE IN'!$F89=0,"",(VLOOKUP($C89,REV!$C:$AA,14,0)-'TRADE IN'!$F89)) -> 6199 | Q89: =IF(VLOOKUP($C89,REV!$C:$AA,15,0)-'TRADE IN'!$F89=0,"",(VLOOKUP($C89,REV!$C:$AA,15,0)-'TRADE IN'!$F89)) -> 5499 | R89: =IF(VLOOKUP($C89,REV!$C:$AA,16,0)-'TRADE IN'!$F89=0,"",(VLOOKUP($C89,REV!$C:$AA,16,0)-'TRADE IN'!$F89)) -> 6299 | S89: =IF(VLOOKUP($C89,REV!$C:$AA,17,0)-'TRADE IN'!$F89=0,"",(VLOOKUP($C89,REV!$C:$AA,17,0)-'TRADE IN'!$F89)) -> 6199 | T89: =IF(VLOOKUP($C89,REV!$C:$AA,18,0)-'TRADE IN'!$F89=0,"",(VLOOKUP($C89,REV!$C:$AA,18,0)-'TRADE IN'!$F89)) -> 5499 | U89: =IF(VLOOKUP($C89,REV!$C:$AA,19,0)-'TRADE IN'!$F89=0,"",(VLOOKUP($C89,REV!$C:$AA,19,0)-'TRADE IN'!$F89)) -> 5499 | V89: =IF(VLOOKUP($C89,REV!$C:$AA,20,0)-'TRADE IN'!$F89=0,"",(VLOOKUP($C89,REV!$C:$AA,20,0)-'TRADE IN'!$F89)) -> 5499 | W89: =IF(VLOOKUP($C89,REV!$C:$AA,21,0)-'TRADE IN'!$F89=0,"",(VLOOKUP($C89,REV!$C:$AA,21,0)-'TRADE IN'!$F89)) -> 5499 | X89: =IF(VLOOKUP($C89,REV!$C:$AA,22,0)-'TRADE IN'!$F89=0,"",(VLOOKUP($C89,REV!$C:$AA,22,0)-'TRADE IN'!$F89)) -> 5399 | Y89: =IF(VLOOKUP($C89,REV!$C:$AA,23,0)-'TRADE IN'!$F89=0,"",(VLOOKUP($C89,REV!$C:$AA,23,0)-'TRADE IN'!$F89)) -> 4999 | Z89: =IF(VLOOKUP($C89,REV!$C:$AA,24,0)-'TRADE IN'!$F89=0,"",(VLOOKUP($C89,REV!$C:$AA,24,0)-'TRADE IN'!$F89)) -> 4999 | AA89: =IF(VLOOKUP($C89,REV!$C:$AA,25,0)-'TRADE IN'!$F89=0,"",(VLOOKUP($C89,REV!$C:$AA,25,0)-'TRADE IN'!$F89)) -> 4949 | AB89: =IF(VLOOKUP($C89,REV!$C:$AL,27,0)-'TRADE IN'!$F89=0,"",(VLOOKUP($C89,REV!$C:$AL,27,0)-'TRADE IN'!$F89)) -> 6399 | AC89: =IF(VLOOKUP($C89,REV!$C:$AL,28,0)-'TRADE IN'!$F89=0,"",(VLOOKUP($C89,REV!$C:$AL,28,0)-'TRADE IN'!$F89)) -> 6399 | AD89: =IF(VLOOKUP($C89,REV!$C:$AL,29,0)-'TRADE IN'!$F89=0,"",(VLOOKUP($C89,REV!$C:$AL,29,0)-'TRADE IN'!$F89)) -> 6299 | AE89: =IF(VLOOKUP($C89,REV!$C:$AL,30,0)-'TRADE IN'!$F89=0,"",(VLOOKUP($C89,REV!$C:$AL,30,0)-'TRADE IN'!$F89)) -> 6199 | AF89: =IF(VLOOKUP($C89,REV!$C:$AL,31,0)-'TRADE IN'!$F89=0,"",(VLOOKUP($C89,REV!$C:$AL,31,0)-'TRADE IN'!$F89)) -> 6199 | AG89: =IF(VLOOKUP($C89,REV!$C:$AL,31,0)-'TRADE IN'!$F89=0,"",(VLOOKUP($C89,REV!$C:$AL,31,0)-'TRADE IN'!$F89)) -> 6199 | AH89: =IF(VLOOKUP($C89,REV!$C:$AL,32,0)-'TRADE IN'!$F89=0,"",(VLOOKUP($C89,REV!$C:$AL,32,0)-'TRADE IN'!$F89)) -> 5499 | AI89: =IF(VLOOKUP($C89,REV!$C:$AL,33,0)-'TRADE IN'!$F89=0,"",(VLOOKUP($C89,REV!$C:$AL,33,0)-'TRADE IN'!$F89)) -> 5499 | AJ89: =IF(VLOOKUP($C89,REV!$C:$AL,34,0)-'TRADE IN'!$F89=0,"",(VLOOKUP($C89,REV!$C:$AL,34,0)-'TRADE IN'!$F89)) -> 5499 | AK89: =IF(VLOOKUP($C89,REV!$C:$AL,35,0)-'TRADE IN'!$F89=0,"",(VLOOKUP($C89,REV!$C:$AL,35,0)-'TRADE IN'!$F89)) -> 5499 | AL89: =IF(VLOOKUP($C89,REV!$C:$AL,36,0)-'TRADE IN'!$F89=0,"",(VLOOKUP($C89,REV!$C:$AL,36,0)-'TRADE IN'!$F89)) -> 4999 | AW89: =REV!AW89 -> 03.11.2026 | AX89: =VLOOKUP(C89,REV!C:AX,48,0) -> 5G
A90: Price Oferta | B90: 21X | C90: 4017480 | D90: APPLE IPHONE 17 256GB | E90: APPLE IPHONE 17 256GB-AZUL NEVOA | J90: =IF(VLOOKUP($C90,REV!$C:$AA,8,0)-'TRADE IN'!$F90=0,"",(VLOOKUP($C90,REV!$C:$AA,8,0)-'TRADE IN'!$F90)) -> 6399 | K90: =IF(VLOOKUP($C90,REV!$C:$AA,9,0)-'TRADE IN'!$F90=0,"",(VLOOKUP($C90,REV!$C:$AA,9,0)-'TRADE IN'!$F90)) -> 6399 | L90: =IF(VLOOKUP($C90,REV!$C:$AA,10,0)-'TRADE IN'!$F90=0,"",(VLOOKUP($C90,REV!$C:$AA,10,0)-'TRADE IN'!$F90)) -> 6399 | M90: =IF(VLOOKUP($C90,REV!$C:$AA,11,0)-'TRADE IN'!$F90=0,"",(VLOOKUP($C90,REV!$C:$AA,11,0)-'TRADE IN'!$F90)) -> 6399 | N90: =IF(VLOOKUP($C90,REV!$C:$AA,12,0)-'TRADE IN'!$F90=0,"",(VLOOKUP($C90,REV!$C:$AA,12,0)-'TRADE IN'!$F90)) -> 6399 | O90: =IF(VLOOKUP($C90,REV!$C:$AA,13,0)-'TRADE IN'!$F90=0,"",(VLOOKUP($C90,REV!$C:$AA,13,0)-'TRADE IN'!$F90)) -> 6299 | P90: =IF(VLOOKUP($C90,REV!$C:$AA,14,0)-'TRADE IN'!$F90=0,"",(VLOOKUP($C90,REV!$C:$AA,14,0)-'TRADE IN'!$F90)) -> 6199 | Q90: =IF(VLOOKUP($C90,REV!$C:$AA,15,0)-'TRADE IN'!$F90=0,"",(VLOOKUP($C90,REV!$C:$AA,15,0)-'TRADE IN'!$F90)) -> 5499 | R90: =IF(VLOOKUP($C90,REV!$C:$AA,16,0)-'TRADE IN'!$F90=0,"",(VLOOKUP($C90,REV!$C:$AA,16,0)-'TRADE IN'!$F90)) -> 6299 | S90: =IF(VLOOKUP($C90,REV!$C:$AA,17,0)-'TRADE IN'!$F90=0,"",(VLOOKUP($C90,REV!$C:$AA,17,0)-'TRADE IN'!$F90)) -> 6199 | T90: =IF(VLOOKUP($C90,REV!$C:$AA,18,0)-'TRADE IN'!$F90=0,"",(VLOOKUP($C90,REV!$C:$AA,18,0)-'TRADE IN'!$F90)) -> 5499 | U90: =IF(VLOOKUP($C90,REV!$C:$AA,19,0)-'TRADE IN'!$F90=0,"",(VLOOKUP($C90,REV!$C:$AA,19,0)-'TRADE IN'!$F90)) -> 5499 | V90: =IF(VLOOKUP($C90,REV!$C:$AA,20,0)-'TRADE IN'!$F90=0,"",(VLOOKUP($C90,REV!$C:$AA,20,0)-'TRADE IN'!$F90)) -> 5499 | W90: =IF(VLOOKUP($C90,REV!$C:$AA,21,0)-'TRADE IN'!$F90=0,"",(VLOOKUP($C90,REV!$C:$AA,21,0)-'TRADE IN'!$F90)) -> 5499 | X90: =IF(VLOOKUP($C90,REV!$C:$AA,22,0)-'TRADE IN'!$F90=0,"",(VLOOKUP($C90,REV!$C:$AA,22,0)-'TRADE IN'!$F90)) -> 5399 | Y90: =IF(VLOOKUP($C90,REV!$C:$AA,23,0)-'TRADE IN'!$F90=0,"",(VLOOKUP($C90,REV!$C:$AA,23,0)-'TRADE IN'!$F90)) -> 4999 | Z90: =IF(VLOOKUP($C90,REV!$C:$AA,24,0)-'TRADE IN'!$F90=0,"",(VLOOKUP($C90,REV!$C:$AA,24,0)-'TRADE IN'!$F90)) -> 4999 | AA90: =IF(VLOOKUP($C90,REV!$C:$AA,25,0)-'TRADE IN'!$F90=0,"",(VLOOKUP($C90,REV!$C:$AA,25,0)-'TRADE IN'!$F90)) -> 4949 | AB90: =IF(VLOOKUP($C90,REV!$C:$AL,27,0)-'TRADE IN'!$F90=0,"",(VLOOKUP($C90,REV!$C:$AL,27,0)-'TRADE IN'!$F90)) -> 6399 | AC90: =IF(VLOOKUP($C90,REV!$C:$AL,28,0)-'TRADE IN'!$F90=0,"",(VLOOKUP($C90,REV!$C:$AL,28,0)-'TRADE IN'!$F90)) -> 6399 | AD90: =IF(VLOOKUP($C90,REV!$C:$AL,29,0)-'TRADE IN'!$F90=0,"",(VLOOKUP($C90,REV!$C:$AL,29,0)-'TRADE IN'!$F90)) -> 6299 | AE90: =IF(VLOOKUP($C90,REV!$C:$AL,30,0)-'TRADE IN'!$F90=0,"",(VLOOKUP($C90,REV!$C:$AL,30,0)-'TRADE IN'!$F90)) -> 6199 | AF90: =IF(VLOOKUP($C90,REV!$C:$AL,31,0)-'TRADE IN'!$F90=0,"",(VLOOKUP($C90,REV!$C:$AL,31,0)-'TRADE IN'!$F90)) -> 6199 | AG90: =IF(VLOOKUP($C90,REV!$C:$AL,31,0)-'TRADE IN'!$F90=0,"",(VLOOKUP($C90,REV!$C:$AL,31,0)-'TRADE IN'!$F90)) -> 6199 | AH90: =IF(VLOOKUP($C90,REV!$C:$AL,32,0)-'TRADE IN'!$F90=0,"",(VLOOKUP($C90,REV!$C:$AL,32,0)-'TRADE IN'!$F90)) -> 5499 | AI90: =IF(VLOOKUP($C90,REV!$C:$AL,33,0)-'TRADE IN'!$F90=0,"",(VLOOKUP($C90,REV!$C:$AL,33,0)-'TRADE IN'!$F90)) -> 5499 | AJ90: =IF(VLOOKUP($C90,REV!$C:$AL,34,0)-'TRADE IN'!$F90=0,"",(VLOOKUP($C90,REV!$C:$AL,34,0)-'TRADE IN'!$F90)) -> 5499 | AK90: =IF(VLOOKUP($C90,REV!$C:$AL,35,0)-'TRADE IN'!$F90=0,"",(VLOOKUP($C90,REV!$C:$AL,35,0)-'TRADE IN'!$F90)) -> 5499 | AL90: =IF(VLOOKUP($C90,REV!$C:$AL,36,0)-'TRADE IN'!$F90=0,"",(VLOOKUP($C90,REV!$C:$AL,36,0)-'TRADE IN'!$F90)) -> 4999 | AW90: =REV!AW90 -> 03.11.2026 | AX90: =VLOOKUP(C90,REV!C:AX,48,0) -> 5G
A91: Price Oferta | B91: 21X | C91: 4017894 | D91: APPLE IPHONE 17 256GB | E91: APPLE IPHONE 17 256GB-AZUL NEVOA NAC | J91: =IF(VLOOKUP($C91,REV!$C:$AA,8,0)-'TRADE IN'!$F91=0,"",(VLOOKUP($C91,REV!$C:$AA,8,0)-'TRADE IN'!$F91)) -> 6399 | K91: =IF(VLOOKUP($C91,REV!$C:$AA,9,0)-'TRADE IN'!$F91=0,"",(VLOOKUP($C91,REV!$C:$AA,9,0)-'TRADE IN'!$F91)) -> 6399 | L91: =IF(VLOOKUP($C91,REV!$C:$AA,10,0)-'TRADE IN'!$F91=0,"",(VLOOKUP($C91,REV!$C:$AA,10,0)-'TRADE IN'!$F91)) -> 6399 | M91: =IF(VLOOKUP($C91,REV!$C:$AA,11,0)-'TRADE IN'!$F91=0,"",(VLOOKUP($C91,REV!$C:$AA,11,0)-'TRADE IN'!$F91)) -> 6399 | N91: =IF(VLOOKUP($C91,REV!$C:$AA,12,0)-'TRADE IN'!$F91=0,"",(VLOOKUP($C91,REV!$C:$AA,12,0)-'TRADE IN'!$F91)) -> 6399 | O91: =IF(VLOOKUP($C91,REV!$C:$AA,13,0)-'TRADE IN'!$F91=0,"",(VLOOKUP($C91,REV!$C:$AA,13,0)-'TRADE IN'!$F91)) -> 6299 | P91: =IF(VLOOKUP($C91,REV!$C:$AA,14,0)-'TRADE IN'!$F91=0,"",(VLOOKUP($C91,REV!$C:$AA,14,0)-'TRADE IN'!$F91)) -> 6199 | Q91: =IF(VLOOKUP($C91,REV!$C:$AA,15,0)-'TRADE IN'!$F91=0,"",(VLOOKUP($C91,REV!$C:$AA,15,0)-'TRADE IN'!$F91)) -> 5499 | R91: =IF(VLOOKUP($C91,REV!$C:$AA,16,0)-'TRADE IN'!$F91=0,"",(VLOOKUP($C91,REV!$C:$AA,16,0)-'TRADE IN'!$F91)) -> 6299 | S91: =IF(VLOOKUP($C91,REV!$C:$AA,17,0)-'TRADE IN'!$F91=0,"",(VLOOKUP($C91,REV!$C:$AA,17,0)-'TRADE IN'!$F91)) -> 6199 | T91: =IF(VLOOKUP($C91,REV!$C:$AA,18,0)-'TRADE IN'!$F91=0,"",(VLOOKUP($C91,REV!$C:$AA,18,0)-'TRADE IN'!$F91)) -> 5499 | U91: =IF(VLOOKUP($C91,REV!$C:$AA,19,0)-'TRADE IN'!$F91=0,"",(VLOOKUP($C91,REV!$C:$AA,19,0)-'TRADE IN'!$F91)) -> 5499 | V91: =IF(VLOOKUP($C91,REV!$C:$AA,20,0)-'TRADE IN'!$F91=0,"",(VLOOKUP($C91,REV!$C:$AA,20,0)-'TRADE IN'!$F91)) -> 5499 | W91: =IF(VLOOKUP($C91,REV!$C:$AA,21,0)-'TRADE IN'!$F91=0,"",(VLOOKUP($C91,REV!$C:$AA,21,0)-'TRADE IN'!$F91)) -> 5499 | X91: =IF(VLOOKUP($C91,REV!$C:$AA,22,0)-'TRADE IN'!$F91=0,"",(VLOOKUP($C91,REV!$C:$AA,22,0)-'TRADE IN'!$F91)) -> 5399 | Y91: =IF(VLOOKUP($C91,REV!$C:$AA,23,0)-'TRADE IN'!$F91=0,"",(VLOOKUP($C91,REV!$C:$AA,23,0)-'TRADE IN'!$F91)) -> 4999 | Z91: =IF(VLOOKUP($C91,REV!$C:$AA,24,0)-'TRADE IN'!$F91=0,"",(VLOOKUP($C91,REV!$C:$AA,24,0)-'TRADE IN'!$F91)) -> 4999 | AA91: =IF(VLOOKUP($C91,REV!$C:$AA,25,0)-'TRADE IN'!$F91=0,"",(VLOOKUP($C91,REV!$C:$AA,25,0)-'TRADE IN'!$F91)) -> 4949 | AB91: =IF(VLOOKUP($C91,REV!$C:$AL,27,0)-'TRADE IN'!$F91=0,"",(VLOOKUP($C91,REV!$C:$AL,27,0)-'TRADE IN'!$F91)) -> 6399 | AC91: =IF(VLOOKUP($C91,REV!$C:$AL,28,0)-'TRADE IN'!$F91=0,"",(VLOOKUP($C91,REV!$C:$AL,28,0)-'TRADE IN'!$F91)) -> 6399 | AD91: =IF(VLOOKUP($C91,REV!$C:$AL,29,0)-'TRADE IN'!$F91=0,"",(VLOOKUP($C91,REV!$C:$AL,29,0)-'TRADE IN'!$F91)) -> 6299 | AE91: =IF(VLOOKUP($C91,REV!$C:$AL,30,0)-'TRADE IN'!$F91=0,"",(VLOOKUP($C91,REV!$C:$AL,30,0)-'TRADE IN'!$F91)) -> 6199 | AF91: =IF(VLOOKUP($C91,REV!$C:$AL,31,0)-'TRADE IN'!$F91=0,"",(VLOOKUP($C91,REV!$C:$AL,31,0)-'TRADE IN'!$F91)) -> 6199 | AG91: =IF(VLOOKUP($C91,REV!$C:$AL,31,0)-'TRADE IN'!$F91=0,"",(VLOOKUP($C91,REV!$C:$AL,31,0)-'TRADE IN'!$F91)) -> 6199 | AH91: =IF(VLOOKUP($C91,REV!$C:$AL,32,0)-'TRADE IN'!$F91=0,"",(VLOOKUP($C91,REV!$C:$AL,32,0)-'TRADE IN'!$F91)) -> 5499 | AI91: =IF(VLOOKUP($C91,REV!$C:$AL,33,0)-'TRADE IN'!$F91=0,"",(VLOOKUP($C91,REV!$C:$AL,33,0)-'TRADE IN'!$F91)) -> 5499 | AJ91: =IF(VLOOKUP($C91,REV!$C:$AL,34,0)-'TRADE IN'!$F91=0,"",(VLOOKUP($C91,REV!$C:$AL,34,0)-'TRADE IN'!$F91)) -> 5499 | AK91: =IF(VLOOKUP($C91,REV!$C:$AL,35,0)-'TRADE IN'!$F91=0,"",(VLOOKUP($C91,REV!$C:$AL,35,0)-'TRADE IN'!$F91)) -> 5499 | AL91: =IF(VLOOKUP($C91,REV!$C:$AL,36,0)-'TRADE IN'!$F91=0,"",(VLOOKUP($C91,REV!$C:$AL,36,0)-'TRADE IN'!$F91)) -> 4999 | AW91: =REV!AW91 -> 03.11.2026 | AX91: =VLOOKUP(C91,REV!C:AX,48,0) -> 5G
A92: Price Oferta | B92: 21X | C92: 4017485 | D92: APPLE IPHONE 17 256GB | E92: APPLE IPHONE 17 256GB-PRETO | J92: =IF(VLOOKUP($C92,REV!$C:$AA,8,0)-'TRADE IN'!$F92=0,"",(VLOOKUP($C92,REV!$C:$AA,8,0)-'TRADE IN'!$F92)) -> 6399 | K92: =IF(VLOOKUP($C92,REV!$C:$AA,9,0)-'TRADE IN'!$F92=0,"",(VLOOKUP($C92,REV!$C:$AA,9,0)-'TRADE IN'!$F92)) -> 6399 | L92: =IF(VLOOKUP($C92,REV!$C:$AA,10,0)-'TRADE IN'!$F92=0,"",(VLOOKUP($C92,REV!$C:$AA,10,0)-'TRADE IN'!$F92)) -> 6399 | M92: =IF(VLOOKUP($C92,REV!$C:$AA,11,0)-'TRADE IN'!$F92=0,"",(VLOOKUP($C92,REV!$C:$AA,11,0)-'TRADE IN'!$F92)) -> 6399 | N92: =IF(VLOOKUP($C92,REV!$C:$AA,12,0)-'TRADE IN'!$F92=0,"",(VLOOKUP($C92,REV!$C:$AA,12,0)-'TRADE IN'!$F92)) -> 6399 | O92: =IF(VLOOKUP($C92,REV!$C:$AA,13,0)-'TRADE IN'!$F92=0,"",(VLOOKUP($C92,REV!$C:$AA,13,0)-'TRADE IN'!$F92)) -> 6299 | P92: =IF(VLOOKUP($C92,REV!$C:$AA,14,0)-'TRADE IN'!$F92=0,"",(VLOOKUP($C92,REV!$C:$AA,14,0)-'TRADE IN'!$F92)) -> 6199 | Q92: =IF(VLOOKUP($C92,REV!$C:$AA,15,0)-'TRADE IN'!$F92=0,"",(VLOOKUP($C92,REV!$C:$AA,15,0)-'TRADE IN'!$F92)) -> 5499 | R92: =IF(VLOOKUP($C92,REV!$C:$AA,16,0)-'TRADE IN'!$F92=0,"",(VLOOKUP($C92,REV!$C:$AA,16,0)-'TRADE IN'!$F92)) -> 6299 | S92: =IF(VLOOKUP($C92,REV!$C:$AA,17,0)-'TRADE IN'!$F92=0,"",(VLOOKUP($C92,REV!$C:$AA,17,0)-'TRADE IN'!$F92)) -> 6199 | T92: =IF(VLOOKUP($C92,REV!$C:$AA,18,0)-'TRADE IN'!$F92=0,"",(VLOOKUP($C92,REV!$C:$AA,18,0)-'TRADE IN'!$F92)) -> 5499 | U92: =IF(VLOOKUP($C92,REV!$C:$AA,19,0)-'TRADE IN'!$F92=0,"",(VLOOKUP($C92,REV!$C:$AA,19,0)-'TRADE IN'!$F92)) -> 5499 | V92: =IF(VLOOKUP($C92,REV!$C:$AA,20,0)-'TRADE IN'!$F92=0,"",(VLOOKUP($C92,REV!$C:$AA,20,0)-'TRADE IN'!$F92)) -> 5499 | W92: =IF(VLOOKUP($C92,REV!$C:$AA,21,0)-'TRADE IN'!$F92=0,"",(VLOOKUP($C92,REV!$C:$AA,21,0)-'TRADE IN'!$F92)) -> 5499 | X92: =IF(VLOOKUP($C92,REV!$C:$AA,22,0)-'TRADE IN'!$F92=0,"",(VLOOKUP($C92,REV!$C:$AA,22,0)-'TRADE IN'!$F92)) -> 5399 | Y92: =IF(VLOOKUP($C92,REV!$C:$AA,23,0)-'TRADE IN'!$F92=0,"",(VLOOKUP($C92,REV!$C:$AA,23,0)-'TRADE IN'!$F92)) -> 4999 | Z92: =IF(VLOOKUP($C92,REV!$C:$AA,24,0)-'TRADE IN'!$F92=0,"",(VLOOKUP($C92,REV!$C:$AA,24,0)-'TRADE IN'!$F92)) -> 4999 | AA92: =IF(VLOOKUP($C92,REV!$C:$AA,25,0)-'TRADE IN'!$F92=0,"",(VLOOKUP($C92,REV!$C:$AA,25,0)-'TRADE IN'!$F92)) -> 4949 | AB92: =IF(VLOOKUP($C92,REV!$C:$AL,27,0)-'TRADE IN'!$F92=0,"",(VLOOKUP($C92,REV!$C:$AL,27,0)-'TRADE IN'!$F92)) -> 6399 | AC92: =IF(VLOOKUP($C92,REV!$C:$AL,28,0)-'TRADE IN'!$F92=0,"",(VLOOKUP($C92,REV!$C:$AL,28,0)-'TRADE IN'!$F92)) -> 6399 | AD92: =IF(VLOOKUP($C92,REV!$C:$AL,29,0)-'TRADE IN'!$F92=0,"",(VLOOKUP($C92,REV!$C:$AL,29,0)-'TRADE IN'!$F92)) -> 6299 | AE92: =IF(VLOOKUP($C92,REV!$C:$AL,30,0)-'TRADE IN'!$F92=0,"",(VLOOKUP($C92,REV!$C:$AL,30,0)-'TRADE IN'!$F92)) -> 6199 | AF92: =IF(VLOOKUP($C92,REV!$C:$AL,31,0)-'TRADE IN'!$F92=0,"",(VLOOKUP($C92,REV!$C:$AL,31,0)-'TRADE IN'!$F92)) -> 6199 | AG92: =IF(VLOOKUP($C92,REV!$C:$AL,31,0)-'TRADE IN'!$F92=0,"",(VLOOKUP($C92,REV!$C:$AL,31,0)-'TRADE IN'!$F92)) -> 6199 | AH92: =IF(VLOOKUP($C92,REV!$C:$AL,32,0)-'TRADE IN'!$F92=0,"",(VLOOKUP($C92,REV!$C:$AL,32,0)-'TRADE IN'!$F92)) -> 5499 | AI92: =IF(VLOOKUP($C92,REV!$C:$AL,33,0)-'TRADE IN'!$F92=0,"",(VLOOKUP($C92,REV!$C:$AL,33,0)-'TRADE IN'!$F92)) -> 5499 | AJ92: =IF(VLOOKUP($C92,REV!$C:$AL,34,0)-'TRADE IN'!$F92=0,"",(VLOOKUP($C92,REV!$C:$AL,34,0)-'TRADE IN'!$F92)) -> 5499 | AK92: =IF(VLOOKUP($C92,REV!$C:$AL,35,0)-'TRADE IN'!$F92=0,"",(VLOOKUP($C92,REV!$C:$AL,35,0)-'TRADE IN'!$F92)) -> 5499 | AL92: =IF(VLOOKUP($C92,REV!$C:$AL,36,0)-'TRADE IN'!$F92=0,"",(VLOOKUP($C92,REV!$C:$AL,36,0)-'TRADE IN'!$F92)) -> 4999 | AW92: =REV!AW92 -> 03.11.2026 | AX92: =VLOOKUP(C92,REV!C:AX,48,0) -> 5G
A93: Price Oferta | B93: 21X | C93: 4017890 | D93: APPLE IPHONE 17 256GB | E93: APPLE IPHONE 17 256GB-PRETO NAC | J93: =IF(VLOOKUP($C93,REV!$C:$AA,8,0)-'TRADE IN'!$F93=0,"",(VLOOKUP($C93,REV!$C:$AA,8,0)-'TRADE IN'!$F93)) -> 6399 | K93: =IF(VLOOKUP($C93,REV!$C:$AA,9,0)-'TRADE IN'!$F93=0,"",(VLOOKUP($C93,REV!$C:$AA,9,0)-'TRADE IN'!$F93)) -> 6399 | L93: =IF(VLOOKUP($C93,REV!$C:$AA,10,0)-'TRADE IN'!$F93=0,"",(VLOOKUP($C93,REV!$C:$AA,10,0)-'TRADE IN'!$F93)) -> 6399 | M93: =IF(VLOOKUP($C93,REV!$C:$AA,11,0)-'TRADE IN'!$F93=0,"",(VLOOKUP($C93,REV!$C:$AA,11,0)-'TRADE IN'!$F93)) -> 6399 | N93: =IF(VLOOKUP($C93,REV!$C:$AA,12,0)-'TRADE IN'!$F93=0,"",(VLOOKUP($C93,REV!$C:$AA,12,0)-'TRADE IN'!$F93)) -> 6399 | O93: =IF(VLOOKUP($C93,REV!$C:$AA,13,0)-'TRADE IN'!$F93=0,"",(VLOOKUP($C93,REV!$C:$AA,13,0)-'TRADE IN'!$F93)) -> 6299 | P93: =IF(VLOOKUP($C93,REV!$C:$AA,14,0)-'TRADE IN'!$F93=0,"",(VLOOKUP($C93,REV!$C:$AA,14,0)-'TRADE IN'!$F93)) -> 6199 | Q93: =IF(VLOOKUP($C93,REV!$C:$AA,15,0)-'TRADE IN'!$F93=0,"",(VLOOKUP($C93,REV!$C:$AA,15,0)-'TRADE IN'!$F93)) -> 5499 | R93: =IF(VLOOKUP($C93,REV!$C:$AA,16,0)-'TRADE IN'!$F93=0,"",(VLOOKUP($C93,REV!$C:$AA,16,0)-'TRADE IN'!$F93)) -> 6299 | S93: =IF(VLOOKUP($C93,REV!$C:$AA,17,0)-'TRADE IN'!$F93=0,"",(VLOOKUP($C93,REV!$C:$AA,17,0)-'TRADE IN'!$F93)) -> 6199 | T93: =IF(VLOOKUP($C93,REV!$C:$AA,18,0)-'TRADE IN'!$F93=0,"",(VLOOKUP($C93,REV!$C:$AA,18,0)-'TRADE IN'!$F93)) -> 5499 | U93: =IF(VLOOKUP($C93,REV!$C:$AA,19,0)-'TRADE IN'!$F93=0,"",(VLOOKUP($C93,REV!$C:$AA,19,0)-'TRADE IN'!$F93)) -> 5499 | V93: =IF(VLOOKUP($C93,REV!$C:$AA,20,0)-'TRADE IN'!$F93=0,"",(VLOOKUP($C93,REV!$C:$AA,20,0)-'TRADE IN'!$F93)) -> 5499 | W93: =IF(VLOOKUP($C93,REV!$C:$AA,21,0)-'TRADE IN'!$F93=0,"",(VLOOKUP($C93,REV!$C:$AA,21,0)-'TRADE IN'!$F93)) -> 5499 | X93: =IF(VLOOKUP($C93,REV!$C:$AA,22,0)-'TRADE IN'!$F93=0,"",(VLOOKUP($C93,REV!$C:$AA,22,0)-'TRADE IN'!$F93)) -> 5399 | Y93: =IF(VLOOKUP($C93,REV!$C:$AA,23,0)-'TRADE IN'!$F93=0,"",(VLOOKUP($C93,REV!$C:$AA,23,0)-'TRADE IN'!$F93)) -> 4999 | Z93: =IF(VLOOKUP($C93,REV!$C:$AA,24,0)-'TRADE IN'!$F93=0,"",(VLOOKUP($C93,REV!$C:$AA,24,0)-'TRADE IN'!$F93)) -> 4999 | AA93: =IF(VLOOKUP($C93,REV!$C:$AA,25,0)-'TRADE IN'!$F93=0,"",(VLOOKUP($C93,REV!$C:$AA,25,0)-'TRADE IN'!$F93)) -> 4949 | AB93: =IF(VLOOKUP($C93,REV!$C:$AL,27,0)-'TRADE IN'!$F93=0,"",(VLOOKUP($C93,REV!$C:$AL,27,0)-'TRADE IN'!$F93)) -> 6399 | AC93: =IF(VLOOKUP($C93,REV!$C:$AL,28,0)-'TRADE IN'!$F93=0,"",(VLOOKUP($C93,REV!$C:$AL,28,0)-'TRADE IN'!$F93)) -> 6399 | AD93: =IF(VLOOKUP($C93,REV!$C:$AL,29,0)-'TRADE IN'!$F93=0,"",(VLOOKUP($C93,REV!$C:$AL,29,0)-'TRADE IN'!$F93)) -> 6299 | AE93: =IF(VLOOKUP($C93,REV!$C:$AL,30,0)-'TRADE IN'!$F93=0,"",(VLOOKUP($C93,REV!$C:$AL,30,0)-'TRADE IN'!$F93)) -> 6199 | AF93: =IF(VLOOKUP($C93,REV!$C:$AL,31,0)-'TRADE IN'!$F93=0,"",(VLOOKUP($C93,REV!$C:$AL,31,0)-'TRADE IN'!$F93)) -> 6199 | AG93: =IF(VLOOKUP($C93,REV!$C:$AL,31,0)-'TRADE IN'!$F93=0,"",(VLOOKUP($C93,REV!$C:$AL,31,0)-'TRADE IN'!$F93)) -> 6199 | AH93: =IF(VLOOKUP($C93,REV!$C:$AL,32,0)-'TRADE IN'!$F93=0,"",(VLOOKUP($C93,REV!$C:$AL,32,0)-'TRADE IN'!$F93)) -> 5499 | AI93: =IF(VLOOKUP($C93,REV!$C:$AL,33,0)-'TRADE IN'!$F93=0,"",(VLOOKUP($C93,REV!$C:$AL,33,0)-'TRADE IN'!$F93)) -> 5499 | AJ93: =IF(VLOOKUP($C93,REV!$C:$AL,34,0)-'TRADE IN'!$F93=0,"",(VLOOKUP($C93,REV!$C:$AL,34,0)-'TRADE IN'!$F93)) -> 5499 | AK93: =IF(VLOOKUP($C93,REV!$C:$AL,35,0)-'TRADE IN'!$F93=0,"",(VLOOKUP($C93,REV!$C:$AL,35,0)-'TRADE IN'!$F93)) -> 5499 | AL93: =IF(VLOOKUP($C93,REV!$C:$AL,36,0)-'TRADE IN'!$F93=0,"",(VLOOKUP($C93,REV!$C:$AL,36,0)-'TRADE IN'!$F93)) -> 4999 | AW93: =REV!AW93 -> 03.11.2026 | AX93: =VLOOKUP(C93,REV!C:AX,48,0) -> 5G
A94: Price Oferta | B94: 21X | C94: 4017486 | D94: APPLE IPHONE 17 256GB | E94: APPLE IPHONE 17 256GB-BRANCO | J94: =IF(VLOOKUP($C94,REV!$C:$AA,8,0)-'TRADE IN'!$F94=0,"",(VLOOKUP($C94,REV!$C:$AA,8,0)-'TRADE IN'!$F94)) -> 6399 | K94: =IF(VLOOKUP($C94,REV!$C:$AA,9,0)-'TRADE IN'!$F94=0,"",(VLOOKUP($C94,REV!$C:$AA,9,0)-'TRADE IN'!$F94)) -> 6399 | L94: =IF(VLOOKUP($C94,REV!$C:$AA,10,0)-'TRADE IN'!$F94=0,"",(VLOOKUP($C94,REV!$C:$AA,10,0)-'TRADE IN'!$F94)) -> 6399 | M94: =IF(VLOOKUP($C94,REV!$C:$AA,11,0)-'TRADE IN'!$F94=0,"",(VLOOKUP($C94,REV!$C:$AA,11,0)-'TRADE IN'!$F94)) -> 6399 | N94: =IF(VLOOKUP($C94,REV!$C:$AA,12,0)-'TRADE IN'!$F94=0,"",(VLOOKUP($C94,REV!$C:$AA,12,0)-'TRADE IN'!$F94)) -> 6399 | O94: =IF(VLOOKUP($C94,REV!$C:$AA,13,0)-'TRADE IN'!$F94=0,"",(VLOOKUP($C94,REV!$C:$AA,13,0)-'TRADE IN'!$F94)) -> 6299 | P94: =IF(VLOOKUP($C94,REV!$C:$AA,14,0)-'TRADE IN'!$F94=0,"",(VLOOKUP($C94,REV!$C:$AA,14,0)-'TRADE IN'!$F94)) -> 6199 | Q94: =IF(VLOOKUP($C94,REV!$C:$AA,15,0)-'TRADE IN'!$F94=0,"",(VLOOKUP($C94,REV!$C:$AA,15,0)-'TRADE IN'!$F94)) -> 5499 | R94: =IF(VLOOKUP($C94,REV!$C:$AA,16,0)-'TRADE IN'!$F94=0,"",(VLOOKUP($C94,REV!$C:$AA,16,0)-'TRADE IN'!$F94)) -> 6299 | S94: =IF(VLOOKUP($C94,REV!$C:$AA,17,0)-'TRADE IN'!$F94=0,"",(VLOOKUP($C94,REV!$C:$AA,17,0)-'TRADE IN'!$F94)) -> 6199 | T94: =IF(VLOOKUP($C94,REV!$C:$AA,18,0)-'TRADE IN'!$F94=0,"",(VLOOKUP($C94,REV!$C:$AA,18,0)-'TRADE IN'!$F94)) -> 5499 | U94: =IF(VLOOKUP($C94,REV!$C:$AA,19,0)-'TRADE IN'!$F94=0,"",(VLOOKUP($C94,REV!$C:$AA,19,0)-'TRADE IN'!$F94)) -> 5499 | V94: =IF(VLOOKUP($C94,REV!$C:$AA,20,0)-'TRADE IN'!$F94=0,"",(VLOOKUP($C94,REV!$C:$AA,20,0)-'TRADE IN'!$F94)) -> 5499 | W94: =IF(VLOOKUP($C94,REV!$C:$AA,21,0)-'TRADE IN'!$F94=0,"",(VLOOKUP($C94,REV!$C:$AA,21,0)-'TRADE IN'!$F94)) -> 5499 | X94: =IF(VLOOKUP($C94,REV!$C:$AA,22,0)-'TRADE IN'!$F94=0,"",(VLOOKUP($C94,REV!$C:$AA,22,0)-'TRADE IN'!$F94)) -> 5399 | Y94: =IF(VLOOKUP($C94,REV!$C:$AA,23,0)-'TRADE IN'!$F94=0,"",(VLOOKUP($C94,REV!$C:$AA,23,0)-'TRADE IN'!$F94)) -> 4999 | Z94: =IF(VLOOKUP($C94,REV!$C:$AA,24,0)-'TRADE IN'!$F94=0,"",(VLOOKUP($C94,REV!$C:$AA,24,0)-'TRADE IN'!$F94)) -> 4999 | AA94: =IF(VLOOKUP($C94,REV!$C:$AA,25,0)-'TRADE IN'!$F94=0,"",(VLOOKUP($C94,REV!$C:$AA,25,0)-'TRADE IN'!$F94)) -> 4949 | AB94: =IF(VLOOKUP($C94,REV!$C:$AL,27,0)-'TRADE IN'!$F94=0,"",(VLOOKUP($C94,REV!$C:$AL,27,0)-'TRADE IN'!$F94)) -> 6399 | AC94: =IF(VLOOKUP($C94,REV!$C:$AL,28,0)-'TRADE IN'!$F94=0,"",(VLOOKUP($C94,REV!$C:$AL,28,0)-'TRADE IN'!$F94)) -> 6399 | AD94: =IF(VLOOKUP($C94,REV!$C:$AL,29,0)-'TRADE IN'!$F94=0,"",(VLOOKUP($C94,REV!$C:$AL,29,0)-'TRADE IN'!$F94)) -> 6299 | AE94: =IF(VLOOKUP($C94,REV!$C:$AL,30,0)-'TRADE IN'!$F94=0,"",(VLOOKUP($C94,REV!$C:$AL,30,0)-'TRADE IN'!$F94)) -> 6199 | AF94: =IF(VLOOKUP($C94,REV!$C:$AL,31,0)-'TRADE IN'!$F94=0,"",(VLOOKUP($C94,REV!$C:$AL,31,0)-'TRADE IN'!$F94)) -> 6199 | AG94: =IF(VLOOKUP($C94,REV!$C:$AL,31,0)-'TRADE IN'!$F94=0,"",(VLOOKUP($C94,REV!$C:$AL,31,0)-'TRADE IN'!$F94)) -> 6199 | AH94: =IF(VLOOKUP($C94,REV!$C:$AL,32,0)-'TRADE IN'!$F94=0,"",(VLOOKUP($C94,REV!$C:$AL,32,0)-'TRADE IN'!$F94)) -> 5499 | AI94: =IF(VLOOKUP($C94,REV!$C:$AL,33,0)-'TRADE IN'!$F94=0,"",(VLOOKUP($C94,REV!$C:$AL,33,0)-'TRADE IN'!$F94)) -> 5499 | AJ94: =IF(VLOOKUP($C94,REV!$C:$AL,34,0)-'TRADE IN'!$F94=0,"",(VLOOKUP($C94,REV!$C:$AL,34,0)-'TRADE IN'!$F94)) -> 5499 | AK94: =IF(VLOOKUP($C94,REV!$C:$AL,35,0)-'TRADE IN'!$F94=0,"",(VLOOKUP($C94,REV!$C:$AL,35,0)-'TRADE IN'!$F94)) -> 5499 | AL94: =IF(VLOOKUP($C94,REV!$C:$AL,36,0)-'TRADE IN'!$F94=0,"",(VLOOKUP($C94,REV!$C:$AL,36,0)-'TRADE IN'!$F94)) -> 4999 | AW94: =REV!AW94 -> 03.11.2026 | AX94: =VLOOKUP(C94,REV!C:AX,48,0) -> 5G
A95: Price Oferta | B95: 21X | C95: 4017892 | D95: APPLE IPHONE 17 256GB | E95: APPLE IPHONE 17 256GB-BRANCO NAC | J95: =IF(VLOOKUP($C95,REV!$C:$AA,8,0)-'TRADE IN'!$F95=0,"",(VLOOKUP($C95,REV!$C:$AA,8,0)-'TRADE IN'!$F95)) -> 6399 | K95: =IF(VLOOKUP($C95,REV!$C:$AA,9,0)-'TRADE IN'!$F95=0,"",(VLOOKUP($C95,REV!$C:$AA,9,0)-'TRADE IN'!$F95)) -> 6399 | L95: =IF(VLOOKUP($C95,REV!$C:$AA,10,0)-'TRADE IN'!$F95=0,"",(VLOOKUP($C95,REV!$C:$AA,10,0)-'TRADE IN'!$F95)) -> 6399 | M95: =IF(VLOOKUP($C95,REV!$C:$AA,11,0)-'TRADE IN'!$F95=0,"",(VLOOKUP($C95,REV!$C:$AA,11,0)-'TRADE IN'!$F95)) -> 6399 | N95: =IF(VLOOKUP($C95,REV!$C:$AA,12,0)-'TRADE IN'!$F95=0,"",(VLOOKUP($C95,REV!$C:$AA,12,0)-'TRADE IN'!$F95)) -> 6399 | O95: =IF(VLOOKUP($C95,REV!$C:$AA,13,0)-'TRADE IN'!$F95=0,"",(VLOOKUP($C95,REV!$C:$AA,13,0)-'TRADE IN'!$F95)) -> 6299 | P95: =IF(VLOOKUP($C95,REV!$C:$AA,14,0)-'TRADE IN'!$F95=0,"",(VLOOKUP($C95,REV!$C:$AA,14,0)-'TRADE IN'!$F95)) -> 6199 | Q95: =IF(VLOOKUP($C95,REV!$C:$AA,15,0)-'TRADE IN'!$F95=0,"",(VLOOKUP($C95,REV!$C:$AA,15,0)-'TRADE IN'!$F95)) -> 5499 | R95: =IF(VLOOKUP($C95,REV!$C:$AA,16,0)-'TRADE IN'!$F95=0,"",(VLOOKUP($C95,REV!$C:$AA,16,0)-'TRADE IN'!$F95)) -> 6299 | S95: =IF(VLOOKUP($C95,REV!$C:$AA,17,0)-'TRADE IN'!$F95=0,"",(VLOOKUP($C95,REV!$C:$AA,17,0)-'TRADE IN'!$F95)) -> 6199 | T95: =IF(VLOOKUP($C95,REV!$C:$AA,18,0)-'TRADE IN'!$F95=0,"",(VLOOKUP($C95,REV!$C:$AA,18,0)-'TRADE IN'!$F95)) -> 5499 | U95: =IF(VLOOKUP($C95,REV!$C:$AA,19,0)-'TRADE IN'!$F95=0,"",(VLOOKUP($C95,REV!$C:$AA,19,0)-'TRADE IN'!$F95)) -> 5499 | V95: =IF(VLOOKUP($C95,REV!$C:$AA,20,0)-'TRADE IN'!$F95=0,"",(VLOOKUP($C95,REV!$C:$AA,20,0)-'TRADE IN'!$F95)) -> 5499 | W95: =IF(VLOOKUP($C95,REV!$C:$AA,21,0)-'TRADE IN'!$F95=0,"",(VLOOKUP($C95,REV!$C:$AA,21,0)-'TRADE IN'!$F95)) -> 5499 | X95: =IF(VLOOKUP($C95,REV!$C:$AA,22,0)-'TRADE IN'!$F95=0,"",(VLOOKUP($C95,REV!$C:$AA,22,0)-'TRADE IN'!$F95)) -> 5399 | Y95: =IF(VLOOKUP($C95,REV!$C:$AA,23,0)-'TRADE IN'!$F95=0,"",(VLOOKUP($C95,REV!$C:$AA,23,0)-'TRADE IN'!$F95)) -> 4999 | Z95: =IF(VLOOKUP($C95,REV!$C:$AA,24,0)-'TRADE IN'!$F95=0,"",(VLOOKUP($C95,REV!$C:$AA,24,0)-'TRADE IN'!$F95)) -> 4999 | AA95: =IF(VLOOKUP($C95,REV!$C:$AA,25,0)-'TRADE IN'!$F95=0,"",(VLOOKUP($C95,REV!$C:$AA,25,0)-'TRADE IN'!$F95)) -> 4949 | AB95: =IF(VLOOKUP($C95,REV!$C:$AL,27,0)-'TRADE IN'!$F95=0,"",(VLOOKUP($C95,REV!$C:$AL,27,0)-'TRADE IN'!$F95)) -> 6399 | AC95: =IF(VLOOKUP($C95,REV!$C:$AL,28,0)-'TRADE IN'!$F95=0,"",(VLOOKUP($C95,REV!$C:$AL,28,0)-'TRADE IN'!$F95)) -> 6399 | AD95: =IF(VLOOKUP($C95,REV!$C:$AL,29,0)-'TRADE IN'!$F95=0,"",(VLOOKUP($C95,REV!$C:$AL,29,0)-'TRADE IN'!$F95)) -> 6299 | AE95: =IF(VLOOKUP($C95,REV!$C:$AL,30,0)-'TRADE IN'!$F95=0,"",(VLOOKUP($C95,REV!$C:$AL,30,0)-'TRADE IN'!$F95)) -> 6199 | AF95: =IF(VLOOKUP($C95,REV!$C:$AL,31,0)-'TRADE IN'!$F95=0,"",(VLOOKUP($C95,REV!$C:$AL,31,0)-'TRADE IN'!$F95)) -> 6199 | AG95: =IF(VLOOKUP($C95,REV!$C:$AL,31,0)-'TRADE IN'!$F95=0,"",(VLOOKUP($C95,REV!$C:$AL,31,0)-'TRADE IN'!$F95)) -> 6199 | AH95: =IF(VLOOKUP($C95,REV!$C:$AL,32,0)-'TRADE IN'!$F95=0,"",(VLOOKUP($C95,REV!$C:$AL,32,0)-'TRADE IN'!$F95)) -> 5499 | AI95: =IF(VLOOKUP($C95,REV!$C:$AL,33,0)-'TRADE IN'!$F95=0,"",(VLOOKUP($C95,REV!$C:$AL,33,0)-'TRADE IN'!$F95)) -> 5499 | AJ95: =IF(VLOOKUP($C95,REV!$C:$AL,34,0)-'TRADE IN'!$F95=0,"",(VLOOKUP($C95,REV!$C:$AL,34,0)-'TRADE IN'!$F95)) -> 5499 | AK95: =IF(VLOOKUP($C95,REV!$C:$AL,35,0)-'TRADE IN'!$F95=0,"",(VLOOKUP($C95,REV!$C:$AL,35,0)-'TRADE IN'!$F95)) -> 5499 | AL95: =IF(VLOOKUP($C95,REV!$C:$AL,36,0)-'TRADE IN'!$F95=0,"",(VLOOKUP($C95,REV!$C:$AL,36,0)-'TRADE IN'!$F95)) -> 4999 | AW95: =REV!AW95 -> 03.11.2026 | AX95: =VLOOKUP(C95,REV!C:AX,48,0) -> 5G
A96: Price Oferta | B96: 21X | C96: 4017483 | D96: APPLE IPHONE 17 256GB | E96: APPLE IPHONE 17 256GB-SALVIA | J96: =IF(VLOOKUP($C96,REV!$C:$AA,8,0)-'TRADE IN'!$F96=0,"",(VLOOKUP($C96,REV!$C:$AA,8,0)-'TRADE IN'!$F96)) -> 6399 | K96: =IF(VLOOKUP($C96,REV!$C:$AA,9,0)-'TRADE IN'!$F96=0,"",(VLOOKUP($C96,REV!$C:$AA,9,0)-'TRADE IN'!$F96)) -> 6399 | L96: =IF(VLOOKUP($C96,REV!$C:$AA,10,0)-'TRADE IN'!$F96=0,"",(VLOOKUP($C96,REV!$C:$AA,10,0)-'TRADE IN'!$F96)) -> 6399 | M96: =IF(VLOOKUP($C96,REV!$C:$AA,11,0)-'TRADE IN'!$F96=0,"",(VLOOKUP($C96,REV!$C:$AA,11,0)-'TRADE IN'!$F96)) -> 6399 | N96: =IF(VLOOKUP($C96,REV!$C:$AA,12,0)-'TRADE IN'!$F96=0,"",(VLOOKUP($C96,REV!$C:$AA,12,0)-'TRADE IN'!$F96)) -> 6399 | O96: =IF(VLOOKUP($C96,REV!$C:$AA,13,0)-'TRADE IN'!$F96=0,"",(VLOOKUP($C96,REV!$C:$AA,13,0)-'TRADE IN'!$F96)) -> 6299 | P96: =IF(VLOOKUP($C96,REV!$C:$AA,14,0)-'TRADE IN'!$F96=0,"",(VLOOKUP($C96,REV!$C:$AA,14,0)-'TRADE IN'!$F96)) -> 6199 | Q96: =IF(VLOOKUP($C96,REV!$C:$AA,15,0)-'TRADE IN'!$F96=0,"",(VLOOKUP($C96,REV!$C:$AA,15,0)-'TRADE IN'!$F96)) -> 5499 | R96: =IF(VLOOKUP($C96,REV!$C:$AA,16,0)-'TRADE IN'!$F96=0,"",(VLOOKUP($C96,REV!$C:$AA,16,0)-'TRADE IN'!$F96)) -> 6299 | S96: =IF(VLOOKUP($C96,REV!$C:$AA,17,0)-'TRADE IN'!$F96=0,"",(VLOOKUP($C96,REV!$C:$AA,17,0)-'TRADE IN'!$F96)) -> 6199 | T96: =IF(VLOOKUP($C96,REV!$C:$AA,18,0)-'TRADE IN'!$F96=0,"",(VLOOKUP($C96,REV!$C:$AA,18,0)-'TRADE IN'!$F96)) -> 5499 | U96: =IF(VLOOKUP($C96,REV!$C:$AA,19,0)-'TRADE IN'!$F96=0,"",(VLOOKUP($C96,REV!$C:$AA,19,0)-'TRADE IN'!$F96)) -> 5499 | V96: =IF(VLOOKUP($C96,REV!$C:$AA,20,0)-'TRADE IN'!$F96=0,"",(VLOOKUP($C96,REV!$C:$AA,20,0)-'TRADE IN'!$F96)) -> 5499 | W96: =IF(VLOOKUP($C96,REV!$C:$AA,21,0)-'TRADE IN'!$F96=0,"",(VLOOKUP($C96,REV!$C:$AA,21,0)-'TRADE IN'!$F96)) -> 5499 | X96: =IF(VLOOKUP($C96,REV!$C:$AA,22,0)-'TRADE IN'!$F96=0,"",(VLOOKUP($C96,REV!$C:$AA,22,0)-'TRADE IN'!$F96)) -> 5399 | Y96: =IF(VLOOKUP($C96,REV!$C:$AA,23,0)-'TRADE IN'!$F96=0,"",(VLOOKUP($C96,REV!$C:$AA,23,0)-'TRADE IN'!$F96)) -> 4999 | Z96: =IF(VLOOKUP($C96,REV!$C:$AA,24,0)-'TRADE IN'!$F96=0,"",(VLOOKUP($C96,REV!$C:$AA,24,0)-'TRADE IN'!$F96)) -> 4999 | AA96: =IF(VLOOKUP($C96,REV!$C:$AA,25,0)-'TRADE IN'!$F96=0,"",(VLOOKUP($C96,REV!$C:$AA,25,0)-'TRADE IN'!$F96)) -> 4949 | AB96: =IF(VLOOKUP($C96,REV!$C:$AL,27,0)-'TRADE IN'!$F96=0,"",(VLOOKUP($C96,REV!$C:$AL,27,0)-'TRADE IN'!$F96)) -> 6399 | AC96: =IF(VLOOKUP($C96,REV!$C:$AL,28,0)-'TRADE IN'!$F96=0,"",(VLOOKUP($C96,REV!$C:$AL,28,0)-'TRADE IN'!$F96)) -> 6399 | AD96: =IF(VLOOKUP($C96,REV!$C:$AL,29,0)-'TRADE IN'!$F96=0,"",(VLOOKUP($C96,REV!$C:$AL,29,0)-'TRADE IN'!$F96)) -> 6299 | AE96: =IF(VLOOKUP($C96,REV!$C:$AL,30,0)-'TRADE IN'!$F96=0,"",(VLOOKUP($C96,REV!$C:$AL,30,0)-'TRADE IN'!$F96)) -> 6199 | AF96: =IF(VLOOKUP($C96,REV!$C:$AL,31,0)-'TRADE IN'!$F96=0,"",(VLOOKUP($C96,REV!$C:$AL,31,0)-'TRADE IN'!$F96)) -> 6199 | AG96: =IF(VLOOKUP($C96,REV!$C:$AL,31,0)-'TRADE IN'!$F96=0,"",(VLOOKUP($C96,REV!$C:$AL,31,0)-'TRADE IN'!$F96)) -> 6199 | AH96: =IF(VLOOKUP($C96,REV!$C:$AL,32,0)-'TRADE IN'!$F96=0,"",(VLOOKUP($C96,REV!$C:$AL,32,0)-'TRADE IN'!$F96)) -> 5499 | AI96: =IF(VLOOKUP($C96,REV!$C:$AL,33,0)-'TRADE IN'!$F96=0,"",(VLOOKUP($C96,REV!$C:$AL,33,0)-'TRADE IN'!$F96)) -> 5499 | AJ96: =IF(VLOOKUP($C96,REV!$C:$AL,34,0)-'TRADE IN'!$F96=0,"",(VLOOKUP($C96,REV!$C:$AL,34,0)-'TRADE IN'!$F96)) -> 5499 | AK96: =IF(VLOOKUP($C96,REV!$C:$AL,35,0)-'TRADE IN'!$F96=0,"",(VLOOKUP($C96,REV!$C:$AL,35,0)-'TRADE IN'!$F96)) -> 5499 | AL96: =IF(VLOOKUP($C96,REV!$C:$AL,36,0)-'TRADE IN'!$F96=0,"",(VLOOKUP($C96,REV!$C:$AL,36,0)-'TRADE IN'!$F96)) -> 4999 | AW96: =REV!AW96 -> 03.11.2026 | AX96: =VLOOKUP(C96,REV!C:AX,48,0) -> 5G
